Compiled from "MythicDungeons.java"
public final class net.playavalon.mythicdungeons.MythicDungeons extends org.bukkit.plugin.java.JavaPlugin implements net.playavalon.mythicdungeons.api.MythicDungeonsService {
  private static net.playavalon.mythicdungeons.MythicDungeons plugin;

  public static java.lang.String debugPrefix;

  public static final int DUNGEON_CONFIG_VER;

  private final net.kyori.adventure.text.minimessage.MiniMessage miniMessage;

  private org.bukkit.configuration.file.FileConfiguration config;

  private org.bukkit.configuration.file.FileConfiguration defaultDungeonConfig;

  private org.bukkit.Material functionBuilderMaterial;

  private org.bukkit.Material roomEditorMaterial;

  private boolean stuckKillsPlayer;

  private boolean inheritedVelocityEnabled;

  private boolean paperSupport;

  private boolean supportsTeleportFlags;

  private boolean supportsTeleportAsync;

  private boolean supportsFAWE;

  private boolean useSameWorldSystem;

  private net.playavalon.mythicdungeons.avngui.AvnAPI avnAPI;

  private io.lumine.mythic.bukkit.MythicBukkit mythicApi;

  private net.citizensnpcs.Citizens citizensApi;

  private net.playavalon.mythicdungeons.compatibility.citizens.MythicNPCRegistry mythicNPCRegistry;

  private net.milkbowl.vault.economy.Economy economy;

  private org.mvplugins.multiverse.inventories.MultiverseInventories multiverseInv;

  private com.github.retrooper.packetevents.PacketEventsAPI<?> packetEvents;

  private boolean betonEnabled;

  private boolean faweEnabled;

  private boolean partiesEnabled;

  private java.lang.String partyPluginName;

  private boolean thirdPartyProvider;

  private com.herocraftonline.heroes.Heroes heroesApi;

  private com.alessiodp.parties.api.interfaces.PartiesAPI partiesAPI;

  private java.io.File dungeonFiles;

  private java.io.File backupFolder;

  private java.io.File playerDataFolder;

  private net.playavalon.mythicdungeons.managers.PlayerManager playerManager;

  private net.playavalon.mythicdungeons.managers.PartyManager partyManager;

  private net.playavalon.mythicdungeons.managers.PartyProviderManager providerManager;

  private net.playavalon.mythicdungeons.managers.DungeonManager dungeons;

  private java.util.Map<java.util.UUID, net.playavalon.mythicdungeons.api.parents.instances.AbstractInstance> activeInstances;

  private net.playavalon.mythicdungeons.managers.FunctionManager functionManager;

  private net.playavalon.mythicdungeons.managers.TriggerManager triggerManager;

  private net.playavalon.mythicdungeons.managers.ConditionManager conditionManager;

  private net.playavalon.mythicdungeons.managers.QueueManager queueManager;

  private net.playavalon.mythicdungeons.managers.LootTableManager lootTableManager;

  private net.playavalon.mythicdungeons.managers.MovingBlockManager movingBlockManager;

  private net.playavalon.mythicdungeons.managers.PartyRecruitmentManager listingManager;

  private net.playavalon.mythicdungeons.managers.HotbarMenuManager hotbarMenus;

  private net.playavalon.mythicdungeons.managers.CommandManager commandManager;

  private net.playavalon.mythicdungeons.managers.SpectatorManager spectatorManager;

  private net.playavalon.mythicdungeons.managers.InstanceContainer overworldContainer;

  private net.playavalon.mythicdungeons.managers.InstanceContainer netherContainer;

  private net.playavalon.mythicdungeons.managers.InstanceContainer endContainer;

  private net.playavalon.mythicdungeons.listeners.DynamicListener elementEventHandler;

  private net.playavalon.mythicdungeons.listeners.DynamicListener instanceEventHandler;

  public net.playavalon.mythicdungeons.MythicDungeons();
    Code:
       0: aload_0
       1: invokespecial #123                // Method org/bukkit/plugin/java/JavaPlugin."<init>":()V
       4: aload_0
       5: invokestatic  #128                // InterfaceMethod net/kyori/adventure/text/minimessage/MiniMessage.miniMessage:()Lnet/kyori/adventure/text/minimessage/MiniMessage;
       8: putfield      #130                // Field miniMessage:Lnet/kyori/adventure/text/minimessage/MiniMessage;
      11: aload_0
      12: iconst_1
      13: putfield      #132                // Field supportsTeleportAsync:Z
      16: aload_0
      17: new           #134                // class net/playavalon/mythicdungeons/listeners/DynamicListener
      20: dup
      21: invokespecial #135                // Method net/playavalon/mythicdungeons/listeners/DynamicListener."<init>":()V
      24: putfield      #137                // Field elementEventHandler:Lnet/playavalon/mythicdungeons/listeners/DynamicListener;
      27: aload_0
      28: new           #134                // class net/playavalon/mythicdungeons/listeners/DynamicListener
      31: dup
      32: invokespecial #135                // Method net/playavalon/mythicdungeons/listeners/DynamicListener."<init>":()V
      35: putfield      #139                // Field instanceEventHandler:Lnet/playavalon/mythicdungeons/listeners/DynamicListener;
      38: return

  public void onLoad();
    Code:
       0: invokestatic  #147                // Method org/bukkit/Bukkit.getPluginManager:()Lorg/bukkit/plugin/PluginManager;
       3: ldc           #149                // String PacketEvents
       5: invokeinterface #155,  2          // InterfaceMethod org/bukkit/plugin/PluginManager.getPlugin:(Ljava/lang/String;)Lorg/bukkit/plugin/Plugin;
      10: ifnull        26
      13: aload_0
      14: invokestatic  #161                // Method io/github/retrooper/packetevents/factory/spigot/SpigotPacketEventsBuilder.build:(Lorg/bukkit/plugin/Plugin;)Lcom/github/retrooper/packetevents/PacketEventsAPI;
      17: invokestatic  #167                // Method com/github/retrooper/packetevents/PacketEvents.setAPI:(Lcom/github/retrooper/packetevents/PacketEventsAPI;)V
      20: invokestatic  #171                // Method com/github/retrooper/packetevents/PacketEvents.getAPI:()Lcom/github/retrooper/packetevents/PacketEventsAPI;
      23: invokevirtual #176                // Method com/github/retrooper/packetevents/PacketEventsAPI.load:()V
      26: invokestatic  #147                // Method org/bukkit/Bukkit.getPluginManager:()Lorg/bukkit/plugin/PluginManager;
      29: ldc           #178                // String MythicMobs
      31: invokeinterface #155,  2          // InterfaceMethod org/bukkit/plugin/PluginManager.getPlugin:(Ljava/lang/String;)Lorg/bukkit/plugin/Plugin;
      36: ifnull        42
      39: invokestatic  #183                // Method net/playavalon/mythicdungeons/mythic/DungeonSkillTriggers.initialiseTriggers:()V
      42: return

  public void onEnable();
    Code:
       0: aload_0
       1: putstatic     #196                // Field plugin:Lnet/playavalon/mythicdungeons/MythicDungeons;
       4: aload_0
       5: invokevirtual #199                // Method saveDefaultConfig:()V
       8: aload_0
       9: aload_0
      10: invokevirtual #203                // Method getConfig:()Lorg/bukkit/configuration/file/FileConfiguration;
      13: putfield      #205                // Field config:Lorg/bukkit/configuration/file/FileConfiguration;
      16: aload_0
      17: new           #207                // class org/bukkit/configuration/file/YamlConfiguration
      20: dup
      21: invokespecial #208                // Method org/bukkit/configuration/file/YamlConfiguration."<init>":()V
      24: putfield      #210                // Field defaultDungeonConfig:Lorg/bukkit/configuration/file/FileConfiguration;
      27: ldc           #212                // String <#9753f5>[Dungeons]
      29: invokestatic  #218                // Method net/playavalon/mythicdungeons/utility/helpers/Util.fullColorModern:(Ljava/lang/String;)Ljava/lang/String;
      32: putstatic     #220                // Field debugPrefix:Ljava/lang/String;
      35: ldc           #222                // String com.destroystokyo.paper.ParticleBuilder
      37: invokestatic  #228                // Method java/lang/Class.forName:(Ljava/lang/String;)Ljava/lang/Class;
      40: pop
      41: aload_0
      42: iconst_1
      43: putfield      #230                // Field paperSupport:Z
      46: ldc           #232                // String io.papermc.paper.entity.TeleportFlag
      48: invokestatic  #228                // Method java/lang/Class.forName:(Ljava/lang/String;)Ljava/lang/Class;
      51: pop
      52: aload_0
      53: iconst_1
      54: putfield      #234                // Field supportsTeleportFlags:Z
      57: ldc           #236                // String org.bukkit.entity.Entity
      59: invokestatic  #228                // Method java/lang/Class.forName:(Ljava/lang/String;)Ljava/lang/Class;
      62: astore_1
      63: aload_1
      64: ldc           #238                // String teleportAsync
      66: iconst_3
      67: anewarray     #224                // class java/lang/Class
      70: dup
      71: iconst_0
      72: ldc           #240                // class org/bukkit/Location
      74: aastore
      75: dup
      76: iconst_1
      77: ldc           #11                 // class org/bukkit/event/player/PlayerTeleportEvent$TeleportCause
      79: aastore
      80: dup
      81: iconst_2
      82: ldc           #242                // class "[Lio/papermc/paper/entity/TeleportFlag;"
      84: aastore
      85: invokevirtual #246                // Method java/lang/Class.getMethod:(Ljava/lang/String;[Ljava/lang/Class;)Ljava/lang/reflect/Method;
      88: pop
      89: goto          98
      92: astore_1
      93: aload_0
      94: iconst_0
      95: putfield      #132                // Field supportsTeleportAsync:Z
      98: goto          102
     101: astore_1
     102: goto          120
     105: astore_1
     106: getstatic     #220                // Field debugPrefix:Ljava/lang/String;
     109: invokedynamic #259,  0            // InvokeDynamic #0:makeConcatWithConstants:(Ljava/lang/String;)Ljava/lang/String;
     114: invokestatic  #218                // Method net/playavalon/mythicdungeons/utility/helpers/Util.fullColorModern:(Ljava/lang/String;)Ljava/lang/String;
     117: invokestatic  #265                // Method net/playavalon/mythicdungeons/utility/helpers/MessageUtils.log:(Ljava/lang/String;)V
     120: invokestatic  #271                // Method net/playavalon/mythicdungeons/utility/ServerVersion.get:()Lnet/playavalon/mythicdungeons/utility/ServerVersion;
     123: getstatic     #275                // Field net/playavalon/mythicdungeons/utility/ServerVersion.v1_19_3:Lnet/playavalon/mythicdungeons/utility/ServerVersion;
     126: invokevirtual #279                // Method net/playavalon/mythicdungeons/utility/ServerVersion.isAfterOrEqual:(Lnet/playavalon/mythicdungeons/utility/ServerVersion;)Z
     129: ifne          160
     132: getstatic     #220                // Field debugPrefix:Ljava/lang/String;
     135: invokedynamic #282,  0            // InvokeDynamic #1:makeConcatWithConstants:(Ljava/lang/String;)Ljava/lang/String;
     140: invokestatic  #218                // Method net/playavalon/mythicdungeons/utility/helpers/Util.fullColorModern:(Ljava/lang/String;)Ljava/lang/String;
     143: invokestatic  #265                // Method net/playavalon/mythicdungeons/utility/helpers/MessageUtils.log:(Ljava/lang/String;)V
     146: getstatic     #220                // Field debugPrefix:Ljava/lang/String;
     149: invokedynamic #285,  0            // InvokeDynamic #2:makeConcatWithConstants:(Ljava/lang/String;)Ljava/lang/String;
     154: invokestatic  #218                // Method net/playavalon/mythicdungeons/utility/helpers/Util.fullColorModern:(Ljava/lang/String;)Ljava/lang/String;
     157: invokestatic  #265                // Method net/playavalon/mythicdungeons/utility/helpers/MessageUtils.log:(Ljava/lang/String;)V
     160: invokestatic  #290                // Method net/playavalon/mythicdungeons/utility/helpers/ReflectionUtils.prepMemoryLeakKiller:()V
     163: aload_0
     164: new           #292                // class java/io/File
     167: dup
     168: getstatic     #196                // Field plugin:Lnet/playavalon/mythicdungeons/MythicDungeons;
     171: invokevirtual #296                // Method getDataFolder:()Ljava/io/File;
     174: ldc_w         #298                // String maps
     177: invokespecial #301                // Method java/io/File."<init>":(Ljava/io/File;Ljava/lang/String;)V
     180: putfield      #303                // Field dungeonFiles:Ljava/io/File;
     183: aload_0
     184: new           #292                // class java/io/File
     187: dup
     188: getstatic     #196                // Field plugin:Lnet/playavalon/mythicdungeons/MythicDungeons;
     191: invokevirtual #296                // Method getDataFolder:()Ljava/io/File;
     194: ldc_w         #305                // String backups
     197: invokespecial #301                // Method java/io/File."<init>":(Ljava/io/File;Ljava/lang/String;)V
     200: putfield      #307                // Field backupFolder:Ljava/io/File;
     203: aload_0
     204: getfield      #307                // Field backupFolder:Ljava/io/File;
     207: invokevirtual #311                // Method java/io/File.exists:()Z
     210: ifeq          223
     213: aload_0
     214: getfield      #307                // Field backupFolder:Ljava/io/File;
     217: invokevirtual #314                // Method java/io/File.isDirectory:()Z
     220: ifne          231
     223: aload_0
     224: getfield      #307                // Field backupFolder:Ljava/io/File;
     227: invokevirtual #317                // Method java/io/File.mkdir:()Z
     230: pop
     231: aload_0
     232: new           #292                // class java/io/File
     235: dup
     236: getstatic     #196                // Field plugin:Lnet/playavalon/mythicdungeons/MythicDungeons;
     239: invokevirtual #296                // Method getDataFolder:()Ljava/io/File;
     242: ldc_w         #319                // String globalplayerdata
     245: invokespecial #301                // Method java/io/File."<init>":(Ljava/io/File;Ljava/lang/String;)V
     248: putfield      #321                // Field playerDataFolder:Ljava/io/File;
     251: aload_0
     252: getfield      #321                // Field playerDataFolder:Ljava/io/File;
     255: invokevirtual #311                // Method java/io/File.exists:()Z
     258: ifne          269
     261: aload_0
     262: getfield      #321                // Field playerDataFolder:Ljava/io/File;
     265: invokevirtual #317                // Method java/io/File.mkdir:()Z
     268: pop
     269: invokestatic  #326                // Method net/playavalon/mythicdungeons/utility/helpers/LangUtils.init:()V
     272: invokestatic  #329                // Method net/playavalon/mythicdungeons/utility/helpers/LangUtils.saveMissingValues:()V
     275: aload_0
     276: aload_0
     277: getfield      #205                // Field config:Lorg/bukkit/configuration/file/FileConfiguration;
     280: ldc_w         #331                // String General.FunctionBuilderItem
     283: ldc_w         #333                // String FEATHER
     286: invokevirtual #339                // Method org/bukkit/configuration/file/FileConfiguration.getString:(Ljava/lang/String;Ljava/lang/String;)Ljava/lang/String;
     289: invokestatic  #345                // Method org/bukkit/Material.getMaterial:(Ljava/lang/String;)Lorg/bukkit/Material;
     292: putfield      #347                // Field functionBuilderMaterial:Lorg/bukkit/Material;
     295: goto          315
     298: astore_1
     299: ldc_w         #349                // String &cWARNING :: FunctionBuilderItem in config.yml must be a valid material! Using FEATHER by default...
     302: invokestatic  #218                // Method net/playavalon/mythicdungeons/utility/helpers/Util.fullColorModern:(Ljava/lang/String;)Ljava/lang/String;
     305: invokestatic  #265                // Method net/playavalon/mythicdungeons/utility/helpers/MessageUtils.log:(Ljava/lang/String;)V
     308: aload_0
     309: getstatic     #351                // Field org/bukkit/Material.FEATHER:Lorg/bukkit/Material;
     312: putfield      #347                // Field functionBuilderMaterial:Lorg/bukkit/Material;
     315: aload_0
     316: aload_0
     317: getfield      #205                // Field config:Lorg/bukkit/configuration/file/FileConfiguration;
     320: ldc_w         #353                // String General.RoomEditorItem
     323: ldc_w         #355                // String GOLDEN_AXE
     326: invokevirtual #339                // Method org/bukkit/configuration/file/FileConfiguration.getString:(Ljava/lang/String;Ljava/lang/String;)Ljava/lang/String;
     329: invokestatic  #345                // Method org/bukkit/Material.getMaterial:(Ljava/lang/String;)Lorg/bukkit/Material;
     332: putfield      #357                // Field roomEditorMaterial:Lorg/bukkit/Material;
     335: goto          355
     338: astore_1
     339: ldc_w         #359                // String &cWARNING :: RoomEditorItem in config.yml must be a valid material! Using GOLDEN_AXE by default...
     342: invokestatic  #218                // Method net/playavalon/mythicdungeons/utility/helpers/Util.fullColorModern:(Ljava/lang/String;)Ljava/lang/String;
     345: invokestatic  #265                // Method net/playavalon/mythicdungeons/utility/helpers/MessageUtils.log:(Ljava/lang/String;)V
     348: aload_0
     349: getstatic     #361                // Field org/bukkit/Material.GOLDEN_AXE:Lorg/bukkit/Material;
     352: putfield      #357                // Field roomEditorMaterial:Lorg/bukkit/Material;
     355: aload_0
     356: aload_0
     357: getfield      #205                // Field config:Lorg/bukkit/configuration/file/FileConfiguration;
     360: ldc_w         #363                // String General.StuckKillsPlayer
     363: iconst_0
     364: invokevirtual #367                // Method org/bukkit/configuration/file/FileConfiguration.getBoolean:(Ljava/lang/String;Z)Z
     367: putfield      #369                // Field stuckKillsPlayer:Z
     370: aload_0
     371: aload_0
     372: getfield      #205                // Field config:Lorg/bukkit/configuration/file/FileConfiguration;
     375: ldc_w         #371                // String Experimental.MovingBlocksMoveEntities
     378: iconst_0
     379: invokevirtual #367                // Method org/bukkit/configuration/file/FileConfiguration.getBoolean:(Ljava/lang/String;Z)Z
     382: putfield      #373                // Field inheritedVelocityEnabled:Z
     385: aload_0
     386: new           #375                // class net/playavalon/mythicdungeons/avngui/AvnAPI
     389: dup
     390: aload_0
     391: invokespecial #378                // Method net/playavalon/mythicdungeons/avngui/AvnAPI."<init>":(Lorg/bukkit/plugin/java/JavaPlugin;)V
     394: putfield      #380                // Field avnAPI:Lnet/playavalon/mythicdungeons/avngui/AvnAPI;
     397: iconst_0
     398: putstatic     #385                // Field net/playavalon/mythicdungeons/avngui/AvnGUI.debug:Z
     401: new           #387                // class net/playavalon/mythicdungeons/bstats/bukkit/Metrics
     404: dup
     405: aload_0
     406: sipush        16578
     409: invokespecial #390                // Method net/playavalon/mythicdungeons/bstats/bukkit/Metrics."<init>":(Lorg/bukkit/plugin/java/JavaPlugin;I)V
     412: astore_1
     413: ldc_w         #392                // class net/playavalon/mythicdungeons/dungeons/rewards/PlayerLootData
     416: invokestatic  #398                // Method org/bukkit/configuration/serialization/ConfigurationSerialization.registerClass:(Ljava/lang/Class;)V
     419: ldc_w         #400                // class net/playavalon/mythicdungeons/dungeons/rewards/LootCooldown
     422: invokestatic  #398                // Method org/bukkit/configuration/serialization/ConfigurationSerialization.registerClass:(Ljava/lang/Class;)V
     425: ldc_w         #402                // class net/playavalon/mythicdungeons/api/parents/FunctionTargetType
     428: invokestatic  #398                // Method org/bukkit/configuration/serialization/ConfigurationSerialization.registerClass:(Ljava/lang/Class;)V
     431: ldc_w         #404                // class net/playavalon/mythicdungeons/dungeons/rewards/LootTable
     434: invokestatic  #398                // Method org/bukkit/configuration/serialization/ConfigurationSerialization.registerClass:(Ljava/lang/Class;)V
     437: ldc_w         #406                // class net/playavalon/mythicdungeons/dungeons/rewards/LootTableItem
     440: invokestatic  #398                // Method org/bukkit/configuration/serialization/ConfigurationSerialization.registerClass:(Ljava/lang/Class;)V
     443: ldc_w         #408                // class net/playavalon/mythicdungeons/dungeons/variables/VariableEditMode
     446: invokestatic  #398                // Method org/bukkit/configuration/serialization/ConfigurationSerialization.registerClass:(Ljava/lang/Class;)V
     449: aload_0
     450: aload_0
     451: getfield      #205                // Field config:Lorg/bukkit/configuration/file/FileConfiguration;
     454: ldc_w         #410                // String General.PartyPlugin
     457: ldc_w         #412                // String Default
     460: invokevirtual #339                // Method org/bukkit/configuration/file/FileConfiguration.getString:(Ljava/lang/String;Ljava/lang/String;)Ljava/lang/String;
     463: putfield      #414                // Field partyPluginName:Ljava/lang/String;
     466: aload_0
     467: new           #416                // class net/playavalon/mythicdungeons/managers/PlayerManager
     470: dup
     471: invokespecial #417                // Method net/playavalon/mythicdungeons/managers/PlayerManager."<init>":()V
     474: putfield      #419                // Field playerManager:Lnet/playavalon/mythicdungeons/managers/PlayerManager;
     477: aload_0
     478: new           #421                // class net/playavalon/mythicdungeons/managers/PartyManager
     481: dup
     482: invokespecial #422                // Method net/playavalon/mythicdungeons/managers/PartyManager."<init>":()V
     485: putfield      #424                // Field partyManager:Lnet/playavalon/mythicdungeons/managers/PartyManager;
     488: aload_0
     489: new           #426                // class net/playavalon/mythicdungeons/managers/PartyProviderManager
     492: dup
     493: invokespecial #427                // Method net/playavalon/mythicdungeons/managers/PartyProviderManager."<init>":()V
     496: putfield      #429                // Field providerManager:Lnet/playavalon/mythicdungeons/managers/PartyProviderManager;
     499: aload_0
     500: new           #431                // class java/util/HashMap
     503: dup
     504: invokespecial #432                // Method java/util/HashMap."<init>":()V
     507: putfield      #434                // Field activeInstances:Ljava/util/Map;
     510: aload_0
     511: new           #436                // class net/playavalon/mythicdungeons/managers/FunctionManager
     514: dup
     515: invokespecial #437                // Method net/playavalon/mythicdungeons/managers/FunctionManager."<init>":()V
     518: putfield      #439                // Field functionManager:Lnet/playavalon/mythicdungeons/managers/FunctionManager;
     521: aload_0
     522: new           #441                // class net/playavalon/mythicdungeons/managers/TriggerManager
     525: dup
     526: invokespecial #442                // Method net/playavalon/mythicdungeons/managers/TriggerManager."<init>":()V
     529: putfield      #444                // Field triggerManager:Lnet/playavalon/mythicdungeons/managers/TriggerManager;
     532: aload_0
     533: new           #446                // class net/playavalon/mythicdungeons/managers/ConditionManager
     536: dup
     537: invokespecial #447                // Method net/playavalon/mythicdungeons/managers/ConditionManager."<init>":()V
     540: putfield      #449                // Field conditionManager:Lnet/playavalon/mythicdungeons/managers/ConditionManager;
     543: aload_0
     544: new           #451                // class net/playavalon/mythicdungeons/managers/QueueManager
     547: dup
     548: invokespecial #452                // Method net/playavalon/mythicdungeons/managers/QueueManager."<init>":()V
     551: putfield      #454                // Field queueManager:Lnet/playavalon/mythicdungeons/managers/QueueManager;
     554: aload_0
     555: new           #456                // class net/playavalon/mythicdungeons/managers/LootTableManager
     558: dup
     559: invokespecial #457                // Method net/playavalon/mythicdungeons/managers/LootTableManager."<init>":()V
     562: putfield      #459                // Field lootTableManager:Lnet/playavalon/mythicdungeons/managers/LootTableManager;
     565: aload_0
     566: new           #461                // class net/playavalon/mythicdungeons/managers/CommandManager
     569: dup
     570: aload_0
     571: invokespecial #464                // Method net/playavalon/mythicdungeons/managers/CommandManager."<init>":(Lnet/playavalon/mythicdungeons/MythicDungeons;)V
     574: putfield      #466                // Field commandManager:Lnet/playavalon/mythicdungeons/managers/CommandManager;
     577: aload_0
     578: new           #468                // class net/playavalon/mythicdungeons/managers/MovingBlockManager
     581: dup
     582: invokespecial #469                // Method net/playavalon/mythicdungeons/managers/MovingBlockManager."<init>":()V
     585: putfield      #471                // Field movingBlockManager:Lnet/playavalon/mythicdungeons/managers/MovingBlockManager;
     588: aload_0
     589: new           #473                // class net/playavalon/mythicdungeons/managers/SpectatorManager
     592: dup
     593: aload_0
     594: invokespecial #474                // Method net/playavalon/mythicdungeons/managers/SpectatorManager."<init>":(Lnet/playavalon/mythicdungeons/MythicDungeons;)V
     597: putfield      #476                // Field spectatorManager:Lnet/playavalon/mythicdungeons/managers/SpectatorManager;
     600: aload_0
     601: getfield      #230                // Field paperSupport:Z
     604: ifeq          636
     607: aload_0
     608: invokevirtual #480                // Method getLogger:()Ljava/util/logging/Logger;
     611: ldc_w         #482                // String Using PaperListener...
     614: invokevirtual #487                // Method java/util/logging/Logger.info:(Ljava/lang/String;)V
     617: invokestatic  #147                // Method org/bukkit/Bukkit.getPluginManager:()Lorg/bukkit/plugin/PluginManager;
     620: new           #489                // class net/playavalon/mythicdungeons/listeners/PaperListener
     623: dup
     624: invokespecial #490                // Method net/playavalon/mythicdungeons/listeners/PaperListener."<init>":()V
     627: aload_0
     628: invokeinterface #494,  3          // InterfaceMethod org/bukkit/plugin/PluginManager.registerEvents:(Lorg/bukkit/event/Listener;Lorg/bukkit/plugin/Plugin;)V
     633: goto          652
     636: invokestatic  #147                // Method org/bukkit/Bukkit.getPluginManager:()Lorg/bukkit/plugin/PluginManager;
     639: new           #496                // class net/playavalon/mythicdungeons/listeners/AvalonListener
     642: dup
     643: invokespecial #497                // Method net/playavalon/mythicdungeons/listeners/AvalonListener."<init>":()V
     646: aload_0
     647: invokeinterface #494,  3          // InterfaceMethod org/bukkit/plugin/PluginManager.registerEvents:(Lorg/bukkit/event/Listener;Lorg/bukkit/plugin/Plugin;)V
     652: invokestatic  #147                // Method org/bukkit/Bukkit.getPluginManager:()Lorg/bukkit/plugin/PluginManager;
     655: new           #499                // class net/playavalon/mythicdungeons/listeners/MythicPartyListener
     658: dup
     659: invokespecial #500                // Method net/playavalon/mythicdungeons/listeners/MythicPartyListener."<init>":()V
     662: aload_0
     663: invokeinterface #494,  3          // InterfaceMethod org/bukkit/plugin/PluginManager.registerEvents:(Lorg/bukkit/event/Listener;Lorg/bukkit/plugin/Plugin;)V
     668: aload_0
     669: getfield      #414                // Field partyPluginName:Ljava/lang/String;
     672: ldc_w         #412                // String Default
     675: invokevirtual #506                // Method java/lang/String.equalsIgnoreCase:(Ljava/lang/String;)Z
     678: ifne          694
     681: aload_0
     682: getfield      #414                // Field partyPluginName:Ljava/lang/String;
     685: ldc_w         #508                // String DungeonParties
     688: invokevirtual #506                // Method java/lang/String.equalsIgnoreCase:(Ljava/lang/String;)Z
     691: ifeq          725
     694: aload_0
     695: iconst_1
     696: putfield      #510                // Field partiesEnabled:Z
     699: aload_0
     700: new           #512                // class net/playavalon/mythicdungeons/managers/PartyRecruitmentManager
     703: dup
     704: invokespecial #513                // Method net/playavalon/mythicdungeons/managers/PartyRecruitmentManager."<init>":()V
     707: putfield      #515                // Field listingManager:Lnet/playavalon/mythicdungeons/managers/PartyRecruitmentManager;
     710: ldc_w         #517                // String Using default parties! Enabled party support.
     713: invokestatic  #218                // Method net/playavalon/mythicdungeons/utility/helpers/Util.fullColorModern:(Ljava/lang/String;)Ljava/lang/String;
     716: invokestatic  #265                // Method net/playavalon/mythicdungeons/utility/helpers/MessageUtils.log:(Ljava/lang/String;)V
     719: invokestatic  #522                // Method net/playavalon/mythicdungeons/gui/RecruitGUIHandler.initPartyBrowser:()V
     722: goto          1175
     725: invokestatic  #147                // Method org/bukkit/Bukkit.getPluginManager:()Lorg/bukkit/plugin/PluginManager;
     728: aload_0
     729: getfield      #414                // Field partyPluginName:Ljava/lang/String;
     732: invokeinterface #155,  2          // InterfaceMethod org/bukkit/plugin/PluginManager.getPlugin:(Ljava/lang/String;)Lorg/bukkit/plugin/Plugin;
     737: ifnonnull     767
     740: aload_0
     741: getfield      #414                // Field partyPluginName:Ljava/lang/String;
     744: ldc_w         #524                // String paf
     747: invokevirtual #506                // Method java/lang/String.equalsIgnoreCase:(Ljava/lang/String;)Z
     750: ifeq          1160
     753: invokestatic  #147                // Method org/bukkit/Bukkit.getPluginManager:()Lorg/bukkit/plugin/PluginManager;
     756: ldc_w         #526                // String PartyAndFriendsGUI
     759: invokeinterface #155,  2          // InterfaceMethod org/bukkit/plugin/PluginManager.getPlugin:(Ljava/lang/String;)Lorg/bukkit/plugin/Plugin;
     764: ifnull        1160
     767: aload_0
     768: iconst_1
     769: putfield      #510                // Field partiesEnabled:Z
     772: aload_0
     773: getfield      #414                // Field partyPluginName:Ljava/lang/String;
     776: invokevirtual #530                // Method java/lang/String.toLowerCase:()Ljava/lang/String;
     779: astore_2
     780: iconst_m1
     781: istore_3
     782: aload_2
     783: invokevirtual #534                // Method java/lang/String.hashCode:()I
     786: lookupswitch  { // 3

           -1220753880: 820

            -792933884: 835

                110741: 850
               default: 862
          }
     820: aload_2
     821: ldc_w         #536                // String heroes
     824: invokevirtual #540                // Method java/lang/String.equals:(Ljava/lang/Object;)Z
     827: ifeq          862
     830: iconst_0
     831: istore_3
     832: goto          862
     835: aload_2
     836: ldc_w         #542                // String parties
     839: invokevirtual #540                // Method java/lang/String.equals:(Ljava/lang/Object;)Z
     842: ifeq          862
     845: iconst_1
     846: istore_3
     847: goto          862
     850: aload_2
     851: ldc_w         #524                // String paf
     854: invokevirtual #540                // Method java/lang/String.equals:(Ljava/lang/Object;)Z
     857: ifeq          862
     860: iconst_2
     861: istore_3
     862: iload_3
     863: tableswitch   { // 0 to 2

                     0: 888

                     1: 932

                     2: 976
               default: 1076
          }
     888: aload_0
     889: iconst_1
     890: putfield      #544                // Field thirdPartyProvider:Z
     893: aload_0
     894: new           #512                // class net/playavalon/mythicdungeons/managers/PartyRecruitmentManager
     897: dup
     898: invokespecial #513                // Method net/playavalon/mythicdungeons/managers/PartyRecruitmentManager."<init>":()V
     901: putfield      #515                // Field listingManager:Lnet/playavalon/mythicdungeons/managers/PartyRecruitmentManager;
     904: aload_0
     905: invokestatic  #550                // Method com/herocraftonline/heroes/Heroes.getInstance:()Lcom/herocraftonline/heroes/Heroes;
     908: putfield      #552                // Field heroesApi:Lcom/herocraftonline/heroes/Heroes;
     911: invokestatic  #147                // Method org/bukkit/Bukkit.getPluginManager:()Lorg/bukkit/plugin/PluginManager;
     914: new           #554                // class net/playavalon/mythicdungeons/listeners/partylisteners/HeroesListener
     917: dup
     918: invokespecial #555                // Method net/playavalon/mythicdungeons/listeners/partylisteners/HeroesListener."<init>":()V
     921: getstatic     #196                // Field plugin:Lnet/playavalon/mythicdungeons/MythicDungeons;
     924: invokeinterface #494,  3          // InterfaceMethod org/bukkit/plugin/PluginManager.registerEvents:(Lorg/bukkit/event/Listener;Lorg/bukkit/plugin/Plugin;)V
     929: goto          1125
     932: aload_0
     933: iconst_1
     934: putfield      #544                // Field thirdPartyProvider:Z
     937: aload_0
     938: new           #512                // class net/playavalon/mythicdungeons/managers/PartyRecruitmentManager
     941: dup
     942: invokespecial #513                // Method net/playavalon/mythicdungeons/managers/PartyRecruitmentManager."<init>":()V
     945: putfield      #515                // Field listingManager:Lnet/playavalon/mythicdungeons/managers/PartyRecruitmentManager;
     948: aload_0
     949: invokestatic  #561                // Method com/alessiodp/parties/api/Parties.getApi:()Lcom/alessiodp/parties/api/interfaces/PartiesAPI;
     952: putfield      #563                // Field partiesAPI:Lcom/alessiodp/parties/api/interfaces/PartiesAPI;
     955: invokestatic  #147                // Method org/bukkit/Bukkit.getPluginManager:()Lorg/bukkit/plugin/PluginManager;
     958: new           #565                // class net/playavalon/mythicdungeons/listeners/partylisteners/PartiesListener
     961: dup
     962: invokespecial #566                // Method net/playavalon/mythicdungeons/listeners/partylisteners/PartiesListener."<init>":()V
     965: getstatic     #196                // Field plugin:Lnet/playavalon/mythicdungeons/MythicDungeons;
     968: invokeinterface #494,  3          // InterfaceMethod org/bukkit/plugin/PluginManager.registerEvents:(Lorg/bukkit/event/Listener;Lorg/bukkit/plugin/Plugin;)V
     973: goto          1125
     976: aload_0
     977: iconst_1
     978: putfield      #544                // Field thirdPartyProvider:Z
     981: aload_0
     982: new           #512                // class net/playavalon/mythicdungeons/managers/PartyRecruitmentManager
     985: dup
     986: invokespecial #513                // Method net/playavalon/mythicdungeons/managers/PartyRecruitmentManager."<init>":()V
     989: putfield      #515                // Field listingManager:Lnet/playavalon/mythicdungeons/managers/PartyRecruitmentManager;
     992: new           #568                // class net/playavalon/mythicdungeons/listeners/partylisteners/PAFListener
     995: dup
     996: invokespecial #569                // Method net/playavalon/mythicdungeons/listeners/partylisteners/PAFListener."<init>":()V
     999: astore        4
    1001: ldc_w         #571                // String de.simonsator.partyandfriends.spigot.api.events.PartyEventManager
    1004: invokestatic  #228                // Method java/lang/Class.forName:(Ljava/lang/String;)Ljava/lang/Class;
    1007: ldc_w         #573                // String registerPartyEventListener
    1010: iconst_1
    1011: anewarray     #224                // class java/lang/Class
    1014: dup
    1015: iconst_0
    1016: ldc_w         #575                // String de.simonsator.partyandfriends.spigot.api.events.PartyEventListenerInterface
    1019: invokestatic  #228                // Method java/lang/Class.forName:(Ljava/lang/String;)Ljava/lang/Class;
    1022: aastore
    1023: invokevirtual #246                // Method java/lang/Class.getMethod:(Ljava/lang/String;[Ljava/lang/Class;)Ljava/lang/reflect/Method;
    1026: aconst_null
    1027: iconst_1
    1028: anewarray     #577                // class java/lang/Object
    1031: dup
    1032: iconst_0
    1033: aload         4
    1035: aastore
    1036: invokevirtual #583                // Method java/lang/reflect/Method.invoke:(Ljava/lang/Object;[Ljava/lang/Object;)Ljava/lang/Object;
    1039: pop
    1040: goto          1060
    1043: astore        5
    1045: invokestatic  #587                // Method inst:()Lnet/playavalon/mythicdungeons/MythicDungeons;
    1048: invokevirtual #480                // Method getLogger:()Ljava/util/logging/Logger;
    1051: ldc_w         #589                // String &cERROR :: Failed to register PartyAndFriends event listener!
    1054: invokestatic  #218                // Method net/playavalon/mythicdungeons/utility/helpers/Util.fullColorModern:(Ljava/lang/String;)Ljava/lang/String;
    1057: invokevirtual #487                // Method java/util/logging/Logger.info:(Ljava/lang/String;)V
    1060: invokestatic  #147                // Method org/bukkit/Bukkit.getPluginManager:()Lorg/bukkit/plugin/PluginManager;
    1063: aload         4
    1065: getstatic     #196                // Field plugin:Lnet/playavalon/mythicdungeons/MythicDungeons;
    1068: invokeinterface #494,  3          // InterfaceMethod org/bukkit/plugin/PluginManager.registerEvents:(Lorg/bukkit/event/Listener;Lorg/bukkit/plugin/Plugin;)V
    1073: goto          1125
    1076: invokestatic  #147                // Method org/bukkit/Bukkit.getPluginManager:()Lorg/bukkit/plugin/PluginManager;
    1079: aload_0
    1080: getfield      #414                // Field partyPluginName:Ljava/lang/String;
    1083: invokeinterface #155,  2          // InterfaceMethod org/bukkit/plugin/PluginManager.getPlugin:(Ljava/lang/String;)Lorg/bukkit/plugin/Plugin;
    1088: ifnonnull     1114
    1091: aload_0
    1092: iconst_0
    1093: putfield      #510                // Field partiesEnabled:Z
    1096: aload_0
    1097: getfield      #414                // Field partyPluginName:Ljava/lang/String;
    1100: invokedynamic #592,  0            // InvokeDynamic #3:makeConcatWithConstants:(Ljava/lang/String;)Ljava/lang/String;
    1105: invokestatic  #218                // Method net/playavalon/mythicdungeons/utility/helpers/Util.fullColorModern:(Ljava/lang/String;)Ljava/lang/String;
    1108: invokestatic  #265                // Method net/playavalon/mythicdungeons/utility/helpers/MessageUtils.log:(Ljava/lang/String;)V
    1111: goto          1125
    1114: aload_0
    1115: new           #512                // class net/playavalon/mythicdungeons/managers/PartyRecruitmentManager
    1118: dup
    1119: invokespecial #513                // Method net/playavalon/mythicdungeons/managers/PartyRecruitmentManager."<init>":()V
    1122: putfield      #515                // Field listingManager:Lnet/playavalon/mythicdungeons/managers/PartyRecruitmentManager;
    1125: aload_0
    1126: getfield      #510                // Field partiesEnabled:Z
    1129: ifeq          1175
    1132: aload_0
    1133: getfield      #414                // Field partyPluginName:Ljava/lang/String;
    1136: invokedynamic #595,  0            // InvokeDynamic #4:makeConcatWithConstants:(Ljava/lang/String;)Ljava/lang/String;
    1141: invokestatic  #218                // Method net/playavalon/mythicdungeons/utility/helpers/Util.fullColorModern:(Ljava/lang/String;)Ljava/lang/String;
    1144: invokestatic  #265                // Method net/playavalon/mythicdungeons/utility/helpers/MessageUtils.log:(Ljava/lang/String;)V
    1147: invokestatic  #522                // Method net/playavalon/mythicdungeons/gui/RecruitGUIHandler.initPartyBrowser:()V
    1150: aload_0
    1151: getfield      #414                // Field partyPluginName:Ljava/lang/String;
    1154: invokestatic  #600                // Method net/playavalon/mythicdungeons/player/party/PartyWrapper.setPartyPlugin:(Ljava/lang/String;)V
    1157: goto          1175
    1160: aload_0
    1161: getfield      #414                // Field partyPluginName:Ljava/lang/String;
    1164: invokedynamic #603,  0            // InvokeDynamic #5:makeConcatWithConstants:(Ljava/lang/String;)Ljava/lang/String;
    1169: invokestatic  #218                // Method net/playavalon/mythicdungeons/utility/helpers/Util.fullColorModern:(Ljava/lang/String;)Ljava/lang/String;
    1172: invokestatic  #265                // Method net/playavalon/mythicdungeons/utility/helpers/MessageUtils.log:(Ljava/lang/String;)V
    1175: aload_0
    1176: new           #605                // class net/playavalon/mythicdungeons/managers/HotbarMenuManager
    1179: dup
    1180: invokespecial #606                // Method net/playavalon/mythicdungeons/managers/HotbarMenuManager."<init>":()V
    1183: putfield      #608                // Field hotbarMenus:Lnet/playavalon/mythicdungeons/managers/HotbarMenuManager;
    1186: invokestatic  #147                // Method org/bukkit/Bukkit.getPluginManager:()Lorg/bukkit/plugin/PluginManager;
    1189: aload_0
    1190: getfield      #608                // Field hotbarMenus:Lnet/playavalon/mythicdungeons/managers/HotbarMenuManager;
    1193: aload_0
    1194: invokeinterface #494,  3          // InterfaceMethod org/bukkit/plugin/PluginManager.registerEvents:(Lorg/bukkit/event/Listener;Lorg/bukkit/plugin/Plugin;)V
    1199: invokestatic  #147                // Method org/bukkit/Bukkit.getPluginManager:()Lorg/bukkit/plugin/PluginManager;
    1202: ldc           #178                // String MythicMobs
    1204: invokeinterface #155,  2          // InterfaceMethod org/bukkit/plugin/PluginManager.getPlugin:(Ljava/lang/String;)Lorg/bukkit/plugin/Plugin;
    1209: ifnull        1251
    1212: ldc_w         #610                // String &dMythicMobs plugin found! Enabled MythicMobs support.
    1215: invokestatic  #218                // Method net/playavalon/mythicdungeons/utility/helpers/Util.fullColorModern:(Ljava/lang/String;)Ljava/lang/String;
    1218: invokestatic  #265                // Method net/playavalon/mythicdungeons/utility/helpers/MessageUtils.log:(Ljava/lang/String;)V
    1221: aload_0
    1222: invokestatic  #615                // Method io/lumine/mythic/bukkit/MythicBukkit.inst:()Lio/lumine/mythic/bukkit/MythicBukkit;
    1225: putfield      #617                // Field mythicApi:Lio/lumine/mythic/bukkit/MythicBukkit;
    1228: invokestatic  #147                // Method org/bukkit/Bukkit.getPluginManager:()Lorg/bukkit/plugin/PluginManager;
    1231: new           #619                // class net/playavalon/mythicdungeons/listeners/MythicListener
    1234: dup
    1235: invokespecial #620                // Method net/playavalon/mythicdungeons/listeners/MythicListener."<init>":()V
    1238: aload_0
    1239: invokeinterface #494,  3          // InterfaceMethod org/bukkit/plugin/PluginManager.registerEvents:(Lorg/bukkit/event/Listener;Lorg/bukkit/plugin/Plugin;)V
    1244: aload_0
    1245: getfield      #617                // Field mythicApi:Lio/lumine/mythic/bukkit/MythicBukkit;
    1248: invokestatic  #626                // Method net/playavalon/mythicdungeons/compatibility/MythicMobsBridge.registerPlaceholders:(Lio/lumine/mythic/bukkit/MythicBukkit;)V
    1251: invokestatic  #147                // Method org/bukkit/Bukkit.getPluginManager:()Lorg/bukkit/plugin/PluginManager;
    1254: ldc_w         #628                // String PlaceholderAPI
    1257: invokeinterface #155,  2          // InterfaceMethod org/bukkit/plugin/PluginManager.getPlugin:(Ljava/lang/String;)Lorg/bukkit/plugin/Plugin;
    1262: ifnull        1277
    1265: new           #630                // class net/playavalon/mythicdungeons/listeners/PAPIPlaceholders
    1268: dup
    1269: aload_0
    1270: invokespecial #631                // Method net/playavalon/mythicdungeons/listeners/PAPIPlaceholders."<init>":(Lnet/playavalon/mythicdungeons/MythicDungeons;)V
    1273: invokevirtual #634                // Method net/playavalon/mythicdungeons/listeners/PAPIPlaceholders.register:()Z
    1276: pop
    1277: invokestatic  #147                // Method org/bukkit/Bukkit.getPluginManager:()Lorg/bukkit/plugin/PluginManager;
    1280: ldc_w         #636                // String Heroes
    1283: invokeinterface #155,  2          // InterfaceMethod org/bukkit/plugin/PluginManager.getPlugin:(Ljava/lang/String;)Lorg/bukkit/plugin/Plugin;
    1288: ifnull        1298
    1291: aload_0
    1292: invokestatic  #550                // Method com/herocraftonline/heroes/Heroes.getInstance:()Lcom/herocraftonline/heroes/Heroes;
    1295: putfield      #552                // Field heroesApi:Lcom/herocraftonline/heroes/Heroes;
    1298: invokestatic  #147                // Method org/bukkit/Bukkit.getPluginManager:()Lorg/bukkit/plugin/PluginManager;
    1301: ldc_w         #638                // String Citizens
    1304: invokeinterface #155,  2          // InterfaceMethod org/bukkit/plugin/PluginManager.getPlugin:(Ljava/lang/String;)Lorg/bukkit/plugin/Plugin;
    1309: ifnull        1341
    1312: aload_0
    1313: invokestatic  #147                // Method org/bukkit/Bukkit.getPluginManager:()Lorg/bukkit/plugin/PluginManager;
    1316: ldc_w         #638                // String Citizens
    1319: invokeinterface #155,  2          // InterfaceMethod org/bukkit/plugin/PluginManager.getPlugin:(Ljava/lang/String;)Lorg/bukkit/plugin/Plugin;
    1324: checkcast     #640                // class net/citizensnpcs/Citizens
    1327: putfield      #642                // Field citizensApi:Lnet/citizensnpcs/Citizens;
    1330: aload_0
    1331: new           #644                // class net/playavalon/mythicdungeons/compatibility/citizens/MythicNPCRegistry
    1334: dup
    1335: invokespecial #645                // Method net/playavalon/mythicdungeons/compatibility/citizens/MythicNPCRegistry."<init>":()V
    1338: putfield      #647                // Field mythicNPCRegistry:Lnet/playavalon/mythicdungeons/compatibility/citizens/MythicNPCRegistry;
    1341: invokestatic  #147                // Method org/bukkit/Bukkit.getPluginManager:()Lorg/bukkit/plugin/PluginManager;
    1344: ldc           #149                // String PacketEvents
    1346: invokeinterface #155,  2          // InterfaceMethod org/bukkit/plugin/PluginManager.getPlugin:(Ljava/lang/String;)Lorg/bukkit/plugin/Plugin;
    1351: ifnull        1368
    1354: aload_0
    1355: invokestatic  #171                // Method com/github/retrooper/packetevents/PacketEvents.getAPI:()Lcom/github/retrooper/packetevents/PacketEventsAPI;
    1358: putfield      #649                // Field packetEvents:Lcom/github/retrooper/packetevents/PacketEventsAPI;
    1361: aload_0
    1362: getfield      #649                // Field packetEvents:Lcom/github/retrooper/packetevents/PacketEventsAPI;
    1365: invokevirtual #650                // Method com/github/retrooper/packetevents/PacketEventsAPI.init:()V
    1368: invokestatic  #147                // Method org/bukkit/Bukkit.getPluginManager:()Lorg/bukkit/plugin/PluginManager;
    1371: ldc_w         #652                // String BetonQuest
    1374: invokeinterface #155,  2          // InterfaceMethod org/bukkit/plugin/PluginManager.getPlugin:(Ljava/lang/String;)Lorg/bukkit/plugin/Plugin;
    1379: astore_2
    1380: aload_2
    1381: ifnull        1485
    1384: aload_2
    1385: invokeinterface #658,  1          // InterfaceMethod org/bukkit/plugin/Plugin.getDescription:()Lorg/bukkit/plugin/PluginDescriptionFile;
    1390: invokevirtual #663                // Method org/bukkit/plugin/PluginDescriptionFile.getVersion:()Ljava/lang/String;
    1393: ldc_w         #665                // String 2
    1396: invokevirtual #668                // Method java/lang/String.startsWith:(Ljava/lang/String;)Z
    1399: ifeq          1420
    1402: aload_2
    1403: invokeinterface #658,  1          // InterfaceMethod org/bukkit/plugin/Plugin.getDescription:()Lorg/bukkit/plugin/PluginDescriptionFile;
    1408: invokevirtual #663                // Method org/bukkit/plugin/PluginDescriptionFile.getVersion:()Ljava/lang/String;
    1411: ldc_w         #670                // String 3
    1414: invokevirtual #668                // Method java/lang/String.startsWith:(Ljava/lang/String;)Z
    1417: ifeq          1441
    1420: ldc_w         #672                // String &eWARNING :: Incompatible BetonQuest version! You must use version 2.0 or higher!
    1423: invokestatic  #218                // Method net/playavalon/mythicdungeons/utility/helpers/Util.fullColorModern:(Ljava/lang/String;)Ljava/lang/String;
    1426: invokestatic  #265                // Method net/playavalon/mythicdungeons/utility/helpers/MessageUtils.log:(Ljava/lang/String;)V
    1429: ldc_w         #674                // String &cBetonQuest compatibility has not been enabled.
    1432: invokestatic  #218                // Method net/playavalon/mythicdungeons/utility/helpers/Util.fullColorModern:(Ljava/lang/String;)Ljava/lang/String;
    1435: invokestatic  #265                // Method net/playavalon/mythicdungeons/utility/helpers/MessageUtils.log:(Ljava/lang/String;)V
    1438: goto          1485
    1441: invokestatic  #679                // Method org/betonquest/betonquest/BetonQuest.getInstance:()Lorg/betonquest/betonquest/BetonQuest;
    1444: ifnull        1485
    1447: ldc_w         #681                // String &dBetonQuest plugin found! Enabled BetonQuest support.
    1450: invokestatic  #218                // Method net/playavalon/mythicdungeons/utility/helpers/Util.fullColorModern:(Ljava/lang/String;)Ljava/lang/String;
    1453: invokestatic  #265                // Method net/playavalon/mythicdungeons/utility/helpers/MessageUtils.log:(Ljava/lang/String;)V
    1456: aload_0
    1457: iconst_1
    1458: putfield      #683                // Field betonEnabled:Z
    1461: invokestatic  #679                // Method org/betonquest/betonquest/BetonQuest.getInstance:()Lorg/betonquest/betonquest/BetonQuest;
    1464: ldc_w         #685                // String finishdungeon
    1467: ldc_w         #687                // class net/playavalon/mythicdungeons/compatibility/betonquest/objectives/CompleteDungeonObjective
    1470: invokevirtual #691                // Method org/betonquest/betonquest/BetonQuest.registerObjectives:(Ljava/lang/String;Ljava/lang/Class;)V
    1473: invokestatic  #679                // Method org/betonquest/betonquest/BetonQuest.getInstance:()Lorg/betonquest/betonquest/BetonQuest;
    1476: ldc_w         #693                // String playdungeon
    1479: ldc_w         #695                // class net/playavalon/mythicdungeons/compatibility/betonquest/events/EnterDungeonEvent
    1482: invokevirtual #697                // Method org/betonquest/betonquest/BetonQuest.registerEvents:(Ljava/lang/String;Ljava/lang/Class;)V
    1485: aload_0
    1486: invokevirtual #700                // Method setupEconomy:()Z
    1489: pop
    1490: aload_0
    1491: invokestatic  #705                // InterfaceMethod net/playavalon/mythicdungeons/api/config/AvalonSerializable.register:(Lorg/bukkit/plugin/Plugin;)V
    1494: aload_0
    1495: getfield      #476                // Field spectatorManager:Lnet/playavalon/mythicdungeons/managers/SpectatorManager;
    1498: invokevirtual #708                // Method net/playavalon/mythicdungeons/managers/SpectatorManager.isLegacy:()Z
    1501: ifne          1514
    1504: aload_0
    1505: ldc_w         #710                // class net/playavalon/mythicdungeons/listeners/dungeonlisteners/PacketEventsPlayListener
    1508: invokevirtual #713                // Method registerInstanceListener:(Ljava/lang/Class;)V
    1511: goto          1521
    1514: aload_0
    1515: ldc_w         #715                // class net/playavalon/mythicdungeons/listeners/dungeonlisteners/PlayListener
    1518: invokevirtual #713                // Method registerInstanceListener:(Ljava/lang/Class;)V
    1521: aload_0
    1522: ldc_w         #717                // class net/playavalon/mythicdungeons/listeners/dungeonlisteners/EditListener
    1525: invokevirtual #713                // Method registerInstanceListener:(Ljava/lang/Class;)V
    1528: aload_0
    1529: ldc_w         #719                // class net/playavalon/mythicdungeons/dungeons/dungeontypes/DungeonClassic
    1532: ldc_w         #721                // String classic
    1535: iconst_1
    1536: anewarray     #502                // class java/lang/String
    1539: dup
    1540: iconst_0
    1541: ldc_w         #723                // String default
    1544: aastore
    1545: invokevirtual #727                // Method registerDungeonType:(Ljava/lang/Class;Ljava/lang/String;[Ljava/lang/String;)V
    1548: aload_0
    1549: ldc_w         #729                // class net/playavalon/mythicdungeons/dungeons/dungeontypes/DungeonContinuous
    1552: ldc_w         #731                // String continuous
    1555: iconst_1
    1556: anewarray     #502                // class java/lang/String
    1559: dup
    1560: iconst_0
    1561: ldc_w         #733                // String ongoing
    1564: aastore
    1565: invokevirtual #727                // Method registerDungeonType:(Ljava/lang/Class;Ljava/lang/String;[Ljava/lang/String;)V
    1568: aload_0
    1569: ldc_w         #735                // class net/playavalon/mythicdungeons/dungeons/dungeontypes/DungeonProcedural
    1572: ldc_w         #737                // String procedural
    1575: iconst_2
    1576: anewarray     #502                // class java/lang/String
    1579: dup
    1580: iconst_0
    1581: ldc_w         #739                // String generated
    1584: aastore
    1585: dup
    1586: iconst_1
    1587: ldc_w         #741                // String room
    1590: aastore
    1591: invokevirtual #727                // Method registerDungeonType:(Ljava/lang/Class;Ljava/lang/String;[Ljava/lang/String;)V
    1594: aload_0
    1595: ldc_w         #743                // class net/playavalon/mythicdungeons/api/generation/layout/LayoutMinecrafty
    1598: ldc_w         #745                // String minecrafty
    1601: iconst_3
    1602: anewarray     #502                // class java/lang/String
    1605: dup
    1606: iconst_0
    1607: ldc_w         #747                // String minecraft
    1610: aastore
    1611: dup
    1612: iconst_1
    1613: ldc_w         #749                // String vanilla
    1616: aastore
    1617: dup
    1618: iconst_2
    1619: ldc_w         #751                // String random
    1622: aastore
    1623: invokevirtual #754                // Method registerLayout:(Ljava/lang/Class;Ljava/lang/String;[Ljava/lang/String;)V
    1626: aload_0
    1627: ldc_w         #756                // class net/playavalon/mythicdungeons/api/generation/layout/LayoutBranching
    1630: ldc_w         #758                // String branching
    1633: iconst_2
    1634: anewarray     #502                // class java/lang/String
    1637: dup
    1638: iconst_0
    1639: ldc_w         #760                // String branch
    1642: aastore
    1643: dup
    1644: iconst_1
    1645: ldc_w         #762                // String linear
    1648: aastore
    1649: invokevirtual #754                // Method registerLayout:(Ljava/lang/Class;Ljava/lang/String;[Ljava/lang/String;)V
    1652: aload_0
    1653: ldc_w         #764                // String net.playavalon.mythicdungeons.dungeons.functions
    1656: invokevirtual #767                // Method registerFunctions:(Ljava/lang/String;)V
    1659: aload_0
    1660: ldc_w         #769                // class net/playavalon/mythicdungeons/dungeons/functions/rewards/FunctionReward
    1663: invokevirtual #772                // Method registerFunction:(Ljava/lang/Class;)V
    1666: aload_0
    1667: ldc_w         #774                // class net/playavalon/mythicdungeons/dungeons/functions/rewards/FunctionRandomReward
    1670: invokevirtual #772                // Method registerFunction:(Ljava/lang/Class;)V
    1673: aload_0
    1674: ldc_w         #776                // String net.playavalon.mythicdungeons.dungeons.triggers
    1677: invokevirtual #779                // Method registerTriggers:(Ljava/lang/String;)V
    1680: aload_0
    1681: ldc_w         #781                // String net.playavalon.mythicdungeons.dungeons.conditions
    1684: invokevirtual #784                // Method registerConditions:(Ljava/lang/String;)V
    1687: aload_0
    1688: getfield      #617                // Field mythicApi:Lio/lumine/mythic/bukkit/MythicBukkit;
    1691: ifnull        1732
    1694: aload_0
    1695: ldc_w         #786                // class net/playavalon/mythicdungeons/dungeons/functions/rewards/FunctionMythicLootTableRewards
    1698: invokevirtual #772                // Method registerFunction:(Ljava/lang/Class;)V
    1701: aload_0
    1702: ldc_w         #788                // class net/playavalon/mythicdungeons/dungeons/functions/FunctionMythicSkill
    1705: invokevirtual #772                // Method registerFunction:(Ljava/lang/Class;)V
    1708: aload_0
    1709: ldc_w         #790                // class net/playavalon/mythicdungeons/dungeons/functions/FunctionMythicSignal
    1712: invokevirtual #772                // Method registerFunction:(Ljava/lang/Class;)V
    1715: aload_0
    1716: ldc_w         #792                // class net/playavalon/mythicdungeons/dungeons/triggers/TriggerMythicMobDeath
    1719: invokevirtual #795                // Method registerTrigger:(Ljava/lang/Class;)V
    1722: aload_0
    1723: ldc_w         #797                // class net/playavalon/mythicdungeons/dungeons/conditions/ConditionMythic
    1726: invokevirtual #800                // Method registerCondition:(Ljava/lang/Class;)V
    1729: goto          1746
    1732: aload_0
    1733: ldc_w         #802                // class net/playavalon/mythicdungeons/dungeons/functions/rewards/FunctionLootTableRewards
    1736: invokevirtual #772                // Method registerFunction:(Ljava/lang/Class;)V
    1739: aload_0
    1740: ldc_w         #804                // class net/playavalon/mythicdungeons/dungeons/triggers/TriggerMobDeath
    1743: invokevirtual #795                // Method registerTrigger:(Ljava/lang/Class;)V
    1746: aload_0
    1747: getfield      #642                // Field citizensApi:Lnet/citizensnpcs/Citizens;
    1750: ifnull        1760
    1753: aload_0
    1754: ldc_w         #806                // class net/playavalon/mythicdungeons/dungeons/functions/FunctionSpawnNPC
    1757: invokevirtual #772                // Method registerFunction:(Ljava/lang/Class;)V
    1760: invokestatic  #147                // Method org/bukkit/Bukkit.getPluginManager:()Lorg/bukkit/plugin/PluginManager;
    1763: ldc_w         #628                // String PlaceholderAPI
    1766: invokeinterface #155,  2          // InterfaceMethod org/bukkit/plugin/PluginManager.getPlugin:(Ljava/lang/String;)Lorg/bukkit/plugin/Plugin;
    1771: ifnull        1781
    1774: aload_0
    1775: ldc_w         #808                // class net/playavalon/mythicdungeons/dungeons/conditions/ConditionPlaceholderAPI
    1778: invokevirtual #800                // Method registerCondition:(Ljava/lang/Class;)V
    1781: aload_0
    1782: getfield      #439                // Field functionManager:Lnet/playavalon/mythicdungeons/managers/FunctionManager;
    1785: invokevirtual #812                // Method net/playavalon/mythicdungeons/managers/FunctionManager.getAll:()Ljava/util/Collection;
    1788: invokeinterface #817,  1          // InterfaceMethod java/util/Collection.size:()I
    1793: invokedynamic #822,  0            // InvokeDynamic #6:makeConcatWithConstants:(I)Ljava/lang/String;
    1798: invokestatic  #218                // Method net/playavalon/mythicdungeons/utility/helpers/Util.fullColorModern:(Ljava/lang/String;)Ljava/lang/String;
    1801: invokestatic  #265                // Method net/playavalon/mythicdungeons/utility/helpers/MessageUtils.log:(Ljava/lang/String;)V
    1804: aload_0
    1805: getfield      #444                // Field triggerManager:Lnet/playavalon/mythicdungeons/managers/TriggerManager;
    1808: invokevirtual #823                // Method net/playavalon/mythicdungeons/managers/TriggerManager.getAll:()Ljava/util/Collection;
    1811: invokeinterface #817,  1          // InterfaceMethod java/util/Collection.size:()I
    1816: invokedynamic #826,  0            // InvokeDynamic #7:makeConcatWithConstants:(I)Ljava/lang/String;
    1821: invokestatic  #218                // Method net/playavalon/mythicdungeons/utility/helpers/Util.fullColorModern:(Ljava/lang/String;)Ljava/lang/String;
    1824: invokestatic  #265                // Method net/playavalon/mythicdungeons/utility/helpers/MessageUtils.log:(Ljava/lang/String;)V
    1827: aload_0
    1828: getfield      #449                // Field conditionManager:Lnet/playavalon/mythicdungeons/managers/ConditionManager;
    1831: invokevirtual #827                // Method net/playavalon/mythicdungeons/managers/ConditionManager.getAll:()Ljava/util/Collection;
    1834: invokeinterface #817,  1          // InterfaceMethod java/util/Collection.size:()I
    1839: invokedynamic #830,  0            // InvokeDynamic #8:makeConcatWithConstants:(I)Ljava/lang/String;
    1844: invokestatic  #218                // Method net/playavalon/mythicdungeons/utility/helpers/Util.fullColorModern:(Ljava/lang/String;)Ljava/lang/String;
    1847: invokestatic  #265                // Method net/playavalon/mythicdungeons/utility/helpers/MessageUtils.log:(Ljava/lang/String;)V
    1850: invokestatic  #835                // Method net/playavalon/mythicdungeons/gui/GUIHandler.initFunctionMenu:()V
    1853: invokestatic  #838                // Method net/playavalon/mythicdungeons/gui/GUIHandler.initTriggerMenu:()V
    1856: invokestatic  #841                // Method net/playavalon/mythicdungeons/gui/GUIHandler.initConditionsMenus:()V
    1859: invokestatic  #844                // Method net/playavalon/mythicdungeons/gui/GUIHandler.initGateTriggerMenus:()V
    1862: invokestatic  #847                // Method net/playavalon/mythicdungeons/gui/GUIHandler.initItemSelectTriggerMenu:()V
    1865: invokestatic  #850                // Method net/playavalon/mythicdungeons/gui/GUIHandler.initItemSelectFunctionMenu:()V
    1868: invokestatic  #855                // Method net/playavalon/mythicdungeons/gui/PlayGUIHandler.initRewardMenu:()V
    1871: invokestatic  #858                // Method net/playavalon/mythicdungeons/gui/PlayGUIHandler.initRevivalMenu:()V
    1874: invokestatic  #861                // Method net/playavalon/mythicdungeons/gui/GUIHandler.initMultiFunctionMenus:()V
    1877: invokestatic  #866                // Method net/playavalon/mythicdungeons/gui/RoomGUIHandler.initConnectorWhitelist:()V
    1880: aload_0
    1881: getfield      #476                // Field spectatorManager:Lnet/playavalon/mythicdungeons/managers/SpectatorManager;
    1884: invokevirtual #708                // Method net/playavalon/mythicdungeons/managers/SpectatorManager.isLegacy:()Z
    1887: ifne          1896
    1890: invokestatic  #871                // Method net/playavalon/mythicdungeons/gui/SpectatorGUIHandler.initTeleportGui:()V
    1893: invokestatic  #874                // Method net/playavalon/mythicdungeons/gui/SpectatorGUIHandler.initSettingsGui:()V
    1896: invokestatic  #879                // Method net/playavalon/mythicdungeons/gui/HotbarMenuHandler.initEditMenu:()V
    1899: invokestatic  #882                // Method net/playavalon/mythicdungeons/gui/HotbarMenuHandler.initRoomEditMenu:()V
    1902: invokestatic  #885                // Method net/playavalon/mythicdungeons/gui/HotbarMenuHandler.initRoomRulesMenu:()V
    1905: ldc_w         #887                // String &dGUI menus initialized!
    1908: invokestatic  #218                // Method net/playavalon/mythicdungeons/utility/helpers/Util.fullColorModern:(Ljava/lang/String;)Ljava/lang/String;
    1911: invokestatic  #265                // Method net/playavalon/mythicdungeons/utility/helpers/MessageUtils.log:(Ljava/lang/String;)V
    1914: aload_0
    1915: aload_0
    1916: getfield      #205                // Field config:Lorg/bukkit/configuration/file/FileConfiguration;
    1919: ldc_w         #889                // String Experimental.OneWorldDungeons
    1922: iconst_0
    1923: invokevirtual #367                // Method org/bukkit/configuration/file/FileConfiguration.getBoolean:(Ljava/lang/String;Z)Z
    1926: putfield      #891                // Field useSameWorldSystem:Z
    1929: aload_0
    1930: new           #893                // class net/playavalon/mythicdungeons/managers/DungeonManager
    1933: dup
    1934: invokespecial #894                // Method net/playavalon/mythicdungeons/managers/DungeonManager."<init>":()V
    1937: putfield      #896                // Field dungeons:Lnet/playavalon/mythicdungeons/managers/DungeonManager;
    1940: invokestatic  #899                // Method org/bukkit/Bukkit.getOnlinePlayers:()Ljava/util/Collection;
    1943: invokeinterface #902,  1          // InterfaceMethod java/util/Collection.isEmpty:()Z
    1948: ifne          1994
    1951: invokestatic  #899                // Method org/bukkit/Bukkit.getOnlinePlayers:()Ljava/util/Collection;
    1954: invokeinterface #906,  1          // InterfaceMethod java/util/Collection.iterator:()Ljava/util/Iterator;
    1959: astore_3
    1960: aload_3
    1961: invokeinterface #911,  1          // InterfaceMethod java/util/Iterator.hasNext:()Z
    1966: ifeq          1994
    1969: aload_3
    1970: invokeinterface #915,  1          // InterfaceMethod java/util/Iterator.next:()Ljava/lang/Object;
    1975: checkcast     #917                // class org/bukkit/entity/Player
    1978: astore        4
    1980: getstatic     #196                // Field plugin:Lnet/playavalon/mythicdungeons/MythicDungeons;
    1983: invokevirtual #921                // Method getPlayerManager:()Lnet/playavalon/mythicdungeons/managers/PlayerManager;
    1986: aload         4
    1988: invokevirtual #925                // Method net/playavalon/mythicdungeons/managers/PlayerManager.put:(Lorg/bukkit/entity/Player;)V
    1991: goto          1960
    1994: aload_0
    1995: invokevirtual #926                // Method getVersion:()Ljava/lang/String;
    1998: invokedynamic #929,  0            // InvokeDynamic #9:makeConcatWithConstants:(Ljava/lang/String;)Ljava/lang/String;
    2003: invokestatic  #218                // Method net/playavalon/mythicdungeons/utility/helpers/Util.fullColorModern:(Ljava/lang/String;)Ljava/lang/String;
    2006: invokestatic  #265                // Method net/playavalon/mythicdungeons/utility/helpers/MessageUtils.log:(Ljava/lang/String;)V
    2009: aload_0
    2010: invokevirtual #933                // Method getServer:()Lorg/bukkit/Server;
    2013: invokeinterface #939,  1          // InterfaceMethod org/bukkit/Server.getServicesManager:()Lorg/bukkit/plugin/ServicesManager;
    2018: ldc           #6                  // class net/playavalon/mythicdungeons/api/MythicDungeonsService
    2020: aload_0
    2021: aload_0
    2022: getstatic     #945                // Field org/bukkit/plugin/ServicePriority.Normal:Lorg/bukkit/plugin/ServicePriority;
    2025: invokeinterface #950,  5          // InterfaceMethod org/bukkit/plugin/ServicesManager.register:(Ljava/lang/Class;Ljava/lang/Object;Lorg/bukkit/plugin/Plugin;Lorg/bukkit/plugin/ServicePriority;)V
    2030: invokestatic  #954                // Method org/bukkit/Bukkit.getScheduler:()Lorg/bukkit/scheduler/BukkitScheduler;
    2033: aload_0
    2034: aload_0
    2035: invokedynamic #970,  0            // InvokeDynamic #10:run:(Lnet/playavalon/mythicdungeons/MythicDungeons;)Ljava/lang/Runnable;
    2040: lconst_1
    2041: invokeinterface #976,  5          // InterfaceMethod org/bukkit/scheduler/BukkitScheduler.runTaskLater:(Lorg/bukkit/plugin/Plugin;Ljava/lang/Runnable;J)Lorg/bukkit/scheduler/BukkitTask;
    2046: pop
    2047: return
    Exception table:
       from    to  target type
          57    89    92   Class java/lang/ClassNotFoundException
          57    89    92   Class java/lang/NoSuchMethodException
          46    98   101   Class java/lang/ClassNotFoundException
          35   102   105   Class java/lang/ClassNotFoundException
         275   295   298   Class java/lang/IllegalArgumentException
         315   335   338   Class java/lang/IllegalArgumentException
        1001  1040  1043   Class java/lang/ClassNotFoundException
        1001  1040  1043   Class java/lang/NoSuchMethodException
        1001  1040  1043   Class java/lang/IllegalAccessException
        1001  1040  1043   Class java/lang/reflect/InvocationTargetException

  public void initDungeonContainer(org.bukkit.World$Environment);
    Code:
       0: getstatic     #998                // Field net/playavalon/mythicdungeons/MythicDungeons$1.$SwitchMap$org$bukkit$World$Environment:[I
       3: aload_1
       4: invokevirtual #1001               // Method org/bukkit/World$Environment.ordinal:()I
       7: iaload
       8: lookupswitch  { // 2

                     1: 36

                     2: 90
               default: 141
          }
      36: aload_0
      37: getfield      #1003               // Field overworldContainer:Lnet/playavalon/mythicdungeons/managers/InstanceContainer;
      40: ifnonnull     59
      43: aload_0
      44: new           #1005               // class net/playavalon/mythicdungeons/managers/InstanceContainer
      47: dup
      48: iconst_0
      49: aload_1
      50: invokespecial #1008               // Method net/playavalon/mythicdungeons/managers/InstanceContainer."<init>":(ILorg/bukkit/World$Environment;)V
      53: putfield      #1003               // Field overworldContainer:Lnet/playavalon/mythicdungeons/managers/InstanceContainer;
      56: goto          80
      59: aload_0
      60: new           #1005               // class net/playavalon/mythicdungeons/managers/InstanceContainer
      63: dup
      64: aload_0
      65: getfield      #1003               // Field overworldContainer:Lnet/playavalon/mythicdungeons/managers/InstanceContainer;
      68: invokevirtual #1011               // Method net/playavalon/mythicdungeons/managers/InstanceContainer.getId:()I
      71: iconst_1
      72: iadd
      73: aload_1
      74: invokespecial #1008               // Method net/playavalon/mythicdungeons/managers/InstanceContainer."<init>":(ILorg/bukkit/World$Environment;)V
      77: putfield      #1003               // Field overworldContainer:Lnet/playavalon/mythicdungeons/managers/InstanceContainer;
      80: aload_0
      81: getfield      #1003               // Field overworldContainer:Lnet/playavalon/mythicdungeons/managers/InstanceContainer;
      84: invokevirtual #1014               // Method net/playavalon/mythicdungeons/managers/InstanceContainer.initWorld:()V
      87: goto          141
      90: aload_0
      91: getfield      #1016               // Field netherContainer:Lnet/playavalon/mythicdungeons/managers/InstanceContainer;
      94: ifnonnull     113
      97: aload_0
      98: new           #1005               // class net/playavalon/mythicdungeons/managers/InstanceContainer
     101: dup
     102: iconst_0
     103: aload_1
     104: invokespecial #1008               // Method net/playavalon/mythicdungeons/managers/InstanceContainer."<init>":(ILorg/bukkit/World$Environment;)V
     107: putfield      #1016               // Field netherContainer:Lnet/playavalon/mythicdungeons/managers/InstanceContainer;
     110: goto          134
     113: aload_0
     114: new           #1005               // class net/playavalon/mythicdungeons/managers/InstanceContainer
     117: dup
     118: aload_0
     119: getfield      #1016               // Field netherContainer:Lnet/playavalon/mythicdungeons/managers/InstanceContainer;
     122: invokevirtual #1011               // Method net/playavalon/mythicdungeons/managers/InstanceContainer.getId:()I
     125: iconst_1
     126: iadd
     127: aload_1
     128: invokespecial #1008               // Method net/playavalon/mythicdungeons/managers/InstanceContainer."<init>":(ILorg/bukkit/World$Environment;)V
     131: putfield      #1016               // Field netherContainer:Lnet/playavalon/mythicdungeons/managers/InstanceContainer;
     134: aload_0
     135: getfield      #1016               // Field netherContainer:Lnet/playavalon/mythicdungeons/managers/InstanceContainer;
     138: invokevirtual #1014               // Method net/playavalon/mythicdungeons/managers/InstanceContainer.initWorld:()V
     141: return

  public net.playavalon.mythicdungeons.managers.InstanceContainer getDungeonContainer(org.bukkit.World$Environment);
    Code:
       0: getstatic     #998                // Field net/playavalon/mythicdungeons/MythicDungeons$1.$SwitchMap$org$bukkit$World$Environment:[I
       3: aload_1
       4: invokevirtual #1001               // Method org/bukkit/World$Environment.ordinal:()I
       7: iaload
       8: tableswitch   { // 1 to 3

                     1: 36

                     2: 41

                     3: 46
               default: 51
          }
      36: aload_0
      37: getfield      #1003               // Field overworldContainer:Lnet/playavalon/mythicdungeons/managers/InstanceContainer;
      40: areturn
      41: aload_0
      42: getfield      #1016               // Field netherContainer:Lnet/playavalon/mythicdungeons/managers/InstanceContainer;
      45: areturn
      46: aload_0
      47: getfield      #1022               // Field endContainer:Lnet/playavalon/mythicdungeons/managers/InstanceContainer;
      50: areturn
      51: aload_0
      52: getfield      #1003               // Field overworldContainer:Lnet/playavalon/mythicdungeons/managers/InstanceContainer;
      55: areturn

  public boolean isLocationInDungeonContainer(org.bukkit.Location);
    Code:
       0: aload_1
       1: invokevirtual #1029               // Method org/bukkit/Location.getWorld:()Lorg/bukkit/World;
       4: aload_0
       5: getfield      #1003               // Field overworldContainer:Lnet/playavalon/mythicdungeons/managers/InstanceContainer;
       8: invokevirtual #1030               // Method net/playavalon/mythicdungeons/managers/InstanceContainer.getWorld:()Lorg/bukkit/World;
      11: if_acmpne     16
      14: iconst_1
      15: ireturn
      16: aload_1
      17: invokevirtual #1029               // Method org/bukkit/Location.getWorld:()Lorg/bukkit/World;
      20: aload_0
      21: getfield      #1016               // Field netherContainer:Lnet/playavalon/mythicdungeons/managers/InstanceContainer;
      24: invokevirtual #1030               // Method net/playavalon/mythicdungeons/managers/InstanceContainer.getWorld:()Lorg/bukkit/World;
      27: if_acmpne     32
      30: iconst_1
      31: ireturn
      32: aload_1
      33: invokevirtual #1029               // Method org/bukkit/Location.getWorld:()Lorg/bukkit/World;
      36: aload_0
      37: getfield      #1022               // Field endContainer:Lnet/playavalon/mythicdungeons/managers/InstanceContainer;
      40: invokevirtual #1030               // Method net/playavalon/mythicdungeons/managers/InstanceContainer.getWorld:()Lorg/bukkit/World;
      43: if_acmpne     48
      46: iconst_1
      47: ireturn
      48: iconst_0
      49: ireturn

  private boolean setupEconomy();
    Code:
       0: aload_0
       1: invokevirtual #933                // Method getServer:()Lorg/bukkit/Server;
       4: invokeinterface #1033,  1         // InterfaceMethod org/bukkit/Server.getPluginManager:()Lorg/bukkit/plugin/PluginManager;
       9: ldc_w         #1035               // String Vault
      12: invokeinterface #155,  2          // InterfaceMethod org/bukkit/plugin/PluginManager.getPlugin:(Ljava/lang/String;)Lorg/bukkit/plugin/Plugin;
      17: ifnonnull     22
      20: iconst_0
      21: ireturn
      22: aload_0
      23: invokevirtual #933                // Method getServer:()Lorg/bukkit/Server;
      26: invokeinterface #939,  1          // InterfaceMethod org/bukkit/Server.getServicesManager:()Lorg/bukkit/plugin/ServicesManager;
      31: ldc_w         #1037               // class net/milkbowl/vault/economy/Economy
      34: invokeinterface #1041,  2         // InterfaceMethod org/bukkit/plugin/ServicesManager.getRegistration:(Ljava/lang/Class;)Lorg/bukkit/plugin/RegisteredServiceProvider;
      39: astore_1
      40: aload_1
      41: ifnonnull     46
      44: iconst_0
      45: ireturn
      46: aload_0
      47: aload_1
      48: invokevirtual #1046               // Method org/bukkit/plugin/RegisteredServiceProvider.getProvider:()Ljava/lang/Object;
      51: checkcast     #1037               // class net/milkbowl/vault/economy/Economy
      54: putfield      #1048               // Field economy:Lnet/milkbowl/vault/economy/Economy;
      57: aload_0
      58: getfield      #1048               // Field economy:Lnet/milkbowl/vault/economy/Economy;
      61: ifnull        68
      64: iconst_1
      65: goto          69
      68: iconst_0
      69: ireturn

  public void onDisable();
    Code:
       0: ldc_w         #1054               // String &dCleaning up dungeons...
       3: invokestatic  #218                // Method net/playavalon/mythicdungeons/utility/helpers/Util.fullColorModern:(Ljava/lang/String;)Ljava/lang/String;
       6: invokestatic  #265                // Method net/playavalon/mythicdungeons/utility/helpers/MessageUtils.log:(Ljava/lang/String;)V
       9: invokestatic  #899                // Method org/bukkit/Bukkit.getOnlinePlayers:()Ljava/util/Collection;
      12: invokeinterface #906,  1          // InterfaceMethod java/util/Collection.iterator:()Ljava/util/Iterator;
      17: astore_1
      18: aload_1
      19: invokeinterface #911,  1          // InterfaceMethod java/util/Iterator.hasNext:()Z
      24: ifeq          69
      27: aload_1
      28: invokeinterface #915,  1          // InterfaceMethod java/util/Iterator.next:()Ljava/lang/Object;
      33: checkcast     #917                // class org/bukkit/entity/Player
      36: astore_2
      37: aload_0
      38: aload_2
      39: invokevirtual #1058               // Method getMythicPlayer:(Lorg/bukkit/entity/Player;)Lnet/playavalon/mythicdungeons/player/MythicPlayer;
      42: astore_3
      43: aload_3
      44: invokevirtual #1063               // Method net/playavalon/mythicdungeons/player/MythicPlayer.restoreHotbar:()V
      47: aload_3
      48: invokevirtual #1066               // Method net/playavalon/mythicdungeons/player/MythicPlayer.getInstance:()Lnet/playavalon/mythicdungeons/api/parents/instances/AbstractInstance;
      51: astore        4
      53: aload         4
      55: ifnull        66
      58: aload_3
      59: invokevirtual #1066               // Method net/playavalon/mythicdungeons/player/MythicPlayer.getInstance:()Lnet/playavalon/mythicdungeons/api/parents/instances/AbstractInstance;
      62: aload_3
      63: invokevirtual #1072               // Method net/playavalon/mythicdungeons/api/parents/instances/AbstractInstance.removePlayer:(Lnet/playavalon/mythicdungeons/player/MythicPlayer;)V
      66: goto          18
      69: aload_0
      70: getfield      #891                // Field useSameWorldSystem:Z
      73: ifeq          181
      76: aload_0
      77: getfield      #1003               // Field overworldContainer:Lnet/playavalon/mythicdungeons/managers/InstanceContainer;
      80: ifnull        111
      83: aload_0
      84: getfield      #1003               // Field overworldContainer:Lnet/playavalon/mythicdungeons/managers/InstanceContainer;
      87: invokevirtual #1030               // Method net/playavalon/mythicdungeons/managers/InstanceContainer.getWorld:()Lorg/bukkit/World;
      90: iconst_0
      91: invokestatic  #1076               // Method org/bukkit/Bukkit.unloadWorld:(Lorg/bukkit/World;Z)Z
      94: pop
      95: aload_0
      96: getfield      #1003               // Field overworldContainer:Lnet/playavalon/mythicdungeons/managers/InstanceContainer;
      99: invokevirtual #1030               // Method net/playavalon/mythicdungeons/managers/InstanceContainer.getWorld:()Lorg/bukkit/World;
     102: invokeinterface #1079,  1         // InterfaceMethod org/bukkit/World.getWorldFolder:()Ljava/io/File;
     107: invokestatic  #1083               // Method net/playavalon/mythicdungeons/utility/helpers/Util.deleteRecursively:(Ljava/io/File;)Z
     110: pop
     111: aload_0
     112: getfield      #1016               // Field netherContainer:Lnet/playavalon/mythicdungeons/managers/InstanceContainer;
     115: ifnull        146
     118: aload_0
     119: getfield      #1016               // Field netherContainer:Lnet/playavalon/mythicdungeons/managers/InstanceContainer;
     122: invokevirtual #1030               // Method net/playavalon/mythicdungeons/managers/InstanceContainer.getWorld:()Lorg/bukkit/World;
     125: iconst_0
     126: invokestatic  #1076               // Method org/bukkit/Bukkit.unloadWorld:(Lorg/bukkit/World;Z)Z
     129: pop
     130: aload_0
     131: getfield      #1016               // Field netherContainer:Lnet/playavalon/mythicdungeons/managers/InstanceContainer;
     134: invokevirtual #1030               // Method net/playavalon/mythicdungeons/managers/InstanceContainer.getWorld:()Lorg/bukkit/World;
     137: invokeinterface #1079,  1         // InterfaceMethod org/bukkit/World.getWorldFolder:()Ljava/io/File;
     142: invokestatic  #1083               // Method net/playavalon/mythicdungeons/utility/helpers/Util.deleteRecursively:(Ljava/io/File;)Z
     145: pop
     146: aload_0
     147: getfield      #1022               // Field endContainer:Lnet/playavalon/mythicdungeons/managers/InstanceContainer;
     150: ifnull        181
     153: aload_0
     154: getfield      #1022               // Field endContainer:Lnet/playavalon/mythicdungeons/managers/InstanceContainer;
     157: invokevirtual #1030               // Method net/playavalon/mythicdungeons/managers/InstanceContainer.getWorld:()Lorg/bukkit/World;
     160: iconst_0
     161: invokestatic  #1076               // Method org/bukkit/Bukkit.unloadWorld:(Lorg/bukkit/World;Z)Z
     164: pop
     165: aload_0
     166: getfield      #1022               // Field endContainer:Lnet/playavalon/mythicdungeons/managers/InstanceContainer;
     169: invokevirtual #1030               // Method net/playavalon/mythicdungeons/managers/InstanceContainer.getWorld:()Lorg/bukkit/World;
     172: invokeinterface #1079,  1         // InterfaceMethod org/bukkit/World.getWorldFolder:()Ljava/io/File;
     177: invokestatic  #1083               // Method net/playavalon/mythicdungeons/utility/helpers/Util.deleteRecursively:(Ljava/io/File;)Z
     180: pop
     181: aload_0
     182: getfield      #896                // Field dungeons:Lnet/playavalon/mythicdungeons/managers/DungeonManager;
     185: ifnonnull     189
     188: return
     189: aload_0
     190: getfield      #896                // Field dungeons:Lnet/playavalon/mythicdungeons/managers/DungeonManager;
     193: invokevirtual #1084               // Method net/playavalon/mythicdungeons/managers/DungeonManager.getAll:()Ljava/util/Collection;
     196: invokeinterface #906,  1          // InterfaceMethod java/util/Collection.iterator:()Ljava/util/Iterator;
     201: astore_1
     202: aload_1
     203: invokeinterface #911,  1          // InterfaceMethod java/util/Iterator.hasNext:()Z
     208: ifeq          274
     211: aload_1
     212: invokeinterface #915,  1          // InterfaceMethod java/util/Iterator.next:()Ljava/lang/Object;
     217: checkcast     #1086               // class net/playavalon/mythicdungeons/api/parents/dungeons/AbstractDungeon
     220: astore_2
     221: new           #1088               // class java/util/ArrayList
     224: dup
     225: aload_2
     226: invokevirtual #1092               // Method net/playavalon/mythicdungeons/api/parents/dungeons/AbstractDungeon.getInstances:()Ljava/util/List;
     229: invokespecial #1095               // Method java/util/ArrayList."<init>":(Ljava/util/Collection;)V
     232: astore_3
     233: aload_3
     234: invokeinterface #1098,  1         // InterfaceMethod java/util/List.iterator:()Ljava/util/Iterator;
     239: astore        4
     241: aload         4
     243: invokeinterface #911,  1          // InterfaceMethod java/util/Iterator.hasNext:()Z
     248: ifeq          271
     251: aload         4
     253: invokeinterface #915,  1          // InterfaceMethod java/util/Iterator.next:()Ljava/lang/Object;
     258: checkcast     #1068               // class net/playavalon/mythicdungeons/api/parents/instances/AbstractInstance
     261: astore        5
     263: aload         5
     265: invokevirtual #1101               // Method net/playavalon/mythicdungeons/api/parents/instances/AbstractInstance.dispose:()V
     268: goto          241
     271: goto          202
     274: aload_0
     275: getfield      #471                // Field movingBlockManager:Lnet/playavalon/mythicdungeons/managers/MovingBlockManager;
     278: invokevirtual #1104               // Method net/playavalon/mythicdungeons/managers/MovingBlockManager.disable:()V
     281: return

  public void reload();
    Code:
       0: aload_0
       1: invokevirtual #1117               // Method reloadAllDungeons:()V
       4: aload_0
       5: invokevirtual #1120               // Method reloadConfigs:()V
       8: return

  public void reloadAllDungeons();
    Code:
       0: invokestatic  #899                // Method org/bukkit/Bukkit.getOnlinePlayers:()Ljava/util/Collection;
       3: invokeinterface #906,  1          // InterfaceMethod java/util/Collection.iterator:()Ljava/util/Iterator;
       8: astore_1
       9: aload_1
      10: invokeinterface #911,  1          // InterfaceMethod java/util/Iterator.hasNext:()Z
      15: ifeq          76
      18: aload_1
      19: invokeinterface #915,  1          // InterfaceMethod java/util/Iterator.next:()Ljava/lang/Object;
      24: checkcast     #917                // class org/bukkit/entity/Player
      27: astore_2
      28: aload_0
      29: aload_2
      30: invokevirtual #1058               // Method getMythicPlayer:(Lorg/bukkit/entity/Player;)Lnet/playavalon/mythicdungeons/player/MythicPlayer;
      33: astore_3
      34: aload_3
      35: invokevirtual #1063               // Method net/playavalon/mythicdungeons/player/MythicPlayer.restoreHotbar:()V
      38: aload_3
      39: invokevirtual #1066               // Method net/playavalon/mythicdungeons/player/MythicPlayer.getInstance:()Lnet/playavalon/mythicdungeons/api/parents/instances/AbstractInstance;
      42: astore        4
      44: aload         4
      46: ifnull        73
      49: aload         4
      51: aload_3
      52: invokevirtual #1072               // Method net/playavalon/mythicdungeons/api/parents/instances/AbstractInstance.removePlayer:(Lnet/playavalon/mythicdungeons/player/MythicPlayer;)V
      55: aload_3
      56: invokevirtual #1124               // Method net/playavalon/mythicdungeons/player/MythicPlayer.getPlayer:()Lorg/bukkit/entity/Player;
      59: getstatic     #220                // Field debugPrefix:Ljava/lang/String;
      62: invokedynamic #1127,  0           // InvokeDynamic #11:makeConcatWithConstants:(Ljava/lang/String;)Ljava/lang/String;
      67: invokestatic  #218                // Method net/playavalon/mythicdungeons/utility/helpers/Util.fullColorModern:(Ljava/lang/String;)Ljava/lang/String;
      70: invokestatic  #1131               // Method net/playavalon/mythicdungeons/utility/helpers/MessageUtils.sendMessage:(Lorg/bukkit/command/CommandSender;Ljava/lang/String;)V
      73: goto          9
      76: new           #1133               // class net/playavalon/mythicdungeons/utility/tasks/ProcessTimer
      79: dup
      80: invokespecial #1134               // Method net/playavalon/mythicdungeons/utility/tasks/ProcessTimer."<init>":()V
      83: ldc_w         #1136               // String Reloading Dungeons
      86: aload_0
      87: invokedynamic #1143,  0           // InvokeDynamic #12:run:(Lnet/playavalon/mythicdungeons/MythicDungeons;)Lnet/playavalon/mythicdungeons/utility/tasks/TrackedTask;
      92: invokevirtual #1146               // Method net/playavalon/mythicdungeons/utility/tasks/ProcessTimer.run:(Ljava/lang/String;Lnet/playavalon/mythicdungeons/utility/tasks/TrackedTask;)V
      95: return

  public void reloadDungeon(net.playavalon.mythicdungeons.api.parents.dungeons.AbstractDungeon);
    Code:
       0: new           #1088               // class java/util/ArrayList
       3: dup
       4: aload_1
       5: invokevirtual #1092               // Method net/playavalon/mythicdungeons/api/parents/dungeons/AbstractDungeon.getInstances:()Ljava/util/List;
       8: invokespecial #1095               // Method java/util/ArrayList."<init>":(Ljava/util/Collection;)V
      11: astore_2
      12: aload_2
      13: invokeinterface #1098,  1         // InterfaceMethod java/util/List.iterator:()Ljava/util/Iterator;
      18: astore_3
      19: aload_3
      20: invokeinterface #911,  1          // InterfaceMethod java/util/Iterator.hasNext:()Z
      25: ifeq          121
      28: aload_3
      29: invokeinterface #915,  1          // InterfaceMethod java/util/Iterator.next:()Ljava/lang/Object;
      34: checkcast     #1068               // class net/playavalon/mythicdungeons/api/parents/instances/AbstractInstance
      37: astore        4
      39: new           #1088               // class java/util/ArrayList
      42: dup
      43: aload         4
      45: invokevirtual #1151               // Method net/playavalon/mythicdungeons/api/parents/instances/AbstractInstance.getPlayers:()Ljava/util/List;
      48: invokespecial #1095               // Method java/util/ArrayList."<init>":(Ljava/util/Collection;)V
      51: astore        5
      53: aload         5
      55: invokeinterface #1098,  1         // InterfaceMethod java/util/List.iterator:()Ljava/util/Iterator;
      60: astore        6
      62: aload         6
      64: invokeinterface #911,  1          // InterfaceMethod java/util/Iterator.hasNext:()Z
      69: ifeq          118
      72: aload         6
      74: invokeinterface #915,  1          // InterfaceMethod java/util/Iterator.next:()Ljava/lang/Object;
      79: checkcast     #1060               // class net/playavalon/mythicdungeons/player/MythicPlayer
      82: astore        7
      84: aload         7
      86: invokevirtual #1063               // Method net/playavalon/mythicdungeons/player/MythicPlayer.restoreHotbar:()V
      89: aload         4
      91: aload         7
      93: invokevirtual #1072               // Method net/playavalon/mythicdungeons/api/parents/instances/AbstractInstance.removePlayer:(Lnet/playavalon/mythicdungeons/player/MythicPlayer;)V
      96: aload         7
      98: invokevirtual #1124               // Method net/playavalon/mythicdungeons/player/MythicPlayer.getPlayer:()Lorg/bukkit/entity/Player;
     101: getstatic     #220                // Field debugPrefix:Ljava/lang/String;
     104: invokedynamic #1127,  0           // InvokeDynamic #11:makeConcatWithConstants:(Ljava/lang/String;)Ljava/lang/String;
     109: invokestatic  #218                // Method net/playavalon/mythicdungeons/utility/helpers/Util.fullColorModern:(Ljava/lang/String;)Ljava/lang/String;
     112: invokestatic  #1131               // Method net/playavalon/mythicdungeons/utility/helpers/MessageUtils.sendMessage:(Lorg/bukkit/command/CommandSender;Ljava/lang/String;)V
     115: goto          62
     118: goto          19
     121: aload_0
     122: getfield      #896                // Field dungeons:Lnet/playavalon/mythicdungeons/managers/DungeonManager;
     125: aload_1
     126: invokevirtual #1154               // Method net/playavalon/mythicdungeons/managers/DungeonManager.remove:(Lnet/playavalon/mythicdungeons/api/parents/dungeons/AbstractDungeon;)V
     129: aload_0
     130: getfield      #896                // Field dungeons:Lnet/playavalon/mythicdungeons/managers/DungeonManager;
     133: aload_1
     134: invokevirtual #1157               // Method net/playavalon/mythicdungeons/api/parents/dungeons/AbstractDungeon.getFolder:()Ljava/io/File;
     137: invokevirtual #1161               // Method net/playavalon/mythicdungeons/managers/DungeonManager.loadDungeon:(Ljava/io/File;)Lnet/playavalon/mythicdungeons/api/parents/dungeons/AbstractDungeon;
     140: pop
     141: return

  public void reloadConfigs();
    Code:
       0: aload_0
       1: invokevirtual #1166               // Method reloadConfig:()V
       4: aload_0
       5: aload_0
       6: invokevirtual #203                // Method getConfig:()Lorg/bukkit/configuration/file/FileConfiguration;
       9: putfield      #205                // Field config:Lorg/bukkit/configuration/file/FileConfiguration;
      12: aload_0
      13: aload_0
      14: getfield      #205                // Field config:Lorg/bukkit/configuration/file/FileConfiguration;
      17: ldc_w         #331                // String General.FunctionBuilderItem
      20: ldc_w         #333                // String FEATHER
      23: invokevirtual #339                // Method org/bukkit/configuration/file/FileConfiguration.getString:(Ljava/lang/String;Ljava/lang/String;)Ljava/lang/String;
      26: invokestatic  #345                // Method org/bukkit/Material.getMaterial:(Ljava/lang/String;)Lorg/bukkit/Material;
      29: putfield      #347                // Field functionBuilderMaterial:Lorg/bukkit/Material;
      32: goto          52
      35: astore_1
      36: ldc_w         #1168               // String &cWARNING: FunctionBuilderItem in config.yml must be a valid material! Using FEATHER by default...
      39: invokestatic  #218                // Method net/playavalon/mythicdungeons/utility/helpers/Util.fullColorModern:(Ljava/lang/String;)Ljava/lang/String;
      42: invokestatic  #265                // Method net/playavalon/mythicdungeons/utility/helpers/MessageUtils.log:(Ljava/lang/String;)V
      45: aload_0
      46: getstatic     #351                // Field org/bukkit/Material.FEATHER:Lorg/bukkit/Material;
      49: putfield      #347                // Field functionBuilderMaterial:Lorg/bukkit/Material;
      52: aload_0
      53: aload_0
      54: getfield      #205                // Field config:Lorg/bukkit/configuration/file/FileConfiguration;
      57: ldc_w         #363                // String General.StuckKillsPlayer
      60: iconst_0
      61: invokevirtual #367                // Method org/bukkit/configuration/file/FileConfiguration.getBoolean:(Ljava/lang/String;Z)Z
      64: putfield      #369                // Field stuckKillsPlayer:Z
      67: invokestatic  #326                // Method net/playavalon/mythicdungeons/utility/helpers/LangUtils.init:()V
      70: aload_0
      71: new           #456                // class net/playavalon/mythicdungeons/managers/LootTableManager
      74: dup
      75: invokespecial #457                // Method net/playavalon/mythicdungeons/managers/LootTableManager."<init>":()V
      78: putfield      #459                // Field lootTableManager:Lnet/playavalon/mythicdungeons/managers/LootTableManager;
      81: return
    Exception table:
       from    to  target type
          12    32    35   Class java/lang/IllegalArgumentException

  public java.lang.String getVersion();
    Code:
       0: aload_0
       1: invokevirtual #1169               // Method getDescription:()Lorg/bukkit/plugin/PluginDescriptionFile;
       4: invokevirtual #663                // Method org/bukkit/plugin/PluginDescriptionFile.getVersion:()Ljava/lang/String;
       7: ldc_w         #1171               // String -
      10: invokevirtual #1175               // Method java/lang/String.split:(Ljava/lang/String;)[Ljava/lang/String;
      13: iconst_0
      14: aaload
      15: areturn

  public java.lang.String getBuildNumber();
    Code:
       0: aload_0
       1: invokevirtual #1169               // Method getDescription:()Lorg/bukkit/plugin/PluginDescriptionFile;
       4: invokevirtual #663                // Method org/bukkit/plugin/PluginDescriptionFile.getVersion:()Ljava/lang/String;
       7: ldc_w         #1171               // String -
      10: invokevirtual #1175               // Method java/lang/String.split:(Ljava/lang/String;)[Ljava/lang/String;
      13: astore_1
      14: aload_1
      15: arraylength
      16: iconst_2
      17: if_icmpne     24
      20: aload_1
      21: iconst_1
      22: aaload
      23: areturn
      24: aload_1
      25: arraylength
      26: iconst_3
      27: if_icmpne     34
      30: aload_1
      31: iconst_2
      32: aaload
      33: areturn
      34: ldc_w         #1180               // String ????
      37: areturn

  public org.bukkit.generator.ChunkGenerator getDefaultWorldGenerator(java.lang.String, java.lang.String);
    Code:
       0: aload_2
       1: ifnonnull     11
       4: aload_0
       5: aload_1
       6: aload_2
       7: invokespecial #1186               // Method org/bukkit/plugin/java/JavaPlugin.getDefaultWorldGenerator:(Ljava/lang/String;Ljava/lang/String;)Lorg/bukkit/generator/ChunkGenerator;
      10: areturn
      11: aload_2
      12: invokevirtual #530                // Method java/lang/String.toLowerCase:()Ljava/lang/String;
      15: ldc_w         #1188               // String block
      18: invokevirtual #668                // Method java/lang/String.startsWith:(Ljava/lang/String;)Z
      21: ifeq          71
      24: aload_2
      25: ldc_w         #1190               // String .
      28: invokevirtual #1194               // Method java/lang/String.contains:(Ljava/lang/CharSequence;)Z
      31: ifeq          71
      34: aload_2
      35: ldc_w         #1196               // String \\.
      38: iconst_2
      39: invokevirtual #1199               // Method java/lang/String.split:(Ljava/lang/String;I)[Ljava/lang/String;
      42: astore_3
      43: getstatic     #1202               // Field org/bukkit/Material.STONE:Lorg/bukkit/Material;
      46: astore        4
      48: aload_3
      49: iconst_1
      50: aaload
      51: invokestatic  #1205               // Method org/bukkit/Material.valueOf:(Ljava/lang/String;)Lorg/bukkit/Material;
      54: astore        4
      56: goto          61
      59: astore        5
      61: new           #1207               // class net/playavalon/mythicdungeons/api/chunkgenerators/FullBlockGenerator
      64: dup
      65: aload         4
      67: invokespecial #1210               // Method net/playavalon/mythicdungeons/api/chunkgenerators/FullBlockGenerator."<init>":(Lorg/bukkit/Material;)V
      70: areturn
      71: aload_2
      72: ldc_w         #1212               // String void
      75: invokevirtual #506                // Method java/lang/String.equalsIgnoreCase:(Ljava/lang/String;)Z
      78: ifeq          89
      81: new           #1214               // class net/playavalon/mythicdungeons/api/chunkgenerators/VoidGenerator
      84: dup
      85: invokespecial #1215               // Method net/playavalon/mythicdungeons/api/chunkgenerators/VoidGenerator."<init>":()V
      88: areturn
      89: aload_0
      90: aload_1
      91: aload_2
      92: invokespecial #1186               // Method org/bukkit/plugin/java/JavaPlugin.getDefaultWorldGenerator:(Ljava/lang/String;Ljava/lang/String;)Lorg/bukkit/generator/ChunkGenerator;
      95: areturn
    Exception table:
       from    to  target type
          48    56    59   Class java/lang/IllegalArgumentException

  public net.playavalon.mythicdungeons.player.MythicPlayer getMythicPlayer(org.bukkit.entity.Player);
    Code:
       0: aload_0
       1: aload_1
       2: invokeinterface #1222,  1         // InterfaceMethod org/bukkit/entity/Player.getUniqueId:()Ljava/util/UUID;
       7: invokevirtual #1225               // Method getMythicPlayer:(Ljava/util/UUID;)Lnet/playavalon/mythicdungeons/player/MythicPlayer;
      10: ifnonnull     23
      13: invokestatic  #587                // Method inst:()Lnet/playavalon/mythicdungeons/MythicDungeons;
      16: invokevirtual #921                // Method getPlayerManager:()Lnet/playavalon/mythicdungeons/managers/PlayerManager;
      19: aload_1
      20: invokevirtual #925                // Method net/playavalon/mythicdungeons/managers/PlayerManager.put:(Lorg/bukkit/entity/Player;)V
      23: aload_0
      24: aload_1
      25: invokeinterface #1222,  1         // InterfaceMethod org/bukkit/entity/Player.getUniqueId:()Ljava/util/UUID;
      30: invokevirtual #1225               // Method getMythicPlayer:(Ljava/util/UUID;)Lnet/playavalon/mythicdungeons/player/MythicPlayer;
      33: areturn

  public net.playavalon.mythicdungeons.player.MythicPlayer getMythicPlayer(java.util.UUID);
    Code:
       0: aload_0
       1: getfield      #419                // Field playerManager:Lnet/playavalon/mythicdungeons/managers/PlayerManager;
       4: aload_1
       5: invokevirtual #1227               // Method net/playavalon/mythicdungeons/managers/PlayerManager.get:(Ljava/util/UUID;)Lnet/playavalon/mythicdungeons/player/MythicPlayer;
       8: areturn

  public boolean sendToDungeon(org.bukkit.entity.Player, java.lang.String);
    Code:
       0: aload_0
       1: aload_1
       2: aload_2
       3: ldc_w         #1233               // String DEFAULT
       6: invokevirtual #1236               // Method sendToDungeon:(Lorg/bukkit/entity/Player;Ljava/lang/String;Ljava/lang/String;)Z
       9: ireturn

  public boolean sendToDungeon(org.bukkit.entity.Player, java.lang.String, java.lang.String);
    Code:
       0: aload_0
       1: aload_1
       2: invokevirtual #1058               // Method getMythicPlayer:(Lorg/bukkit/entity/Player;)Lnet/playavalon/mythicdungeons/player/MythicPlayer;
       5: astore        4
       7: aload_0
       8: getfield      #896                // Field dungeons:Lnet/playavalon/mythicdungeons/managers/DungeonManager;
      11: aload_2
      12: invokevirtual #1240               // Method net/playavalon/mythicdungeons/managers/DungeonManager.get:(Ljava/lang/String;)Lnet/playavalon/mythicdungeons/api/parents/dungeons/AbstractDungeon;
      15: astore        5
      17: aload_0
      18: getfield      #510                // Field partiesEnabled:Z
      21: ifeq          247
      24: aload         4
      26: invokevirtual #1244               // Method net/playavalon/mythicdungeons/player/MythicPlayer.getDungeonParty:()Lnet/playavalon/mythicdungeons/api/party/IDungeonParty;
      29: astore        6
      31: aload_0
      32: getfield      #544                // Field thirdPartyProvider:Z
      35: ifeq          73
      38: aload         6
      40: ifnonnull     54
      43: new           #597                // class net/playavalon/mythicdungeons/player/party/PartyWrapper
      46: dup
      47: aload         4
      49: invokespecial #1246               // Method net/playavalon/mythicdungeons/player/party/PartyWrapper."<init>":(Lnet/playavalon/mythicdungeons/player/MythicPlayer;)V
      52: astore        6
      54: aload         6
      56: invokeinterface #1249,  1         // InterfaceMethod net/playavalon/mythicdungeons/api/party/IDungeonParty.getPlayers:()Ljava/util/List;
      61: invokeinterface #1250,  1         // InterfaceMethod java/util/List.size:()I
      66: iconst_1
      67: if_icmpne     73
      70: aconst_null
      71: astore        6
      73: aload         6
      75: ifnull        227
      78: aload_0
      79: getfield      #205                // Field config:Lorg/bukkit/configuration/file/FileConfiguration;
      82: ldc_w         #1252               // String General.LeaderOnlyQueue
      85: iconst_1
      86: invokevirtual #367                // Method org/bukkit/configuration/file/FileConfiguration.getBoolean:(Ljava/lang/String;Z)Z
      89: ifeq          115
      92: aload_1
      93: aload         4
      95: invokevirtual #1244               // Method net/playavalon/mythicdungeons/player/MythicPlayer.getDungeonParty:()Lnet/playavalon/mythicdungeons/api/party/IDungeonParty;
      98: invokeinterface #1256,  1         // InterfaceMethod net/playavalon/mythicdungeons/api/party/IDungeonParty.getLeader:()Lorg/bukkit/OfflinePlayer;
     103: if_acmpeq     115
     106: aload_1
     107: ldc_w         #1258               // String commands.play.party-lead-only
     110: invokestatic  #1259               // Method net/playavalon/mythicdungeons/utility/helpers/LangUtils.sendMessage:(Lorg/bukkit/command/CommandSender;Ljava/lang/String;)V
     113: iconst_0
     114: ireturn
     115: iconst_1
     116: istore        7
     118: aload         6
     120: invokeinterface #1249,  1         // InterfaceMethod net/playavalon/mythicdungeons/api/party/IDungeonParty.getPlayers:()Ljava/util/List;
     125: invokeinterface #1098,  1         // InterfaceMethod java/util/List.iterator:()Ljava/util/Iterator;
     130: astore        8
     132: aload         8
     134: invokeinterface #911,  1          // InterfaceMethod java/util/Iterator.hasNext:()Z
     139: ifeq          197
     142: aload         8
     144: invokeinterface #915,  1          // InterfaceMethod java/util/Iterator.next:()Ljava/lang/Object;
     149: checkcast     #917                // class org/bukkit/entity/Player
     152: astore        9
     154: aload_0
     155: aload         9
     157: invokevirtual #1058               // Method getMythicPlayer:(Lorg/bukkit/entity/Player;)Lnet/playavalon/mythicdungeons/player/MythicPlayer;
     160: astore        10
     162: aload         10
     164: invokevirtual #1066               // Method net/playavalon/mythicdungeons/player/MythicPlayer.getInstance:()Lnet/playavalon/mythicdungeons/api/parents/instances/AbstractInstance;
     167: ifnull        194
     170: aload_1
     171: ldc_w         #1261               // String commands.play.player-in-dungeon
     174: iconst_1
     175: anewarray     #502                // class java/lang/String
     178: dup
     179: iconst_0
     180: aload         9
     182: invokeinterface #1264,  1         // InterfaceMethod org/bukkit/entity/Player.getName:()Ljava/lang/String;
     187: aastore
     188: invokestatic  #1267               // Method net/playavalon/mythicdungeons/utility/helpers/LangUtils.sendMessage:(Lorg/bukkit/command/CommandSender;Ljava/lang/String;[Ljava/lang/String;)V
     191: iconst_0
     192: istore        7
     194: goto          132
     197: iload         7
     199: ifne          204
     202: iconst_0
     203: ireturn
     204: aload         5
     206: aload         6
     208: invokevirtual #1271               // Method net/playavalon/mythicdungeons/api/parents/dungeons/AbstractDungeon.partyMeetsRequirements:(Lnet/playavalon/mythicdungeons/api/party/IDungeonParty;)Z
     211: ifne          216
     214: iconst_0
     215: ireturn
     216: aload         6
     218: iconst_1
     219: invokeinterface #1275,  2         // InterfaceMethod net/playavalon/mythicdungeons/api/party/IDungeonParty.setAwaitingDungeon:(Z)V
     224: goto          244
     227: aload         5
     229: aload_1
     230: invokevirtual #1278               // Method net/playavalon/mythicdungeons/api/parents/dungeons/AbstractDungeon.partyMeetsRequirements:(Lorg/bukkit/entity/Player;)Z
     233: ifne          238
     236: iconst_0
     237: ireturn
     238: aload         4
     240: iconst_1
     241: invokevirtual #1279               // Method net/playavalon/mythicdungeons/player/MythicPlayer.setAwaitingDungeon:(Z)V
     244: goto          264
     247: aload         5
     249: aload_1
     250: invokevirtual #1278               // Method net/playavalon/mythicdungeons/api/parents/dungeons/AbstractDungeon.partyMeetsRequirements:(Lorg/bukkit/entity/Player;)Z
     253: ifne          258
     256: iconst_0
     257: ireturn
     258: aload         4
     260: iconst_1
     261: invokevirtual #1279               // Method net/playavalon/mythicdungeons/player/MythicPlayer.setAwaitingDungeon:(Z)V
     264: new           #1281               // class net/playavalon/mythicdungeons/api/queue/QueueData
     267: dup
     268: aload         4
     270: aload         5
     272: aload_3
     273: invokespecial #1284               // Method net/playavalon/mythicdungeons/api/queue/QueueData."<init>":(Lnet/playavalon/mythicdungeons/player/MythicPlayer;Lnet/playavalon/mythicdungeons/api/parents/dungeons/AbstractDungeon;Ljava/lang/String;)V
     276: astore        6
     278: aload_0
     279: getfield      #454                // Field queueManager:Lnet/playavalon/mythicdungeons/managers/QueueManager;
     282: aload         6
     284: invokevirtual #1288               // Method net/playavalon/mythicdungeons/managers/QueueManager.enqueue:(Lnet/playavalon/mythicdungeons/api/queue/QueueData;)V
     287: aload_0
     288: getfield      #434                // Field activeInstances:Ljava/util/Map;
     291: invokeinterface #1291,  1         // InterfaceMethod java/util/Map.size:()I
     296: aload_0
     297: getfield      #205                // Field config:Lorg/bukkit/configuration/file/FileConfiguration;
     300: ldc_w         #1293               // String General.MaxInstances
     303: bipush        10
     305: invokevirtual #1297               // Method org/bukkit/configuration/file/FileConfiguration.getInt:(Ljava/lang/String;I)I
     308: if_icmpge     319
     311: aload         5
     313: invokevirtual #1300               // Method net/playavalon/mythicdungeons/api/parents/dungeons/AbstractDungeon.hasAvailableInstances:()Z
     316: ifne          335
     319: aload_1
     320: ldc_w         #1302               // String commands.play.instances-full
     323: invokestatic  #1259               // Method net/playavalon/mythicdungeons/utility/helpers/LangUtils.sendMessage:(Lorg/bukkit/command/CommandSender;Ljava/lang/String;)V
     326: aload_1
     327: ldc_w         #1304               // String commands.play.how-to-cancel
     330: invokestatic  #1259               // Method net/playavalon/mythicdungeons/utility/helpers/LangUtils.sendMessage:(Lorg/bukkit/command/CommandSender;Ljava/lang/String;)V
     333: iconst_1
     334: ireturn
     335: aload         4
     337: invokevirtual #1244               // Method net/playavalon/mythicdungeons/player/MythicPlayer.getDungeonParty:()Lnet/playavalon/mythicdungeons/api/party/IDungeonParty;
     340: ifnull        376
     343: aload         4
     345: invokevirtual #1244               // Method net/playavalon/mythicdungeons/player/MythicPlayer.getDungeonParty:()Lnet/playavalon/mythicdungeons/api/party/IDungeonParty;
     348: invokeinterface #1249,  1         // InterfaceMethod net/playavalon/mythicdungeons/api/party/IDungeonParty.getPlayers:()Ljava/util/List;
     353: invokeinterface #1250,  1         // InterfaceMethod java/util/List.size:()I
     358: iconst_1
     359: if_icmpeq     376
     362: aload_0
     363: getfield      #205                // Field config:Lorg/bukkit/configuration/file/FileConfiguration;
     366: ldc_w         #1306               // String General.ReadyCheckOnCommand
     369: iconst_1
     370: invokevirtual #367                // Method org/bukkit/configuration/file/FileConfiguration.getBoolean:(Ljava/lang/String;Z)Z
     373: ifne          380
     376: iconst_1
     377: goto          381
     380: iconst_0
     381: istore        7
     383: aload         6
     385: iload         7
     387: invokevirtual #1309               // Method net/playavalon/mythicdungeons/api/queue/QueueData.enterDungeon:(Z)V
     390: iconst_1
     391: ireturn

  public java.io.File getDungeonsFolder();
    Code:
       0: aload_0
       1: getfield      #303                // Field dungeonFiles:Ljava/io/File;
       4: areturn

  public net.playavalon.mythicdungeons.managers.DungeonManager getDungeonManager();
    Code:
       0: aload_0
       1: getfield      #896                // Field dungeons:Lnet/playavalon/mythicdungeons/managers/DungeonManager;
       4: areturn

  public <T extends net.playavalon.mythicdungeons.api.parents.dungeons.AbstractDungeon> void registerDungeonType(java.lang.Class<T>, java.lang.String, java.lang.String...);
    Code:
       0: aload_1
       1: aload_2
       2: aload_3
       3: invokestatic  #1327               // Method net/playavalon/mythicdungeons/managers/DungeonTypeManager.register:(Ljava/lang/Class;Ljava/lang/String;[Ljava/lang/String;)V
       6: return

  public <T extends net.playavalon.mythicdungeons.api.generation.layout.Layout> void registerLayout(java.lang.Class<T>, java.lang.String, java.lang.String...);
    Code:
       0: aload_1
       1: aload_2
       2: aload_3
       3: invokestatic  #1335               // Method net/playavalon/mythicdungeons/managers/LayoutManager.register:(Ljava/lang/Class;Ljava/lang/String;[Ljava/lang/String;)V
       6: return

  public <T extends net.playavalon.mythicdungeons.listeners.dungeonlisteners.InstanceListener> void registerInstanceListener(java.lang.Class<T>);
    Code:
       0: new           #1088               // class java/util/ArrayList
       3: dup
       4: invokespecial #1337               // Method java/util/ArrayList."<init>":()V
       7: astore_2
       8: aload_2
       9: aload_1
      10: ldc_w         #1339               // class org/bukkit/event/EventHandler
      13: invokestatic  #1343               // Method net/playavalon/mythicdungeons/utility/helpers/ReflectionUtils.getAnnotatedMethods:(Ljava/util/List;Ljava/lang/Class;Ljava/lang/Class;)V
      16: aload_2
      17: invokeinterface #1098,  1         // InterfaceMethod java/util/List.iterator:()Ljava/util/Iterator;
      22: astore_3
      23: aload_3
      24: invokeinterface #911,  1          // InterfaceMethod java/util/Iterator.hasNext:()Z
      29: ifeq          128
      32: aload_3
      33: invokeinterface #915,  1          // InterfaceMethod java/util/Iterator.next:()Ljava/lang/Object;
      38: checkcast     #579                // class java/lang/reflect/Method
      41: astore        4
      43: aload         4
      45: ldc_w         #1339               // class org/bukkit/event/EventHandler
      48: invokevirtual #1347               // Method java/lang/reflect/Method.getAnnotation:(Ljava/lang/Class;)Ljava/lang/annotation/Annotation;
      51: checkcast     #1339               // class org/bukkit/event/EventHandler
      54: astore        5
      56: aload         4
      58: invokevirtual #1351               // Method java/lang/reflect/Method.getParameterTypes:()[Ljava/lang/Class;
      61: iconst_0
      62: aaload
      63: astore        6
      65: ldc_w         #1353               // class org/bukkit/event/Event
      68: aload         6
      70: invokevirtual #1357               // Method java/lang/Class.isAssignableFrom:(Ljava/lang/Class;)Z
      73: ifne          79
      76: goto          23
      79: aload         6
      81: ldc_w         #1353               // class org/bukkit/event/Event
      84: invokevirtual #1361               // Method java/lang/Class.asSubclass:(Ljava/lang/Class;)Ljava/lang/Class;
      87: astore        7
      89: invokestatic  #147                // Method org/bukkit/Bukkit.getPluginManager:()Lorg/bukkit/plugin/PluginManager;
      92: aload         7
      94: invokestatic  #587                // Method inst:()Lnet/playavalon/mythicdungeons/MythicDungeons;
      97: invokevirtual #1365               // Method getInstanceEventHandler:()Lnet/playavalon/mythicdungeons/listeners/DynamicListener;
     100: aload         5
     102: invokeinterface #1369,  1         // InterfaceMethod org/bukkit/event/EventHandler.priority:()Lorg/bukkit/event/EventPriority;
     107: aload         7
     109: aload_1
     110: aload         4
     112: invokedynamic #1380,  0           // InvokeDynamic #13:execute:(Ljava/lang/Class;Ljava/lang/Class;Ljava/lang/reflect/Method;)Lorg/bukkit/plugin/EventExecutor;
     117: invokestatic  #587                // Method inst:()Lnet/playavalon/mythicdungeons/MythicDungeons;
     120: invokeinterface #1384,  6         // InterfaceMethod org/bukkit/plugin/PluginManager.registerEvent:(Ljava/lang/Class;Lorg/bukkit/event/Listener;Lorg/bukkit/event/EventPriority;Lorg/bukkit/plugin/EventExecutor;Lorg/bukkit/plugin/Plugin;)V
     125: goto          23
     128: return

  public <T extends net.playavalon.mythicdungeons.api.parents.elements.DungeonFunction> void registerFunction(java.lang.Class<T>);
    Code:
       0: aload_0
       1: getfield      #439                // Field functionManager:Lnet/playavalon/mythicdungeons/managers/FunctionManager;
       4: aload_1
       5: invokevirtual #1396               // Method net/playavalon/mythicdungeons/managers/FunctionManager.register:(Ljava/lang/Class;)V
       8: aload_1
       9: invokestatic  #398                // Method org/bukkit/configuration/serialization/ConfigurationSerialization.registerClass:(Ljava/lang/Class;)V
      12: return

  public <T extends net.playavalon.mythicdungeons.api.parents.elements.DungeonTrigger> void registerTrigger(java.lang.Class<T>);
    Code:
       0: aload_0
       1: getfield      #444                // Field triggerManager:Lnet/playavalon/mythicdungeons/managers/TriggerManager;
       4: aload_1
       5: invokevirtual #1399               // Method net/playavalon/mythicdungeons/managers/TriggerManager.register:(Ljava/lang/Class;)V
       8: aload_1
       9: invokestatic  #398                // Method org/bukkit/configuration/serialization/ConfigurationSerialization.registerClass:(Ljava/lang/Class;)V
      12: return

  public <T extends net.playavalon.mythicdungeons.api.parents.elements.TriggerCondition> void registerCondition(java.lang.Class<T>);
    Code:
       0: aload_0
       1: getfield      #449                // Field conditionManager:Lnet/playavalon/mythicdungeons/managers/ConditionManager;
       4: aload_1
       5: invokevirtual #1402               // Method net/playavalon/mythicdungeons/managers/ConditionManager.register:(Ljava/lang/Class;)V
       8: aload_1
       9: invokestatic  #398                // Method org/bukkit/configuration/serialization/ConfigurationSerialization.registerClass:(Ljava/lang/Class;)V
      12: return

  public void registerFunctions(java.lang.String);
    Code:
       0: new           #1405               // class org/reflections/Reflections
       3: dup
       4: aload_1
       5: iconst_0
       6: anewarray     #1407               // class org/reflections/scanners/Scanner
       9: invokespecial #1410               // Method org/reflections/Reflections."<init>":(Ljava/lang/String;[Lorg/reflections/scanners/Scanner;)V
      12: ldc_w         #1412               // class net/playavalon/mythicdungeons/api/annotations/DeclaredFunction
      15: invokevirtual #1416               // Method org/reflections/Reflections.getTypesAnnotatedWith:(Ljava/lang/Class;)Ljava/util/Set;
      18: astore_2
      19: aload_2
      20: invokeinterface #1419,  1         // InterfaceMethod java/util/Set.iterator:()Ljava/util/Iterator;
      25: astore_3
      26: aload_3
      27: invokeinterface #911,  1          // InterfaceMethod java/util/Iterator.hasNext:()Z
      32: ifeq          55
      35: aload_3
      36: invokeinterface #915,  1          // InterfaceMethod java/util/Iterator.next:()Ljava/lang/Object;
      41: checkcast     #224                // class java/lang/Class
      44: astore        4
      46: aload_0
      47: aload         4
      49: invokevirtual #772                // Method registerFunction:(Ljava/lang/Class;)V
      52: goto          26
      55: return

  public void registerTriggers(java.lang.String);
    Code:
       0: new           #1405               // class org/reflections/Reflections
       3: dup
       4: aload_1
       5: iconst_0
       6: anewarray     #1407               // class org/reflections/scanners/Scanner
       9: invokespecial #1410               // Method org/reflections/Reflections."<init>":(Ljava/lang/String;[Lorg/reflections/scanners/Scanner;)V
      12: ldc_w         #1425               // class net/playavalon/mythicdungeons/api/annotations/DeclaredTrigger
      15: invokevirtual #1416               // Method org/reflections/Reflections.getTypesAnnotatedWith:(Ljava/lang/Class;)Ljava/util/Set;
      18: astore_2
      19: aload_2
      20: invokeinterface #1419,  1         // InterfaceMethod java/util/Set.iterator:()Ljava/util/Iterator;
      25: astore_3
      26: aload_3
      27: invokeinterface #911,  1          // InterfaceMethod java/util/Iterator.hasNext:()Z
      32: ifeq          55
      35: aload_3
      36: invokeinterface #915,  1          // InterfaceMethod java/util/Iterator.next:()Ljava/lang/Object;
      41: checkcast     #224                // class java/lang/Class
      44: astore        4
      46: aload_0
      47: aload         4
      49: invokevirtual #795                // Method registerTrigger:(Ljava/lang/Class;)V
      52: goto          26
      55: return

  public void registerConditions(java.lang.String);
    Code:
       0: new           #1405               // class org/reflections/Reflections
       3: dup
       4: aload_1
       5: iconst_0
       6: anewarray     #1407               // class org/reflections/scanners/Scanner
       9: invokespecial #1410               // Method org/reflections/Reflections."<init>":(Ljava/lang/String;[Lorg/reflections/scanners/Scanner;)V
      12: ldc_w         #1428               // class net/playavalon/mythicdungeons/api/annotations/DeclaredCondition
      15: invokevirtual #1416               // Method org/reflections/Reflections.getTypesAnnotatedWith:(Ljava/lang/Class;)Ljava/util/Set;
      18: astore_2
      19: aload_2
      20: invokeinterface #1419,  1         // InterfaceMethod java/util/Set.iterator:()Ljava/util/Iterator;
      25: astore_3
      26: aload_3
      27: invokeinterface #911,  1          // InterfaceMethod java/util/Iterator.hasNext:()Z
      32: ifeq          55
      35: aload_3
      36: invokeinterface #915,  1          // InterfaceMethod java/util/Iterator.next:()Ljava/lang/Object;
      41: checkcast     #224                // class java/lang/Class
      44: astore        4
      46: aload_0
      47: aload         4
      49: invokevirtual #800                // Method registerCondition:(Ljava/lang/Class;)V
      52: goto          26
      55: return

  public static net.playavalon.mythicdungeons.MythicDungeons inst();
    Code:
       0: ldc           #2                  // class net/playavalon/mythicdungeons/MythicDungeons
       2: invokestatic  #1432               // Method getPlugin:(Ljava/lang/Class;)Lorg/bukkit/plugin/java/JavaPlugin;
       5: checkcast     #2                  // class net/playavalon/mythicdungeons/MythicDungeons
       8: areturn

  private boolean checkIfInternalPartySystem();
    Code:
       0: aload_0
       1: getfield      #510                // Field partiesEnabled:Z
       4: ifeq          35
       7: aload_0
       8: getfield      #414                // Field partyPluginName:Ljava/lang/String;
      11: ldc_w         #508                // String DungeonParties
      14: invokevirtual #540                // Method java/lang/String.equals:(Ljava/lang/Object;)Z
      17: ifne          33
      20: aload_0
      21: getfield      #414                // Field partyPluginName:Ljava/lang/String;
      24: ldc_w         #412                // String Default
      27: invokevirtual #540                // Method java/lang/String.equals:(Ljava/lang/Object;)Z
      30: ifeq          35
      33: iconst_1
      34: ireturn
      35: aload_0
      36: invokevirtual #480                // Method getLogger:()Ljava/util/logging/Logger;
      39: ldc_w         #1435               // String Cannot process API call. Party system is not enabled or the internal party system is not selected.
      42: invokevirtual #487                // Method java/util/logging/Logger.info:(Ljava/lang/String;)V
      45: iconst_0
      46: ireturn

  public boolean isPlayerInDungeon(org.bukkit.entity.Player);
    Code:
       0: aload_0
       1: invokevirtual #921                // Method getPlayerManager:()Lnet/playavalon/mythicdungeons/managers/PlayerManager;
       4: aload_1
       5: invokevirtual #1438               // Method net/playavalon/mythicdungeons/managers/PlayerManager.contains:(Lorg/bukkit/entity/Player;)Z
       8: ifne          13
      11: iconst_0
      12: ireturn
      13: aload_0
      14: invokevirtual #921                // Method getPlayerManager:()Lnet/playavalon/mythicdungeons/managers/PlayerManager;
      17: aload_1
      18: invokeinterface #1222,  1         // InterfaceMethod org/bukkit/entity/Player.getUniqueId:()Ljava/util/UUID;
      23: invokevirtual #1227               // Method net/playavalon/mythicdungeons/managers/PlayerManager.get:(Ljava/util/UUID;)Lnet/playavalon/mythicdungeons/player/MythicPlayer;
      26: invokevirtual #1066               // Method net/playavalon/mythicdungeons/player/MythicPlayer.getInstance:()Lnet/playavalon/mythicdungeons/api/parents/instances/AbstractInstance;
      29: ifnull        36
      32: iconst_1
      33: goto          37
      36: iconst_0
      37: ireturn

  public net.playavalon.mythicdungeons.api.parents.instances.AbstractInstance getDungeonInstance(org.bukkit.entity.Player);
    Code:
       0: aload_0
       1: invokevirtual #921                // Method getPlayerManager:()Lnet/playavalon/mythicdungeons/managers/PlayerManager;
       4: aload_1
       5: invokevirtual #1438               // Method net/playavalon/mythicdungeons/managers/PlayerManager.contains:(Lorg/bukkit/entity/Player;)Z
       8: ifne          13
      11: aconst_null
      12: areturn
      13: aload_0
      14: invokevirtual #921                // Method getPlayerManager:()Lnet/playavalon/mythicdungeons/managers/PlayerManager;
      17: aload_1
      18: invokeinterface #1222,  1         // InterfaceMethod org/bukkit/entity/Player.getUniqueId:()Ljava/util/UUID;
      23: invokevirtual #1227               // Method net/playavalon/mythicdungeons/managers/PlayerManager.get:(Ljava/util/UUID;)Lnet/playavalon/mythicdungeons/player/MythicPlayer;
      26: invokevirtual #1066               // Method net/playavalon/mythicdungeons/player/MythicPlayer.getInstance:()Lnet/playavalon/mythicdungeons/api/parents/instances/AbstractInstance;
      29: areturn

  public net.playavalon.mythicdungeons.api.parents.instances.AbstractInstance getDungeonInstance(java.lang.String);
    Code:
       0: aload_0
       1: getfield      #434                // Field activeInstances:Ljava/util/Map;
       4: invokeinterface #1444,  1         // InterfaceMethod java/util/Map.values:()Ljava/util/Collection;
       9: invokeinterface #906,  1          // InterfaceMethod java/util/Collection.iterator:()Ljava/util/Iterator;
      14: astore_2
      15: aload_2
      16: invokeinterface #911,  1          // InterfaceMethod java/util/Iterator.hasNext:()Z
      21: ifeq          55
      24: aload_2
      25: invokeinterface #915,  1          // InterfaceMethod java/util/Iterator.next:()Ljava/lang/Object;
      30: checkcast     #1068               // class net/playavalon/mythicdungeons/api/parents/instances/AbstractInstance
      33: astore_3
      34: aload_3
      35: invokevirtual #1447               // Method net/playavalon/mythicdungeons/api/parents/instances/AbstractInstance.getInstanceWorld:()Lorg/bukkit/World;
      38: invokeinterface #1448,  1         // InterfaceMethod org/bukkit/World.getName:()Ljava/lang/String;
      43: aload_1
      44: invokevirtual #540                // Method java/lang/String.equals:(Ljava/lang/Object;)Z
      47: ifeq          52
      50: aload_3
      51: areturn
      52: goto          15
      55: aconst_null
      56: areturn

  public java.util.Collection<net.playavalon.mythicdungeons.api.parents.dungeons.AbstractDungeon> getAllDungeons();
    Code:
       0: aload_0
       1: getfield      #896                // Field dungeons:Lnet/playavalon/mythicdungeons/managers/DungeonManager;
       4: invokevirtual #1084               // Method net/playavalon/mythicdungeons/managers/DungeonManager.getAll:()Ljava/util/Collection;
       7: areturn

  public boolean initiateDungeonForPlayer(org.bukkit.entity.Player, java.lang.String);
    Code:
       0: aload_0
       1: invokevirtual #1453               // Method getDungeonManager:()Lnet/playavalon/mythicdungeons/managers/DungeonManager;
       4: aload_2
       5: invokevirtual #1240               // Method net/playavalon/mythicdungeons/managers/DungeonManager.get:(Ljava/lang/String;)Lnet/playavalon/mythicdungeons/api/parents/dungeons/AbstractDungeon;
       8: dup
       9: astore_3
      10: ifnonnull     30
      13: aload_1
      14: ldc_w         #1455               // String commands.play.dungeon-not-found
      17: iconst_1
      18: anewarray     #502                // class java/lang/String
      21: dup
      22: iconst_0
      23: aload_2
      24: aastore
      25: invokestatic  #1267               // Method net/playavalon/mythicdungeons/utility/helpers/LangUtils.sendMessage:(Lorg/bukkit/command/CommandSender;Ljava/lang/String;[Ljava/lang/String;)V
      28: iconst_0
      29: ireturn
      30: aload_0
      31: aload_1
      32: invokevirtual #1058               // Method getMythicPlayer:(Lorg/bukkit/entity/Player;)Lnet/playavalon/mythicdungeons/player/MythicPlayer;
      35: astore        4
      37: aload         4
      39: invokevirtual #1066               // Method net/playavalon/mythicdungeons/player/MythicPlayer.getInstance:()Lnet/playavalon/mythicdungeons/api/parents/instances/AbstractInstance;
      42: ifnull        79
      45: aload         4
      47: invokevirtual #1066               // Method net/playavalon/mythicdungeons/player/MythicPlayer.getInstance:()Lnet/playavalon/mythicdungeons/api/parents/instances/AbstractInstance;
      50: invokevirtual #1459               // Method net/playavalon/mythicdungeons/api/parents/instances/AbstractInstance.getDungeon:()Lnet/playavalon/mythicdungeons/api/parents/dungeons/AbstractDungeon;
      53: aload_3
      54: if_acmpeq     79
      57: aload_1
      58: ldc_w         #1261               // String commands.play.player-in-dungeon
      61: iconst_1
      62: anewarray     #502                // class java/lang/String
      65: dup
      66: iconst_0
      67: aload_1
      68: invokeinterface #1264,  1         // InterfaceMethod org/bukkit/entity/Player.getName:()Ljava/lang/String;
      73: aastore
      74: invokestatic  #1267               // Method net/playavalon/mythicdungeons/utility/helpers/LangUtils.sendMessage:(Lorg/bukkit/command/CommandSender;Ljava/lang/String;[Ljava/lang/String;)V
      77: iconst_0
      78: ireturn
      79: aload_1
      80: ldc_w         #1461               // String dungeons.play
      83: invokestatic  #1465               // Method net/playavalon/mythicdungeons/utility/helpers/Util.hasPermission:(Lorg/bukkit/command/CommandSender;Ljava/lang/String;)Z
      86: ifne          111
      89: aload_1
      90: ldc_w         #1467               // String commands.play.requirements-not-met
      93: iconst_1
      94: anewarray     #502                // class java/lang/String
      97: dup
      98: iconst_0
      99: aload_1
     100: invokeinterface #1264,  1         // InterfaceMethod org/bukkit/entity/Player.getName:()Ljava/lang/String;
     105: aastore
     106: invokestatic  #1267               // Method net/playavalon/mythicdungeons/utility/helpers/LangUtils.sendMessage:(Lorg/bukkit/command/CommandSender;Ljava/lang/String;[Ljava/lang/String;)V
     109: iconst_0
     110: ireturn
     111: aload_0
     112: aload_1
     113: aload_2
     114: invokevirtual #1469               // Method sendToDungeon:(Lorg/bukkit/entity/Player;Ljava/lang/String;)Z
     117: pop
     118: iconst_0
     119: ireturn

  public boolean createParty(org.bukkit.entity.Player);
    Code:
       0: aload_0
       1: invokevirtual #1472               // Method checkIfInternalPartySystem:()Z
       4: ifne          9
       7: iconst_0
       8: ireturn
       9: aload_0
      10: aload_1
      11: invokevirtual #1058               // Method getMythicPlayer:(Lorg/bukkit/entity/Player;)Lnet/playavalon/mythicdungeons/player/MythicPlayer;
      14: astore_2
      15: aload_2
      16: invokevirtual #1476               // Method net/playavalon/mythicdungeons/player/MythicPlayer.getMythicParty:()Lnet/playavalon/mythicdungeons/player/party/partysystem/MythicParty;
      19: ifnull        24
      22: iconst_0
      23: ireturn
      24: aload_2
      25: new           #1478               // class net/playavalon/mythicdungeons/player/party/partysystem/MythicParty
      28: dup
      29: aload_1
      30: invokespecial #1480               // Method net/playavalon/mythicdungeons/player/party/partysystem/MythicParty."<init>":(Lorg/bukkit/entity/Player;)V
      33: invokevirtual #1484               // Method net/playavalon/mythicdungeons/player/MythicPlayer.setMythicParty:(Lnet/playavalon/mythicdungeons/player/party/partysystem/MythicParty;)V
      36: iconst_1
      37: ireturn

  public boolean removeFromParty(org.bukkit.entity.Player);
    Code:
       0: aload_0
       1: invokevirtual #1472               // Method checkIfInternalPartySystem:()Z
       4: ifne          9
       7: iconst_0
       8: ireturn
       9: aload_0
      10: aload_1
      11: invokevirtual #1058               // Method getMythicPlayer:(Lorg/bukkit/entity/Player;)Lnet/playavalon/mythicdungeons/player/MythicPlayer;
      14: astore_2
      15: aload_2
      16: invokevirtual #1476               // Method net/playavalon/mythicdungeons/player/MythicPlayer.getMythicParty:()Lnet/playavalon/mythicdungeons/player/party/partysystem/MythicParty;
      19: astore_3
      20: aload_3
      21: ifnonnull     26
      24: iconst_0
      25: ireturn
      26: aload_3
      27: aload_2
      28: invokevirtual #1124               // Method net/playavalon/mythicdungeons/player/MythicPlayer.getPlayer:()Lorg/bukkit/entity/Player;
      31: invokevirtual #1489               // Method net/playavalon/mythicdungeons/player/party/partysystem/MythicParty.removePlayer:(Lorg/bukkit/entity/Player;)V
      34: iconst_1
      35: ireturn

  public boolean disbandParty(net.playavalon.mythicdungeons.player.party.partysystem.MythicParty);
    Code:
       0: aload_0
       1: invokevirtual #1472               // Method checkIfInternalPartySystem:()Z
       4: ifne          9
       7: iconst_0
       8: ireturn
       9: aload_1
      10: invokevirtual #1495               // Method net/playavalon/mythicdungeons/player/party/partysystem/MythicParty.disband:()V
      13: iconst_1
      14: ireturn

  public boolean disbandParty(org.bukkit.entity.Player);
    Code:
       0: aload_0
       1: invokevirtual #1472               // Method checkIfInternalPartySystem:()Z
       4: ifne          9
       7: iconst_0
       8: ireturn
       9: aload_0
      10: aload_1
      11: invokevirtual #1058               // Method getMythicPlayer:(Lorg/bukkit/entity/Player;)Lnet/playavalon/mythicdungeons/player/MythicPlayer;
      14: astore_2
      15: aload_2
      16: invokevirtual #1476               // Method net/playavalon/mythicdungeons/player/MythicPlayer.getMythicParty:()Lnet/playavalon/mythicdungeons/player/party/partysystem/MythicParty;
      19: astore_3
      20: aload_3
      21: ifnonnull     26
      24: iconst_0
      25: ireturn
      26: aload_3
      27: invokevirtual #1495               // Method net/playavalon/mythicdungeons/player/party/partysystem/MythicParty.disband:()V
      30: iconst_1
      31: ireturn

  public boolean inviteToParty(org.bukkit.entity.Player, org.bukkit.entity.Player);
    Code:
       0: aload_0
       1: invokevirtual #1472               // Method checkIfInternalPartySystem:()Z
       4: ifne          9
       7: iconst_0
       8: ireturn
       9: aload_0
      10: aload_1
      11: invokevirtual #1058               // Method getMythicPlayer:(Lorg/bukkit/entity/Player;)Lnet/playavalon/mythicdungeons/player/MythicPlayer;
      14: astore_3
      15: aload_3
      16: invokevirtual #1500               // Method net/playavalon/mythicdungeons/player/MythicPlayer.hasParty:()Z
      19: ifne          24
      22: iconst_0
      23: ireturn
      24: aload_0
      25: aload_2
      26: invokevirtual #1058               // Method getMythicPlayer:(Lorg/bukkit/entity/Player;)Lnet/playavalon/mythicdungeons/player/MythicPlayer;
      29: astore        4
      31: aload         4
      33: invokevirtual #1500               // Method net/playavalon/mythicdungeons/player/MythicPlayer.hasParty:()Z
      36: ifeq          41
      39: iconst_0
      40: ireturn
      41: aload         4
      43: aload_1
      44: invokevirtual #1503               // Method net/playavalon/mythicdungeons/player/MythicPlayer.setInviteFrom:(Lorg/bukkit/entity/Player;)V
      47: iconst_1
      48: ireturn

  public boolean acceptPartyInvite(org.bukkit.entity.Player);
    Code:
       0: aload_0
       1: invokevirtual #1472               // Method checkIfInternalPartySystem:()Z
       4: ifne          9
       7: iconst_0
       8: ireturn
       9: aload_0
      10: aload_1
      11: invokevirtual #1058               // Method getMythicPlayer:(Lorg/bukkit/entity/Player;)Lnet/playavalon/mythicdungeons/player/MythicPlayer;
      14: astore_2
      15: aload_2
      16: invokevirtual #1500               // Method net/playavalon/mythicdungeons/player/MythicPlayer.hasParty:()Z
      19: ifeq          24
      22: iconst_0
      23: ireturn
      24: aload_2
      25: invokevirtual #1510               // Method net/playavalon/mythicdungeons/player/MythicPlayer.getInviteFrom:()Lorg/bukkit/entity/Player;
      28: ifnonnull     33
      31: iconst_0
      32: ireturn
      33: aload_2
      34: invokevirtual #1510               // Method net/playavalon/mythicdungeons/player/MythicPlayer.getInviteFrom:()Lorg/bukkit/entity/Player;
      37: astore_3
      38: aload_0
      39: aload_3
      40: invokevirtual #1058               // Method getMythicPlayer:(Lorg/bukkit/entity/Player;)Lnet/playavalon/mythicdungeons/player/MythicPlayer;
      43: astore        4
      45: aload         4
      47: invokevirtual #1476               // Method net/playavalon/mythicdungeons/player/MythicPlayer.getMythicParty:()Lnet/playavalon/mythicdungeons/player/party/partysystem/MythicParty;
      50: astore        5
      52: aload         5
      54: ifnonnull     59
      57: iconst_0
      58: ireturn
      59: aload         5
      61: aload_2
      62: invokevirtual #1124               // Method net/playavalon/mythicdungeons/player/MythicPlayer.getPlayer:()Lorg/bukkit/entity/Player;
      65: invokevirtual #1513               // Method net/playavalon/mythicdungeons/player/party/partysystem/MythicParty.addPlayer:(Lorg/bukkit/entity/Player;)V
      68: iconst_1
      69: ireturn

  public boolean declinePartyInvite(org.bukkit.entity.Player);
    Code:
       0: aload_0
       1: invokevirtual #1472               // Method checkIfInternalPartySystem:()Z
       4: ifne          9
       7: iconst_0
       8: ireturn
       9: aload_0
      10: aload_1
      11: invokevirtual #1058               // Method getMythicPlayer:(Lorg/bukkit/entity/Player;)Lnet/playavalon/mythicdungeons/player/MythicPlayer;
      14: astore_2
      15: aload_2
      16: invokevirtual #1500               // Method net/playavalon/mythicdungeons/player/MythicPlayer.hasParty:()Z
      19: ifeq          24
      22: iconst_0
      23: ireturn
      24: aload_2
      25: invokevirtual #1510               // Method net/playavalon/mythicdungeons/player/MythicPlayer.getInviteFrom:()Lorg/bukkit/entity/Player;
      28: ifnonnull     33
      31: iconst_0
      32: ireturn
      33: aload_2
      34: aconst_null
      35: invokevirtual #1503               // Method net/playavalon/mythicdungeons/player/MythicPlayer.setInviteFrom:(Lorg/bukkit/entity/Player;)V
      38: iconst_0
      39: ireturn

  public boolean setPartyLeader(org.bukkit.entity.Player);
    Code:
       0: aload_0
       1: invokevirtual #1472               // Method checkIfInternalPartySystem:()Z
       4: ifne          9
       7: iconst_0
       8: ireturn
       9: aload_0
      10: aload_1
      11: invokevirtual #1058               // Method getMythicPlayer:(Lorg/bukkit/entity/Player;)Lnet/playavalon/mythicdungeons/player/MythicPlayer;
      14: astore_2
      15: aload_2
      16: invokevirtual #1500               // Method net/playavalon/mythicdungeons/player/MythicPlayer.hasParty:()Z
      19: ifne          24
      22: iconst_0
      23: ireturn
      24: aload_2
      25: invokevirtual #1476               // Method net/playavalon/mythicdungeons/player/MythicPlayer.getMythicParty:()Lnet/playavalon/mythicdungeons/player/party/partysystem/MythicParty;
      28: astore_3
      29: aload_3
      30: aload_1
      31: invokevirtual #1520               // Method net/playavalon/mythicdungeons/player/party/partysystem/MythicParty.setMythicLeader:(Lorg/bukkit/entity/Player;)V
      34: iconst_1
      35: ireturn

  public net.playavalon.mythicdungeons.player.party.partysystem.MythicParty getParty(org.bukkit.entity.Player);
    Code:
       0: aload_0
       1: invokevirtual #1472               // Method checkIfInternalPartySystem:()Z
       4: ifne          9
       7: aconst_null
       8: areturn
       9: aload_0
      10: aload_1
      11: invokevirtual #1058               // Method getMythicPlayer:(Lorg/bukkit/entity/Player;)Lnet/playavalon/mythicdungeons/player/MythicPlayer;
      14: astore_2
      15: aload_2
      16: invokevirtual #1500               // Method net/playavalon/mythicdungeons/player/MythicPlayer.hasParty:()Z
      19: ifne          24
      22: aconst_null
      23: areturn
      24: aload_2
      25: invokevirtual #1476               // Method net/playavalon/mythicdungeons/player/MythicPlayer.getMythicParty:()Lnet/playavalon/mythicdungeons/player/party/partysystem/MythicParty;
      28: areturn

  public java.lang.String isPartyQueuedForDungeon(org.bukkit.entity.Player);
    Code:
       0: aload_0
       1: aload_1
       2: invokevirtual #1058               // Method getMythicPlayer:(Lorg/bukkit/entity/Player;)Lnet/playavalon/mythicdungeons/player/MythicPlayer;
       5: astore_2
       6: aload_0
       7: getfield      #454                // Field queueManager:Lnet/playavalon/mythicdungeons/managers/QueueManager;
      10: aload_2
      11: invokevirtual #1528               // Method net/playavalon/mythicdungeons/managers/QueueManager.getQueue:(Lnet/playavalon/mythicdungeons/player/MythicPlayer;)Lnet/playavalon/mythicdungeons/api/queue/QueueData;
      14: astore_3
      15: aload_3
      16: ifnonnull     21
      19: aconst_null
      20: areturn
      21: aload_3
      22: invokevirtual #1529               // Method net/playavalon/mythicdungeons/api/queue/QueueData.getDungeon:()Lnet/playavalon/mythicdungeons/api/parents/dungeons/AbstractDungeon;
      25: invokevirtual #1532               // Method net/playavalon/mythicdungeons/api/parents/dungeons/AbstractDungeon.getWorldName:()Ljava/lang/String;
      28: areturn

  public java.lang.String isPartyQueuedForDungeon(net.playavalon.mythicdungeons.api.party.IDungeonParty);
    Code:
       0: aload_1
       1: invokeinterface #1256,  1         // InterfaceMethod net/playavalon/mythicdungeons/api/party/IDungeonParty.getLeader:()Lorg/bukkit/OfflinePlayer;
       6: ifnonnull     11
       9: aconst_null
      10: areturn
      11: aload_0
      12: aload_1
      13: invokeinterface #1256,  1         // InterfaceMethod net/playavalon/mythicdungeons/api/party/IDungeonParty.getLeader:()Lorg/bukkit/OfflinePlayer;
      18: invokeinterface #1536,  1         // InterfaceMethod org/bukkit/OfflinePlayer.getUniqueId:()Ljava/util/UUID;
      23: invokevirtual #1225               // Method getMythicPlayer:(Ljava/util/UUID;)Lnet/playavalon/mythicdungeons/player/MythicPlayer;
      26: astore_2
      27: aload_0
      28: getfield      #454                // Field queueManager:Lnet/playavalon/mythicdungeons/managers/QueueManager;
      31: aload_2
      32: invokevirtual #1528               // Method net/playavalon/mythicdungeons/managers/QueueManager.getQueue:(Lnet/playavalon/mythicdungeons/player/MythicPlayer;)Lnet/playavalon/mythicdungeons/api/queue/QueueData;
      35: astore_3
      36: aload_3
      37: ifnonnull     42
      40: aconst_null
      41: areturn
      42: aload_3
      43: invokevirtual #1529               // Method net/playavalon/mythicdungeons/api/queue/QueueData.getDungeon:()Lnet/playavalon/mythicdungeons/api/parents/dungeons/AbstractDungeon;
      46: invokevirtual #1532               // Method net/playavalon/mythicdungeons/api/parents/dungeons/AbstractDungeon.getWorldName:()Ljava/lang/String;
      49: areturn

  public net.kyori.adventure.text.minimessage.MiniMessage getMiniMessage();
    Code:
       0: aload_0
       1: getfield      #130                // Field miniMessage:Lnet/kyori/adventure/text/minimessage/MiniMessage;
       4: areturn

  public org.bukkit.configuration.file.FileConfiguration getDefaultDungeonConfig();
    Code:
       0: aload_0
       1: getfield      #210                // Field defaultDungeonConfig:Lorg/bukkit/configuration/file/FileConfiguration;
       4: areturn

  public org.bukkit.Material getFunctionBuilderMaterial();
    Code:
       0: aload_0
       1: getfield      #347                // Field functionBuilderMaterial:Lorg/bukkit/Material;
       4: areturn

  public org.bukkit.Material getRoomEditorMaterial();
    Code:
       0: aload_0
       1: getfield      #357                // Field roomEditorMaterial:Lorg/bukkit/Material;
       4: areturn

  public boolean isStuckKillsPlayer();
    Code:
       0: aload_0
       1: getfield      #369                // Field stuckKillsPlayer:Z
       4: ireturn

  public boolean isInheritedVelocityEnabled();
    Code:
       0: aload_0
       1: getfield      #373                // Field inheritedVelocityEnabled:Z
       4: ireturn

  public boolean isPaperSupport();
    Code:
       0: aload_0
       1: getfield      #230                // Field paperSupport:Z
       4: ireturn

  public boolean isSupportsTeleportFlags();
    Code:
       0: aload_0
       1: getfield      #234                // Field supportsTeleportFlags:Z
       4: ireturn

  public boolean isSupportsTeleportAsync();
    Code:
       0: aload_0
       1: getfield      #132                // Field supportsTeleportAsync:Z
       4: ireturn

  public boolean isSupportsFAWE();
    Code:
       0: aload_0
       1: getfield      #1549               // Field supportsFAWE:Z
       4: ireturn

  public boolean isUseSameWorldSystem();
    Code:
       0: aload_0
       1: getfield      #891                // Field useSameWorldSystem:Z
       4: ireturn

  public net.playavalon.mythicdungeons.avngui.AvnAPI getAvnAPI();
    Code:
       0: aload_0
       1: getfield      #380                // Field avnAPI:Lnet/playavalon/mythicdungeons/avngui/AvnAPI;
       4: areturn

  public io.lumine.mythic.bukkit.MythicBukkit getMythicApi();
    Code:
       0: aload_0
       1: getfield      #617                // Field mythicApi:Lio/lumine/mythic/bukkit/MythicBukkit;
       4: areturn

  public net.citizensnpcs.Citizens getCitizensApi();
    Code:
       0: aload_0
       1: getfield      #642                // Field citizensApi:Lnet/citizensnpcs/Citizens;
       4: areturn

  public net.playavalon.mythicdungeons.compatibility.citizens.MythicNPCRegistry getMythicNPCRegistry();
    Code:
       0: aload_0
       1: getfield      #647                // Field mythicNPCRegistry:Lnet/playavalon/mythicdungeons/compatibility/citizens/MythicNPCRegistry;
       4: areturn

  public net.milkbowl.vault.economy.Economy getEconomy();
    Code:
       0: aload_0
       1: getfield      #1048               // Field economy:Lnet/milkbowl/vault/economy/Economy;
       4: areturn

  public org.mvplugins.multiverse.inventories.MultiverseInventories getMultiverseInv();
    Code:
       0: aload_0
       1: getfield      #1563               // Field multiverseInv:Lorg/mvplugins/multiverse/inventories/MultiverseInventories;
       4: areturn

  public com.github.retrooper.packetevents.PacketEventsAPI<?> getPacketEvents();
    Code:
       0: aload_0
       1: getfield      #649                // Field packetEvents:Lcom/github/retrooper/packetevents/PacketEventsAPI;
       4: areturn

  public boolean isBetonEnabled();
    Code:
       0: aload_0
       1: getfield      #683                // Field betonEnabled:Z
       4: ireturn

  public void setBetonEnabled(boolean);
    Code:
       0: aload_0
       1: iload_1
       2: putfield      #683                // Field betonEnabled:Z
       5: return

  public boolean isFaweEnabled();
    Code:
       0: aload_0
       1: getfield      #1570               // Field faweEnabled:Z
       4: ireturn

  public void setFaweEnabled(boolean);
    Code:
       0: aload_0
       1: iload_1
       2: putfield      #1570               // Field faweEnabled:Z
       5: return

  public boolean isPartiesEnabled();
    Code:
       0: aload_0
       1: getfield      #510                // Field partiesEnabled:Z
       4: ireturn

  public java.lang.String getPartyPluginName();
    Code:
       0: aload_0
       1: getfield      #414                // Field partyPluginName:Ljava/lang/String;
       4: areturn

  public boolean isThirdPartyProvider();
    Code:
       0: aload_0
       1: getfield      #544                // Field thirdPartyProvider:Z
       4: ireturn

  public com.herocraftonline.heroes.Heroes getHeroesApi();
    Code:
       0: aload_0
       1: getfield      #552                // Field heroesApi:Lcom/herocraftonline/heroes/Heroes;
       4: areturn

  public com.alessiodp.parties.api.interfaces.PartiesAPI getPartiesAPI();
    Code:
       0: aload_0
       1: getfield      #563                // Field partiesAPI:Lcom/alessiodp/parties/api/interfaces/PartiesAPI;
       4: areturn

  public java.io.File getDungeonFiles();
    Code:
       0: aload_0
       1: getfield      #303                // Field dungeonFiles:Ljava/io/File;
       4: areturn

  public java.io.File getBackupFolder();
    Code:
       0: aload_0
       1: getfield      #307                // Field backupFolder:Ljava/io/File;
       4: areturn

  public java.io.File getPlayerDataFolder();
    Code:
       0: aload_0
       1: getfield      #321                // Field playerDataFolder:Ljava/io/File;
       4: areturn

  public net.playavalon.mythicdungeons.managers.PlayerManager getPlayerManager();
    Code:
       0: aload_0
       1: getfield      #419                // Field playerManager:Lnet/playavalon/mythicdungeons/managers/PlayerManager;
       4: areturn

  public net.playavalon.mythicdungeons.managers.PartyManager getPartyManager();
    Code:
       0: aload_0
       1: getfield      #424                // Field partyManager:Lnet/playavalon/mythicdungeons/managers/PartyManager;
       4: areturn

  public net.playavalon.mythicdungeons.managers.PartyProviderManager getProviderManager();
    Code:
       0: aload_0
       1: getfield      #429                // Field providerManager:Lnet/playavalon/mythicdungeons/managers/PartyProviderManager;
       4: areturn

  public net.playavalon.mythicdungeons.managers.DungeonManager getDungeons();
    Code:
       0: aload_0
       1: getfield      #896                // Field dungeons:Lnet/playavalon/mythicdungeons/managers/DungeonManager;
       4: areturn

  public java.util.Map<java.util.UUID, net.playavalon.mythicdungeons.api.parents.instances.AbstractInstance> getActiveInstances();
    Code:
       0: aload_0
       1: getfield      #434                // Field activeInstances:Ljava/util/Map;
       4: areturn

  public net.playavalon.mythicdungeons.managers.FunctionManager getFunctionManager();
    Code:
       0: aload_0
       1: getfield      #439                // Field functionManager:Lnet/playavalon/mythicdungeons/managers/FunctionManager;
       4: areturn

  public net.playavalon.mythicdungeons.managers.TriggerManager getTriggerManager();
    Code:
       0: aload_0
       1: getfield      #444                // Field triggerManager:Lnet/playavalon/mythicdungeons/managers/TriggerManager;
       4: areturn

  public net.playavalon.mythicdungeons.managers.ConditionManager getConditionManager();
    Code:
       0: aload_0
       1: getfield      #449                // Field conditionManager:Lnet/playavalon/mythicdungeons/managers/ConditionManager;
       4: areturn

  public net.playavalon.mythicdungeons.managers.QueueManager getQueueManager();
    Code:
       0: aload_0
       1: getfield      #454                // Field queueManager:Lnet/playavalon/mythicdungeons/managers/QueueManager;
       4: areturn

  public net.playavalon.mythicdungeons.managers.LootTableManager getLootTableManager();
    Code:
       0: aload_0
       1: getfield      #459                // Field lootTableManager:Lnet/playavalon/mythicdungeons/managers/LootTableManager;
       4: areturn

  public net.playavalon.mythicdungeons.managers.MovingBlockManager getMovingBlockManager();
    Code:
       0: aload_0
       1: getfield      #471                // Field movingBlockManager:Lnet/playavalon/mythicdungeons/managers/MovingBlockManager;
       4: areturn

  public net.playavalon.mythicdungeons.managers.PartyRecruitmentManager getListingManager();
    Code:
       0: aload_0
       1: getfield      #515                // Field listingManager:Lnet/playavalon/mythicdungeons/managers/PartyRecruitmentManager;
       4: areturn

  public net.playavalon.mythicdungeons.managers.HotbarMenuManager getHotbarMenus();
    Code:
       0: aload_0
       1: getfield      #608                // Field hotbarMenus:Lnet/playavalon/mythicdungeons/managers/HotbarMenuManager;
       4: areturn

  public net.playavalon.mythicdungeons.managers.CommandManager getCommandManager();
    Code:
       0: aload_0
       1: getfield      #466                // Field commandManager:Lnet/playavalon/mythicdungeons/managers/CommandManager;
       4: areturn

  public net.playavalon.mythicdungeons.managers.SpectatorManager getSpectatorManager();
    Code:
       0: aload_0
       1: getfield      #476                // Field spectatorManager:Lnet/playavalon/mythicdungeons/managers/SpectatorManager;
       4: areturn

  public net.playavalon.mythicdungeons.listeners.DynamicListener getElementEventHandler();
    Code:
       0: aload_0
       1: getfield      #137                // Field elementEventHandler:Lnet/playavalon/mythicdungeons/listeners/DynamicListener;
       4: areturn

  public net.playavalon.mythicdungeons.listeners.DynamicListener getInstanceEventHandler();
    Code:
       0: aload_0
       1: getfield      #139                // Field instanceEventHandler:Lnet/playavalon/mythicdungeons/listeners/DynamicListener;
       4: areturn

  private static void lambda$registerInstanceListener$2(java.lang.Class, java.lang.Class, java.lang.reflect.Method, org.bukkit.event.Listener, org.bukkit.event.Event) throws org.bukkit.event.EventException;
    Code:
       0: invokestatic  #587                // Method inst:()Lnet/playavalon/mythicdungeons/MythicDungeons;
       3: invokevirtual #1614               // Method getActiveInstances:()Ljava/util/Map;
       6: invokeinterface #1444,  1         // InterfaceMethod java/util/Map.values:()Ljava/util/Collection;
      11: astore        5
      13: aload         5
      15: invokeinterface #906,  1          // InterfaceMethod java/util/Collection.iterator:()Ljava/util/Iterator;
      20: astore        6
      22: aload         6
      24: invokeinterface #911,  1          // InterfaceMethod java/util/Iterator.hasNext:()Z
      29: ifeq          118
      32: aload         6
      34: invokeinterface #915,  1          // InterfaceMethod java/util/Iterator.next:()Ljava/lang/Object;
      39: checkcast     #1068               // class net/playavalon/mythicdungeons/api/parents/instances/AbstractInstance
      42: astore        7
      44: aload_0
      45: aload         4
      47: invokevirtual #1618               // Method java/lang/Object.getClass:()Ljava/lang/Class;
      50: invokevirtual #1357               // Method java/lang/Class.isAssignableFrom:(Ljava/lang/Class;)Z
      53: ifne          59
      56: goto          22
      59: aload         7
      61: invokevirtual #1622               // Method net/playavalon/mythicdungeons/api/parents/instances/AbstractInstance.getListener:()Lnet/playavalon/mythicdungeons/listeners/dungeonlisteners/InstanceListener;
      64: astore        8
      66: aload         8
      68: ifnonnull     74
      71: goto          22
      74: aload_1
      75: aload         8
      77: invokevirtual #1618               // Method java/lang/Object.getClass:()Ljava/lang/Class;
      80: invokevirtual #1357               // Method java/lang/Class.isAssignableFrom:(Ljava/lang/Class;)Z
      83: ifne          89
      86: goto          22
      89: aload_2
      90: aload         8
      92: iconst_1
      93: anewarray     #577                // class java/lang/Object
      96: dup
      97: iconst_0
      98: aload         4
     100: aastore
     101: invokevirtual #583                // Method java/lang/reflect/Method.invoke:(Ljava/lang/Object;[Ljava/lang/Object;)Ljava/lang/Object;
     104: pop
     105: goto          115
     108: astore        9
     110: aload         9
     112: invokevirtual #1627               // Method java/lang/Exception.printStackTrace:()V
     115: goto          22
     118: return
    Exception table:
       from    to  target type
          89   105   108   Class java/lang/Exception

  private void lambda$reloadAllDungeons$1();
    Code:
       0: aload_0
       1: new           #893                // class net/playavalon/mythicdungeons/managers/DungeonManager
       4: dup
       5: invokespecial #894                // Method net/playavalon/mythicdungeons/managers/DungeonManager."<init>":()V
       8: putfield      #896                // Field dungeons:Lnet/playavalon/mythicdungeons/managers/DungeonManager;
      11: return

  private void lambda$onEnable$0();
    Code:
       0: aload_0
       1: invokestatic  #1637               // Method org/bukkit/Bukkit.getServer:()Lorg/bukkit/Server;
       4: invokeinterface #1033,  1         // InterfaceMethod org/bukkit/Server.getPluginManager:()Lorg/bukkit/plugin/PluginManager;
       9: ldc_w         #1639               // String Multiverse-Inventories
      12: invokeinterface #155,  2          // InterfaceMethod org/bukkit/plugin/PluginManager.getPlugin:(Ljava/lang/String;)Lorg/bukkit/plugin/Plugin;
      17: checkcast     #1641               // class org/mvplugins/multiverse/inventories/MultiverseInventories
      20: putfield      #1563               // Field multiverseInv:Lorg/mvplugins/multiverse/inventories/MultiverseInventories;
      23: return
}
