Compiled from "AxiomPermissionSet.java"
public class com.moulberry.axiom.restrictions.AxiomPermissionSet {
  public final java.util.EnumSet<com.moulberry.axiom.restrictions.AxiomPermission> explicitlyAllowed;

  public final java.util.EnumSet<com.moulberry.axiom.restrictions.AxiomPermission> explicitlyDenied;

  private java.util.EnumSet<com.moulberry.axiom.restrictions.AxiomPermission> calculated;

  public static com.moulberry.axiom.restrictions.AxiomPermissionSet ALL;

  public static com.moulberry.axiom.restrictions.AxiomPermissionSet DEFAULT;

  public static com.moulberry.axiom.restrictions.AxiomPermissionSet NONE;

  private static final com.moulberry.axiom.restrictions.AxiomPermission[] PERMISSIONS;

  public com.moulberry.axiom.restrictions.AxiomPermissionSet(java.util.EnumSet<com.moulberry.axiom.restrictions.AxiomPermission>, java.util.EnumSet<com.moulberry.axiom.restrictions.AxiomPermission>);
    Code:
       0: aload_0
       1: invokespecial #22                 // Method java/lang/Object."<init>":()V
       4: aload_0
       5: aconst_null
       6: putfield      #24                 // Field calculated:Ljava/util/EnumSet;
       9: aload_0
      10: aload_1
      11: putfield      #26                 // Field explicitlyAllowed:Ljava/util/EnumSet;
      14: aload_0
      15: aload_2
      16: putfield      #28                 // Field explicitlyDenied:Ljava/util/EnumSet;
      19: return

  public boolean contains(com.moulberry.axiom.restrictions.AxiomPermission);
    Code:
       0: aload_0
       1: getfield      #24                 // Field calculated:Ljava/util/EnumSet;
       4: ifnonnull     11
       7: aload_0
       8: invokevirtual #35                 // Method calculate:()V
      11: aload_0
      12: getfield      #24                 // Field calculated:Ljava/util/EnumSet;
      15: aload_1
      16: invokevirtual #40                 // Method java/util/EnumSet.contains:(Ljava/lang/Object;)Z
      19: ireturn

  public boolean containsAll(java.util.EnumSet<com.moulberry.axiom.restrictions.AxiomPermission>);
    Code:
       0: aload_0
       1: getfield      #24                 // Field calculated:Ljava/util/EnumSet;
       4: ifnonnull     11
       7: aload_0
       8: invokevirtual #35                 // Method calculate:()V
      11: aload_0
      12: getfield      #24                 // Field calculated:Ljava/util/EnumSet;
      15: aload_1
      16: invokevirtual #48                 // Method java/util/EnumSet.containsAll:(Ljava/util/Collection;)Z
      19: ireturn

  public boolean containsAll(com.moulberry.axiom.restrictions.AxiomPermissionSet);
    Code:
       0: aload_0
       1: getfield      #24                 // Field calculated:Ljava/util/EnumSet;
       4: ifnonnull     11
       7: aload_0
       8: invokevirtual #35                 // Method calculate:()V
      11: aload_1
      12: getfield      #24                 // Field calculated:Ljava/util/EnumSet;
      15: ifnonnull     22
      18: aload_1
      19: invokevirtual #35                 // Method calculate:()V
      22: aload_0
      23: getfield      #24                 // Field calculated:Ljava/util/EnumSet;
      26: aload_1
      27: getfield      #24                 // Field calculated:Ljava/util/EnumSet;
      30: invokevirtual #48                 // Method java/util/EnumSet.containsAll:(Ljava/util/Collection;)Z
      33: ireturn

  public boolean containsAllButIgnore(com.moulberry.axiom.restrictions.AxiomPermissionSet, java.util.EnumSet<com.moulberry.axiom.restrictions.AxiomPermission>);
    Code:
       0: aload_0
       1: getfield      #24                 // Field calculated:Ljava/util/EnumSet;
       4: ifnonnull     11
       7: aload_0
       8: invokevirtual #35                 // Method calculate:()V
      11: aload_1
      12: getfield      #24                 // Field calculated:Ljava/util/EnumSet;
      15: ifnonnull     22
      18: aload_1
      19: invokevirtual #35                 // Method calculate:()V
      22: aload_0
      23: getfield      #24                 // Field calculated:Ljava/util/EnumSet;
      26: invokestatic  #58                 // Method java/util/EnumSet.copyOf:(Ljava/util/EnumSet;)Ljava/util/EnumSet;
      29: astore_3
      30: aload_1
      31: getfield      #24                 // Field calculated:Ljava/util/EnumSet;
      34: invokestatic  #58                 // Method java/util/EnumSet.copyOf:(Ljava/util/EnumSet;)Ljava/util/EnumSet;
      37: astore        4
      39: aload_3
      40: aload_2
      41: invokevirtual #61                 // Method java/util/EnumSet.removeAll:(Ljava/util/Collection;)Z
      44: pop
      45: aload         4
      47: aload_2
      48: invokevirtual #61                 // Method java/util/EnumSet.removeAll:(Ljava/util/Collection;)Z
      51: pop
      52: aload_3
      53: aload         4
      55: invokevirtual #48                 // Method java/util/EnumSet.containsAll:(Ljava/util/Collection;)Z
      58: ireturn

  private void calculate();
    Code:
       0: aload_0
       1: getfield      #26                 // Field explicitlyAllowed:Ljava/util/EnumSet;
       4: getstatic     #67                 // Field com/moulberry/axiom/restrictions/AxiomPermission.ALL:Lcom/moulberry/axiom/restrictions/AxiomPermission;
       7: invokevirtual #40                 // Method java/util/EnumSet.contains:(Ljava/lang/Object;)Z
      10: ifeq          23
      13: aload_0
      14: ldc           #65                 // class com/moulberry/axiom/restrictions/AxiomPermission
      16: invokestatic  #71                 // Method java/util/EnumSet.allOf:(Ljava/lang/Class;)Ljava/util/EnumSet;
      19: putfield      #24                 // Field calculated:Ljava/util/EnumSet;
      22: return
      23: aload_0
      24: ldc           #65                 // class com/moulberry/axiom/restrictions/AxiomPermission
      26: invokestatic  #74                 // Method java/util/EnumSet.noneOf:(Ljava/lang/Class;)Ljava/util/EnumSet;
      29: putfield      #24                 // Field calculated:Ljava/util/EnumSet;
      32: getstatic     #76                 // Field PERMISSIONS:[Lcom/moulberry/axiom/restrictions/AxiomPermission;
      35: astore_1
      36: aload_1
      37: arraylength
      38: istore_2
      39: iconst_0
      40: istore_3
      41: iload_3
      42: iload_2
      43: if_icmpge     127
      46: aload_1
      47: iload_3
      48: aaload
      49: astore        4
      51: aload_0
      52: getfield      #26                 // Field explicitlyAllowed:Ljava/util/EnumSet;
      55: aload         4
      57: invokevirtual #40                 // Method java/util/EnumSet.contains:(Ljava/lang/Object;)Z
      60: ifeq          76
      63: aload_0
      64: getfield      #24                 // Field calculated:Ljava/util/EnumSet;
      67: aload         4
      69: invokevirtual #80                 // Method java/util/EnumSet.add:(Ljava/lang/Object;)Z
      72: pop
      73: goto          121
      76: aload_0
      77: getfield      #28                 // Field explicitlyDenied:Ljava/util/EnumSet;
      80: aload         4
      82: invokevirtual #40                 // Method java/util/EnumSet.contains:(Ljava/lang/Object;)Z
      85: ifne          121
      88: aload         4
      90: getfield      #83                 // Field com/moulberry/axiom/restrictions/AxiomPermission.parent:Lcom/moulberry/axiom/restrictions/AxiomPermission;
      93: ifnull        121
      96: aload_0
      97: getfield      #24                 // Field calculated:Ljava/util/EnumSet;
     100: aload         4
     102: getfield      #83                 // Field com/moulberry/axiom/restrictions/AxiomPermission.parent:Lcom/moulberry/axiom/restrictions/AxiomPermission;
     105: invokevirtual #40                 // Method java/util/EnumSet.contains:(Ljava/lang/Object;)Z
     108: ifeq          121
     111: aload_0
     112: getfield      #24                 // Field calculated:Ljava/util/EnumSet;
     115: aload         4
     117: invokevirtual #80                 // Method java/util/EnumSet.add:(Ljava/lang/Object;)Z
     120: pop
     121: iinc          3, 1
     124: goto          41
     127: return

  static {};
    Code:
       0: new           #2                  // class com/moulberry/axiom/restrictions/AxiomPermissionSet
       3: dup
       4: getstatic     #67                 // Field com/moulberry/axiom/restrictions/AxiomPermission.ALL:Lcom/moulberry/axiom/restrictions/AxiomPermission;
       7: invokestatic  #89                 // Method java/util/EnumSet.of:(Ljava/lang/Enum;)Ljava/util/EnumSet;
      10: ldc           #65                 // class com/moulberry/axiom/restrictions/AxiomPermission
      12: invokestatic  #74                 // Method java/util/EnumSet.noneOf:(Ljava/lang/Class;)Ljava/util/EnumSet;
      15: invokespecial #91                 // Method "<init>":(Ljava/util/EnumSet;Ljava/util/EnumSet;)V
      18: putstatic     #93                 // Field ALL:Lcom/moulberry/axiom/restrictions/AxiomPermissionSet;
      21: new           #2                  // class com/moulberry/axiom/restrictions/AxiomPermissionSet
      24: dup
      25: getstatic     #95                 // Field com/moulberry/axiom/restrictions/AxiomPermission.DEFAULT:Lcom/moulberry/axiom/restrictions/AxiomPermission;
      28: invokestatic  #89                 // Method java/util/EnumSet.of:(Ljava/lang/Enum;)Ljava/util/EnumSet;
      31: ldc           #65                 // class com/moulberry/axiom/restrictions/AxiomPermission
      33: invokestatic  #74                 // Method java/util/EnumSet.noneOf:(Ljava/lang/Class;)Ljava/util/EnumSet;
      36: invokespecial #91                 // Method "<init>":(Ljava/util/EnumSet;Ljava/util/EnumSet;)V
      39: putstatic     #97                 // Field DEFAULT:Lcom/moulberry/axiom/restrictions/AxiomPermissionSet;
      42: new           #2                  // class com/moulberry/axiom/restrictions/AxiomPermissionSet
      45: dup
      46: ldc           #65                 // class com/moulberry/axiom/restrictions/AxiomPermission
      48: invokestatic  #74                 // Method java/util/EnumSet.noneOf:(Ljava/lang/Class;)Ljava/util/EnumSet;
      51: ldc           #65                 // class com/moulberry/axiom/restrictions/AxiomPermission
      53: invokestatic  #71                 // Method java/util/EnumSet.allOf:(Ljava/lang/Class;)Ljava/util/EnumSet;
      56: invokespecial #91                 // Method "<init>":(Ljava/util/EnumSet;Ljava/util/EnumSet;)V
      59: putstatic     #99                 // Field NONE:Lcom/moulberry/axiom/restrictions/AxiomPermissionSet;
      62: invokestatic  #103                // Method com/moulberry/axiom/restrictions/AxiomPermission.values:()[Lcom/moulberry/axiom/restrictions/AxiomPermission;
      65: putstatic     #76                 // Field PERMISSIONS:[Lcom/moulberry/axiom/restrictions/AxiomPermission;
      68: return
}
