Compiled from "WrapperPacketListener.java"
public class com.moulberry.axiom.packet.WrapperPacketListener implements org.bukkit.plugin.messaging.PluginMessageListener {
  private final com.moulberry.axiom.packet.PacketHandler packetHandler;

  public com.moulberry.axiom.packet.WrapperPacketListener(com.moulberry.axiom.packet.PacketHandler);
    Code:
       0: aload_0
       1: invokespecial #19                 // Method java/lang/Object."<init>":()V
       4: aload_0
       5: aload_1
       6: putfield      #21                 // Field packetHandler:Lcom/moulberry/axiom/packet/PacketHandler;
       9: return

  public void onPluginMessageReceived(java.lang.String, org.bukkit.entity.Player, byte[]);
    Code:
       0: new           #33                 // class net/minecraft/network/PacketDataSerializer
       3: dup
       4: aload_3
       5: invokestatic  #39                 // Method io/netty/buffer/Unpooled.wrappedBuffer:([B)Lio/netty/buffer/ByteBuf;
       8: invokespecial #42                 // Method net/minecraft/network/PacketDataSerializer."<init>":(Lio/netty/buffer/ByteBuf;)V
      11: astore        4
      13: aload_0
      14: getfield      #21                 // Field packetHandler:Lcom/moulberry/axiom/packet/PacketHandler;
      17: aload_2
      18: aload         4
      20: invokeinterface #48,  3           // InterfaceMethod com/moulberry/axiom/packet/PacketHandler.onReceive:(Lorg/bukkit/entity/Player;Lnet/minecraft/network/PacketDataSerializer;)V
      25: goto          50
      28: astore        5
      30: aload_2
      31: aload_1
      32: aload         5
      34: invokevirtual #58                 // Method java/lang/Throwable.getMessage:()Ljava/lang/String;
      37: invokedynamic #70,  0             // InvokeDynamic #0:makeConcatWithConstants:(Ljava/lang/String;Ljava/lang/String;)Ljava/lang/String;
      42: invokestatic  #76                 // InterfaceMethod net/kyori/adventure/text/Component.text:(Ljava/lang/String;)Lnet/kyori/adventure/text/TextComponent;
      45: invokeinterface #80,  2           // InterfaceMethod org/bukkit/entity/Player.kick:(Lnet/kyori/adventure/text/Component;)V
      50: return
    Exception table:
       from    to  target type
          13    25    28   Class java/lang/Throwable
}
