Compiled from "PaperListener.java"
public class net.playavalon.mythicdungeons.listeners.PaperListener extends net.playavalon.mythicdungeons.listeners.AvalonListener {
  public net.playavalon.mythicdungeons.listeners.PaperListener();
    Code:
       0: aload_0
       1: invokespecial #1                  // Method net/playavalon/mythicdungeons/listeners/AvalonListener."<init>":()V
       4: return

  public void onRoomNameInput(io.papermc.paper.event.player.AsyncChatDecorateEvent);
    Code:
       0: aload_1
       1: invokevirtual #7                  // Method io/papermc/paper/event/player/AsyncChatDecorateEvent.player:()Lorg/bukkit/entity/Player;
       4: astore_2
       5: invokestatic  #13                 // Method net/playavalon/mythicdungeons/MythicDungeons.inst:()Lnet/playavalon/mythicdungeons/MythicDungeons;
       8: aload_2
       9: invokevirtual #19                 // Method net/playavalon/mythicdungeons/MythicDungeons.getMythicPlayer:(Lorg/bukkit/entity/Player;)Lnet/playavalon/mythicdungeons/player/MythicPlayer;
      12: astore_3
      13: aload_3
      14: ifnonnull     18
      17: return
      18: aload_3
      19: invokevirtual #23                 // Method net/playavalon/mythicdungeons/player/MythicPlayer.getInstance:()Lnet/playavalon/mythicdungeons/api/parents/instances/AbstractInstance;
      22: ifnonnull     26
      25: return
      26: aload_3
      27: invokevirtual #23                 // Method net/playavalon/mythicdungeons/player/MythicPlayer.getInstance:()Lnet/playavalon/mythicdungeons/api/parents/instances/AbstractInstance;
      30: ldc           #29                 // class net/playavalon/mythicdungeons/dungeons/instancetypes/edit/InstanceEditableProcedural
      32: invokevirtual #31                 // Method net/playavalon/mythicdungeons/api/parents/instances/AbstractInstance.as:(Ljava/lang/Class;)Lnet/playavalon/mythicdungeons/api/parents/instances/AbstractInstance;
      35: checkcast     #29                 // class net/playavalon/mythicdungeons/dungeons/instancetypes/edit/InstanceEditableProcedural
      38: astore        4
      40: aload         4
      42: ifnonnull     46
      45: return
      46: aload         4
      48: invokevirtual #37                 // Method net/playavalon/mythicdungeons/dungeons/instancetypes/edit/InstanceEditableProcedural.getDungeon:()Lnet/playavalon/mythicdungeons/dungeons/dungeontypes/DungeonProcedural;
      51: astore        5
      53: aload_3
      54: invokevirtual #41                 // Method net/playavalon/mythicdungeons/player/MythicPlayer.isAwaitingRoomName:()Z
      57: ifne          61
      60: return
      61: aload_1
      62: ldc           #45                 // String
      64: invokestatic  #47                 // Method net/playavalon/mythicdungeons/utility/helpers/Util.modernizeColorsComponent:(Ljava/lang/String;)Lnet/kyori/adventure/text/Component;
      67: invokevirtual #53                 // Method io/papermc/paper/event/player/AsyncChatDecorateEvent.result:(Lnet/kyori/adventure/text/Component;)V
      70: aload_1
      71: iconst_1
      72: invokevirtual #57                 // Method io/papermc/paper/event/player/AsyncChatDecorateEvent.setCancelled:(Z)V
      75: invokestatic  #61                 // InterfaceMethod net/kyori/adventure/text/serializer/plain/PlainTextComponentSerializer.plainText:()Lnet/kyori/adventure/text/serializer/plain/PlainTextComponentSerializer;
      78: aload_1
      79: invokevirtual #67                 // Method io/papermc/paper/event/player/AsyncChatDecorateEvent.originalMessage:()Lnet/kyori/adventure/text/Component;
      82: invokeinterface #71,  2           // InterfaceMethod net/kyori/adventure/text/serializer/plain/PlainTextComponentSerializer.serialize:(Lnet/kyori/adventure/text/Component;)Ljava/lang/String;
      87: astore        6
      89: ldc           #75                 // String [^a-z0-9]
      91: iconst_2
      92: invokestatic  #79                 // Method java/util/regex/Pattern.compile:(Ljava/lang/String;I)Ljava/util/regex/Pattern;
      95: astore        7
      97: aload         7
      99: aload         6
     101: invokevirtual #83                 // Method java/util/regex/Pattern.matcher:(Ljava/lang/CharSequence;)Ljava/util/regex/Matcher;
     104: astore        8
     106: aload         8
     108: invokevirtual #87                 // Method java/util/regex/Matcher.find:()Z
     111: ifeq          121
     114: aload_2
     115: ldc           #92                 // String instance.editmode.room-name-invalid
     117: invokestatic  #94                 // Method net/playavalon/mythicdungeons/utility/helpers/LangUtils.sendMessage:(Lorg/bukkit/command/CommandSender;Ljava/lang/String;)V
     120: return
     121: aload_3
     122: iconst_0
     123: invokevirtual #100                // Method net/playavalon/mythicdungeons/player/MythicPlayer.setAwaitingRoomName:(Z)V
     126: aload_3
     127: invokevirtual #103                // Method net/playavalon/mythicdungeons/player/MythicPlayer.getActiveRoom:()Lnet/playavalon/mythicdungeons/api/generation/rooms/DungeonRoomContainer;
     130: astore        9
     132: aload_3
     133: invokevirtual #107                // Method net/playavalon/mythicdungeons/player/MythicPlayer.getActiveConnector:()Lnet/playavalon/mythicdungeons/api/generation/rooms/Connector;
     136: astore        10
     138: aload_3
     139: invokevirtual #111                // Method net/playavalon/mythicdungeons/player/MythicPlayer.isAddingWhitelistEntry:()Z
     142: ifeq          260
     145: aload         5
     147: aload         6
     149: invokevirtual #114                // Method net/playavalon/mythicdungeons/dungeons/dungeontypes/DungeonProcedural.getRoom:(Ljava/lang/String;)Lnet/playavalon/mythicdungeons/api/generation/rooms/DungeonRoomContainer;
     152: astore        11
     154: aload         11
     156: ifnonnull     160
     159: return
     160: aload_2
     161: aload_2
     162: invokeinterface #120,  1          // InterfaceMethod org/bukkit/entity/Player.getLocation:()Lorg/bukkit/Location;
     167: ldc           #126                // String minecraft:entity.experience_orb.pickup
     169: ldc           #128                // float 0.5f
     171: ldc           #129                // float 1.2f
     173: invokeinterface #130,  5          // InterfaceMethod org/bukkit/entity/Player.playSound:(Lorg/bukkit/Location;Ljava/lang/String;FF)V
     178: aload         10
     180: ifnull        219
     183: aload         10
     185: invokevirtual #134                // Method net/playavalon/mythicdungeons/api/generation/rooms/Connector.getRoomWhitelist:()Ljava/util/List;
     188: new           #140                // class net/playavalon/mythicdungeons/api/generation/rooms/WhitelistEntry
     191: dup
     192: aload         11
     194: invokespecial #142                // Method net/playavalon/mythicdungeons/api/generation/rooms/WhitelistEntry."<init>":(Lnet/playavalon/mythicdungeons/api/generation/rooms/DungeonRoomContainer;)V
     197: invokeinterface #145,  2          // InterfaceMethod java/util/List.add:(Ljava/lang/Object;)Z
     202: pop
     203: aload_2
     204: ldc           #151                // String instance.editmode.room-whitelist.add-success
     206: iconst_1
     207: anewarray     #153                // class java/lang/String
     210: dup
     211: iconst_0
     212: aload         6
     214: aastore
     215: invokestatic  #155                // Method net/playavalon/mythicdungeons/utility/helpers/LangUtils.sendMessage:(Lorg/bukkit/command/CommandSender;Ljava/lang/String;[Ljava/lang/String;)V
     218: return
     219: aload         9
     221: invokevirtual #158                // Method net/playavalon/mythicdungeons/api/generation/rooms/DungeonRoomContainer.getRoomWhitelist:()Ljava/util/List;
     224: new           #140                // class net/playavalon/mythicdungeons/api/generation/rooms/WhitelistEntry
     227: dup
     228: aload         11
     230: invokespecial #142                // Method net/playavalon/mythicdungeons/api/generation/rooms/WhitelistEntry."<init>":(Lnet/playavalon/mythicdungeons/api/generation/rooms/DungeonRoomContainer;)V
     233: invokeinterface #145,  2          // InterfaceMethod java/util/List.add:(Ljava/lang/Object;)Z
     238: pop
     239: aload_2
     240: ldc           #151                // String instance.editmode.room-whitelist.add-success
     242: iconst_1
     243: anewarray     #153                // class java/lang/String
     246: dup
     247: iconst_0
     248: aload         6
     250: aastore
     251: invokestatic  #155                // Method net/playavalon/mythicdungeons/utility/helpers/LangUtils.sendMessage:(Lorg/bukkit/command/CommandSender;Ljava/lang/String;[Ljava/lang/String;)V
     254: aload_3
     255: iconst_0
     256: invokevirtual #161                // Method net/playavalon/mythicdungeons/player/MythicPlayer.setAddingWhitelistEntry:(Z)V
     259: return
     260: aload_3
     261: invokevirtual #164                // Method net/playavalon/mythicdungeons/player/MythicPlayer.isEditingWhitelistEntry:()Z
     264: ifeq          315
     267: aload         5
     269: aload         6
     271: invokevirtual #114                // Method net/playavalon/mythicdungeons/dungeons/dungeontypes/DungeonProcedural.getRoom:(Ljava/lang/String;)Lnet/playavalon/mythicdungeons/api/generation/rooms/DungeonRoomContainer;
     274: astore        11
     276: aload         11
     278: ifnonnull     282
     281: return
     282: aload_2
     283: aload_2
     284: invokeinterface #120,  1          // InterfaceMethod org/bukkit/entity/Player.getLocation:()Lorg/bukkit/Location;
     289: ldc           #126                // String minecraft:entity.experience_orb.pickup
     291: ldc           #128                // float 0.5f
     293: ldc           #129                // float 1.2f
     295: invokeinterface #130,  5          // InterfaceMethod org/bukkit/entity/Player.playSound:(Lorg/bukkit/Location;Ljava/lang/String;FF)V
     300: aload_2
     301: ldc           #167                // String &cNOT IMPLEMENTED!
     303: invokestatic  #169                // Method net/playavalon/mythicdungeons/utility/helpers/Util.fullColorModern:(Ljava/lang/String;)Ljava/lang/String;
     306: invokestatic  #173                // Method net/playavalon/mythicdungeons/utility/helpers/MessageUtils.sendMessage:(Lorg/bukkit/command/CommandSender;Ljava/lang/String;)V
     309: aload_3
     310: iconst_0
     311: invokevirtual #176                // Method net/playavalon/mythicdungeons/player/MythicPlayer.setEditingWhitelistEntry:(Z)V
     314: return
     315: aload_3
     316: invokevirtual #179                // Method net/playavalon/mythicdungeons/player/MythicPlayer.isRemovingWhitelistEntry:()Z
     319: ifeq          501
     322: aload         5
     324: aload         6
     326: invokevirtual #114                // Method net/playavalon/mythicdungeons/dungeons/dungeontypes/DungeonProcedural.getRoom:(Ljava/lang/String;)Lnet/playavalon/mythicdungeons/api/generation/rooms/DungeonRoomContainer;
     329: astore        11
     331: aload         11
     333: ifnonnull     337
     336: return
     337: aload_2
     338: aload_2
     339: invokeinterface #120,  1          // InterfaceMethod org/bukkit/entity/Player.getLocation:()Lorg/bukkit/Location;
     344: ldc           #126                // String minecraft:entity.experience_orb.pickup
     346: ldc           #128                // float 0.5f
     348: ldc           #129                // float 1.2f
     350: invokeinterface #130,  5          // InterfaceMethod org/bukkit/entity/Player.playSound:(Lorg/bukkit/Location;Ljava/lang/String;FF)V
     355: aconst_null
     356: astore        12
     358: aload         10
     360: ifnull        377
     363: new           #182                // class java/util/ArrayList
     366: dup
     367: aload         10
     369: invokevirtual #134                // Method net/playavalon/mythicdungeons/api/generation/rooms/Connector.getRoomWhitelist:()Ljava/util/List;
     372: invokespecial #184                // Method java/util/ArrayList."<init>":(Ljava/util/Collection;)V
     375: astore        12
     377: aload         12
     379: ifnonnull     396
     382: new           #182                // class java/util/ArrayList
     385: dup
     386: aload         9
     388: invokevirtual #158                // Method net/playavalon/mythicdungeons/api/generation/rooms/DungeonRoomContainer.getRoomWhitelist:()Ljava/util/List;
     391: invokespecial #184                // Method java/util/ArrayList."<init>":(Ljava/util/Collection;)V
     394: astore        12
     396: aload         12
     398: invokeinterface #187,  1          // InterfaceMethod java/util/List.iterator:()Ljava/util/Iterator;
     403: astore        13
     405: aload         13
     407: invokeinterface #191,  1          // InterfaceMethod java/util/Iterator.hasNext:()Z
     412: ifeq          480
     415: aload         13
     417: invokeinterface #196,  1          // InterfaceMethod java/util/Iterator.next:()Ljava/lang/Object;
     422: checkcast     #140                // class net/playavalon/mythicdungeons/api/generation/rooms/WhitelistEntry
     425: astore        14
     427: aload         14
     429: invokevirtual #200                // Method net/playavalon/mythicdungeons/api/generation/rooms/WhitelistEntry.getRoomName:()Ljava/lang/String;
     432: aload         6
     434: invokevirtual #204                // Method java/lang/String.equals:(Ljava/lang/Object;)Z
     437: ifne          443
     440: goto          405
     443: aload         10
     445: ifnull        464
     448: aload         10
     450: invokevirtual #134                // Method net/playavalon/mythicdungeons/api/generation/rooms/Connector.getRoomWhitelist:()Ljava/util/List;
     453: aload         14
     455: invokeinterface #207,  2          // InterfaceMethod java/util/List.remove:(Ljava/lang/Object;)Z
     460: pop
     461: goto          477
     464: aload         9
     466: invokevirtual #158                // Method net/playavalon/mythicdungeons/api/generation/rooms/DungeonRoomContainer.getRoomWhitelist:()Ljava/util/List;
     469: aload         14
     471: invokeinterface #207,  2          // InterfaceMethod java/util/List.remove:(Ljava/lang/Object;)Z
     476: pop
     477: goto          405
     480: aload_2
     481: ldc           #210                // String instance.editmode.room-whitelist.remove-success
     483: iconst_1
     484: anewarray     #153                // class java/lang/String
     487: dup
     488: iconst_0
     489: aload         6
     491: aastore
     492: invokestatic  #155                // Method net/playavalon/mythicdungeons/utility/helpers/LangUtils.sendMessage:(Lorg/bukkit/command/CommandSender;Ljava/lang/String;[Ljava/lang/String;)V
     495: aload_3
     496: iconst_0
     497: invokevirtual #212                // Method net/playavalon/mythicdungeons/player/MythicPlayer.setRemovingWhitelistEntry:(Z)V
     500: return
     501: aload_2
     502: aload_2
     503: invokeinterface #120,  1          // InterfaceMethod org/bukkit/entity/Player.getLocation:()Lorg/bukkit/Location;
     508: ldc           #126                // String minecraft:entity.experience_orb.pickup
     510: ldc           #128                // float 0.5f
     512: ldc           #129                // float 1.2f
     514: invokeinterface #130,  5          // InterfaceMethod org/bukkit/entity/Player.playSound:(Lorg/bukkit/Location;Ljava/lang/String;FF)V
     519: aload_3
     520: invokevirtual #215                // Method net/playavalon/mythicdungeons/player/MythicPlayer.getPos1:()Lorg/bukkit/Location;
     523: aload_3
     524: invokevirtual #218                // Method net/playavalon/mythicdungeons/player/MythicPlayer.getPos2:()Lorg/bukkit/Location;
     527: invokestatic  #221                // Method net/playavalon/mythicdungeons/utility/helpers/Util.captureBoundingBox:(Lorg/bukkit/Location;Lorg/bukkit/Location;)Lorg/bukkit/util/BoundingBox;
     530: astore        11
     532: aload         5
     534: aload         6
     536: aload         11
     538: invokevirtual #225                // Method net/playavalon/mythicdungeons/dungeons/dungeontypes/DungeonProcedural.defineRoom:(Ljava/lang/String;Lorg/bukkit/util/BoundingBox;)Lnet/playavalon/mythicdungeons/api/generation/rooms/DungeonRoomContainer;
     541: astore        9
     543: aload         9
     545: ifnonnull     549
     548: return
     549: aload         9
     551: astore        12
     553: invokestatic  #229                // Method org/bukkit/Bukkit.getScheduler:()Lorg/bukkit/scheduler/BukkitScheduler;
     556: invokestatic  #13                 // Method net/playavalon/mythicdungeons/MythicDungeons.inst:()Lnet/playavalon/mythicdungeons/MythicDungeons;
     559: aload         4
     561: aload         12
     563: invokedynamic #235,  0            // InvokeDynamic #0:run:(Lnet/playavalon/mythicdungeons/dungeons/instancetypes/edit/InstanceEditableProcedural;Lnet/playavalon/mythicdungeons/api/generation/rooms/DungeonRoomContainer;)Ljava/lang/Runnable;
     568: invokeinterface #239,  3          // InterfaceMethod org/bukkit/scheduler/BukkitScheduler.runTask:(Lorg/bukkit/plugin/Plugin;Ljava/lang/Runnable;)Lorg/bukkit/scheduler/BukkitTask;
     573: pop
     574: aload_2
     575: ldc           #245                // String instance.editmode.room-created
     577: iconst_1
     578: anewarray     #153                // class java/lang/String
     581: dup
     582: iconst_0
     583: aload         6
     585: aastore
     586: invokestatic  #155                // Method net/playavalon/mythicdungeons/utility/helpers/LangUtils.sendMessage:(Lorg/bukkit/command/CommandSender;Ljava/lang/String;[Ljava/lang/String;)V
     589: aload_3
     590: aconst_null
     591: invokevirtual #247                // Method net/playavalon/mythicdungeons/player/MythicPlayer.setPos1:(Lorg/bukkit/Location;)V
     594: aload_3
     595: aconst_null
     596: invokevirtual #251                // Method net/playavalon/mythicdungeons/player/MythicPlayer.setPos2:(Lorg/bukkit/Location;)V
     599: return

  private static void lambda$onRoomNameInput$0(net.playavalon.mythicdungeons.dungeons.instancetypes.edit.InstanceEditableProcedural, net.playavalon.mythicdungeons.api.generation.rooms.DungeonRoomContainer);
    Code:
       0: aload_0
       1: aload_1
       2: invokevirtual #254                // Method net/playavalon/mythicdungeons/dungeons/instancetypes/edit/InstanceEditableProcedural.setRoomLabel:(Lnet/playavalon/mythicdungeons/api/generation/rooms/DungeonRoomContainer;)V
       5: return
}
