Compiled from "LegacyMapper.java"
public final class com.sk89q.worldedit.world.registry.LegacyMapper {
  private static final org.apache.logging.log4j.Logger LOGGER;

  private static com.sk89q.worldedit.world.registry.LegacyMapper INSTANCE;

  private final com.sk89q.worldedit.util.io.ResourceLoader resourceLoader;

  private final com.sk89q.worldedit.bukkit.fastutil.ints.Int2ObjectArrayMap<java.lang.Integer> blockStateToLegacyId4Data;

  private final com.sk89q.worldedit.bukkit.fastutil.ints.Int2ObjectArrayMap<java.lang.Integer> extraId4DataToStateId;

  private final int[] blockArr;

  private final com.google.common.collect.BiMap<java.lang.Integer, com.sk89q.worldedit.world.item.ItemType> itemMap;

  private final java.util.Map<java.lang.String, java.lang.String> blockEntries;

  private final java.util.Map<java.lang.String, com.sk89q.worldedit.world.block.BlockState> stringToBlockMap;

  private final com.google.common.collect.Multimap<com.sk89q.worldedit.world.block.BlockState, java.lang.String> blockToStringMap;

  private com.sk89q.worldedit.world.registry.LegacyMapper();
    Code:
       0: aload_0
       1: invokespecial #52                 // Method java/lang/Object."<init>":()V
       4: aload_0
       5: new           #54                 // class com/sk89q/worldedit/bukkit/fastutil/ints/Int2ObjectArrayMap
       8: dup
       9: invokespecial #55                 // Method com/sk89q/worldedit/bukkit/fastutil/ints/Int2ObjectArrayMap."<init>":()V
      12: putfield      #57                 // Field blockStateToLegacyId4Data:Lcom/sk89q/worldedit/bukkit/fastutil/ints/Int2ObjectArrayMap;
      15: aload_0
      16: new           #54                 // class com/sk89q/worldedit/bukkit/fastutil/ints/Int2ObjectArrayMap
      19: dup
      20: invokespecial #55                 // Method com/sk89q/worldedit/bukkit/fastutil/ints/Int2ObjectArrayMap."<init>":()V
      23: putfield      #59                 // Field extraId4DataToStateId:Lcom/sk89q/worldedit/bukkit/fastutil/ints/Int2ObjectArrayMap;
      26: aload_0
      27: sipush        4096
      30: newarray       int
      32: putfield      #61                 // Field blockArr:[I
      35: aload_0
      36: invokestatic  #67                 // Method com/google/common/collect/HashBiMap.create:()Lcom/google/common/collect/HashBiMap;
      39: putfield      #69                 // Field itemMap:Lcom/google/common/collect/BiMap;
      42: aload_0
      43: new           #71                 // class java/util/HashMap
      46: dup
      47: invokespecial #72                 // Method java/util/HashMap."<init>":()V
      50: putfield      #74                 // Field blockEntries:Ljava/util/Map;
      53: aload_0
      54: new           #71                 // class java/util/HashMap
      57: dup
      58: invokespecial #72                 // Method java/util/HashMap."<init>":()V
      61: putfield      #76                 // Field stringToBlockMap:Ljava/util/Map;
      64: aload_0
      65: invokestatic  #81                 // Method com/google/common/collect/HashMultimap.create:()Lcom/google/common/collect/HashMultimap;
      68: putfield      #83                 // Field blockToStringMap:Lcom/google/common/collect/Multimap;
      71: aload_0
      72: invokestatic  #89                 // Method com/sk89q/worldedit/WorldEdit.getInstance:()Lcom/sk89q/worldedit/WorldEdit;
      75: invokevirtual #93                 // Method com/sk89q/worldedit/WorldEdit.getPlatformManager:()Lcom/sk89q/worldedit/extension/platform/PlatformManager;
      78: getstatic     #99                 // Field com/sk89q/worldedit/extension/platform/Capability.CONFIGURATION:Lcom/sk89q/worldedit/extension/platform/Capability;
      81: invokevirtual #105                // Method com/sk89q/worldedit/extension/platform/PlatformManager.queryCapability:(Lcom/sk89q/worldedit/extension/platform/Capability;)Lcom/sk89q/worldedit/extension/platform/Platform;
      84: invokeinterface #111,  1          // InterfaceMethod com/sk89q/worldedit/extension/platform/Platform.getResourceLoader:()Lcom/sk89q/worldedit/util/io/ResourceLoader;
      89: putfield      #113                // Field resourceLoader:Lcom/sk89q/worldedit/util/io/ResourceLoader;
      92: aload_0
      93: invokevirtual #116                // Method loadFromResource:()V
      96: goto          111
      99: astore_1
     100: getstatic     #118                // Field LOGGER:Lorg/apache/logging/log4j/Logger;
     103: ldc           #120                // String Failed to load the built-in legacy id registry
     105: aload_1
     106: invokeinterface #126,  3          // InterfaceMethod org/apache/logging/log4j/Logger.warn:(Ljava/lang/String;Ljava/lang/Throwable;)V
     111: return
    Exception table:
       from    to  target type
          92    96    99   Class java/lang/Throwable

  private void loadFromResource() throws java.io.IOException;
    Code:
       0: new           #137                // class com/google/gson/GsonBuilder
       3: dup
       4: invokespecial #138                // Method com/google/gson/GsonBuilder."<init>":()V
       7: astore_1
       8: aload_1
       9: ldc           #140                // class com/sk89q/worldedit/math/Vector3
      11: new           #142                // class com/sk89q/worldedit/util/gson/VectorAdapter
      14: dup
      15: invokespecial #143                // Method com/sk89q/worldedit/util/gson/VectorAdapter."<init>":()V
      18: invokevirtual #147                // Method com/google/gson/GsonBuilder.registerTypeAdapter:(Ljava/lang/reflect/Type;Ljava/lang/Object;)Lcom/google/gson/GsonBuilder;
      21: pop
      22: aload_1
      23: invokevirtual #151                // Method com/google/gson/GsonBuilder.disableHtmlEscaping:()Lcom/google/gson/GsonBuilder;
      26: invokevirtual #154                // Method com/google/gson/GsonBuilder.create:()Lcom/google/gson/Gson;
      29: astore_2
      30: aload_0
      31: getfield      #113                // Field resourceLoader:Lcom/sk89q/worldedit/util/io/ResourceLoader;
      34: ldc           #2                  // class com/sk89q/worldedit/world/registry/LegacyMapper
      36: ldc           #156                // String legacy.json
      38: invokeinterface #162,  3          // InterfaceMethod com/sk89q/worldedit/util/io/ResourceLoader.getResource:(Ljava/lang/Class;Ljava/lang/String;)Ljava/net/URL;
      43: astore_3
      44: aload_3
      45: ifnonnull     58
      48: new           #131                // class java/io/IOException
      51: dup
      52: ldc           #164                // String Could not find legacy.json
      54: invokespecial #167                // Method java/io/IOException."<init>":(Ljava/lang/String;)V
      57: athrow
      58: aload_3
      59: invokestatic  #177                // Method java/nio/charset/Charset.defaultCharset:()Ljava/nio/charset/Charset;
      62: invokestatic  #183                // Method com/google/common/io/Resources.toString:(Ljava/net/URL;Ljava/nio/charset/Charset;)Ljava/lang/String;
      65: astore        4
      67: aload_2
      68: aload         4
      70: new           #9                  // class com/sk89q/worldedit/world/registry/LegacyMapper$1
      73: dup
      74: aload_0
      75: invokespecial #186                // Method com/sk89q/worldedit/world/registry/LegacyMapper$1."<init>":(Lcom/sk89q/worldedit/world/registry/LegacyMapper;)V
      78: invokevirtual #190                // Method com/sk89q/worldedit/world/registry/LegacyMapper$1.getType:()Ljava/lang/reflect/Type;
      81: invokevirtual #194                // Method com/google/gson/Gson.fromJson:(Ljava/lang/String;Ljava/lang/reflect/Type;)Ljava/lang/Object;
      84: checkcast     #7                  // class com/sk89q/worldedit/world/registry/LegacyMapper$LegacyDataFile
      87: astore        5
      89: invokestatic  #89                 // Method com/sk89q/worldedit/WorldEdit.getInstance:()Lcom/sk89q/worldedit/WorldEdit;
      92: invokevirtual #93                 // Method com/sk89q/worldedit/WorldEdit.getPlatformManager:()Lcom/sk89q/worldedit/extension/platform/PlatformManager;
      95: getstatic     #197                // Field com/sk89q/worldedit/extension/platform/Capability.WORLD_EDITING:Lcom/sk89q/worldedit/extension/platform/Capability;
      98: invokevirtual #105                // Method com/sk89q/worldedit/extension/platform/PlatformManager.queryCapability:(Lcom/sk89q/worldedit/extension/platform/Capability;)Lcom/sk89q/worldedit/extension/platform/Platform;
     101: invokeinterface #201,  1          // InterfaceMethod com/sk89q/worldedit/extension/platform/Platform.getDataFixer:()Lcom/sk89q/worldedit/world/DataFixer;
     106: astore        6
     108: new           #203                // class com/sk89q/worldedit/extension/input/ParserContext
     111: dup
     112: invokespecial #204                // Method com/sk89q/worldedit/extension/input/ParserContext."<init>":()V
     115: astore        7
     117: aload         7
     119: iconst_0
     120: invokevirtual #208                // Method com/sk89q/worldedit/extension/input/ParserContext.setPreferringWildcard:(Z)V
     123: aload         7
     125: iconst_0
     126: invokevirtual #211                // Method com/sk89q/worldedit/extension/input/ParserContext.setRestricted:(Z)V
     129: aload         7
     131: iconst_0
     132: invokevirtual #214                // Method com/sk89q/worldedit/extension/input/ParserContext.setTryLegacy:(Z)V
     135: aload         5
     137: getfield      #217                // Field com/sk89q/worldedit/world/registry/LegacyMapper$LegacyDataFile.blocks:Ljava/util/Map;
     140: invokeinterface #221,  1          // InterfaceMethod java/util/Map.entrySet:()Ljava/util/Set;
     145: invokeinterface #227,  1          // InterfaceMethod java/util/Set.iterator:()Ljava/util/Iterator;
     150: astore        8
     152: aload         8
     154: invokeinterface #235,  1          // InterfaceMethod java/util/Iterator.hasNext:()Z
     159: ifeq          465
     162: aload         8
     164: invokeinterface #239,  1          // InterfaceMethod java/util/Iterator.next:()Ljava/lang/Object;
     169: checkcast     #12                 // class java/util/Map$Entry
     172: astore        9
     174: aload         9
     176: invokeinterface #242,  1          // InterfaceMethod java/util/Map$Entry.getKey:()Ljava/lang/Object;
     181: checkcast     #229                // class java/lang/String
     184: astore        10
     186: aload         9
     188: invokeinterface #245,  1          // InterfaceMethod java/util/Map$Entry.getValue:()Ljava/lang/Object;
     193: checkcast     #229                // class java/lang/String
     196: astore        11
     198: aload_0
     199: aload         9
     201: invokeinterface #242,  1          // InterfaceMethod java/util/Map$Entry.getKey:()Ljava/lang/Object;
     206: checkcast     #229                // class java/lang/String
     209: invokevirtual #249                // Method getCombinedId:(Ljava/lang/String;)I
     212: invokestatic  #255                // Method java/lang/Integer.valueOf:(I)Ljava/lang/Integer;
     215: astore        12
     217: aload_0
     218: getfield      #74                 // Field blockEntries:Ljava/util/Map;
     221: aload         10
     223: aload         11
     225: invokeinterface #259,  3          // InterfaceMethod java/util/Map.put:(Ljava/lang/Object;Ljava/lang/Object;)Ljava/lang/Object;
     230: pop
     231: aconst_null
     232: astore        13
     234: aconst_null
     235: aload         9
     237: invokeinterface #245,  1          // InterfaceMethod java/util/Map$Entry.getValue:()Ljava/lang/Object;
     242: checkcast     #229                // class java/lang/String
     245: invokestatic  #265                // Method com/sk89q/worldedit/world/block/BlockState.get:(Lcom/sk89q/worldedit/world/block/BlockType;Ljava/lang/String;)Lcom/sk89q/worldedit/world/block/BlockState;
     248: astore        13
     250: aload         13
     252: invokevirtual #269                // Method com/sk89q/worldedit/world/block/BlockState.getBlockType:()Lcom/sk89q/worldedit/world/block/BlockType;
     255: astore        14
     257: aload         14
     259: getstatic     #275                // Field com/fastasyncworldedit/core/registry/state/PropertyKey.WATERLOGGED:Lcom/fastasyncworldedit/core/registry/state/PropertyKey;
     262: invokevirtual #281                // Method com/sk89q/worldedit/world/block/BlockType.hasProperty:(Lcom/fastasyncworldedit/core/registry/state/PropertyKey;)Z
     265: ifeq          282
     268: aload         13
     270: getstatic     #275                // Field com/fastasyncworldedit/core/registry/state/PropertyKey.WATERLOGGED:Lcom/fastasyncworldedit/core/registry/state/PropertyKey;
     273: iconst_0
     274: invokestatic  #286                // Method java/lang/Boolean.valueOf:(Z)Ljava/lang/Boolean;
     277: invokevirtual #290                // Method com/sk89q/worldedit/world/block/BlockState.with:(Lcom/fastasyncworldedit/core/registry/state/PropertyKey;Ljava/lang/Object;)Lcom/sk89q/worldedit/world/block/BlockState;
     280: astore        13
     282: goto          412
     285: astore        14
     287: invokestatic  #89                 // Method com/sk89q/worldedit/WorldEdit.getInstance:()Lcom/sk89q/worldedit/WorldEdit;
     290: invokevirtual #294                // Method com/sk89q/worldedit/WorldEdit.getBlockFactory:()Lcom/sk89q/worldedit/extension/factory/BlockFactory;
     293: astore        15
     295: aload         6
     297: ifnull        339
     300: aload         6
     302: getstatic     #298                // Field com/sk89q/worldedit/world/DataFixer$FixTypes.BLOCK_STATE:Lcom/sk89q/worldedit/world/DataFixer$FixType;
     305: aload         11
     307: sipush        1631
     310: invokeinterface #302,  4          // InterfaceMethod com/sk89q/worldedit/world/DataFixer.fixUp:(Lcom/sk89q/worldedit/world/DataFixer$FixType;Ljava/lang/Object;I)Ljava/lang/Object;
     315: checkcast     #229                // class java/lang/String
     318: astore        16
     320: aload         15
     322: aload         16
     324: aload         7
     326: invokevirtual #308                // Method com/sk89q/worldedit/extension/factory/BlockFactory.parseFromInput:(Ljava/lang/String;Lcom/sk89q/worldedit/extension/input/ParserContext;)Lcom/sk89q/worldedit/world/block/BaseBlock;
     329: invokevirtual #314                // Method com/sk89q/worldedit/world/block/BaseBlock.toImmutableState:()Lcom/sk89q/worldedit/world/block/BlockState;
     332: astore        13
     334: goto          339
     337: astore        16
     339: aload         13
     341: ifnonnull     363
     344: aload         15
     346: aload         11
     348: aload         7
     350: invokevirtual #308                // Method com/sk89q/worldedit/extension/factory/BlockFactory.parseFromInput:(Ljava/lang/String;Lcom/sk89q/worldedit/extension/input/ParserContext;)Lcom/sk89q/worldedit/world/block/BaseBlock;
     353: invokevirtual #314                // Method com/sk89q/worldedit/world/block/BaseBlock.toImmutableState:()Lcom/sk89q/worldedit/world/block/BlockState;
     356: astore        13
     358: goto          363
     361: astore        16
     363: aload         13
     365: ifnonnull     384
     368: getstatic     #118                // Field LOGGER:Lorg/apache/logging/log4j/Logger;
     371: ldc_w         #316                // String Unknown block: {}. Neither the DataFixer nor defaulting worked to recognize this block.
     374: aload         11
     376: invokeinterface #320,  3          // InterfaceMethod org/apache/logging/log4j/Logger.error:(Ljava/lang/String;Ljava/lang/Object;)V
     381: goto          412
     384: aload_0
     385: getfield      #83                 // Field blockToStringMap:Lcom/google/common/collect/Multimap;
     388: aload         13
     390: aload         10
     392: invokeinterface #325,  3          // InterfaceMethod com/google/common/collect/Multimap.put:(Ljava/lang/Object;Ljava/lang/Object;)Z
     397: pop
     398: aload_0
     399: getfield      #76                 // Field stringToBlockMap:Ljava/util/Map;
     402: aload         10
     404: aload         13
     406: invokeinterface #259,  3          // InterfaceMethod java/util/Map.put:(Ljava/lang/Object;Ljava/lang/Object;)Ljava/lang/Object;
     411: pop
     412: aload         13
     414: ifnull        462
     417: aload_0
     418: getfield      #61                 // Field blockArr:[I
     421: aload         12
     423: invokevirtual #329                // Method java/lang/Integer.intValue:()I
     426: aload         13
     428: invokevirtual #332                // Method com/sk89q/worldedit/world/block/BlockState.getInternalId:()I
     431: iastore
     432: aload_0
     433: getfield      #57                 // Field blockStateToLegacyId4Data:Lcom/sk89q/worldedit/bukkit/fastutil/ints/Int2ObjectArrayMap;
     436: aload         13
     438: invokevirtual #332                // Method com/sk89q/worldedit/world/block/BlockState.getInternalId:()I
     441: aload         12
     443: invokevirtual #335                // Method com/sk89q/worldedit/bukkit/fastutil/ints/Int2ObjectArrayMap.put:(ILjava/lang/Object;)Ljava/lang/Object;
     446: pop
     447: aload_0
     448: getfield      #57                 // Field blockStateToLegacyId4Data:Lcom/sk89q/worldedit/bukkit/fastutil/ints/Int2ObjectArrayMap;
     451: aload         13
     453: invokevirtual #338                // Method com/sk89q/worldedit/world/block/BlockState.getInternalBlockTypeId:()I
     456: aload         12
     458: invokevirtual #341                // Method com/sk89q/worldedit/bukkit/fastutil/ints/Int2ObjectArrayMap.putIfAbsent:(ILjava/lang/Object;)Ljava/lang/Object;
     461: pop
     462: goto          152
     465: iconst_0
     466: istore        8
     468: iload         8
     470: sipush        256
     473: if_icmpge     540
     476: iload         8
     478: iconst_4
     479: ishl
     480: istore        9
     482: aload_0
     483: getfield      #61                 // Field blockArr:[I
     486: iload         9
     488: iaload
     489: istore        10
     491: iload         10
     493: ifeq          534
     496: iconst_0
     497: istore        11
     499: iload         11
     501: bipush        16
     503: if_icmpge     534
     506: aload_0
     507: getfield      #61                 // Field blockArr:[I
     510: iload         9
     512: iaload
     513: ifne          525
     516: aload_0
     517: getfield      #61                 // Field blockArr:[I
     520: iload         9
     522: iload         10
     524: iastore
     525: iinc          11, 1
     528: iinc          9, 1
     531: goto          499
     534: iinc          8, 1
     537: goto          468
     540: aload         5
     542: getfield      #344                // Field com/sk89q/worldedit/world/registry/LegacyMapper$LegacyDataFile.items:Ljava/util/Map;
     545: invokeinterface #221,  1          // InterfaceMethod java/util/Map.entrySet:()Ljava/util/Set;
     550: invokeinterface #227,  1          // InterfaceMethod java/util/Set.iterator:()Ljava/util/Iterator;
     555: astore        8
     557: aload         8
     559: invokeinterface #235,  1          // InterfaceMethod java/util/Iterator.hasNext:()Z
     564: ifeq          697
     567: aload         8
     569: invokeinterface #239,  1          // InterfaceMethod java/util/Iterator.next:()Ljava/lang/Object;
     574: checkcast     #12                 // class java/util/Map$Entry
     577: astore        9
     579: aload         9
     581: invokeinterface #242,  1          // InterfaceMethod java/util/Map$Entry.getKey:()Ljava/lang/Object;
     586: checkcast     #229                // class java/lang/String
     589: astore        10
     591: aload         9
     593: invokeinterface #245,  1          // InterfaceMethod java/util/Map$Entry.getValue:()Ljava/lang/Object;
     598: checkcast     #229                // class java/lang/String
     601: astore        11
     603: aload         11
     605: invokestatic  #349                // Method com/sk89q/worldedit/world/item/ItemTypes.get:(Ljava/lang/String;)Lcom/sk89q/worldedit/world/item/ItemType;
     608: astore        12
     610: aload         12
     612: ifnonnull     647
     615: aload         6
     617: ifnull        647
     620: aload         6
     622: getstatic     #352                // Field com/sk89q/worldedit/world/DataFixer$FixTypes.ITEM_TYPE:Lcom/sk89q/worldedit/world/DataFixer$FixType;
     625: aload         11
     627: sipush        1631
     630: invokeinterface #302,  4          // InterfaceMethod com/sk89q/worldedit/world/DataFixer.fixUp:(Lcom/sk89q/worldedit/world/DataFixer$FixType;Ljava/lang/Object;I)Ljava/lang/Object;
     635: checkcast     #229                // class java/lang/String
     638: astore        11
     640: aload         11
     642: invokestatic  #349                // Method com/sk89q/worldedit/world/item/ItemTypes.get:(Ljava/lang/String;)Lcom/sk89q/worldedit/world/item/ItemType;
     645: astore        12
     647: aload         12
     649: ifnonnull     668
     652: getstatic     #118                // Field LOGGER:Lorg/apache/logging/log4j/Logger;
     655: ldc_w         #356                // String Unknown item: {}. Neither the DataFixer nor defaulting worked to recognize this item.
     658: aload         11
     660: invokeinterface #320,  3          // InterfaceMethod org/apache/logging/log4j/Logger.error:(Ljava/lang/String;Ljava/lang/Object;)V
     665: goto          694
     668: aload_0
     669: getfield      #69                 // Field itemMap:Lcom/google/common/collect/BiMap;
     672: aload_0
     673: aload         10
     675: invokevirtual #249                // Method getCombinedId:(Ljava/lang/String;)I
     678: invokestatic  #255                // Method java/lang/Integer.valueOf:(I)Ljava/lang/Integer;
     681: aload         12
     683: invokeinterface #359,  3          // InterfaceMethod com/google/common/collect/BiMap.put:(Ljava/lang/Object;Ljava/lang/Object;)Ljava/lang/Object;
     688: pop
     689: goto          694
     692: astore        13
     694: goto          557
     697: return
    Exception table:
       from    to  target type
         234   282   285   Class com/sk89q/worldedit/extension/input/InputParseException
         300   334   337   Class com/sk89q/worldedit/extension/input/InputParseException
         344   358   361   Class com/sk89q/worldedit/extension/input/InputParseException
         668   689   692   Class java/lang/Exception

  private int getCombinedId(java.lang.String);
    Code:
       0: aload_1
       1: ldc_w         #397                // String :
       4: invokevirtual #401                // Method java/lang/String.split:(Ljava/lang/String;)[Ljava/lang/String;
       7: astore_2
       8: aload_2
       9: iconst_0
      10: aaload
      11: invokestatic  #404                // Method java/lang/Integer.parseInt:(Ljava/lang/String;)I
      14: iconst_4
      15: ishl
      16: aload_2
      17: arraylength
      18: iconst_2
      19: if_icmpne     31
      22: aload_2
      23: iconst_1
      24: aaload
      25: invokestatic  #404                // Method java/lang/Integer.parseInt:(Ljava/lang/String;)I
      28: goto          32
      31: iconst_0
      32: iadd
      33: ireturn

  public com.sk89q.worldedit.world.item.ItemType getItemFromLegacy(int);
    Code:
       0: aload_0
       1: getfield      #69                 // Field itemMap:Lcom/google/common/collect/BiMap;
       4: iload_1
       5: iconst_4
       6: ishl
       7: invokestatic  #255                // Method java/lang/Integer.valueOf:(I)Ljava/lang/Integer;
      10: invokeinterface #413,  2          // InterfaceMethod com/google/common/collect/BiMap.get:(Ljava/lang/Object;)Ljava/lang/Object;
      15: checkcast     #354                // class com/sk89q/worldedit/world/item/ItemType
      18: areturn

  public com.sk89q.worldedit.world.item.ItemType getItemFromLegacy(java.lang.String);
    Code:
       0: aload_1
       1: ldc_w         #415                // String minecraft:
       4: invokevirtual #419                // Method java/lang/String.startsWith:(Ljava/lang/String;)Z
       7: ifeq          17
      10: aload_1
      11: bipush        10
      13: invokevirtual #423                // Method java/lang/String.substring:(I)Ljava/lang/String;
      16: astore_1
      17: aload_0
      18: getfield      #69                 // Field itemMap:Lcom/google/common/collect/BiMap;
      21: aload_0
      22: aload_1
      23: invokevirtual #249                // Method getCombinedId:(Ljava/lang/String;)I
      26: invokestatic  #255                // Method java/lang/Integer.valueOf:(I)Ljava/lang/Integer;
      29: invokeinterface #413,  2          // InterfaceMethod com/google/common/collect/BiMap.get:(Ljava/lang/Object;)Ljava/lang/Object;
      34: checkcast     #354                // class com/sk89q/worldedit/world/item/ItemType
      37: areturn

  public com.sk89q.worldedit.world.block.BlockState getBlockFromLegacy(java.lang.String);
    Code:
       0: aload_1
       1: ldc_w         #415                // String minecraft:
       4: invokevirtual #419                // Method java/lang/String.startsWith:(Ljava/lang/String;)Z
       7: ifeq          17
      10: aload_1
      11: bipush        10
      13: invokevirtual #423                // Method java/lang/String.substring:(I)Ljava/lang/String;
      16: astore_1
      17: aload_0
      18: getfield      #61                 // Field blockArr:[I
      21: aload_0
      22: aload_1
      23: invokevirtual #249                // Method getCombinedId:(Ljava/lang/String;)I
      26: iaload
      27: invokestatic  #429                // Method com/sk89q/worldedit/world/block/BlockState.getFromInternalId:(I)Lcom/sk89q/worldedit/world/block/BlockState;
      30: areturn
      31: astore_2
      32: aload_2
      33: invokevirtual #432                // Method com/sk89q/worldedit/extension/input/InputParseException.printStackTrace:()V
      36: aconst_null
      37: areturn
    Exception table:
       from    to  target type
          17    30    31   Class com/sk89q/worldedit/extension/input/InputParseException

  public com.sk89q.worldedit.world.item.ItemType getItemFromLegacy(int, int);
    Code:
       0: aload_0
       1: getfield      #69                 // Field itemMap:Lcom/google/common/collect/BiMap;
       4: iload_1
       5: iconst_4
       6: ishl
       7: iload_2
       8: iadd
       9: invokestatic  #255                // Method java/lang/Integer.valueOf:(I)Ljava/lang/Integer;
      12: invokeinterface #413,  2          // InterfaceMethod com/google/common/collect/BiMap.get:(Ljava/lang/Object;)Ljava/lang/Object;
      17: checkcast     #354                // class com/sk89q/worldedit/world/item/ItemType
      20: areturn

  public java.lang.Integer getLegacyCombined(com.sk89q.worldedit.world.item.ItemType);
    Code:
       0: aload_0
       1: getfield      #69                 // Field itemMap:Lcom/google/common/collect/BiMap;
       4: invokeinterface #440,  1          // InterfaceMethod com/google/common/collect/BiMap.inverse:()Lcom/google/common/collect/BiMap;
       9: aload_1
      10: invokeinterface #413,  2          // InterfaceMethod com/google/common/collect/BiMap.get:(Ljava/lang/Object;)Ljava/lang/Object;
      15: checkcast     #251                // class java/lang/Integer
      18: areturn

  public int[] getLegacyFromItem(com.sk89q.worldedit.world.item.ItemType);
    Code:
       0: aload_0
       1: aload_1
       2: invokevirtual #444                // Method getLegacyCombined:(Lcom/sk89q/worldedit/world/item/ItemType;)Ljava/lang/Integer;
       5: astore_2
       6: aload_2
       7: ifnonnull     12
      10: aconst_null
      11: areturn
      12: iconst_2
      13: newarray       int
      15: dup
      16: iconst_0
      17: aload_2
      18: invokevirtual #329                // Method java/lang/Integer.intValue:()I
      21: iconst_4
      22: ishr
      23: iastore
      24: dup
      25: iconst_1
      26: aload_2
      27: invokevirtual #329                // Method java/lang/Integer.intValue:()I
      30: bipush        15
      32: iand
      33: iastore
      34: areturn

  public com.sk89q.worldedit.world.block.BlockState getBlockFromLegacy(int);
    Code:
       0: aload_0
       1: iload_1
       2: iconst_4
       3: ishl
       4: invokevirtual #447                // Method getBlock:(I)Lcom/sk89q/worldedit/world/block/BlockState;
       7: areturn

  public com.sk89q.worldedit.world.block.BlockState getBlockFromLegacyCombinedId(int);
    Code:
       0: aload_0
       1: iload_1
       2: invokevirtual #447                // Method getBlock:(I)Lcom/sk89q/worldedit/world/block/BlockState;
       5: areturn

  public com.sk89q.worldedit.world.block.BlockState getBlockFromLegacy(int, int);
    Code:
       0: aload_0
       1: iload_1
       2: iconst_4
       3: ishl
       4: iload_2
       5: iadd
       6: invokevirtual #447                // Method getBlock:(I)Lcom/sk89q/worldedit/world/block/BlockState;
       9: areturn

  private com.sk89q.worldedit.world.block.BlockState getBlock(int);
    Code:
       0: iload_1
       1: aload_0
       2: getfield      #61                 // Field blockArr:[I
       5: arraylength
       6: if_icmpge     38
       9: aload_0
      10: getfield      #61                 // Field blockArr:[I
      13: iload_1
      14: iaload
      15: istore_2
      16: iload_2
      17: ifne          22
      20: aconst_null
      21: areturn
      22: iload_2
      23: invokestatic  #429                // Method com/sk89q/worldedit/world/block/BlockState.getFromInternalId:(I)Lcom/sk89q/worldedit/world/block/BlockState;
      26: areturn
      27: astore_3
      28: aload_3
      29: invokevirtual #432                // Method com/sk89q/worldedit/extension/input/InputParseException.printStackTrace:()V
      32: goto          38
      35: astore_2
      36: aconst_null
      37: areturn
      38: aload_0
      39: getfield      #59                 // Field extraId4DataToStateId:Lcom/sk89q/worldedit/bukkit/fastutil/ints/Int2ObjectArrayMap;
      42: iload_1
      43: invokevirtual #454                // Method com/sk89q/worldedit/bukkit/fastutil/ints/Int2ObjectArrayMap.get:(I)Ljava/lang/Object;
      46: checkcast     #251                // class java/lang/Integer
      49: astore_2
      50: aload_2
      51: ifnonnull     70
      54: aload_0
      55: getfield      #59                 // Field extraId4DataToStateId:Lcom/sk89q/worldedit/bukkit/fastutil/ints/Int2ObjectArrayMap;
      58: iload_1
      59: sipush        4080
      62: iand
      63: invokevirtual #454                // Method com/sk89q/worldedit/bukkit/fastutil/ints/Int2ObjectArrayMap.get:(I)Ljava/lang/Object;
      66: checkcast     #251                // class java/lang/Integer
      69: astore_2
      70: aload_2
      71: ifnull        87
      74: aload_2
      75: invokevirtual #329                // Method java/lang/Integer.intValue:()I
      78: invokestatic  #429                // Method com/sk89q/worldedit/world/block/BlockState.getFromInternalId:(I)Lcom/sk89q/worldedit/world/block/BlockState;
      81: areturn
      82: astore_3
      83: aload_3
      84: invokevirtual #432                // Method com/sk89q/worldedit/extension/input/InputParseException.printStackTrace:()V
      87: aconst_null
      88: areturn
    Exception table:
       from    to  target type
          22    26    27   Class com/sk89q/worldedit/extension/input/InputParseException
           9    21    35   Class java/lang/IndexOutOfBoundsException
          22    26    35   Class java/lang/IndexOutOfBoundsException
          27    32    35   Class java/lang/IndexOutOfBoundsException
          74    81    82   Class com/sk89q/worldedit/extension/input/InputParseException

  public void register(int, int, com.sk89q.worldedit.world.block.BlockStateHolder);
    Code:
       0: iload_1
       1: iconst_4
       2: ishl
       3: iload_2
       4: iadd
       5: invokestatic  #255                // Method java/lang/Integer.valueOf:(I)Ljava/lang/Integer;
       8: astore        4
      10: aload_0
      11: getfield      #59                 // Field extraId4DataToStateId:Lcom/sk89q/worldedit/bukkit/fastutil/ints/Int2ObjectArrayMap;
      14: aload         4
      16: aload_3
      17: invokeinterface #463,  1          // InterfaceMethod com/sk89q/worldedit/world/block/BlockStateHolder.getInternalId:()I
      22: invokestatic  #255                // Method java/lang/Integer.valueOf:(I)Ljava/lang/Integer;
      25: invokevirtual #466                // Method com/sk89q/worldedit/bukkit/fastutil/ints/Int2ObjectArrayMap.put:(Ljava/lang/Integer;Ljava/lang/Object;)Ljava/lang/Object;
      28: pop
      29: aload_0
      30: getfield      #57                 // Field blockStateToLegacyId4Data:Lcom/sk89q/worldedit/bukkit/fastutil/ints/Int2ObjectArrayMap;
      33: aload_3
      34: invokeinterface #463,  1          // InterfaceMethod com/sk89q/worldedit/world/block/BlockStateHolder.getInternalId:()I
      39: aload         4
      41: invokevirtual #341                // Method com/sk89q/worldedit/bukkit/fastutil/ints/Int2ObjectArrayMap.putIfAbsent:(ILjava/lang/Object;)Ljava/lang/Object;
      44: pop
      45: return

  public java.lang.Integer getLegacyCombined(com.sk89q.worldedit.world.block.BlockState);
    Code:
       0: aload_0
       1: getfield      #57                 // Field blockStateToLegacyId4Data:Lcom/sk89q/worldedit/bukkit/fastutil/ints/Int2ObjectArrayMap;
       4: aload_1
       5: invokevirtual #332                // Method com/sk89q/worldedit/world/block/BlockState.getInternalId:()I
       8: invokevirtual #454                // Method com/sk89q/worldedit/bukkit/fastutil/ints/Int2ObjectArrayMap.get:(I)Ljava/lang/Object;
      11: checkcast     #251                // class java/lang/Integer
      14: astore_2
      15: aload_2
      16: ifnonnull     34
      19: aload_0
      20: getfield      #57                 // Field blockStateToLegacyId4Data:Lcom/sk89q/worldedit/bukkit/fastutil/ints/Int2ObjectArrayMap;
      23: aload_1
      24: invokevirtual #338                // Method com/sk89q/worldedit/world/block/BlockState.getInternalBlockTypeId:()I
      27: invokevirtual #454                // Method com/sk89q/worldedit/bukkit/fastutil/ints/Int2ObjectArrayMap.get:(I)Ljava/lang/Object;
      30: checkcast     #251                // class java/lang/Integer
      33: astore_2
      34: aload_2
      35: areturn

  public java.lang.Integer getLegacyCombined(com.sk89q.worldedit.world.block.BlockType);
    Code:
       0: aload_0
       1: getfield      #57                 // Field blockStateToLegacyId4Data:Lcom/sk89q/worldedit/bukkit/fastutil/ints/Int2ObjectArrayMap;
       4: aload_1
       5: invokevirtual #474                // Method com/sk89q/worldedit/world/block/BlockType.getDefaultState:()Lcom/sk89q/worldedit/world/block/BlockState;
       8: invokevirtual #332                // Method com/sk89q/worldedit/world/block/BlockState.getInternalId:()I
      11: invokevirtual #454                // Method com/sk89q/worldedit/bukkit/fastutil/ints/Int2ObjectArrayMap.get:(I)Ljava/lang/Object;
      14: checkcast     #251                // class java/lang/Integer
      17: areturn

  public int[] getLegacyFromBlock(com.sk89q.worldedit.world.block.BlockState);
    Code:
       0: aload_0
       1: aload_1
       2: invokevirtual #479                // Method getLegacyCombined:(Lcom/sk89q/worldedit/world/block/BlockState;)Ljava/lang/Integer;
       5: astore_2
       6: aload_2
       7: ifnonnull     14
      10: aconst_null
      11: goto          36
      14: iconst_2
      15: newarray       int
      17: dup
      18: iconst_0
      19: aload_2
      20: invokevirtual #329                // Method java/lang/Integer.intValue:()I
      23: iconst_4
      24: ishr
      25: iastore
      26: dup
      27: iconst_1
      28: aload_2
      29: invokevirtual #329                // Method java/lang/Integer.intValue:()I
      32: bipush        15
      34: iand
      35: iastore
      36: areturn

  public static com.sk89q.worldedit.world.registry.LegacyMapper getInstance();
    Code:
       0: getstatic     #483                // Field INSTANCE:Lcom/sk89q/worldedit/world/registry/LegacyMapper;
       3: ifnonnull     16
       6: new           #2                  // class com/sk89q/worldedit/world/registry/LegacyMapper
       9: dup
      10: invokespecial #484                // Method "<init>":()V
      13: putstatic     #483                // Field INSTANCE:Lcom/sk89q/worldedit/world/registry/LegacyMapper;
      16: getstatic     #483                // Field INSTANCE:Lcom/sk89q/worldedit/world/registry/LegacyMapper;
      19: areturn

  static {};
    Code:
       0: invokestatic  #491                // Method com/sk89q/worldedit/internal/util/LogManagerCompat.getLogger:()Lorg/apache/logging/log4j/Logger;
       3: putstatic     #118                // Field LOGGER:Lorg/apache/logging/log4j/Logger;
       6: return
}
