Compiled from "VolatileAIHandlerImpl.java"
public class io.lumine.mythic.core.volatilecode.v1_20_R1.VolatileAIHandlerImpl implements io.lumine.mythic.api.volatilecode.handlers.VolatileAIHandler {
  private io.lumine.mythic.bukkit.utils.reflection.Reflector<net.minecraft.world.entity.EntityInsentient> refEntityInsentient;

  private io.lumine.mythic.bukkit.utils.reflection.Reflector<net.minecraft.world.entity.ai.goal.PathfinderGoalSelector> refGoalSelector;

  private final java.util.Map<java.lang.String, java.lang.Class<? extends io.lumine.mythic.core.mobs.ai.PathfinderAdapter>> AI_GOALS;

  private final java.util.Map<java.lang.String, java.lang.Class<? extends io.lumine.mythic.core.mobs.ai.PathfinderAdapter>> AI_TARGETS;

  public io.lumine.mythic.core.volatilecode.v1_20_R1.VolatileAIHandlerImpl(io.lumine.mythic.api.volatilecode.VolatileCodeHandler);
    Code:
       0: aload_0
       1: invokespecial #23                 // Method java/lang/Object."<init>":()V
       4: aload_0
       5: new           #25                 // class io/lumine/mythic/bukkit/utils/reflection/Reflector
       8: dup
       9: ldc           #27                 // class net/minecraft/world/entity/EntityInsentient
      11: iconst_3
      12: anewarray     #29                 // class java/lang/String
      15: dup
      16: iconst_0
      17: ldc           #31                 // String bS
      19: aastore
      20: dup
      21: iconst_1
      22: ldc           #33                 // String bT
      24: aastore
      25: dup
      26: iconst_2
      27: ldc           #35                 // String bU
      29: aastore
      30: invokespecial #38                 // Method io/lumine/mythic/bukkit/utils/reflection/Reflector."<init>":(Ljava/lang/Class;[Ljava/lang/String;)V
      33: putfield      #40                 // Field refEntityInsentient:Lio/lumine/mythic/bukkit/utils/reflection/Reflector;
      36: aload_0
      37: new           #25                 // class io/lumine/mythic/bukkit/utils/reflection/Reflector
      40: dup
      41: ldc           #42                 // class net/minecraft/world/entity/ai/goal/PathfinderGoalSelector
      43: iconst_2
      44: anewarray     #29                 // class java/lang/String
      47: dup
      48: iconst_0
      49: ldc           #44                 // String b
      51: aastore
      52: dup
      53: iconst_1
      54: ldc           #46                 // String c
      56: aastore
      57: invokespecial #38                 // Method io/lumine/mythic/bukkit/utils/reflection/Reflector."<init>":(Ljava/lang/Class;[Ljava/lang/String;)V
      60: putfield      #48                 // Field refGoalSelector:Lio/lumine/mythic/bukkit/utils/reflection/Reflector;
      63: aload_0
      64: new           #50                 // class java/util/concurrent/ConcurrentHashMap
      67: dup
      68: invokespecial #51                 // Method java/util/concurrent/ConcurrentHashMap."<init>":()V
      71: putfield      #53                 // Field AI_GOALS:Ljava/util/Map;
      74: aload_0
      75: new           #50                 // class java/util/concurrent/ConcurrentHashMap
      78: dup
      79: invokespecial #51                 // Method java/util/concurrent/ConcurrentHashMap."<init>":()V
      82: putfield      #55                 // Field AI_TARGETS:Ljava/util/Map;
      85: invokestatic  #61                 // Method io/lumine/mythic/bukkit/MythicBukkit.inst:()Lio/lumine/mythic/bukkit/MythicBukkit;
      88: ldc           #63                 // String io.lumine.mythic.core.mobs.ai.goals
      90: ldc           #65                 // class io/lumine/mythic/core/utils/annotations/MythicAIGoal
      92: invokestatic  #71                 // Method io/lumine/mythic/core/utils/annotations/AnnotationUtil.getAnnotatedClasses:(Lorg/bukkit/plugin/java/JavaPlugin;Ljava/lang/String;Ljava/lang/Class;)Ljava/util/Collection;
      95: astore_2
      96: aload_2
      97: invokeinterface #77,  1           // InterfaceMethod java/util/Collection.iterator:()Ljava/util/Iterator;
     102: astore_3
     103: aload_3
     104: invokeinterface #85,  1           // InterfaceMethod java/util/Iterator.hasNext:()Z
     109: ifeq          258
     112: aload_3
     113: invokeinterface #89,  1           // InterfaceMethod java/util/Iterator.next:()Ljava/lang/Object;
     118: checkcast     #91                 // class java/lang/Class
     121: astore        4
     123: aload         4
     125: ldc           #65                 // class io/lumine/mythic/core/utils/annotations/MythicAIGoal
     127: invokevirtual #95                 // Method java/lang/Class.getAnnotation:(Ljava/lang/Class;)Ljava/lang/annotation/Annotation;
     130: checkcast     #65                 // class io/lumine/mythic/core/utils/annotations/MythicAIGoal
     133: invokeinterface #99,  1           // InterfaceMethod io/lumine/mythic/core/utils/annotations/MythicAIGoal.name:()Ljava/lang/String;
     138: astore        5
     140: aload         4
     142: ldc           #65                 // class io/lumine/mythic/core/utils/annotations/MythicAIGoal
     144: invokevirtual #95                 // Method java/lang/Class.getAnnotation:(Ljava/lang/Class;)Ljava/lang/annotation/Annotation;
     147: checkcast     #65                 // class io/lumine/mythic/core/utils/annotations/MythicAIGoal
     150: invokeinterface #103,  1          // InterfaceMethod io/lumine/mythic/core/utils/annotations/MythicAIGoal.aliases:()[Ljava/lang/String;
     155: astore        6
     157: ldc           #105                // class io/lumine/mythic/core/mobs/ai/PathfinderAdapter
     159: aload         4
     161: invokevirtual #109                // Method java/lang/Class.isAssignableFrom:(Ljava/lang/Class;)Z
     164: ifeq          233
     167: aload_0
     168: getfield      #53                 // Field AI_GOALS:Ljava/util/Map;
     171: aload         5
     173: invokevirtual #112                // Method java/lang/String.toUpperCase:()Ljava/lang/String;
     176: aload         4
     178: invokeinterface #118,  3          // InterfaceMethod java/util/Map.put:(Ljava/lang/Object;Ljava/lang/Object;)Ljava/lang/Object;
     183: pop
     184: aload         6
     186: astore        7
     188: aload         7
     190: arraylength
     191: istore        8
     193: iconst_0
     194: istore        9
     196: iload         9
     198: iload         8
     200: if_icmpge     233
     203: aload         7
     205: iload         9
     207: aaload
     208: astore        10
     210: aload_0
     211: getfield      #53                 // Field AI_GOALS:Ljava/util/Map;
     214: aload         10
     216: invokevirtual #112                // Method java/lang/String.toUpperCase:()Ljava/lang/String;
     219: aload         4
     221: invokeinterface #118,  3          // InterfaceMethod java/util/Map.put:(Ljava/lang/Object;Ljava/lang/Object;)Ljava/lang/Object;
     226: pop
     227: iinc          9, 1
     230: goto          196
     233: goto          255
     236: astore        5
     238: ldc           #122                // String Failed to load custom AI goal {0}
     240: iconst_1
     241: anewarray     #4                  // class java/lang/Object
     244: dup
     245: iconst_0
     246: aload         4
     248: invokevirtual #125                // Method java/lang/Class.getCanonicalName:()Ljava/lang/String;
     251: aastore
     252: invokestatic  #131                // Method io/lumine/mythic/core/logging/MythicLogger.error:(Ljava/lang/String;[Ljava/lang/Object;)V
     255: goto          103
     258: invokestatic  #61                 // Method io/lumine/mythic/bukkit/MythicBukkit.inst:()Lio/lumine/mythic/bukkit/MythicBukkit;
     261: ldc           #133                // String io.lumine.mythic.core.volatilecode.v1_20_R1.ai.goals
     263: ldc           #65                 // class io/lumine/mythic/core/utils/annotations/MythicAIGoal
     265: invokestatic  #71                 // Method io/lumine/mythic/core/utils/annotations/AnnotationUtil.getAnnotatedClasses:(Lorg/bukkit/plugin/java/JavaPlugin;Ljava/lang/String;Ljava/lang/Class;)Ljava/util/Collection;
     268: astore_3
     269: aload_3
     270: invokeinterface #77,  1           // InterfaceMethod java/util/Collection.iterator:()Ljava/util/Iterator;
     275: astore        4
     277: aload         4
     279: invokeinterface #85,  1           // InterfaceMethod java/util/Iterator.hasNext:()Z
     284: ifeq          434
     287: aload         4
     289: invokeinterface #89,  1           // InterfaceMethod java/util/Iterator.next:()Ljava/lang/Object;
     294: checkcast     #91                 // class java/lang/Class
     297: astore        5
     299: aload         5
     301: ldc           #65                 // class io/lumine/mythic/core/utils/annotations/MythicAIGoal
     303: invokevirtual #95                 // Method java/lang/Class.getAnnotation:(Ljava/lang/Class;)Ljava/lang/annotation/Annotation;
     306: checkcast     #65                 // class io/lumine/mythic/core/utils/annotations/MythicAIGoal
     309: invokeinterface #99,  1           // InterfaceMethod io/lumine/mythic/core/utils/annotations/MythicAIGoal.name:()Ljava/lang/String;
     314: astore        6
     316: aload         5
     318: ldc           #65                 // class io/lumine/mythic/core/utils/annotations/MythicAIGoal
     320: invokevirtual #95                 // Method java/lang/Class.getAnnotation:(Ljava/lang/Class;)Ljava/lang/annotation/Annotation;
     323: checkcast     #65                 // class io/lumine/mythic/core/utils/annotations/MythicAIGoal
     326: invokeinterface #103,  1          // InterfaceMethod io/lumine/mythic/core/utils/annotations/MythicAIGoal.aliases:()[Ljava/lang/String;
     331: astore        7
     333: ldc           #105                // class io/lumine/mythic/core/mobs/ai/PathfinderAdapter
     335: aload         5
     337: invokevirtual #109                // Method java/lang/Class.isAssignableFrom:(Ljava/lang/Class;)Z
     340: ifeq          409
     343: aload_0
     344: getfield      #53                 // Field AI_GOALS:Ljava/util/Map;
     347: aload         6
     349: invokevirtual #112                // Method java/lang/String.toUpperCase:()Ljava/lang/String;
     352: aload         5
     354: invokeinterface #118,  3          // InterfaceMethod java/util/Map.put:(Ljava/lang/Object;Ljava/lang/Object;)Ljava/lang/Object;
     359: pop
     360: aload         7
     362: astore        8
     364: aload         8
     366: arraylength
     367: istore        9
     369: iconst_0
     370: istore        10
     372: iload         10
     374: iload         9
     376: if_icmpge     409
     379: aload         8
     381: iload         10
     383: aaload
     384: astore        11
     386: aload_0
     387: getfield      #53                 // Field AI_GOALS:Ljava/util/Map;
     390: aload         11
     392: invokevirtual #112                // Method java/lang/String.toUpperCase:()Ljava/lang/String;
     395: aload         5
     397: invokeinterface #118,  3          // InterfaceMethod java/util/Map.put:(Ljava/lang/Object;Ljava/lang/Object;)Ljava/lang/Object;
     402: pop
     403: iinc          10, 1
     406: goto          372
     409: goto          431
     412: astore        6
     414: ldc           #135                // String Failed to load wrapped AI goal {0}
     416: iconst_1
     417: anewarray     #4                  // class java/lang/Object
     420: dup
     421: iconst_0
     422: aload         5
     424: invokevirtual #125                // Method java/lang/Class.getCanonicalName:()Ljava/lang/String;
     427: aastore
     428: invokestatic  #131                // Method io/lumine/mythic/core/logging/MythicLogger.error:(Ljava/lang/String;[Ljava/lang/Object;)V
     431: goto          277
     434: invokestatic  #61                 // Method io/lumine/mythic/bukkit/MythicBukkit.inst:()Lio/lumine/mythic/bukkit/MythicBukkit;
     437: ldc           #137                // String io.lumine.mythic.core.mobs.ai.targeters
     439: ldc           #65                 // class io/lumine/mythic/core/utils/annotations/MythicAIGoal
     441: invokestatic  #71                 // Method io/lumine/mythic/core/utils/annotations/AnnotationUtil.getAnnotatedClasses:(Lorg/bukkit/plugin/java/JavaPlugin;Ljava/lang/String;Ljava/lang/Class;)Ljava/util/Collection;
     444: astore        4
     446: aload         4
     448: invokeinterface #77,  1           // InterfaceMethod java/util/Collection.iterator:()Ljava/util/Iterator;
     453: astore        5
     455: aload         5
     457: invokeinterface #85,  1           // InterfaceMethod java/util/Iterator.hasNext:()Z
     462: ifeq          612
     465: aload         5
     467: invokeinterface #89,  1           // InterfaceMethod java/util/Iterator.next:()Ljava/lang/Object;
     472: checkcast     #91                 // class java/lang/Class
     475: astore        6
     477: aload         6
     479: ldc           #65                 // class io/lumine/mythic/core/utils/annotations/MythicAIGoal
     481: invokevirtual #95                 // Method java/lang/Class.getAnnotation:(Ljava/lang/Class;)Ljava/lang/annotation/Annotation;
     484: checkcast     #65                 // class io/lumine/mythic/core/utils/annotations/MythicAIGoal
     487: invokeinterface #99,  1           // InterfaceMethod io/lumine/mythic/core/utils/annotations/MythicAIGoal.name:()Ljava/lang/String;
     492: astore        7
     494: aload         6
     496: ldc           #65                 // class io/lumine/mythic/core/utils/annotations/MythicAIGoal
     498: invokevirtual #95                 // Method java/lang/Class.getAnnotation:(Ljava/lang/Class;)Ljava/lang/annotation/Annotation;
     501: checkcast     #65                 // class io/lumine/mythic/core/utils/annotations/MythicAIGoal
     504: invokeinterface #103,  1          // InterfaceMethod io/lumine/mythic/core/utils/annotations/MythicAIGoal.aliases:()[Ljava/lang/String;
     509: astore        8
     511: ldc           #105                // class io/lumine/mythic/core/mobs/ai/PathfinderAdapter
     513: aload         6
     515: invokevirtual #109                // Method java/lang/Class.isAssignableFrom:(Ljava/lang/Class;)Z
     518: ifeq          587
     521: aload_0
     522: getfield      #55                 // Field AI_TARGETS:Ljava/util/Map;
     525: aload         7
     527: invokevirtual #112                // Method java/lang/String.toUpperCase:()Ljava/lang/String;
     530: aload         6
     532: invokeinterface #118,  3          // InterfaceMethod java/util/Map.put:(Ljava/lang/Object;Ljava/lang/Object;)Ljava/lang/Object;
     537: pop
     538: aload         8
     540: astore        9
     542: aload         9
     544: arraylength
     545: istore        10
     547: iconst_0
     548: istore        11
     550: iload         11
     552: iload         10
     554: if_icmpge     587
     557: aload         9
     559: iload         11
     561: aaload
     562: astore        12
     564: aload_0
     565: getfield      #55                 // Field AI_TARGETS:Ljava/util/Map;
     568: aload         12
     570: invokevirtual #112                // Method java/lang/String.toUpperCase:()Ljava/lang/String;
     573: aload         6
     575: invokeinterface #118,  3          // InterfaceMethod java/util/Map.put:(Ljava/lang/Object;Ljava/lang/Object;)Ljava/lang/Object;
     580: pop
     581: iinc          11, 1
     584: goto          550
     587: goto          609
     590: astore        7
     592: ldc           #139                // String Failed to load custom AI targeter {0}
     594: iconst_1
     595: anewarray     #4                  // class java/lang/Object
     598: dup
     599: iconst_0
     600: aload         6
     602: invokevirtual #125                // Method java/lang/Class.getCanonicalName:()Ljava/lang/String;
     605: aastore
     606: invokestatic  #131                // Method io/lumine/mythic/core/logging/MythicLogger.error:(Ljava/lang/String;[Ljava/lang/Object;)V
     609: goto          455
     612: invokestatic  #61                 // Method io/lumine/mythic/bukkit/MythicBukkit.inst:()Lio/lumine/mythic/bukkit/MythicBukkit;
     615: ldc           #141                // String io.lumine.mythic.core.volatilecode.v1_20_R1.ai.targeters
     617: ldc           #65                 // class io/lumine/mythic/core/utils/annotations/MythicAIGoal
     619: invokestatic  #71                 // Method io/lumine/mythic/core/utils/annotations/AnnotationUtil.getAnnotatedClasses:(Lorg/bukkit/plugin/java/JavaPlugin;Ljava/lang/String;Ljava/lang/Class;)Ljava/util/Collection;
     622: astore        5
     624: aload         5
     626: invokeinterface #77,  1           // InterfaceMethod java/util/Collection.iterator:()Ljava/util/Iterator;
     631: astore        6
     633: aload         6
     635: invokeinterface #85,  1           // InterfaceMethod java/util/Iterator.hasNext:()Z
     640: ifeq          790
     643: aload         6
     645: invokeinterface #89,  1           // InterfaceMethod java/util/Iterator.next:()Ljava/lang/Object;
     650: checkcast     #91                 // class java/lang/Class
     653: astore        7
     655: aload         7
     657: ldc           #65                 // class io/lumine/mythic/core/utils/annotations/MythicAIGoal
     659: invokevirtual #95                 // Method java/lang/Class.getAnnotation:(Ljava/lang/Class;)Ljava/lang/annotation/Annotation;
     662: checkcast     #65                 // class io/lumine/mythic/core/utils/annotations/MythicAIGoal
     665: invokeinterface #99,  1           // InterfaceMethod io/lumine/mythic/core/utils/annotations/MythicAIGoal.name:()Ljava/lang/String;
     670: astore        8
     672: aload         7
     674: ldc           #65                 // class io/lumine/mythic/core/utils/annotations/MythicAIGoal
     676: invokevirtual #95                 // Method java/lang/Class.getAnnotation:(Ljava/lang/Class;)Ljava/lang/annotation/Annotation;
     679: checkcast     #65                 // class io/lumine/mythic/core/utils/annotations/MythicAIGoal
     682: invokeinterface #103,  1          // InterfaceMethod io/lumine/mythic/core/utils/annotations/MythicAIGoal.aliases:()[Ljava/lang/String;
     687: astore        9
     689: ldc           #105                // class io/lumine/mythic/core/mobs/ai/PathfinderAdapter
     691: aload         7
     693: invokevirtual #109                // Method java/lang/Class.isAssignableFrom:(Ljava/lang/Class;)Z
     696: ifeq          765
     699: aload_0
     700: getfield      #55                 // Field AI_TARGETS:Ljava/util/Map;
     703: aload         8
     705: invokevirtual #112                // Method java/lang/String.toUpperCase:()Ljava/lang/String;
     708: aload         7
     710: invokeinterface #118,  3          // InterfaceMethod java/util/Map.put:(Ljava/lang/Object;Ljava/lang/Object;)Ljava/lang/Object;
     715: pop
     716: aload         9
     718: astore        10
     720: aload         10
     722: arraylength
     723: istore        11
     725: iconst_0
     726: istore        12
     728: iload         12
     730: iload         11
     732: if_icmpge     765
     735: aload         10
     737: iload         12
     739: aaload
     740: astore        13
     742: aload_0
     743: getfield      #55                 // Field AI_TARGETS:Ljava/util/Map;
     746: aload         13
     748: invokevirtual #112                // Method java/lang/String.toUpperCase:()Ljava/lang/String;
     751: aload         7
     753: invokeinterface #118,  3          // InterfaceMethod java/util/Map.put:(Ljava/lang/Object;Ljava/lang/Object;)Ljava/lang/Object;
     758: pop
     759: iinc          12, 1
     762: goto          728
     765: goto          787
     768: astore        8
     770: ldc           #143                // String Failed to load wrapped AI targeter {0}
     772: iconst_1
     773: anewarray     #4                  // class java/lang/Object
     776: dup
     777: iconst_0
     778: aload         7
     780: invokevirtual #125                // Method java/lang/Class.getCanonicalName:()Ljava/lang/String;
     783: aastore
     784: invokestatic  #131                // Method io/lumine/mythic/core/logging/MythicLogger.error:(Ljava/lang/String;[Ljava/lang/Object;)V
     787: goto          633
     790: return
    Exception table:
       from    to  target type
         123   233   236   Class java/lang/Exception
         299   409   412   Class java/lang/Exception
         477   587   590   Class java/lang/Exception
         655   765   768   Class java/lang/Exception

  public io.lumine.mythic.api.mobs.MobEars createEars(io.lumine.mythic.core.mobs.ActiveMob);
    Code:
       0: new           #164                // class io/lumine/mythic/core/volatilecode/v1_20_R1/ai/EntityHearingAid
       3: dup
       4: aload_1
       5: invokespecial #167                // Method io/lumine/mythic/core/volatilecode/v1_20_R1/ai/EntityHearingAid."<init>":(Lio/lumine/mythic/core/mobs/ActiveMob;)V
       8: areturn

  public void navigateToLocation(io.lumine.mythic.api.adapters.AbstractEntity, io.lumine.mythic.api.adapters.AbstractLocation, double);
    Code:
       0: aload_1
       1: invokeinterface #176,  1          // InterfaceMethod io/lumine/mythic/api/adapters/AbstractEntity.isLiving:()Z
       6: ifne          10
       9: return
      10: aload_1
      11: invokestatic  #182                // Method io/lumine/mythic/bukkit/BukkitAdapter.adapt:(Lio/lumine/mythic/api/adapters/AbstractEntity;)Lorg/bukkit/entity/Entity;
      14: checkcast     #184                // class org/bukkit/craftbukkit/v1_20_R1/entity/CraftLivingEntity
      17: invokevirtual #188                // Method org/bukkit/craftbukkit/v1_20_R1/entity/CraftLivingEntity.getHandle:()Lnet/minecraft/world/entity/EntityLiving;
      20: checkcast     #27                 // class net/minecraft/world/entity/EntityInsentient
      23: astore        5
      25: aload         5
      27: invokevirtual #192                // Method net/minecraft/world/entity/EntityInsentient.J:()Lnet/minecraft/world/entity/ai/navigation/NavigationAbstract;
      30: aload_2
      31: invokevirtual #198                // Method io/lumine/mythic/api/adapters/AbstractLocation.getX:()D
      34: aload_2
      35: invokevirtual #201                // Method io/lumine/mythic/api/adapters/AbstractLocation.getY:()D
      38: aload_2
      39: invokevirtual #204                // Method io/lumine/mythic/api/adapters/AbstractLocation.getZ:()D
      42: dload_3
      43: invokevirtual #210                // Method net/minecraft/world/entity/ai/navigation/NavigationAbstract.a:(DDDD)Z
      46: pop
      47: return

  public void clearPathfinderGoals(io.lumine.mythic.api.adapters.AbstractEntity);
    Code:
       0: aload_1
       1: invokeinterface #176,  1          // InterfaceMethod io/lumine/mythic/api/adapters/AbstractEntity.isLiving:()Z
       6: ifne          10
       9: return
      10: aload_1
      11: invokestatic  #182                // Method io/lumine/mythic/bukkit/BukkitAdapter.adapt:(Lio/lumine/mythic/api/adapters/AbstractEntity;)Lorg/bukkit/entity/Entity;
      14: checkcast     #184                // class org/bukkit/craftbukkit/v1_20_R1/entity/CraftLivingEntity
      17: invokevirtual #188                // Method org/bukkit/craftbukkit/v1_20_R1/entity/CraftLivingEntity.getHandle:()Lnet/minecraft/world/entity/EntityLiving;
      20: checkcast     #27                 // class net/minecraft/world/entity/EntityInsentient
      23: astore_2
      24: aload_0
      25: getfield      #40                 // Field refEntityInsentient:Lio/lumine/mythic/bukkit/utils/reflection/Reflector;
      28: aload_2
      29: ldc           #33                 // String bT
      31: invokevirtual #224                // Method io/lumine/mythic/bukkit/utils/reflection/Reflector.get:(Ljava/lang/Object;Ljava/lang/String;)Ljava/lang/Object;
      34: checkcast     #42                 // class net/minecraft/world/entity/ai/goal/PathfinderGoalSelector
      37: astore_3
      38: aload_0
      39: getfield      #48                 // Field refGoalSelector:Lio/lumine/mythic/bukkit/utils/reflection/Reflector;
      42: aload_3
      43: ldc           #44                 // String b
      45: invokevirtual #224                // Method io/lumine/mythic/bukkit/utils/reflection/Reflector.get:(Ljava/lang/Object;Ljava/lang/String;)Ljava/lang/Object;
      48: checkcast     #114                // class java/util/Map
      51: invokeinterface #227,  1          // InterfaceMethod java/util/Map.clear:()V
      56: aload_0
      57: getfield      #48                 // Field refGoalSelector:Lio/lumine/mythic/bukkit/utils/reflection/Reflector;
      60: aload_3
      61: ldc           #46                 // String c
      63: invokevirtual #224                // Method io/lumine/mythic/bukkit/utils/reflection/Reflector.get:(Ljava/lang/Object;Ljava/lang/String;)Ljava/lang/Object;
      66: checkcast     #229                // class java/util/Set
      69: invokeinterface #230,  1          // InterfaceMethod java/util/Set.clear:()V
      74: return

  public void clearPathfinderTargets(io.lumine.mythic.api.adapters.AbstractEntity);
    Code:
       0: aload_1
       1: invokeinterface #176,  1          // InterfaceMethod io/lumine/mythic/api/adapters/AbstractEntity.isLiving:()Z
       6: ifne          10
       9: return
      10: aload_1
      11: invokestatic  #182                // Method io/lumine/mythic/bukkit/BukkitAdapter.adapt:(Lio/lumine/mythic/api/adapters/AbstractEntity;)Lorg/bukkit/entity/Entity;
      14: checkcast     #184                // class org/bukkit/craftbukkit/v1_20_R1/entity/CraftLivingEntity
      17: invokevirtual #188                // Method org/bukkit/craftbukkit/v1_20_R1/entity/CraftLivingEntity.getHandle:()Lnet/minecraft/world/entity/EntityLiving;
      20: checkcast     #27                 // class net/minecraft/world/entity/EntityInsentient
      23: astore_2
      24: aload_0
      25: getfield      #40                 // Field refEntityInsentient:Lio/lumine/mythic/bukkit/utils/reflection/Reflector;
      28: aload_2
      29: ldc           #35                 // String bU
      31: invokevirtual #224                // Method io/lumine/mythic/bukkit/utils/reflection/Reflector.get:(Ljava/lang/Object;Ljava/lang/String;)Ljava/lang/Object;
      34: checkcast     #42                 // class net/minecraft/world/entity/ai/goal/PathfinderGoalSelector
      37: astore_3
      38: aload_0
      39: getfield      #48                 // Field refGoalSelector:Lio/lumine/mythic/bukkit/utils/reflection/Reflector;
      42: aload_3
      43: ldc           #44                 // String b
      45: invokevirtual #224                // Method io/lumine/mythic/bukkit/utils/reflection/Reflector.get:(Ljava/lang/Object;Ljava/lang/String;)Ljava/lang/Object;
      48: checkcast     #114                // class java/util/Map
      51: invokeinterface #227,  1          // InterfaceMethod java/util/Map.clear:()V
      56: aload_0
      57: getfield      #48                 // Field refGoalSelector:Lio/lumine/mythic/bukkit/utils/reflection/Reflector;
      60: aload_3
      61: ldc           #46                 // String c
      63: invokevirtual #224                // Method io/lumine/mythic/bukkit/utils/reflection/Reflector.get:(Ljava/lang/Object;Ljava/lang/String;)Ljava/lang/Object;
      66: checkcast     #229                // class java/util/Set
      69: invokeinterface #230,  1          // InterfaceMethod java/util/Set.clear:()V
      74: return

  public void addPathfindersGoal(int, io.lumine.mythic.api.adapters.AbstractEntity, net.minecraft.world.entity.ai.goal.PathfinderGoal, java.util.function.Predicate<io.lumine.mythic.api.adapters.AbstractEntity>);
    Code:
       0: aload         4
       2: ifnull        17
       5: aload         4
       7: aload_2
       8: invokeinterface #242,  2          // InterfaceMethod java/util/function/Predicate.test:(Ljava/lang/Object;)Z
      13: ifne          17
      16: return
      17: aload_2
      18: invokestatic  #182                // Method io/lumine/mythic/bukkit/BukkitAdapter.adapt:(Lio/lumine/mythic/api/adapters/AbstractEntity;)Lorg/bukkit/entity/Entity;
      21: checkcast     #184                // class org/bukkit/craftbukkit/v1_20_R1/entity/CraftLivingEntity
      24: invokevirtual #188                // Method org/bukkit/craftbukkit/v1_20_R1/entity/CraftLivingEntity.getHandle:()Lnet/minecraft/world/entity/EntityLiving;
      27: checkcast     #27                 // class net/minecraft/world/entity/EntityInsentient
      30: astore        5
      32: aload_0
      33: getfield      #40                 // Field refEntityInsentient:Lio/lumine/mythic/bukkit/utils/reflection/Reflector;
      36: aload         5
      38: ldc           #244                // String
      40: invokevirtual #224                // Method io/lumine/mythic/bukkit/utils/reflection/Reflector.get:(Ljava/lang/Object;Ljava/lang/String;)Ljava/lang/Object;
      43: checkcast     #42                 // class net/minecraft/world/entity/ai/goal/PathfinderGoalSelector
      46: astore        6
      48: aload         6
      50: iload_1
      51: aload_3
      52: invokevirtual #247                // Method net/minecraft/world/entity/ai/goal/PathfinderGoalSelector.a:(ILnet/minecraft/world/entity/ai/goal/PathfinderGoal;)V
      55: goto          70
      58: astore        7
      60: ldc           #251                // String Failed to apply pathfinder goal
      62: invokestatic  #254                // Method io/lumine/mythic/core/logging/MythicLogger.error:(Ljava/lang/String;)V
      65: aload         7
      67: invokestatic  #258                // Method io/lumine/mythic/core/logging/MythicLogger.handleMinorError:(Ljava/lang/Throwable;)V
      70: return
    Exception table:
       from    to  target type
          48    55    58   Class java/lang/Exception

  public void addPathfinderGoals(org.bukkit.entity.LivingEntity, java.util.List<java.lang.String>);
    Code:
       0: aload_1
       1: checkcast     #184                // class org/bukkit/craftbukkit/v1_20_R1/entity/CraftLivingEntity
       4: invokevirtual #188                // Method org/bukkit/craftbukkit/v1_20_R1/entity/CraftLivingEntity.getHandle:()Lnet/minecraft/world/entity/EntityLiving;
       7: checkcast     #27                 // class net/minecraft/world/entity/EntityInsentient
      10: astore_3
      11: aload_0
      12: getfield      #40                 // Field refEntityInsentient:Lio/lumine/mythic/bukkit/utils/reflection/Reflector;
      15: aload_3
      16: ldc           #33                 // String bT
      18: invokevirtual #224                // Method io/lumine/mythic/bukkit/utils/reflection/Reflector.get:(Ljava/lang/Object;Ljava/lang/String;)Ljava/lang/Object;
      21: checkcast     #42                 // class net/minecraft/world/entity/ai/goal/PathfinderGoalSelector
      24: astore        4
      26: iconst_0
      27: istore        5
      29: iconst_0
      30: istore        6
      32: aload_2
      33: invokeinterface #274,  1          // InterfaceMethod java/util/List.iterator:()Ljava/util/Iterator;
      38: astore        13
      40: aload         13
      42: invokeinterface #85,  1           // InterfaceMethod java/util/Iterator.hasNext:()Z
      47: ifeq          619
      50: aload         13
      52: invokeinterface #89,  1           // InterfaceMethod java/util/Iterator.next:()Ljava/lang/Object;
      57: checkcast     #29                 // class java/lang/String
      60: astore        14
      62: iinc          5, 1
      65: aload         14
      67: ldc_w         #278                // String
      70: invokevirtual #282                // Method java/lang/String.split:(Ljava/lang/String;)[Ljava/lang/String;
      73: astore        12
      75: aload         12
      77: iconst_0
      78: aaload
      79: ldc_w         #284                // String [0-9]*
      82: invokevirtual #288                // Method java/lang/String.matches:(Ljava/lang/String;)Z
      85: ifeq          144
      88: aload         12
      90: iconst_0
      91: aaload
      92: invokestatic  #294                // Method java/lang/Integer.parseInt:(Ljava/lang/String;)I
      95: istore        6
      97: aload         12
      99: iconst_1
     100: aaload
     101: astore        8
     103: aload         12
     105: arraylength
     106: iconst_2
     107: if_icmple     119
     110: aload         12
     112: iconst_2
     113: aaload
     114: astore        9
     116: goto          122
     119: aconst_null
     120: astore        9
     122: aload         12
     124: arraylength
     125: iconst_3
     126: if_icmple     138
     129: aload         12
     131: iconst_3
     132: aaload
     133: astore        10
     135: goto          192
     138: aconst_null
     139: astore        10
     141: goto          192
     144: iload         5
     146: istore        6
     148: aload         12
     150: iconst_0
     151: aaload
     152: astore        8
     154: aload         12
     156: arraylength
     157: iconst_1
     158: if_icmple     170
     161: aload         12
     163: iconst_1
     164: aaload
     165: astore        9
     167: goto          173
     170: aconst_null
     171: astore        9
     173: aload         12
     175: arraylength
     176: iconst_2
     177: if_icmple     189
     180: aload         12
     182: iconst_2
     183: aaload
     184: astore        10
     186: goto          192
     189: aconst_null
     190: astore        10
     192: new           #296                // class io/lumine/mythic/core/config/MythicLineConfigImpl
     195: dup
     196: aload         8
     198: invokestatic  #300                // Method io/lumine/mythic/core/config/MythicLineConfigImpl.unparseBlock:(Ljava/lang/String;)Ljava/lang/String;
     201: invokespecial #302                // Method io/lumine/mythic/core/config/MythicLineConfigImpl."<init>":(Ljava/lang/String;)V
     204: astore        11
     206: aload         11
     208: invokeinterface #307,  1          // InterfaceMethod io/lumine/mythic/api/config/MythicLineConfig.getKey:()Ljava/lang/String;
     213: astore        8
     215: aload_0
     216: getfield      #53                 // Field AI_GOALS:Ljava/util/Map;
     219: aload         8
     221: invokevirtual #112                // Method java/lang/String.toUpperCase:()Ljava/lang/String;
     224: invokeinterface #310,  2          // InterfaceMethod java/util/Map.containsKey:(Ljava/lang/Object;)Z
     229: ifeq          472
     232: aload_0
     233: getfield      #53                 // Field AI_GOALS:Ljava/util/Map;
     236: aload         8
     238: invokevirtual #112                // Method java/lang/String.toUpperCase:()Ljava/lang/String;
     241: invokeinterface #313,  2          // InterfaceMethod java/util/Map.get:(Ljava/lang/Object;)Ljava/lang/Object;
     246: checkcast     #91                 // class java/lang/Class
     249: astore        15
     251: ldc_w         #315                // class io/lumine/mythic/core/mobs/ai/Pathfinder
     254: aload         15
     256: invokevirtual #109                // Method java/lang/Class.isAssignableFrom:(Ljava/lang/Class;)Z
     259: ifeq          331
     262: aload         15
     264: iconst_3
     265: anewarray     #91                 // class java/lang/Class
     268: dup
     269: iconst_0
     270: ldc           #173                // class io/lumine/mythic/api/adapters/AbstractEntity
     272: aastore
     273: dup
     274: iconst_1
     275: ldc           #29                 // class java/lang/String
     277: aastore
     278: dup
     279: iconst_2
     280: ldc_w         #304                // class io/lumine/mythic/api/config/MythicLineConfig
     283: aastore
     284: invokevirtual #319                // Method java/lang/Class.getConstructor:([Ljava/lang/Class;)Ljava/lang/reflect/Constructor;
     287: iconst_3
     288: anewarray     #4                  // class java/lang/Object
     291: dup
     292: iconst_0
     293: aload_1
     294: invokestatic  #322                // Method io/lumine/mythic/bukkit/BukkitAdapter.adapt:(Lorg/bukkit/entity/Entity;)Lio/lumine/mythic/api/adapters/AbstractEntity;
     297: aastore
     298: dup
     299: iconst_1
     300: aload         14
     302: aastore
     303: dup
     304: iconst_2
     305: aload         11
     307: aastore
     308: invokevirtual #328                // Method java/lang/reflect/Constructor.newInstance:([Ljava/lang/Object;)Ljava/lang/Object;
     311: checkcast     #315                // class io/lumine/mythic/core/mobs/ai/Pathfinder
     314: astore        16
     316: aload         4
     318: iload         6
     320: aload         16
     322: invokestatic  #334                // Method io/lumine/mythic/core/volatilecode/v1_20_R1/ai/CustomAIAdapter.create:(Lio/lumine/mythic/core/mobs/ai/Pathfinder;)Lnet/minecraft/world/entity/ai/goal/PathfinderGoal;
     325: invokevirtual #247                // Method net/minecraft/world/entity/ai/goal/PathfinderGoalSelector.a:(ILnet/minecraft/world/entity/ai/goal/PathfinderGoal;)V
     328: goto          447
     331: aload         15
     333: iconst_3
     334: anewarray     #91                 // class java/lang/Class
     337: dup
     338: iconst_0
     339: ldc           #173                // class io/lumine/mythic/api/adapters/AbstractEntity
     341: aastore
     342: dup
     343: iconst_1
     344: ldc           #29                 // class java/lang/String
     346: aastore
     347: dup
     348: iconst_2
     349: ldc_w         #304                // class io/lumine/mythic/api/config/MythicLineConfig
     352: aastore
     353: invokevirtual #319                // Method java/lang/Class.getConstructor:([Ljava/lang/Class;)Ljava/lang/reflect/Constructor;
     356: iconst_3
     357: anewarray     #4                  // class java/lang/Object
     360: dup
     361: iconst_0
     362: aload_1
     363: invokestatic  #322                // Method io/lumine/mythic/bukkit/BukkitAdapter.adapt:(Lorg/bukkit/entity/Entity;)Lio/lumine/mythic/api/adapters/AbstractEntity;
     366: aastore
     367: dup
     368: iconst_1
     369: aload         14
     371: aastore
     372: dup
     373: iconst_2
     374: aload         11
     376: aastore
     377: invokevirtual #328                // Method java/lang/reflect/Constructor.newInstance:([Ljava/lang/Object;)Ljava/lang/Object;
     380: checkcast     #336                // class io/lumine/mythic/core/mobs/ai/WrappedPathfinder
     383: astore        16
     385: aload         16
     387: checkcast     #338                // class io/lumine/mythic/core/volatilecode/v1_20_R1/ai/PathfinderHolder
     390: astore        17
     392: aload         17
     394: invokeinterface #341,  1          // InterfaceMethod io/lumine/mythic/core/volatilecode/v1_20_R1/ai/PathfinderHolder.isValid:()Z
     399: ifeq          423
     402: aload         17
     404: invokeinterface #344,  1          // InterfaceMethod io/lumine/mythic/core/volatilecode/v1_20_R1/ai/PathfinderHolder.create:()Lnet/minecraft/world/entity/ai/goal/PathfinderGoal;
     409: astore        18
     411: aload         4
     413: iload         6
     415: aload         18
     417: invokevirtual #247                // Method net/minecraft/world/entity/ai/goal/PathfinderGoalSelector.a:(ILnet/minecraft/world/entity/ai/goal/PathfinderGoal;)V
     420: goto          447
     423: ldc_w         #346                // String AI pathfinder {0} is not valid for mob type {1}
     426: iconst_2
     427: anewarray     #4                  // class java/lang/Object
     430: dup
     431: iconst_0
     432: aload         8
     434: aastore
     435: dup
     436: iconst_1
     437: aload_1
     438: invokeinterface #350,  1          // InterfaceMethod org/bukkit/entity/LivingEntity.getType:()Lorg/bukkit/entity/EntityType;
     443: aastore
     444: invokestatic  #131                // Method io/lumine/mythic/core/logging/MythicLogger.error:(Ljava/lang/String;[Ljava/lang/Object;)V
     447: goto          40
     450: astore        16
     452: ldc_w         #354                // String Failed to construct AI pathfinder {0}
     455: iconst_1
     456: anewarray     #4                  // class java/lang/Object
     459: dup
     460: iconst_0
     461: aload         8
     463: aastore
     464: invokestatic  #131                // Method io/lumine/mythic/core/logging/MythicLogger.error:(Ljava/lang/String;[Ljava/lang/Object;)V
     467: aload         16
     469: invokevirtual #357                // Method java/lang/Throwable.printStackTrace:()V
     472: aload         8
     474: invokevirtual #360                // Method java/lang/String.toLowerCase:()Ljava/lang/String;
     477: astore        15
     479: iconst_m1
     480: istore        16
     482: aload         15
     484: invokevirtual #364                // Method java/lang/String.hashCode:()I
     487: lookupswitch  { // 2

              94746189: 529

             108404047: 512
               default: 543
          }
     512: aload         15
     514: ldc_w         #366                // String reset
     517: invokevirtual #369                // Method java/lang/String.equals:(Ljava/lang/Object;)Z
     520: ifeq          543
     523: iconst_0
     524: istore        16
     526: goto          543
     529: aload         15
     531: ldc_w         #370                // String clear
     534: invokevirtual #369                // Method java/lang/String.equals:(Ljava/lang/Object;)Z
     537: ifeq          543
     540: iconst_1
     541: istore        16
     543: iload         16
     545: lookupswitch  { // 2

                     0: 572

                     1: 572
               default: 613
          }
     572: aload_0
     573: getfield      #48                 // Field refGoalSelector:Lio/lumine/mythic/bukkit/utils/reflection/Reflector;
     576: aload         4
     578: ldc           #44                 // String b
     580: invokevirtual #224                // Method io/lumine/mythic/bukkit/utils/reflection/Reflector.get:(Ljava/lang/Object;Ljava/lang/String;)Ljava/lang/Object;
     583: checkcast     #114                // class java/util/Map
     586: invokeinterface #227,  1          // InterfaceMethod java/util/Map.clear:()V
     591: aload_0
     592: getfield      #48                 // Field refGoalSelector:Lio/lumine/mythic/bukkit/utils/reflection/Reflector;
     595: aload         4
     597: ldc           #46                 // String c
     599: invokevirtual #224                // Method io/lumine/mythic/bukkit/utils/reflection/Reflector.get:(Ljava/lang/Object;Ljava/lang/String;)Ljava/lang/Object;
     602: checkcast     #229                // class java/util/Set
     605: invokeinterface #230,  1          // InterfaceMethod java/util/Set.clear:()V
     610: goto          616
     613: goto          40
     616: goto          40
     619: goto          633
     622: astore_3
     623: ldc_w         #372                // String An error occurred while adding an AIGoalSelector, enable debugging for a stack trace.
     626: invokestatic  #254                // Method io/lumine/mythic/core/logging/MythicLogger.error:(Ljava/lang/String;)V
     629: aload_3
     630: invokestatic  #258                // Method io/lumine/mythic/core/logging/MythicLogger.handleMinorError:(Ljava/lang/Throwable;)V
     633: return
    Exception table:
       from    to  target type
         251   447   450   Class java/lang/Exception
         251   447   450   Class java/lang/Error
           0   619   622   Class java/lang/Exception

  public void addTargetGoals(org.bukkit.entity.LivingEntity, java.util.List<java.lang.String>);
    Code:
       0: aload_1
       1: checkcast     #184                // class org/bukkit/craftbukkit/v1_20_R1/entity/CraftLivingEntity
       4: invokevirtual #188                // Method org/bukkit/craftbukkit/v1_20_R1/entity/CraftLivingEntity.getHandle:()Lnet/minecraft/world/entity/EntityLiving;
       7: checkcast     #27                 // class net/minecraft/world/entity/EntityInsentient
      10: astore_3
      11: aload_0
      12: getfield      #40                 // Field refEntityInsentient:Lio/lumine/mythic/bukkit/utils/reflection/Reflector;
      15: aload_3
      16: ldc           #35                 // String bU
      18: invokevirtual #224                // Method io/lumine/mythic/bukkit/utils/reflection/Reflector.get:(Ljava/lang/Object;Ljava/lang/String;)Ljava/lang/Object;
      21: checkcast     #42                 // class net/minecraft/world/entity/ai/goal/PathfinderGoalSelector
      24: astore        4
      26: iconst_0
      27: istore        5
      29: iconst_0
      30: istore        6
      32: aload_2
      33: invokeinterface #274,  1          // InterfaceMethod java/util/List.iterator:()Ljava/util/Iterator;
      38: astore        13
      40: aload         13
      42: invokeinterface #85,  1           // InterfaceMethod java/util/Iterator.hasNext:()Z
      47: ifeq          588
      50: aload         13
      52: invokeinterface #89,  1           // InterfaceMethod java/util/Iterator.next:()Ljava/lang/Object;
      57: checkcast     #29                 // class java/lang/String
      60: astore        14
      62: iinc          5, 1
      65: aload         14
      67: ldc_w         #278                // String
      70: invokevirtual #282                // Method java/lang/String.split:(Ljava/lang/String;)[Ljava/lang/String;
      73: astore        12
      75: aload         12
      77: iconst_0
      78: aaload
      79: ldc_w         #284                // String [0-9]*
      82: invokevirtual #288                // Method java/lang/String.matches:(Ljava/lang/String;)Z
      85: ifeq          126
      88: aload         12
      90: iconst_0
      91: aaload
      92: invokestatic  #294                // Method java/lang/Integer.parseInt:(Ljava/lang/String;)I
      95: istore        6
      97: aload         12
      99: iconst_1
     100: aaload
     101: astore        8
     103: aload         12
     105: arraylength
     106: iconst_2
     107: if_icmple     119
     110: aload         12
     112: iconst_2
     113: aaload
     114: astore        9
     116: goto          156
     119: ldc           #244                // String
     121: astore        9
     123: goto          156
     126: iload         5
     128: istore        6
     130: aload         12
     132: iconst_0
     133: aaload
     134: astore        8
     136: aload         12
     138: arraylength
     139: iconst_1
     140: if_icmple     152
     143: aload         12
     145: iconst_1
     146: aaload
     147: astore        9
     149: goto          156
     152: ldc           #244                // String
     154: astore        9
     156: new           #296                // class io/lumine/mythic/core/config/MythicLineConfigImpl
     159: dup
     160: aload         8
     162: invokespecial #302                // Method io/lumine/mythic/core/config/MythicLineConfigImpl."<init>":(Ljava/lang/String;)V
     165: astore        11
     167: aload         11
     169: invokeinterface #307,  1          // InterfaceMethod io/lumine/mythic/api/config/MythicLineConfig.getKey:()Ljava/lang/String;
     174: astore        8
     176: aload_0
     177: getfield      #55                 // Field AI_TARGETS:Ljava/util/Map;
     180: aload         8
     182: invokevirtual #112                // Method java/lang/String.toUpperCase:()Ljava/lang/String;
     185: invokeinterface #310,  2          // InterfaceMethod java/util/Map.containsKey:(Ljava/lang/Object;)Z
     190: ifeq          433
     193: aload_0
     194: getfield      #55                 // Field AI_TARGETS:Ljava/util/Map;
     197: aload         8
     199: invokevirtual #112                // Method java/lang/String.toUpperCase:()Ljava/lang/String;
     202: invokeinterface #313,  2          // InterfaceMethod java/util/Map.get:(Ljava/lang/Object;)Ljava/lang/Object;
     207: checkcast     #91                 // class java/lang/Class
     210: astore        15
     212: aload         15
     214: ldc_w         #315                // class io/lumine/mythic/core/mobs/ai/Pathfinder
     217: invokevirtual #109                // Method java/lang/Class.isAssignableFrom:(Ljava/lang/Class;)Z
     220: ifeq          292
     223: aload         15
     225: iconst_3
     226: anewarray     #91                 // class java/lang/Class
     229: dup
     230: iconst_0
     231: ldc           #173                // class io/lumine/mythic/api/adapters/AbstractEntity
     233: aastore
     234: dup
     235: iconst_1
     236: ldc           #29                 // class java/lang/String
     238: aastore
     239: dup
     240: iconst_2
     241: ldc_w         #304                // class io/lumine/mythic/api/config/MythicLineConfig
     244: aastore
     245: invokevirtual #319                // Method java/lang/Class.getConstructor:([Ljava/lang/Class;)Ljava/lang/reflect/Constructor;
     248: iconst_3
     249: anewarray     #4                  // class java/lang/Object
     252: dup
     253: iconst_0
     254: aload_1
     255: invokestatic  #322                // Method io/lumine/mythic/bukkit/BukkitAdapter.adapt:(Lorg/bukkit/entity/Entity;)Lio/lumine/mythic/api/adapters/AbstractEntity;
     258: aastore
     259: dup
     260: iconst_1
     261: aload         14
     263: aastore
     264: dup
     265: iconst_2
     266: aload         11
     268: aastore
     269: invokevirtual #328                // Method java/lang/reflect/Constructor.newInstance:([Ljava/lang/Object;)Ljava/lang/Object;
     272: checkcast     #315                // class io/lumine/mythic/core/mobs/ai/Pathfinder
     275: astore        16
     277: aload         4
     279: iload         6
     281: aload         16
     283: invokestatic  #334                // Method io/lumine/mythic/core/volatilecode/v1_20_R1/ai/CustomAIAdapter.create:(Lio/lumine/mythic/core/mobs/ai/Pathfinder;)Lnet/minecraft/world/entity/ai/goal/PathfinderGoal;
     286: invokevirtual #247                // Method net/minecraft/world/entity/ai/goal/PathfinderGoalSelector.a:(ILnet/minecraft/world/entity/ai/goal/PathfinderGoal;)V
     289: goto          408
     292: aload         15
     294: iconst_3
     295: anewarray     #91                 // class java/lang/Class
     298: dup
     299: iconst_0
     300: ldc           #173                // class io/lumine/mythic/api/adapters/AbstractEntity
     302: aastore
     303: dup
     304: iconst_1
     305: ldc           #29                 // class java/lang/String
     307: aastore
     308: dup
     309: iconst_2
     310: ldc_w         #304                // class io/lumine/mythic/api/config/MythicLineConfig
     313: aastore
     314: invokevirtual #319                // Method java/lang/Class.getConstructor:([Ljava/lang/Class;)Ljava/lang/reflect/Constructor;
     317: iconst_3
     318: anewarray     #4                  // class java/lang/Object
     321: dup
     322: iconst_0
     323: aload_1
     324: invokestatic  #322                // Method io/lumine/mythic/bukkit/BukkitAdapter.adapt:(Lorg/bukkit/entity/Entity;)Lio/lumine/mythic/api/adapters/AbstractEntity;
     327: aastore
     328: dup
     329: iconst_1
     330: aload         14
     332: aastore
     333: dup
     334: iconst_2
     335: aload         11
     337: aastore
     338: invokevirtual #328                // Method java/lang/reflect/Constructor.newInstance:([Ljava/lang/Object;)Ljava/lang/Object;
     341: checkcast     #336                // class io/lumine/mythic/core/mobs/ai/WrappedPathfinder
     344: astore        16
     346: aload         16
     348: checkcast     #338                // class io/lumine/mythic/core/volatilecode/v1_20_R1/ai/PathfinderHolder
     351: astore        17
     353: aload         17
     355: invokeinterface #341,  1          // InterfaceMethod io/lumine/mythic/core/volatilecode/v1_20_R1/ai/PathfinderHolder.isValid:()Z
     360: ifeq          384
     363: aload         17
     365: invokeinterface #344,  1          // InterfaceMethod io/lumine/mythic/core/volatilecode/v1_20_R1/ai/PathfinderHolder.create:()Lnet/minecraft/world/entity/ai/goal/PathfinderGoal;
     370: astore        18
     372: aload         4
     374: iload         6
     376: aload         18
     378: invokevirtual #247                // Method net/minecraft/world/entity/ai/goal/PathfinderGoalSelector.a:(ILnet/minecraft/world/entity/ai/goal/PathfinderGoal;)V
     381: goto          408
     384: ldc_w         #346                // String AI pathfinder {0} is not valid for mob type {1}
     387: iconst_2
     388: anewarray     #4                  // class java/lang/Object
     391: dup
     392: iconst_0
     393: aload         8
     395: aastore
     396: dup
     397: iconst_1
     398: aload_1
     399: invokeinterface #350,  1          // InterfaceMethod org/bukkit/entity/LivingEntity.getType:()Lorg/bukkit/entity/EntityType;
     404: aastore
     405: invokestatic  #131                // Method io/lumine/mythic/core/logging/MythicLogger.error:(Ljava/lang/String;[Ljava/lang/Object;)V
     408: goto          40
     411: astore        16
     413: ldc_w         #354                // String Failed to construct AI pathfinder {0}
     416: iconst_1
     417: anewarray     #4                  // class java/lang/Object
     420: dup
     421: iconst_0
     422: aload         8
     424: aastore
     425: invokestatic  #131                // Method io/lumine/mythic/core/logging/MythicLogger.error:(Ljava/lang/String;[Ljava/lang/Object;)V
     428: aload         16
     430: invokevirtual #357                // Method java/lang/Throwable.printStackTrace:()V
     433: aload         8
     435: invokevirtual #360                // Method java/lang/String.toLowerCase:()Ljava/lang/String;
     438: astore        15
     440: iconst_m1
     441: istore        16
     443: aload         15
     445: invokevirtual #364                // Method java/lang/String.hashCode:()I
     448: lookupswitch  { // 2

              94746189: 493

             108404047: 476
               default: 507
          }
     476: aload         15
     478: ldc_w         #366                // String reset
     481: invokevirtual #369                // Method java/lang/String.equals:(Ljava/lang/Object;)Z
     484: ifeq          507
     487: iconst_0
     488: istore        16
     490: goto          507
     493: aload         15
     495: ldc_w         #370                // String clear
     498: invokevirtual #369                // Method java/lang/String.equals:(Ljava/lang/Object;)Z
     501: ifeq          507
     504: iconst_1
     505: istore        16
     507: iload         16
     509: lookupswitch  { // 2

                     0: 536

                     1: 536
               default: 582
          }
     536: aload_0
     537: getfield      #48                 // Field refGoalSelector:Lio/lumine/mythic/bukkit/utils/reflection/Reflector;
     540: aload         4
     542: ldc           #44                 // String b
     544: invokevirtual #224                // Method io/lumine/mythic/bukkit/utils/reflection/Reflector.get:(Ljava/lang/Object;Ljava/lang/String;)Ljava/lang/Object;
     547: checkcast     #114                // class java/util/Map
     550: invokeinterface #227,  1          // InterfaceMethod java/util/Map.clear:()V
     555: aload_0
     556: getfield      #48                 // Field refGoalSelector:Lio/lumine/mythic/bukkit/utils/reflection/Reflector;
     559: aload         4
     561: ldc           #46                 // String c
     563: invokevirtual #224                // Method io/lumine/mythic/bukkit/utils/reflection/Reflector.get:(Ljava/lang/Object;Ljava/lang/String;)Ljava/lang/Object;
     566: checkcast     #229                // class java/util/Set
     569: invokeinterface #230,  1          // InterfaceMethod java/util/Set.clear:()V
     574: aload_3
     575: aconst_null
     576: invokevirtual #396                // Method net/minecraft/world/entity/EntityInsentient.h:(Lnet/minecraft/world/entity/EntityLiving;)V
     579: goto          585
     582: goto          40
     585: goto          40
     588: goto          602
     591: astore_3
     592: ldc_w         #398                // String An error has occurred, enable debugging for a stack trace.
     595: invokestatic  #254                // Method io/lumine/mythic/core/logging/MythicLogger.error:(Ljava/lang/String;)V
     598: aload_3
     599: invokestatic  #258                // Method io/lumine/mythic/core/logging/MythicLogger.handleMinorError:(Ljava/lang/Throwable;)V
     602: return
    Exception table:
       from    to  target type
         212   408   411   Class java/lang/Exception
         212   408   411   Class java/lang/Error
           0   588   591   Class java/lang/Exception

  public void setNavigationController(io.lumine.mythic.api.adapters.AbstractEntity, java.lang.String);
    Code:
       0: aload_1
       1: invokeinterface #176,  1          // InterfaceMethod io/lumine/mythic/api/adapters/AbstractEntity.isLiving:()Z
       6: ifne          10
       9: return
      10: aload_1
      11: invokeinterface #404,  1          // InterfaceMethod io/lumine/mythic/api/adapters/AbstractEntity.getBukkitEntity:()Lorg/bukkit/entity/Entity;
      16: checkcast     #184                // class org/bukkit/craftbukkit/v1_20_R1/entity/CraftLivingEntity
      19: invokevirtual #188                // Method org/bukkit/craftbukkit/v1_20_R1/entity/CraftLivingEntity.getHandle:()Lnet/minecraft/world/entity/EntityLiving;
      22: checkcast     #27                 // class net/minecraft/world/entity/EntityInsentient
      25: astore_3
      26: new           #406                // class io/lumine/mythic/core/volatilecode/v1_20_R1/ai/navigators/StayInLavaNavigator
      29: dup
      30: aload_3
      31: aload_3
      32: invokevirtual #410                // Method net/minecraft/world/entity/EntityInsentient.dI:()Lnet/minecraft/world/level/World;
      35: invokespecial #413                // Method io/lumine/mythic/core/volatilecode/v1_20_R1/ai/navigators/StayInLavaNavigator."<init>":(Lnet/minecraft/world/entity/EntityInsentient;Lnet/minecraft/world/level/World;)V
      38: astore        4
      40: aload_0
      41: getfield      #40                 // Field refEntityInsentient:Lio/lumine/mythic/bukkit/utils/reflection/Reflector;
      44: aload_3
      45: ldc           #31                 // String bS
      47: aload         4
      49: invokevirtual #417                // Method io/lumine/mythic/bukkit/utils/reflection/Reflector.set:(Ljava/lang/Object;Ljava/lang/String;Ljava/lang/Object;)V
      52: goto          74
      55: astore_3
      56: ldc_w         #419                // String Invalid Navigation Controller supplied: {0}
      59: iconst_1
      60: anewarray     #4                  // class java/lang/Object
      63: dup
      64: iconst_0
      65: aload_2
      66: aastore
      67: invokestatic  #131                // Method io/lumine/mythic/core/logging/MythicLogger.error:(Ljava/lang/String;[Ljava/lang/Object;)V
      70: aload_3
      71: invokevirtual #357                // Method java/lang/Throwable.printStackTrace:()V
      74: return
    Exception table:
       from    to  target type
          10    52    55   Class java/lang/Exception
          10    52    55   Class java/lang/Error

  public void setPathfindingMalus(io.lumine.mythic.api.adapters.AbstractEntity, java.lang.String, float);
    Code:
       0: aload_1
       1: invokeinterface #176,  1          // InterfaceMethod io/lumine/mythic/api/adapters/AbstractEntity.isLiving:()Z
       6: ifne          10
       9: return
      10: aload_1
      11: invokeinterface #404,  1          // InterfaceMethod io/lumine/mythic/api/adapters/AbstractEntity.getBukkitEntity:()Lorg/bukkit/entity/Entity;
      16: checkcast     #184                // class org/bukkit/craftbukkit/v1_20_R1/entity/CraftLivingEntity
      19: invokevirtual #188                // Method org/bukkit/craftbukkit/v1_20_R1/entity/CraftLivingEntity.getHandle:()Lnet/minecraft/world/entity/EntityLiving;
      22: checkcast     #27                 // class net/minecraft/world/entity/EntityInsentient
      25: astore        4
      27: aload_2
      28: invokevirtual #112                // Method java/lang/String.toUpperCase:()Ljava/lang/String;
      31: invokestatic  #431                // Method net/minecraft/world/level/pathfinder/PathType.valueOf:(Ljava/lang/String;)Lnet/minecraft/world/level/pathfinder/PathType;
      34: astore        5
      36: aload         4
      38: aload         5
      40: fload_3
      41: invokevirtual #434                // Method net/minecraft/world/entity/EntityInsentient.a:(Lnet/minecraft/world/level/pathfinder/PathType;F)V
      44: goto          68
      47: astore        4
      49: ldc_w         #436                // String Invalid PathfindingMalus BlockPathTypes supplied: {0}
      52: iconst_1
      53: anewarray     #4                  // class java/lang/Object
      56: dup
      57: iconst_0
      58: aload_2
      59: aastore
      60: invokestatic  #131                // Method io/lumine/mythic/core/logging/MythicLogger.error:(Ljava/lang/String;[Ljava/lang/Object;)V
      63: aload         4
      65: invokevirtual #357                // Method java/lang/Throwable.printStackTrace:()V
      68: return
    Exception table:
       from    to  target type
          10    44    47   Class java/lang/Exception
          10    44    47   Class java/lang/Error
}
