Compiled from "MobListeners.java"
public class io.lumine.mythic.bukkit.listeners.MobListeners extends io.lumine.mythic.bukkit.utils.plugin.ReloadableModule<io.lumine.mythic.bukkit.MythicBukkit> implements org.bukkit.event.Listener {
  public io.lumine.mythic.bukkit.listeners.MobListeners(io.lumine.mythic.bukkit.MythicBukkit);
    Code:
       0: aload_0
       1: aload_1
       2: invokespecial #38                 // Method io/lumine/mythic/bukkit/utils/plugin/ReloadableModule."<init>":(Lio/lumine/mythic/bukkit/utils/plugin/LuminePlugin;)V
       5: return

  public void load(io.lumine.mythic.bukkit.MythicBukkit);
    Code:
       0: ldc           #45                 // class org/bukkit/event/player/PlayerArmorStandManipulateEvent
       2: invokestatic  #51                 // Method io/lumine/mythic/bukkit/utils/Events.subscribe:(Ljava/lang/Class;)Lio/lumine/mythic/bukkit/utils/events/functional/single/SingleSubscriptionBuilder;
       5: aload_0
       6: invokedynamic #70,  0             // InvokeDynamic #0:accept:(Lio/lumine/mythic/bukkit/listeners/MobListeners;)Ljava/util/function/Consumer;
      11: invokeinterface #76,  2           // InterfaceMethod io/lumine/mythic/bukkit/utils/events/functional/single/SingleSubscriptionBuilder.handler:(Ljava/util/function/Consumer;)Lio/lumine/mythic/bukkit/utils/events/SingleSubscription;
      16: aload_0
      17: invokeinterface #82,  2           // InterfaceMethod io/lumine/mythic/bukkit/utils/events/SingleSubscription.bindWith:(Lio/lumine/mythic/bukkit/utils/terminable/TerminableConsumer;)V
      22: getstatic     #88                 // Field io/lumine/mythic/bukkit/utils/version/MinecraftVersions.v1_19_4:Lio/lumine/mythic/bukkit/utils/version/MinecraftVersion;
      25: invokestatic  #94                 // Method io/lumine/mythic/bukkit/utils/version/ServerVersion.isAfterOrEq:(Lio/lumine/mythic/bukkit/utils/version/MinecraftVersion;)Z
      28: ifeq          63
      31: ldc           #96                 // class org/bukkit/event/entity/EntityDamageByEntityEvent
      33: invokestatic  #51                 // Method io/lumine/mythic/bukkit/utils/Events.subscribe:(Ljava/lang/Class;)Lio/lumine/mythic/bukkit/utils/events/functional/single/SingleSubscriptionBuilder;
      36: invokedynamic #108,  0            // InvokeDynamic #1:test:()Ljava/util/function/Predicate;
      41: invokeinterface #112,  2          // InterfaceMethod io/lumine/mythic/bukkit/utils/events/functional/single/SingleSubscriptionBuilder.filter:(Ljava/util/function/Predicate;)Lio/lumine/mythic/bukkit/utils/events/functional/single/SingleSubscriptionBuilder;
      46: aload_0
      47: invokedynamic #119,  0            // InvokeDynamic #2:accept:(Lio/lumine/mythic/bukkit/listeners/MobListeners;)Ljava/util/function/Consumer;
      52: invokeinterface #76,  2           // InterfaceMethod io/lumine/mythic/bukkit/utils/events/functional/single/SingleSubscriptionBuilder.handler:(Ljava/util/function/Consumer;)Lio/lumine/mythic/bukkit/utils/events/SingleSubscription;
      57: aload_0
      58: invokeinterface #82,  2           // InterfaceMethod io/lumine/mythic/bukkit/utils/events/SingleSubscription.bindWith:(Lio/lumine/mythic/bukkit/utils/terminable/TerminableConsumer;)V
      63: ldc           #121                // class org/bukkit/event/entity/SlimeSplitEvent
      65: getstatic     #127                // Field org/bukkit/event/EventPriority.HIGH:Lorg/bukkit/event/EventPriority;
      68: invokestatic  #130                // Method io/lumine/mythic/bukkit/utils/Events.subscribe:(Ljava/lang/Class;Lorg/bukkit/event/EventPriority;)Lio/lumine/mythic/bukkit/utils/events/functional/single/SingleSubscriptionBuilder;
      71: invokedynamic #139,  0            // InvokeDynamic #3:accept:()Ljava/util/function/Consumer;
      76: invokeinterface #76,  2           // InterfaceMethod io/lumine/mythic/bukkit/utils/events/functional/single/SingleSubscriptionBuilder.handler:(Ljava/util/function/Consumer;)Lio/lumine/mythic/bukkit/utils/events/SingleSubscription;
      81: aload_0
      82: invokeinterface #82,  2           // InterfaceMethod io/lumine/mythic/bukkit/utils/events/SingleSubscription.bindWith:(Lio/lumine/mythic/bukkit/utils/terminable/TerminableConsumer;)V
      87: ldc           #27                 // class org/bukkit/event/entity/CreatureSpawnEvent
      89: getstatic     #142                // Field org/bukkit/event/EventPriority.HIGHEST:Lorg/bukkit/event/EventPriority;
      92: invokestatic  #130                // Method io/lumine/mythic/bukkit/utils/Events.subscribe:(Ljava/lang/Class;Lorg/bukkit/event/EventPriority;)Lio/lumine/mythic/bukkit/utils/events/functional/single/SingleSubscriptionBuilder;
      95: aload_0
      96: aload_1
      97: invokedynamic #152,  0            // InvokeDynamic #4:accept:(Lio/lumine/mythic/bukkit/listeners/MobListeners;Lio/lumine/mythic/bukkit/MythicBukkit;)Ljava/util/function/Consumer;
     102: invokeinterface #76,  2           // InterfaceMethod io/lumine/mythic/bukkit/utils/events/functional/single/SingleSubscriptionBuilder.handler:(Ljava/util/function/Consumer;)Lio/lumine/mythic/bukkit/utils/events/SingleSubscription;
     107: aload_0
     108: invokeinterface #82,  2           // InterfaceMethod io/lumine/mythic/bukkit/utils/events/SingleSubscription.bindWith:(Lio/lumine/mythic/bukkit/utils/terminable/TerminableConsumer;)V
     113: ldc           #154                // class org/bukkit/event/world/EntitiesLoadEvent
     115: getstatic     #142                // Field org/bukkit/event/EventPriority.HIGHEST:Lorg/bukkit/event/EventPriority;
     118: invokestatic  #130                // Method io/lumine/mythic/bukkit/utils/Events.subscribe:(Ljava/lang/Class;Lorg/bukkit/event/EventPriority;)Lio/lumine/mythic/bukkit/utils/events/functional/single/SingleSubscriptionBuilder;
     121: aload_0
     122: invokedynamic #161,  0            // InvokeDynamic #5:accept:(Lio/lumine/mythic/bukkit/listeners/MobListeners;)Ljava/util/function/Consumer;
     127: invokeinterface #76,  2           // InterfaceMethod io/lumine/mythic/bukkit/utils/events/functional/single/SingleSubscriptionBuilder.handler:(Ljava/util/function/Consumer;)Lio/lumine/mythic/bukkit/utils/events/SingleSubscription;
     132: aload_0
     133: invokeinterface #82,  2           // InterfaceMethod io/lumine/mythic/bukkit/utils/events/SingleSubscription.bindWith:(Lio/lumine/mythic/bukkit/utils/terminable/TerminableConsumer;)V
     138: ldc           #163                // class org/bukkit/event/world/ChunkLoadEvent
     140: getstatic     #142                // Field org/bukkit/event/EventPriority.HIGHEST:Lorg/bukkit/event/EventPriority;
     143: invokestatic  #130                // Method io/lumine/mythic/bukkit/utils/Events.subscribe:(Ljava/lang/Class;Lorg/bukkit/event/EventPriority;)Lio/lumine/mythic/bukkit/utils/events/functional/single/SingleSubscriptionBuilder;
     146: invokedynamic #170,  0            // InvokeDynamic #6:test:()Ljava/util/function/Predicate;
     151: invokeinterface #112,  2          // InterfaceMethod io/lumine/mythic/bukkit/utils/events/functional/single/SingleSubscriptionBuilder.filter:(Ljava/util/function/Predicate;)Lio/lumine/mythic/bukkit/utils/events/functional/single/SingleSubscriptionBuilder;
     156: aload_0
     157: invokedynamic #177,  0            // InvokeDynamic #7:accept:(Lio/lumine/mythic/bukkit/listeners/MobListeners;)Ljava/util/function/Consumer;
     162: invokeinterface #76,  2           // InterfaceMethod io/lumine/mythic/bukkit/utils/events/functional/single/SingleSubscriptionBuilder.handler:(Ljava/util/function/Consumer;)Lio/lumine/mythic/bukkit/utils/events/SingleSubscription;
     167: aload_0
     168: invokeinterface #82,  2           // InterfaceMethod io/lumine/mythic/bukkit/utils/events/SingleSubscription.bindWith:(Lio/lumine/mythic/bukkit/utils/terminable/TerminableConsumer;)V
     173: ldc           #179                // class org/bukkit/event/entity/EntityTransformEvent
     175: invokestatic  #51                 // Method io/lumine/mythic/bukkit/utils/Events.subscribe:(Ljava/lang/Class;)Lio/lumine/mythic/bukkit/utils/events/functional/single/SingleSubscriptionBuilder;
     178: aload_0
     179: invokedynamic #186,  0            // InvokeDynamic #8:accept:(Lio/lumine/mythic/bukkit/listeners/MobListeners;)Ljava/util/function/Consumer;
     184: invokeinterface #76,  2           // InterfaceMethod io/lumine/mythic/bukkit/utils/events/functional/single/SingleSubscriptionBuilder.handler:(Ljava/util/function/Consumer;)Lio/lumine/mythic/bukkit/utils/events/SingleSubscription;
     189: aload_0
     190: invokeinterface #82,  2           // InterfaceMethod io/lumine/mythic/bukkit/utils/events/SingleSubscription.bindWith:(Lio/lumine/mythic/bukkit/utils/terminable/TerminableConsumer;)V
     195: ldc           #27                 // class org/bukkit/event/entity/CreatureSpawnEvent
     197: getstatic     #142                // Field org/bukkit/event/EventPriority.HIGHEST:Lorg/bukkit/event/EventPriority;
     200: invokestatic  #130                // Method io/lumine/mythic/bukkit/utils/Events.subscribe:(Ljava/lang/Class;Lorg/bukkit/event/EventPriority;)Lio/lumine/mythic/bukkit/utils/events/functional/single/SingleSubscriptionBuilder;
     203: invokedynamic #193,  0            // InvokeDynamic #9:test:()Ljava/util/function/Predicate;
     208: invokeinterface #112,  2          // InterfaceMethod io/lumine/mythic/bukkit/utils/events/functional/single/SingleSubscriptionBuilder.filter:(Ljava/util/function/Predicate;)Lio/lumine/mythic/bukkit/utils/events/functional/single/SingleSubscriptionBuilder;
     213: invokedynamic #198,  0            // InvokeDynamic #10:test:()Ljava/util/function/Predicate;
     218: invokeinterface #112,  2          // InterfaceMethod io/lumine/mythic/bukkit/utils/events/functional/single/SingleSubscriptionBuilder.filter:(Ljava/util/function/Predicate;)Lio/lumine/mythic/bukkit/utils/events/functional/single/SingleSubscriptionBuilder;
     223: aload_0
     224: invokedynamic #203,  0            // InvokeDynamic #11:accept:(Lio/lumine/mythic/bukkit/listeners/MobListeners;)Ljava/util/function/Consumer;
     229: invokeinterface #76,  2           // InterfaceMethod io/lumine/mythic/bukkit/utils/events/functional/single/SingleSubscriptionBuilder.handler:(Ljava/util/function/Consumer;)Lio/lumine/mythic/bukkit/utils/events/SingleSubscription;
     234: aload_0
     235: invokeinterface #82,  2           // InterfaceMethod io/lumine/mythic/bukkit/utils/events/SingleSubscription.bindWith:(Lio/lumine/mythic/bukkit/utils/terminable/TerminableConsumer;)V
     240: ldc           #205                // class org/bukkit/event/entity/EntityCombustEvent
     242: getstatic     #142                // Field org/bukkit/event/EventPriority.HIGHEST:Lorg/bukkit/event/EventPriority;
     245: invokestatic  #130                // Method io/lumine/mythic/bukkit/utils/Events.subscribe:(Ljava/lang/Class;Lorg/bukkit/event/EventPriority;)Lio/lumine/mythic/bukkit/utils/events/functional/single/SingleSubscriptionBuilder;
     248: invokedynamic #212,  0            // InvokeDynamic #12:test:()Ljava/util/function/Predicate;
     253: invokeinterface #112,  2          // InterfaceMethod io/lumine/mythic/bukkit/utils/events/functional/single/SingleSubscriptionBuilder.filter:(Ljava/util/function/Predicate;)Lio/lumine/mythic/bukkit/utils/events/functional/single/SingleSubscriptionBuilder;
     258: invokedynamic #217,  0            // InvokeDynamic #13:test:()Ljava/util/function/Predicate;
     263: invokeinterface #112,  2          // InterfaceMethod io/lumine/mythic/bukkit/utils/events/functional/single/SingleSubscriptionBuilder.filter:(Ljava/util/function/Predicate;)Lio/lumine/mythic/bukkit/utils/events/functional/single/SingleSubscriptionBuilder;
     268: invokedynamic #222,  0            // InvokeDynamic #14:test:()Ljava/util/function/Predicate;
     273: invokeinterface #112,  2          // InterfaceMethod io/lumine/mythic/bukkit/utils/events/functional/single/SingleSubscriptionBuilder.filter:(Ljava/util/function/Predicate;)Lio/lumine/mythic/bukkit/utils/events/functional/single/SingleSubscriptionBuilder;
     278: aload_0
     279: invokedynamic #229,  0            // InvokeDynamic #15:accept:(Lio/lumine/mythic/bukkit/listeners/MobListeners;)Ljava/util/function/Consumer;
     284: invokeinterface #76,  2           // InterfaceMethod io/lumine/mythic/bukkit/utils/events/functional/single/SingleSubscriptionBuilder.handler:(Ljava/util/function/Consumer;)Lio/lumine/mythic/bukkit/utils/events/SingleSubscription;
     289: aload_0
     290: invokeinterface #82,  2           // InterfaceMethod io/lumine/mythic/bukkit/utils/events/SingleSubscription.bindWith:(Lio/lumine/mythic/bukkit/utils/terminable/TerminableConsumer;)V
     295: ldc           #231                // class org/bukkit/event/entity/EntityDamageEvent
     297: getstatic     #234                // Field org/bukkit/event/EventPriority.LOWEST:Lorg/bukkit/event/EventPriority;
     300: invokestatic  #130                // Method io/lumine/mythic/bukkit/utils/Events.subscribe:(Ljava/lang/Class;Lorg/bukkit/event/EventPriority;)Lio/lumine/mythic/bukkit/utils/events/functional/single/SingleSubscriptionBuilder;
     303: invokedynamic #241,  0            // InvokeDynamic #16:test:()Ljava/util/function/Predicate;
     308: invokeinterface #112,  2          // InterfaceMethod io/lumine/mythic/bukkit/utils/events/functional/single/SingleSubscriptionBuilder.filter:(Ljava/util/function/Predicate;)Lio/lumine/mythic/bukkit/utils/events/functional/single/SingleSubscriptionBuilder;
     313: aload_0
     314: invokedynamic #248,  0            // InvokeDynamic #17:accept:(Lio/lumine/mythic/bukkit/listeners/MobListeners;)Ljava/util/function/Consumer;
     319: invokeinterface #76,  2           // InterfaceMethod io/lumine/mythic/bukkit/utils/events/functional/single/SingleSubscriptionBuilder.handler:(Ljava/util/function/Consumer;)Lio/lumine/mythic/bukkit/utils/events/SingleSubscription;
     324: aload_0
     325: invokeinterface #82,  2           // InterfaceMethod io/lumine/mythic/bukkit/utils/events/SingleSubscription.bindWith:(Lio/lumine/mythic/bukkit/utils/terminable/TerminableConsumer;)V
     330: ldc           #96                 // class org/bukkit/event/entity/EntityDamageByEntityEvent
     332: getstatic     #234                // Field org/bukkit/event/EventPriority.LOWEST:Lorg/bukkit/event/EventPriority;
     335: invokestatic  #130                // Method io/lumine/mythic/bukkit/utils/Events.subscribe:(Ljava/lang/Class;Lorg/bukkit/event/EventPriority;)Lio/lumine/mythic/bukkit/utils/events/functional/single/SingleSubscriptionBuilder;
     338: invokedynamic #253,  0            // InvokeDynamic #18:test:()Ljava/util/function/Predicate;
     343: invokeinterface #112,  2          // InterfaceMethod io/lumine/mythic/bukkit/utils/events/functional/single/SingleSubscriptionBuilder.filter:(Ljava/util/function/Predicate;)Lio/lumine/mythic/bukkit/utils/events/functional/single/SingleSubscriptionBuilder;
     348: aload_0
     349: invokedynamic #254,  0            // InvokeDynamic #19:accept:(Lio/lumine/mythic/bukkit/listeners/MobListeners;)Ljava/util/function/Consumer;
     354: invokeinterface #76,  2           // InterfaceMethod io/lumine/mythic/bukkit/utils/events/functional/single/SingleSubscriptionBuilder.handler:(Ljava/util/function/Consumer;)Lio/lumine/mythic/bukkit/utils/events/SingleSubscription;
     359: aload_0
     360: invokeinterface #82,  2           // InterfaceMethod io/lumine/mythic/bukkit/utils/events/SingleSubscription.bindWith:(Lio/lumine/mythic/bukkit/utils/terminable/TerminableConsumer;)V
     365: ldc_w         #256                // class org/bukkit/event/entity/EntityDamageByBlockEvent
     368: getstatic     #234                // Field org/bukkit/event/EventPriority.LOWEST:Lorg/bukkit/event/EventPriority;
     371: invokestatic  #130                // Method io/lumine/mythic/bukkit/utils/Events.subscribe:(Ljava/lang/Class;Lorg/bukkit/event/EventPriority;)Lio/lumine/mythic/bukkit/utils/events/functional/single/SingleSubscriptionBuilder;
     374: invokedynamic #263,  0            // InvokeDynamic #20:test:()Ljava/util/function/Predicate;
     379: invokeinterface #112,  2          // InterfaceMethod io/lumine/mythic/bukkit/utils/events/functional/single/SingleSubscriptionBuilder.filter:(Ljava/util/function/Predicate;)Lio/lumine/mythic/bukkit/utils/events/functional/single/SingleSubscriptionBuilder;
     384: aload_0
     385: invokedynamic #266,  0            // InvokeDynamic #21:accept:(Lio/lumine/mythic/bukkit/listeners/MobListeners;)Ljava/util/function/Consumer;
     390: invokeinterface #76,  2           // InterfaceMethod io/lumine/mythic/bukkit/utils/events/functional/single/SingleSubscriptionBuilder.handler:(Ljava/util/function/Consumer;)Lio/lumine/mythic/bukkit/utils/events/SingleSubscription;
     395: aload_0
     396: invokeinterface #82,  2           // InterfaceMethod io/lumine/mythic/bukkit/utils/events/SingleSubscription.bindWith:(Lio/lumine/mythic/bukkit/utils/terminable/TerminableConsumer;)V
     401: ldc_w         #268                // class org/bukkit/event/player/PlayerInteractEntityEvent
     404: getstatic     #127                // Field org/bukkit/event/EventPriority.HIGH:Lorg/bukkit/event/EventPriority;
     407: invokestatic  #130                // Method io/lumine/mythic/bukkit/utils/Events.subscribe:(Ljava/lang/Class;Lorg/bukkit/event/EventPriority;)Lio/lumine/mythic/bukkit/utils/events/functional/single/SingleSubscriptionBuilder;
     410: aload_0
     411: invokedynamic #275,  0            // InvokeDynamic #22:accept:(Lio/lumine/mythic/bukkit/listeners/MobListeners;)Ljava/util/function/Consumer;
     416: invokeinterface #76,  2           // InterfaceMethod io/lumine/mythic/bukkit/utils/events/functional/single/SingleSubscriptionBuilder.handler:(Ljava/util/function/Consumer;)Lio/lumine/mythic/bukkit/utils/events/SingleSubscription;
     421: aload_0
     422: invokeinterface #82,  2           // InterfaceMethod io/lumine/mythic/bukkit/utils/events/SingleSubscription.bindWith:(Lio/lumine/mythic/bukkit/utils/terminable/TerminableConsumer;)V
     427: ldc_w         #277                // class org/bukkit/event/entity/PlayerLeashEntityEvent
     430: getstatic     #127                // Field org/bukkit/event/EventPriority.HIGH:Lorg/bukkit/event/EventPriority;
     433: invokestatic  #130                // Method io/lumine/mythic/bukkit/utils/Events.subscribe:(Ljava/lang/Class;Lorg/bukkit/event/EventPriority;)Lio/lumine/mythic/bukkit/utils/events/functional/single/SingleSubscriptionBuilder;
     436: aload_0
     437: invokedynamic #284,  0            // InvokeDynamic #23:accept:(Lio/lumine/mythic/bukkit/listeners/MobListeners;)Ljava/util/function/Consumer;
     442: invokeinterface #76,  2           // InterfaceMethod io/lumine/mythic/bukkit/utils/events/functional/single/SingleSubscriptionBuilder.handler:(Ljava/util/function/Consumer;)Lio/lumine/mythic/bukkit/utils/events/SingleSubscription;
     447: aload_0
     448: invokeinterface #82,  2           // InterfaceMethod io/lumine/mythic/bukkit/utils/events/SingleSubscription.bindWith:(Lio/lumine/mythic/bukkit/utils/terminable/TerminableConsumer;)V
     453: ldc_w         #286                // class org/bukkit/event/entity/EntityChangeBlockEvent
     456: getstatic     #127                // Field org/bukkit/event/EventPriority.HIGH:Lorg/bukkit/event/EventPriority;
     459: invokestatic  #130                // Method io/lumine/mythic/bukkit/utils/Events.subscribe:(Ljava/lang/Class;Lorg/bukkit/event/EventPriority;)Lio/lumine/mythic/bukkit/utils/events/functional/single/SingleSubscriptionBuilder;
     462: aload_0
     463: invokedynamic #293,  0            // InvokeDynamic #24:accept:(Lio/lumine/mythic/bukkit/listeners/MobListeners;)Ljava/util/function/Consumer;
     468: invokeinterface #76,  2           // InterfaceMethod io/lumine/mythic/bukkit/utils/events/functional/single/SingleSubscriptionBuilder.handler:(Ljava/util/function/Consumer;)Lio/lumine/mythic/bukkit/utils/events/SingleSubscription;
     473: aload_0
     474: invokeinterface #82,  2           // InterfaceMethod io/lumine/mythic/bukkit/utils/events/SingleSubscription.bindWith:(Lio/lumine/mythic/bukkit/utils/terminable/TerminableConsumer;)V
     479: ldc_w         #295                // class org/bukkit/event/block/EntityBlockFormEvent
     482: getstatic     #127                // Field org/bukkit/event/EventPriority.HIGH:Lorg/bukkit/event/EventPriority;
     485: invokestatic  #130                // Method io/lumine/mythic/bukkit/utils/Events.subscribe:(Ljava/lang/Class;Lorg/bukkit/event/EventPriority;)Lio/lumine/mythic/bukkit/utils/events/functional/single/SingleSubscriptionBuilder;
     488: aload_0
     489: invokedynamic #302,  0            // InvokeDynamic #25:accept:(Lio/lumine/mythic/bukkit/listeners/MobListeners;)Ljava/util/function/Consumer;
     494: invokeinterface #76,  2           // InterfaceMethod io/lumine/mythic/bukkit/utils/events/functional/single/SingleSubscriptionBuilder.handler:(Ljava/util/function/Consumer;)Lio/lumine/mythic/bukkit/utils/events/SingleSubscription;
     499: aload_0
     500: invokeinterface #82,  2           // InterfaceMethod io/lumine/mythic/bukkit/utils/events/SingleSubscription.bindWith:(Lio/lumine/mythic/bukkit/utils/terminable/TerminableConsumer;)V
     505: ldc_w         #304                // class org/bukkit/event/entity/EntityTeleportEvent
     508: getstatic     #127                // Field org/bukkit/event/EventPriority.HIGH:Lorg/bukkit/event/EventPriority;
     511: invokestatic  #130                // Method io/lumine/mythic/bukkit/utils/Events.subscribe:(Ljava/lang/Class;Lorg/bukkit/event/EventPriority;)Lio/lumine/mythic/bukkit/utils/events/functional/single/SingleSubscriptionBuilder;
     514: aload_0
     515: invokedynamic #311,  0            // InvokeDynamic #26:accept:(Lio/lumine/mythic/bukkit/listeners/MobListeners;)Ljava/util/function/Consumer;
     520: invokeinterface #76,  2           // InterfaceMethod io/lumine/mythic/bukkit/utils/events/functional/single/SingleSubscriptionBuilder.handler:(Ljava/util/function/Consumer;)Lio/lumine/mythic/bukkit/utils/events/SingleSubscription;
     525: aload_0
     526: invokeinterface #82,  2           // InterfaceMethod io/lumine/mythic/bukkit/utils/events/SingleSubscription.bindWith:(Lio/lumine/mythic/bukkit/utils/terminable/TerminableConsumer;)V
     531: ldc_w         #313                // class io/lumine/mythic/bukkit/events/MythicDamageEvent
     534: getstatic     #127                // Field org/bukkit/event/EventPriority.HIGH:Lorg/bukkit/event/EventPriority;
     537: invokestatic  #130                // Method io/lumine/mythic/bukkit/utils/Events.subscribe:(Ljava/lang/Class;Lorg/bukkit/event/EventPriority;)Lio/lumine/mythic/bukkit/utils/events/functional/single/SingleSubscriptionBuilder;
     540: invokedynamic #320,  0            // InvokeDynamic #27:test:()Ljava/util/function/Predicate;
     545: invokeinterface #112,  2          // InterfaceMethod io/lumine/mythic/bukkit/utils/events/functional/single/SingleSubscriptionBuilder.filter:(Ljava/util/function/Predicate;)Lio/lumine/mythic/bukkit/utils/events/functional/single/SingleSubscriptionBuilder;
     550: aload_0
     551: invokedynamic #327,  0            // InvokeDynamic #28:accept:(Lio/lumine/mythic/bukkit/listeners/MobListeners;)Ljava/util/function/Consumer;
     556: invokeinterface #76,  2           // InterfaceMethod io/lumine/mythic/bukkit/utils/events/functional/single/SingleSubscriptionBuilder.handler:(Ljava/util/function/Consumer;)Lio/lumine/mythic/bukkit/utils/events/SingleSubscription;
     561: aload_0
     562: invokeinterface #82,  2           // InterfaceMethod io/lumine/mythic/bukkit/utils/events/SingleSubscription.bindWith:(Lio/lumine/mythic/bukkit/utils/terminable/TerminableConsumer;)V
     567: invokestatic  #331                // Method io/lumine/mythic/bukkit/utils/version/ServerVersion.isPaper:()Z
     570: ifeq          604
     573: ldc_w         #333                // class io/papermc/paper/event/entity/EntityKnockbackEvent
     576: getstatic     #127                // Field org/bukkit/event/EventPriority.HIGH:Lorg/bukkit/event/EventPriority;
     579: invokestatic  #130                // Method io/lumine/mythic/bukkit/utils/Events.subscribe:(Ljava/lang/Class;Lorg/bukkit/event/EventPriority;)Lio/lumine/mythic/bukkit/utils/events/functional/single/SingleSubscriptionBuilder;
     582: invokeinterface #337,  1          // InterfaceMethod io/lumine/mythic/bukkit/utils/events/functional/single/SingleSubscriptionBuilder.handleSubclasses:()Lio/lumine/mythic/bukkit/utils/events/functional/single/SingleSubscriptionBuilder;
     587: aload_0
     588: invokedynamic #344,  0            // InvokeDynamic #29:accept:(Lio/lumine/mythic/bukkit/listeners/MobListeners;)Ljava/util/function/Consumer;
     593: invokeinterface #76,  2           // InterfaceMethod io/lumine/mythic/bukkit/utils/events/functional/single/SingleSubscriptionBuilder.handler:(Ljava/util/function/Consumer;)Lio/lumine/mythic/bukkit/utils/events/SingleSubscription;
     598: aload_0
     599: invokeinterface #82,  2           // InterfaceMethod io/lumine/mythic/bukkit/utils/events/SingleSubscription.bindWith:(Lio/lumine/mythic/bukkit/utils/terminable/TerminableConsumer;)V
     604: return

  public void unload();
    Code:
       0: return

  public void damagePassthroughEvent(org.bukkit.event.entity.EntityDamageEvent);
    Code:
       0: aload_1
       1: invokevirtual #350                // Method org/bukkit/event/entity/EntityDamageEvent.getEntity:()Lorg/bukkit/entity/Entity;
       4: astore_3
       5: aload_3
       6: instanceof    #352                // class org/bukkit/entity/Damageable
       9: ifeq          20
      12: aload_3
      13: checkcast     #352                // class org/bukkit/entity/Damageable
      16: astore_2
      17: goto          21
      20: return
      21: aload_0
      22: invokevirtual #356                // Method getPlugin:()Lio/lumine/mythic/bukkit/utils/plugin/LuminePlugin;
      25: checkcast     #358                // class io/lumine/mythic/bukkit/MythicBukkit
      28: invokevirtual #362                // Method io/lumine/mythic/bukkit/MythicBukkit.getMobManager:()Lio/lumine/mythic/core/mobs/MobExecutor;
      31: aload_2
      32: invokeinterface #366,  1          // InterfaceMethod org/bukkit/entity/Damageable.getUniqueId:()Ljava/util/UUID;
      37: invokevirtual #372                // Method io/lumine/mythic/core/mobs/MobExecutor.isActiveMob:(Ljava/util/UUID;)Z
      40: ifne          44
      43: return
      44: aload_0
      45: invokevirtual #356                // Method getPlugin:()Lio/lumine/mythic/bukkit/utils/plugin/LuminePlugin;
      48: checkcast     #358                // class io/lumine/mythic/bukkit/MythicBukkit
      51: invokevirtual #362                // Method io/lumine/mythic/bukkit/MythicBukkit.getMobManager:()Lio/lumine/mythic/core/mobs/MobExecutor;
      54: aload_2
      55: invokevirtual #376                // Method io/lumine/mythic/core/mobs/MobExecutor.getMythicMobInstance:(Lorg/bukkit/entity/Entity;)Lio/lumine/mythic/core/mobs/ActiveMob;
      58: astore_3
      59: aload_3
      60: invokevirtual #380                // Method io/lumine/mythic/core/mobs/ActiveMob.getType:()Lio/lumine/mythic/api/mobs/MythicMob;
      63: invokeinterface #386,  1          // InterfaceMethod io/lumine/mythic/api/mobs/MythicMob.getPassthroughDamage:()Ljava/lang/Boolean;
      68: invokevirtual #391                // Method java/lang/Boolean.booleanValue:()Z
      71: ifeq          84
      74: aload_3
      75: invokevirtual #395                // Method io/lumine/mythic/core/mobs/ActiveMob.getParent:()Lio/lumine/mythic/bukkit/utils/serialize/Optl;
      78: invokevirtual #400                // Method io/lumine/mythic/bukkit/utils/serialize/Optl.isPresent:()Z
      81: ifne          85
      84: return
      85: getstatic     #404                // Field io/lumine/mythic/core/logging/MythicLogger$DebugLevel.TRIGGER:Lio/lumine/mythic/core/logging/MythicLogger$DebugLevel;
      88: ldc_w         #406                // String Passing damage to parent
      91: iconst_0
      92: anewarray     #408                // class java/lang/Object
      95: invokestatic  #412                // Method io/lumine/mythic/core/logging/MythicLogger.debug:(Lio/lumine/mythic/core/logging/MythicLogger$DebugLevel;Ljava/lang/String;[Ljava/lang/Object;)V
      98: aload_1
      99: iconst_1
     100: invokevirtual #416                // Method org/bukkit/event/entity/EntityDamageEvent.setCancelled:(Z)V
     103: aload_3
     104: invokevirtual #395                // Method io/lumine/mythic/core/mobs/ActiveMob.getParent:()Lio/lumine/mythic/bukkit/utils/serialize/Optl;
     107: invokevirtual #420                // Method io/lumine/mythic/bukkit/utils/serialize/Optl.get:()Ljava/lang/Object;
     110: checkcast     #422                // class io/lumine/mythic/api/adapters/AbstractEntity
     113: invokeinterface #425,  1          // InterfaceMethod io/lumine/mythic/api/adapters/AbstractEntity.getBukkitEntity:()Lorg/bukkit/entity/Entity;
     118: checkcast     #427                // class org/bukkit/entity/LivingEntity
     121: astore        4
     123: aload_1
     124: invokevirtual #431                // Method org/bukkit/event/entity/EntityDamageEvent.getFinalDamage:()D
     127: dstore        5
     129: aload_1
     130: instanceof    #96                 // class org/bukkit/event/entity/EntityDamageByEntityEvent
     133: ifeq          249
     136: aload_1
     137: checkcast     #96                 // class org/bukkit/event/entity/EntityDamageByEntityEvent
     140: astore        7
     142: aload         7
     144: invokevirtual #434                // Method org/bukkit/event/entity/EntityDamageByEntityEvent.getDamager:()Lorg/bukkit/entity/Entity;
     147: astore        8
     149: aload         8
     151: instanceof    #436                // class org/bukkit/entity/Projectile
     154: ifeq          235
     157: aload         8
     159: checkcast     #436                // class org/bukkit/entity/Projectile
     162: astore        9
     164: getstatic     #439                // Field io/lumine/mythic/core/logging/MythicLogger$DebugLevel.INFO:Lio/lumine/mythic/core/logging/MythicLogger$DebugLevel;
     167: ldc_w         #441                // String Damage passed from arrow
     170: iconst_0
     171: anewarray     #408                // class java/lang/Object
     174: invokestatic  #412                // Method io/lumine/mythic/core/logging/MythicLogger.debug:(Lio/lumine/mythic/core/logging/MythicLogger$DebugLevel;Ljava/lang/String;[Ljava/lang/Object;)V
     177: aload         9
     179: invokeinterface #445,  1          // InterfaceMethod org/bukkit/entity/Projectile.getShooter:()Lorg/bukkit/projectiles/ProjectileSource;
     184: astore        10
     186: aload         10
     188: instanceof    #427                // class org/bukkit/entity/LivingEntity
     191: ifeq          216
     194: aload         4
     196: dload         5
     198: aload         9
     200: invokeinterface #445,  1          // InterfaceMethod org/bukkit/entity/Projectile.getShooter:()Lorg/bukkit/projectiles/ProjectileSource;
     205: checkcast     #447                // class org/bukkit/entity/Entity
     208: invokeinterface #451,  4          // InterfaceMethod org/bukkit/entity/LivingEntity.damage:(DLorg/bukkit/entity/Entity;)V
     213: goto          225
     216: aload         4
     218: dload         5
     220: invokeinterface #456,  3          // InterfaceMethod org/bukkit/entity/LivingEntity.damage:(D)V
     225: aload         8
     227: invokeinterface #459,  1          // InterfaceMethod org/bukkit/entity/Entity.remove:()V
     232: goto          246
     235: aload         4
     237: dload         5
     239: aload         8
     241: invokeinterface #451,  4          // InterfaceMethod org/bukkit/entity/LivingEntity.damage:(DLorg/bukkit/entity/Entity;)V
     246: goto          267
     249: aload         4
     251: dload         5
     253: aload_1
     254: invokevirtual #463                // Method org/bukkit/event/entity/EntityDamageEvent.getDamageSource:()Lorg/bukkit/damage/DamageSource;
     257: invokeinterface #468,  1          // InterfaceMethod org/bukkit/damage/DamageSource.getCausingEntity:()Lorg/bukkit/entity/Entity;
     262: invokeinterface #451,  4          // InterfaceMethod org/bukkit/entity/LivingEntity.damage:(DLorg/bukkit/entity/Entity;)V
     267: return

  public void onTagEntity(org.bukkit.event.player.PlayerInteractEntityEvent);
    Code:
       0: aload_1
       1: invokevirtual #488                // Method org/bukkit/event/player/PlayerInteractEntityEvent.getRightClicked:()Lorg/bukkit/entity/Entity;
       4: instanceof    #427                // class org/bukkit/entity/LivingEntity
       7: ifne          11
      10: return
      11: aload_1
      12: invokevirtual #488                // Method org/bukkit/event/player/PlayerInteractEntityEvent.getRightClicked:()Lorg/bukkit/entity/Entity;
      15: checkcast     #427                // class org/bukkit/entity/LivingEntity
      18: astore_2
      19: aload_0
      20: invokevirtual #356                // Method getPlugin:()Lio/lumine/mythic/bukkit/utils/plugin/LuminePlugin;
      23: checkcast     #358                // class io/lumine/mythic/bukkit/MythicBukkit
      26: invokevirtual #362                // Method io/lumine/mythic/bukkit/MythicBukkit.getMobManager:()Lio/lumine/mythic/core/mobs/MobExecutor;
      29: aload_2
      30: invokeinterface #489,  1          // InterfaceMethod org/bukkit/entity/LivingEntity.getUniqueId:()Ljava/util/UUID;
      35: invokevirtual #372                // Method io/lumine/mythic/core/mobs/MobExecutor.isActiveMob:(Ljava/util/UUID;)Z
      38: ifne          42
      41: return
      42: aload_1
      43: invokevirtual #493                // Method org/bukkit/event/player/PlayerInteractEntityEvent.getPlayer:()Lorg/bukkit/entity/Player;
      46: invokeinterface #499,  1          // InterfaceMethod org/bukkit/entity/Player.getEquipment:()Lorg/bukkit/inventory/EntityEquipment;
      51: astore_3
      52: aload_3
      53: ifnull        72
      56: aload_3
      57: invokeinterface #505,  1          // InterfaceMethod org/bukkit/inventory/EntityEquipment.getItemInMainHand:()Lorg/bukkit/inventory/ItemStack;
      62: invokevirtual #510                // Method org/bukkit/inventory/ItemStack.getType:()Lorg/bukkit/Material;
      65: getstatic     #516                // Field org/bukkit/Material.NAME_TAG:Lorg/bukkit/Material;
      68: if_acmpeq     72
      71: return
      72: aload_0
      73: invokevirtual #356                // Method getPlugin:()Lio/lumine/mythic/bukkit/utils/plugin/LuminePlugin;
      76: checkcast     #358                // class io/lumine/mythic/bukkit/MythicBukkit
      79: invokevirtual #362                // Method io/lumine/mythic/bukkit/MythicBukkit.getMobManager:()Lio/lumine/mythic/core/mobs/MobExecutor;
      82: aload_2
      83: invokevirtual #376                // Method io/lumine/mythic/core/mobs/MobExecutor.getMythicMobInstance:(Lorg/bukkit/entity/Entity;)Lio/lumine/mythic/core/mobs/ActiveMob;
      86: astore        4
      88: aload         4
      90: invokevirtual #380                // Method io/lumine/mythic/core/mobs/ActiveMob.getType:()Lio/lumine/mythic/api/mobs/MythicMob;
      93: invokeinterface #519,  1          // InterfaceMethod io/lumine/mythic/api/mobs/MythicMob.getPreventRename:()Ljava/lang/Boolean;
      98: invokevirtual #391                // Method java/lang/Boolean.booleanValue:()Z
     101: ifeq          124
     104: aload_1
     105: iconst_1
     106: invokevirtual #520                // Method org/bukkit/event/player/PlayerInteractEntityEvent.setCancelled:(Z)V
     109: aload_1
     110: invokevirtual #493                // Method org/bukkit/event/player/PlayerInteractEntityEvent.getPlayer:()Lorg/bukkit/entity/Player;
     113: ldc_w         #522                // String ?cThis mob can\'t be renamed
     116: invokeinterface #526,  2          // InterfaceMethod org/bukkit/entity/Player.sendMessage:(Ljava/lang/String;)V
     121: goto          151
     124: aload         4
     126: getstatic     #532                // Field io/lumine/mythic/core/mobs/DespawnMode.PERSISTENT:Lio/lumine/mythic/core/mobs/DespawnMode;
     129: invokevirtual #536                // Method io/lumine/mythic/core/mobs/ActiveMob.setDespawnMode:(Lio/lumine/mythic/core/mobs/DespawnMode;)V
     132: aload_2
     133: invokestatic  #542                // Method io/lumine/mythic/bukkit/utils/Schedulers.of:(Lorg/bukkit/entity/Entity;)Lio/lumine/mythic/bukkit/utils/tasks/TaskScheduler;
     136: aload         4
     138: aload_2
     139: invokedynamic #552,  0            // InvokeDynamic #30:run:(Lio/lumine/mythic/core/mobs/ActiveMob;Lorg/bukkit/entity/LivingEntity;)Ljava/lang/Runnable;
     144: lconst_1
     145: invokeinterface #558,  4          // InterfaceMethod io/lumine/mythic/bukkit/utils/tasks/TaskScheduler.runLater:(Ljava/lang/Runnable;J)Lio/lumine/mythic/bukkit/utils/promise/Promise;
     150: pop
     151: return

  public void onLeashEntity(org.bukkit.event.entity.PlayerLeashEntityEvent);
    Code:
       0: aload_1
       1: invokevirtual #564                // Method org/bukkit/event/entity/PlayerLeashEntityEvent.getEntity:()Lorg/bukkit/entity/Entity;
       4: instanceof    #427                // class org/bukkit/entity/LivingEntity
       7: ifne          11
      10: return
      11: aload_1
      12: invokevirtual #564                // Method org/bukkit/event/entity/PlayerLeashEntityEvent.getEntity:()Lorg/bukkit/entity/Entity;
      15: checkcast     #427                // class org/bukkit/entity/LivingEntity
      18: astore_2
      19: aload_0
      20: invokevirtual #356                // Method getPlugin:()Lio/lumine/mythic/bukkit/utils/plugin/LuminePlugin;
      23: checkcast     #358                // class io/lumine/mythic/bukkit/MythicBukkit
      26: invokevirtual #362                // Method io/lumine/mythic/bukkit/MythicBukkit.getMobManager:()Lio/lumine/mythic/core/mobs/MobExecutor;
      29: aload_2
      30: invokeinterface #489,  1          // InterfaceMethod org/bukkit/entity/LivingEntity.getUniqueId:()Ljava/util/UUID;
      35: invokevirtual #372                // Method io/lumine/mythic/core/mobs/MobExecutor.isActiveMob:(Ljava/util/UUID;)Z
      38: ifne          42
      41: return
      42: aload_0
      43: invokevirtual #356                // Method getPlugin:()Lio/lumine/mythic/bukkit/utils/plugin/LuminePlugin;
      46: checkcast     #358                // class io/lumine/mythic/bukkit/MythicBukkit
      49: invokevirtual #362                // Method io/lumine/mythic/bukkit/MythicBukkit.getMobManager:()Lio/lumine/mythic/core/mobs/MobExecutor;
      52: aload_2
      53: invokevirtual #376                // Method io/lumine/mythic/core/mobs/MobExecutor.getMythicMobInstance:(Lorg/bukkit/entity/Entity;)Lio/lumine/mythic/core/mobs/ActiveMob;
      56: astore_3
      57: aload_3
      58: invokevirtual #380                // Method io/lumine/mythic/core/mobs/ActiveMob.getType:()Lio/lumine/mythic/api/mobs/MythicMob;
      61: invokeinterface #567,  1          // InterfaceMethod io/lumine/mythic/api/mobs/MythicMob.getPreventLeashing:()Ljava/lang/Boolean;
      66: invokevirtual #391                // Method java/lang/Boolean.booleanValue:()Z
      69: ifeq          97
      72: aload_1
      73: iconst_1
      74: invokevirtual #568                // Method org/bukkit/event/entity/PlayerLeashEntityEvent.setCancelled:(Z)V
      77: aload_1
      78: invokevirtual #569                // Method org/bukkit/event/entity/PlayerLeashEntityEvent.getPlayer:()Lorg/bukkit/entity/Player;
      81: getstatic     #575                // Field org/bukkit/ChatColor.RED:Lorg/bukkit/ChatColor;
      84: invokestatic  #581                // Method java/lang/String.valueOf:(Ljava/lang/Object;)Ljava/lang/String;
      87: invokedynamic #593,  0            // InvokeDynamic #31:makeConcatWithConstants:(Ljava/lang/String;)Ljava/lang/String;
      92: invokeinterface #526,  2          // InterfaceMethod org/bukkit/entity/Player.sendMessage:(Ljava/lang/String;)V
      97: return

  private void onKnockbackEntity(io.papermc.paper.event.entity.EntityKnockbackEvent);
    Code:
       0: aload_0
       1: invokevirtual #356                // Method getPlugin:()Lio/lumine/mythic/bukkit/utils/plugin/LuminePlugin;
       4: checkcast     #358                // class io/lumine/mythic/bukkit/MythicBukkit
       7: invokevirtual #362                // Method io/lumine/mythic/bukkit/MythicBukkit.getMobManager:()Lio/lumine/mythic/core/mobs/MobExecutor;
      10: aload_1
      11: invokevirtual #595                // Method io/papermc/paper/event/entity/EntityKnockbackEvent.getEntity:()Lorg/bukkit/entity/Entity;
      14: invokevirtual #599                // Method io/lumine/mythic/core/mobs/MobExecutor.isMythicMob:(Lorg/bukkit/entity/Entity;)Z
      17: ifne          21
      20: return
      21: aload_0
      22: invokevirtual #356                // Method getPlugin:()Lio/lumine/mythic/bukkit/utils/plugin/LuminePlugin;
      25: checkcast     #358                // class io/lumine/mythic/bukkit/MythicBukkit
      28: invokevirtual #362                // Method io/lumine/mythic/bukkit/MythicBukkit.getMobManager:()Lio/lumine/mythic/core/mobs/MobExecutor;
      31: aload_1
      32: invokevirtual #595                // Method io/papermc/paper/event/entity/EntityKnockbackEvent.getEntity:()Lorg/bukkit/entity/Entity;
      35: invokevirtual #376                // Method io/lumine/mythic/core/mobs/MobExecutor.getMythicMobInstance:(Lorg/bukkit/entity/Entity;)Lio/lumine/mythic/core/mobs/ActiveMob;
      38: astore_2
      39: aload_2
      40: ifnull        63
      43: aload_2
      44: invokevirtual #380                // Method io/lumine/mythic/core/mobs/ActiveMob.getType:()Lio/lumine/mythic/api/mobs/MythicMob;
      47: invokeinterface #602,  1          // InterfaceMethod io/lumine/mythic/api/mobs/MythicMob.getPreventKnockback:()Ljava/lang/Boolean;
      52: invokevirtual #391                // Method java/lang/Boolean.booleanValue:()Z
      55: ifeq          63
      58: aload_1
      59: iconst_1
      60: invokevirtual #603                // Method io/papermc/paper/event/entity/EntityKnockbackEvent.setCancelled:(Z)V
      63: return

  public void onBlockForm(org.bukkit.event.block.EntityBlockFormEvent);
    Code:
       0: aload_0
       1: invokevirtual #356                // Method getPlugin:()Lio/lumine/mythic/bukkit/utils/plugin/LuminePlugin;
       4: checkcast     #358                // class io/lumine/mythic/bukkit/MythicBukkit
       7: invokevirtual #362                // Method io/lumine/mythic/bukkit/MythicBukkit.getMobManager:()Lio/lumine/mythic/core/mobs/MobExecutor;
      10: aload_1
      11: invokevirtual #605                // Method org/bukkit/event/block/EntityBlockFormEvent.getEntity:()Lorg/bukkit/entity/Entity;
      14: invokeinterface #606,  1          // InterfaceMethod org/bukkit/entity/Entity.getUniqueId:()Ljava/util/UUID;
      19: invokevirtual #372                // Method io/lumine/mythic/core/mobs/MobExecutor.isActiveMob:(Ljava/util/UUID;)Z
      22: ifeq          84
      25: aload_0
      26: invokevirtual #356                // Method getPlugin:()Lio/lumine/mythic/bukkit/utils/plugin/LuminePlugin;
      29: checkcast     #358                // class io/lumine/mythic/bukkit/MythicBukkit
      32: invokevirtual #362                // Method io/lumine/mythic/bukkit/MythicBukkit.getMobManager:()Lio/lumine/mythic/core/mobs/MobExecutor;
      35: aload_1
      36: invokevirtual #605                // Method org/bukkit/event/block/EntityBlockFormEvent.getEntity:()Lorg/bukkit/entity/Entity;
      39: invokevirtual #376                // Method io/lumine/mythic/core/mobs/MobExecutor.getMythicMobInstance:(Lorg/bukkit/entity/Entity;)Lio/lumine/mythic/core/mobs/ActiveMob;
      42: astore_2
      43: aload_2
      44: invokevirtual #380                // Method io/lumine/mythic/core/mobs/ActiveMob.getType:()Lio/lumine/mythic/api/mobs/MythicMob;
      47: invokeinterface #610,  1          // InterfaceMethod io/lumine/mythic/api/mobs/MythicMob.getMythicEntity:()Lio/lumine/mythic/bukkit/adapters/BukkitEntityType;
      52: instanceof    #612                // class io/lumine/mythic/bukkit/entities/BukkitSnowman
      55: ifeq          84
      58: aload_2
      59: invokevirtual #380                // Method io/lumine/mythic/core/mobs/ActiveMob.getType:()Lio/lumine/mythic/api/mobs/MythicMob;
      62: invokeinterface #610,  1          // InterfaceMethod io/lumine/mythic/api/mobs/MythicMob.getMythicEntity:()Lio/lumine/mythic/bukkit/adapters/BukkitEntityType;
      67: checkcast     #612                // class io/lumine/mythic/bukkit/entities/BukkitSnowman
      70: invokevirtual #615                // Method io/lumine/mythic/bukkit/entities/BukkitSnowman.getPreventSnowFormation:()Ljava/lang/Boolean;
      73: invokevirtual #391                // Method java/lang/Boolean.booleanValue:()Z
      76: ifeq          84
      79: aload_1
      80: iconst_1
      81: invokevirtual #616                // Method org/bukkit/event/block/EntityBlockFormEvent.setCancelled:(Z)V
      84: return

  public void onTeleportEvent(org.bukkit.event.entity.EntityTeleportEvent);
    Code:
       0: aload_1
       1: invokevirtual #618                // Method org/bukkit/event/entity/EntityTeleportEvent.getEntity:()Lorg/bukkit/entity/Entity;
       4: astore_3
       5: aload_3
       6: instanceof    #427                // class org/bukkit/entity/LivingEntity
       9: ifeq          20
      12: aload_3
      13: checkcast     #427                // class org/bukkit/entity/LivingEntity
      16: astore_2
      17: goto          21
      20: return
      21: aload_0
      22: invokevirtual #356                // Method getPlugin:()Lio/lumine/mythic/bukkit/utils/plugin/LuminePlugin;
      25: checkcast     #358                // class io/lumine/mythic/bukkit/MythicBukkit
      28: invokevirtual #362                // Method io/lumine/mythic/bukkit/MythicBukkit.getMobManager:()Lio/lumine/mythic/core/mobs/MobExecutor;
      31: aload_1
      32: invokevirtual #618                // Method org/bukkit/event/entity/EntityTeleportEvent.getEntity:()Lorg/bukkit/entity/Entity;
      35: invokevirtual #376                // Method io/lumine/mythic/core/mobs/MobExecutor.getMythicMobInstance:(Lorg/bukkit/entity/Entity;)Lio/lumine/mythic/core/mobs/ActiveMob;
      38: astore_3
      39: aload_3
      40: ifnonnull     44
      43: return
      44: aload_3
      45: invokevirtual #621                // Method io/lumine/mythic/core/mobs/ActiveMob.getEntity:()Lio/lumine/mythic/api/adapters/AbstractEntity;
      48: ldc_w         #623                // String teleporting
      51: invokeinterface #627,  2          // InterfaceMethod io/lumine/mythic/api/adapters/AbstractEntity.hasMetadata:(Ljava/lang/String;)Z
      56: ifeq          60
      59: return
      60: aload_3
      61: invokevirtual #380                // Method io/lumine/mythic/core/mobs/ActiveMob.getType:()Lio/lumine/mythic/api/mobs/MythicMob;
      64: invokeinterface #630,  1          // InterfaceMethod io/lumine/mythic/api/mobs/MythicMob.getPreventEndermanTeleport:()Ljava/lang/Boolean;
      69: invokevirtual #391                // Method java/lang/Boolean.booleanValue:()Z
      72: ifeq          125
      75: aload_3
      76: invokevirtual #621                // Method io/lumine/mythic/core/mobs/ActiveMob.getEntity:()Lio/lumine/mythic/api/adapters/AbstractEntity;
      79: ldc_w         #623                // String teleporting
      82: iconst_1
      83: invokestatic  #633                // Method java/lang/Boolean.valueOf:(Z)Ljava/lang/Boolean;
      86: invokeinterface #637,  3          // InterfaceMethod io/lumine/mythic/api/adapters/AbstractEntity.setMetadata:(Ljava/lang/String;Ljava/lang/Object;)V
      91: aload_1
      92: invokevirtual #618                // Method org/bukkit/event/entity/EntityTeleportEvent.getEntity:()Lorg/bukkit/entity/Entity;
      95: aload_1
      96: invokevirtual #641                // Method org/bukkit/event/entity/EntityTeleportEvent.getFrom:()Lorg/bukkit/Location;
      99: invokeinterface #645,  2          // InterfaceMethod org/bukkit/entity/Entity.teleport:(Lorg/bukkit/Location;)Z
     104: pop
     105: aload_3
     106: invokevirtual #621                // Method io/lumine/mythic/core/mobs/ActiveMob.getEntity:()Lio/lumine/mythic/api/adapters/AbstractEntity;
     109: ldc_w         #623                // String teleporting
     112: invokeinterface #648,  2          // InterfaceMethod io/lumine/mythic/api/adapters/AbstractEntity.removeMetadata:(Ljava/lang/String;)V
     117: aload_1
     118: iconst_1
     119: invokevirtual #649                // Method org/bukkit/event/entity/EntityTeleportEvent.setCancelled:(Z)V
     122: goto          183
     125: aload_0
     126: invokevirtual #356                // Method getPlugin:()Lio/lumine/mythic/bukkit/utils/plugin/LuminePlugin;
     129: checkcast     #358                // class io/lumine/mythic/bukkit/MythicBukkit
     132: invokevirtual #653                // Method io/lumine/mythic/bukkit/MythicBukkit.getSkillManager:()Lio/lumine/mythic/core/skills/SkillExecutor;
     135: invokevirtual #659                // Method io/lumine/mythic/core/skills/SkillExecutor.getEventBus:()Lio/lumine/mythic/core/skills/EventExecutor;
     138: getstatic     #665                // Field io/lumine/mythic/core/skills/SkillTriggers.TELEPORT:Lio/lumine/mythic/api/skills/SkillTrigger;
     141: aload_3
     142: aconst_null
     143: aconst_null
     144: iconst_0
     145: invokevirtual #671                // Method io/lumine/mythic/core/skills/EventExecutor.buildSkillMetadata:(Lio/lumine/mythic/api/skills/SkillTrigger;Lio/lumine/mythic/api/skills/SkillCaster;Lio/lumine/mythic/api/adapters/AbstractEntity;Lio/lumine/mythic/api/adapters/AbstractLocation;Z)Lio/lumine/mythic/api/skills/SkillMetadata;
     148: astore        4
     150: aload_0
     151: invokevirtual #356                // Method getPlugin:()Lio/lumine/mythic/bukkit/utils/plugin/LuminePlugin;
     154: checkcast     #358                // class io/lumine/mythic/bukkit/MythicBukkit
     157: invokevirtual #653                // Method io/lumine/mythic/bukkit/MythicBukkit.getSkillManager:()Lio/lumine/mythic/core/skills/SkillExecutor;
     160: invokevirtual #659                // Method io/lumine/mythic/core/skills/SkillExecutor.getEventBus:()Lio/lumine/mythic/core/skills/EventExecutor;
     163: aload         4
     165: invokevirtual #675                // Method io/lumine/mythic/core/skills/EventExecutor.processTriggerMechanics:(Lio/lumine/mythic/api/skills/SkillMetadata;)Lio/lumine/mythic/core/skills/TriggeredSkill;
     168: astore        5
     170: aload         5
     172: invokevirtual #680                // Method io/lumine/mythic/core/skills/TriggeredSkill.getCancelled:()Z
     175: ifeq          183
     178: aload_1
     179: iconst_1
     180: invokevirtual #649                // Method org/bukkit/event/entity/EntityTeleportEvent.setCancelled:(Z)V
     183: return

  public void onChangeBlockEvent(org.bukkit.event.entity.EntityChangeBlockEvent);
    Code:
       0: aload_0
       1: invokevirtual #356                // Method getPlugin:()Lio/lumine/mythic/bukkit/utils/plugin/LuminePlugin;
       4: checkcast     #358                // class io/lumine/mythic/bukkit/MythicBukkit
       7: invokevirtual #362                // Method io/lumine/mythic/bukkit/MythicBukkit.getMobManager:()Lio/lumine/mythic/core/mobs/MobExecutor;
      10: aload_1
      11: invokevirtual #687                // Method org/bukkit/event/entity/EntityChangeBlockEvent.getEntity:()Lorg/bukkit/entity/Entity;
      14: invokeinterface #606,  1          // InterfaceMethod org/bukkit/entity/Entity.getUniqueId:()Ljava/util/UUID;
      19: invokevirtual #372                // Method io/lumine/mythic/core/mobs/MobExecutor.isActiveMob:(Ljava/util/UUID;)Z
      22: ifne          26
      25: return
      26: aload_0
      27: invokevirtual #356                // Method getPlugin:()Lio/lumine/mythic/bukkit/utils/plugin/LuminePlugin;
      30: checkcast     #358                // class io/lumine/mythic/bukkit/MythicBukkit
      33: invokevirtual #362                // Method io/lumine/mythic/bukkit/MythicBukkit.getMobManager:()Lio/lumine/mythic/core/mobs/MobExecutor;
      36: aload_1
      37: invokevirtual #687                // Method org/bukkit/event/entity/EntityChangeBlockEvent.getEntity:()Lorg/bukkit/entity/Entity;
      40: invokevirtual #376                // Method io/lumine/mythic/core/mobs/MobExecutor.getMythicMobInstance:(Lorg/bukkit/entity/Entity;)Lio/lumine/mythic/core/mobs/ActiveMob;
      43: astore_2
      44: aload_1
      45: invokevirtual #691                // Method org/bukkit/event/entity/EntityChangeBlockEvent.getEntityType:()Lorg/bukkit/entity/EntityType;
      48: getstatic     #697                // Field org/bukkit/entity/EntityType.FALLING_BLOCK:Lorg/bukkit/entity/EntityType;
      51: if_acmpne     110
      54: aload_0
      55: invokevirtual #356                // Method getPlugin:()Lio/lumine/mythic/bukkit/utils/plugin/LuminePlugin;
      58: checkcast     #358                // class io/lumine/mythic/bukkit/MythicBukkit
      61: invokevirtual #653                // Method io/lumine/mythic/bukkit/MythicBukkit.getSkillManager:()Lio/lumine/mythic/core/skills/SkillExecutor;
      64: invokevirtual #659                // Method io/lumine/mythic/core/skills/SkillExecutor.getEventBus:()Lio/lumine/mythic/core/skills/EventExecutor;
      67: getstatic     #700                // Field io/lumine/mythic/core/skills/SkillTriggers.DEATH:Lio/lumine/mythic/api/skills/SkillTrigger;
      70: aload_2
      71: aconst_null
      72: aconst_null
      73: iconst_1
      74: invokevirtual #671                // Method io/lumine/mythic/core/skills/EventExecutor.buildSkillMetadata:(Lio/lumine/mythic/api/skills/SkillTrigger;Lio/lumine/mythic/api/skills/SkillCaster;Lio/lumine/mythic/api/adapters/AbstractEntity;Lio/lumine/mythic/api/adapters/AbstractLocation;Z)Lio/lumine/mythic/api/skills/SkillMetadata;
      77: astore_3
      78: aload_0
      79: invokevirtual #356                // Method getPlugin:()Lio/lumine/mythic/bukkit/utils/plugin/LuminePlugin;
      82: checkcast     #358                // class io/lumine/mythic/bukkit/MythicBukkit
      85: invokevirtual #653                // Method io/lumine/mythic/bukkit/MythicBukkit.getSkillManager:()Lio/lumine/mythic/core/skills/SkillExecutor;
      88: invokevirtual #659                // Method io/lumine/mythic/core/skills/SkillExecutor.getEventBus:()Lio/lumine/mythic/core/skills/EventExecutor;
      91: aload_3
      92: invokevirtual #675                // Method io/lumine/mythic/core/skills/EventExecutor.processTriggerMechanics:(Lio/lumine/mythic/api/skills/SkillMetadata;)Lio/lumine/mythic/core/skills/TriggeredSkill;
      95: astore        4
      97: aload         4
      99: invokevirtual #680                // Method io/lumine/mythic/core/skills/TriggeredSkill.getCancelled:()Z
     102: ifeq          110
     105: aload_1
     106: iconst_1
     107: invokevirtual #701                // Method org/bukkit/event/entity/EntityChangeBlockEvent.setCancelled:(Z)V
     110: aload_2
     111: invokevirtual #380                // Method io/lumine/mythic/core/mobs/ActiveMob.getType:()Lio/lumine/mythic/api/mobs/MythicMob;
     114: invokeinterface #610,  1          // InterfaceMethod io/lumine/mythic/api/mobs/MythicMob.getMythicEntity:()Lio/lumine/mythic/bukkit/adapters/BukkitEntityType;
     119: instanceof    #703                // class io/lumine/mythic/bukkit/entities/BukkitSilverfish
     122: ifeq          396
     125: aload_2
     126: invokevirtual #380                // Method io/lumine/mythic/core/mobs/ActiveMob.getType:()Lio/lumine/mythic/api/mobs/MythicMob;
     129: invokeinterface #610,  1          // InterfaceMethod io/lumine/mythic/api/mobs/MythicMob.getMythicEntity:()Lio/lumine/mythic/bukkit/adapters/BukkitEntityType;
     134: checkcast     #703                // class io/lumine/mythic/bukkit/entities/BukkitSilverfish
     137: invokevirtual #706                // Method io/lumine/mythic/bukkit/entities/BukkitSilverfish.getPreventBlockInfection:()Z
     140: ifeq          396
     143: aload_1
     144: iconst_1
     145: invokevirtual #701                // Method org/bukkit/event/entity/EntityChangeBlockEvent.setCancelled:(Z)V
     148: aload_1
     149: invokevirtual #687                // Method org/bukkit/event/entity/EntityChangeBlockEvent.getEntity:()Lorg/bukkit/entity/Entity;
     152: checkcast     #427                // class org/bukkit/entity/LivingEntity
     155: astore_3
     156: aload_2
     157: invokevirtual #380                // Method io/lumine/mythic/core/mobs/ActiveMob.getType:()Lio/lumine/mythic/api/mobs/MythicMob;
     160: aload_2
     161: invokevirtual #621                // Method io/lumine/mythic/core/mobs/ActiveMob.getEntity:()Lio/lumine/mythic/api/adapters/AbstractEntity;
     164: invokeinterface #710,  1          // InterfaceMethod io/lumine/mythic/api/adapters/AbstractEntity.getLocation:()Lio/lumine/mythic/api/adapters/AbstractLocation;
     169: aload_2
     170: invokevirtual #713                // Method io/lumine/mythic/core/mobs/ActiveMob.getLevel:()D
     173: getstatic     #719                // Field io/lumine/mythic/api/mobs/entities/SpawnReason.OTHER:Lio/lumine/mythic/api/mobs/entities/SpawnReason;
     176: invokeinterface #723,  5          // InterfaceMethod io/lumine/mythic/api/mobs/MythicMob.spawn:(Lio/lumine/mythic/api/adapters/AbstractLocation;DLio/lumine/mythic/api/mobs/entities/SpawnReason;)Lio/lumine/mythic/core/mobs/ActiveMob;
     181: astore        4
     183: aload         4
     185: invokevirtual #621                // Method io/lumine/mythic/core/mobs/ActiveMob.getEntity:()Lio/lumine/mythic/api/adapters/AbstractEntity;
     188: invokestatic  #729                // Method io/lumine/mythic/bukkit/BukkitAdapter.adapt:(Lio/lumine/mythic/api/adapters/AbstractEntity;)Lorg/bukkit/entity/Entity;
     191: checkcast     #427                // class org/bukkit/entity/LivingEntity
     194: astore        5
     196: aload         5
     198: aload_3
     199: invokeinterface #732,  1          // InterfaceMethod org/bukkit/entity/LivingEntity.getMaxHealth:()D
     204: invokeinterface #735,  3          // InterfaceMethod org/bukkit/entity/LivingEntity.setMaxHealth:(D)V
     209: aload         5
     211: aload_3
     212: invokeinterface #738,  1          // InterfaceMethod org/bukkit/entity/LivingEntity.getHealth:()D
     217: invokeinterface #741,  3          // InterfaceMethod org/bukkit/entity/LivingEntity.setHealth:(D)V
     222: aload_3
     223: invokeinterface #744,  1          // InterfaceMethod org/bukkit/entity/LivingEntity.getPassenger:()Lorg/bukkit/entity/Entity;
     228: ifnull        245
     231: aload         5
     233: aload_3
     234: invokeinterface #744,  1          // InterfaceMethod org/bukkit/entity/LivingEntity.getPassenger:()Lorg/bukkit/entity/Entity;
     239: invokeinterface #747,  2          // InterfaceMethod org/bukkit/entity/LivingEntity.setPassenger:(Lorg/bukkit/entity/Entity;)Z
     244: pop
     245: aload_3
     246: invokeinterface #750,  1          // InterfaceMethod org/bukkit/entity/LivingEntity.getVehicle:()Lorg/bukkit/entity/Entity;
     251: ifnull        268
     254: aload_3
     255: invokeinterface #750,  1          // InterfaceMethod org/bukkit/entity/LivingEntity.getVehicle:()Lorg/bukkit/entity/Entity;
     260: aload         5
     262: invokeinterface #751,  2          // InterfaceMethod org/bukkit/entity/Entity.setPassenger:(Lorg/bukkit/entity/Entity;)Z
     267: pop
     268: aload_3
     269: invokeinterface #755,  1          // InterfaceMethod org/bukkit/entity/LivingEntity.getActivePotionEffects:()Ljava/util/Collection;
     274: astore        6
     276: aload         6
     278: invokeinterface #761,  1          // InterfaceMethod java/util/Collection.iterator:()Ljava/util/Iterator;
     283: astore        7
     285: aload         7
     287: invokeinterface #766,  1          // InterfaceMethod java/util/Iterator.hasNext:()Z
     292: ifeq          320
     295: aload         7
     297: invokeinterface #769,  1          // InterfaceMethod java/util/Iterator.next:()Ljava/lang/Object;
     302: checkcast     #771                // class org/bukkit/potion/PotionEffect
     305: astore        8
     307: aload         5
     309: aload         8
     311: invokeinterface #775,  2          // InterfaceMethod org/bukkit/entity/LivingEntity.addPotionEffect:(Lorg/bukkit/potion/PotionEffect;)Z
     316: pop
     317: goto          285
     320: aload_0
     321: invokevirtual #356                // Method getPlugin:()Lio/lumine/mythic/bukkit/utils/plugin/LuminePlugin;
     324: checkcast     #358                // class io/lumine/mythic/bukkit/MythicBukkit
     327: invokevirtual #362                // Method io/lumine/mythic/bukkit/MythicBukkit.getMobManager:()Lio/lumine/mythic/core/mobs/MobExecutor;
     330: aload         5
     332: invokestatic  #778                // Method io/lumine/mythic/bukkit/BukkitAdapter.adapt:(Lorg/bukkit/entity/Entity;)Lio/lumine/mythic/api/adapters/AbstractEntity;
     335: invokevirtual #781                // Method io/lumine/mythic/core/mobs/MobExecutor.getMythicMobInstance:(Lio/lumine/mythic/api/adapters/AbstractEntity;)Lio/lumine/mythic/core/mobs/ActiveMob;
     338: astore        7
     340: aload         7
     342: ifnonnull     359
     345: getstatic     #439                // Field io/lumine/mythic/core/logging/MythicLogger$DebugLevel.INFO:Lio/lumine/mythic/core/logging/MythicLogger$DebugLevel;
     348: ldc_w         #783                // String -- Something prevented Silverfish from respawning! PreventBlockInfection failed :(
     351: iconst_0
     352: anewarray     #408                // class java/lang/Object
     355: invokestatic  #412                // Method io/lumine/mythic/core/logging/MythicLogger.debug:(Lio/lumine/mythic/core/logging/MythicLogger$DebugLevel;Ljava/lang/String;[Ljava/lang/Object;)V
     358: return
     359: aload         7
     361: aload_2
     362: invokevirtual #787                // Method io/lumine/mythic/core/mobs/ActiveMob.getStance:()Ljava/lang/String;
     365: invokevirtual #790                // Method io/lumine/mythic/core/mobs/ActiveMob.setStance:(Ljava/lang/String;)V
     368: aload         7
     370: aload_2
     371: invokevirtual #794                // Method io/lumine/mythic/core/mobs/ActiveMob.getPlayerKills:()I
     374: invokevirtual #798                // Method io/lumine/mythic/core/mobs/ActiveMob.importPlayerKills:(I)V
     377: aload         7
     379: aload_2
     380: invokevirtual #802                // Method io/lumine/mythic/core/mobs/ActiveMob.getThreatTable:()Lio/lumine/mythic/core/mobs/ActiveMob$ThreatTable;
     383: invokevirtual #806                // Method io/lumine/mythic/core/mobs/ActiveMob.importThreatTable:(Lio/lumine/mythic/core/mobs/ActiveMob$ThreatTable;)V
     386: aload_3
     387: invokeinterface #807,  1          // InterfaceMethod org/bukkit/entity/LivingEntity.remove:()V
     392: aload_2
     393: invokevirtual #810                // Method io/lumine/mythic/core/mobs/ActiveMob.setDead:()V
     396: return

  public void onMythicDamage(io.lumine.mythic.bukkit.events.MythicDamageEvent);
    Code:
       0: aload_0
       1: getfield      #822                // Field plugin:Lio/lumine/mythic/bukkit/utils/plugin/LuminePlugin;
       4: checkcast     #358                // class io/lumine/mythic/bukkit/MythicBukkit
       7: invokevirtual #826                // Method io/lumine/mythic/bukkit/MythicBukkit.getVolatileCodeHandler:()Lio/lumine/mythic/api/volatilecode/VolatileCodeHandler;
      10: invokeinterface #832,  1          // InterfaceMethod io/lumine/mythic/api/volatilecode/VolatileCodeHandler.getEntityHandler:()Lio/lumine/mythic/api/volatilecode/handlers/VolatileEntityHandler;
      15: aload_1
      16: invokevirtual #836                // Method io/lumine/mythic/bukkit/events/MythicDamageEvent.getDamageMetadata:()Lio/lumine/mythic/api/skills/damage/DamageMetadata;
      19: aload_1
      20: invokevirtual #839                // Method io/lumine/mythic/bukkit/events/MythicDamageEvent.getTarget:()Lio/lumine/mythic/api/adapters/AbstractEntity;
      23: invokeinterface #845,  3          // InterfaceMethod io/lumine/mythic/api/volatilecode/handlers/VolatileEntityHandler.doDamage:(Lio/lumine/mythic/api/skills/damage/DamageMetadata;Lio/lumine/mythic/api/adapters/AbstractEntity;)Z
      28: ifne          36
      31: aload_1
      32: iconst_1
      33: invokevirtual #846                // Method io/lumine/mythic/bukkit/events/MythicDamageEvent.setCancelled:(Z)V
      36: return

  public void load(io.lumine.mythic.bukkit.utils.plugin.LuminePlugin);
    Code:
       0: aload_0
       1: aload_1
       2: checkcast     #358                // class io/lumine/mythic/bukkit/MythicBukkit
       5: invokevirtual #849                // Method load:(Lio/lumine/mythic/bukkit/MythicBukkit;)V
       8: return

  private static void lambda$onTagEntity$24(io.lumine.mythic.core.mobs.ActiveMob, org.bukkit.entity.LivingEntity);
    Code:
       0: aload_0
       1: aload_1
       2: invokeinterface #852,  1          // InterfaceMethod org/bukkit/entity/LivingEntity.getName:()Ljava/lang/String;
       7: invokevirtual #855                // Method io/lumine/mythic/core/mobs/ActiveMob.setDisplayName:(Ljava/lang/String;)V
      10: return

  private static boolean lambda$load$23(io.lumine.mythic.bukkit.events.MythicDamageEvent);
    Code:
       0: aload_0
       1: invokevirtual #858                // Method io/lumine/mythic/bukkit/events/MythicDamageEvent.isCancelled:()Z
       4: ifne          11
       7: iconst_1
       8: goto          12
      11: iconst_0
      12: ireturn

  private static boolean lambda$load$22(org.bukkit.event.entity.EntityDamageByBlockEvent);
    Code:
       0: aload_0
       1: invokevirtual #859                // Method org/bukkit/event/entity/EntityDamageByBlockEvent.isCancelled:()Z
       4: ifne          11
       7: iconst_1
       8: goto          12
      11: iconst_0
      12: ireturn

  private static boolean lambda$load$21(org.bukkit.event.entity.EntityDamageByEntityEvent);
    Code:
       0: aload_0
       1: invokevirtual #861                // Method org/bukkit/event/entity/EntityDamageByEntityEvent.isCancelled:()Z
       4: ifne          11
       7: iconst_1
       8: goto          12
      11: iconst_0
      12: ireturn

  private static boolean lambda$load$20(org.bukkit.event.entity.EntityDamageEvent);
    Code:
       0: aload_0
       1: invokevirtual #862                // Method org/bukkit/event/entity/EntityDamageEvent.isCancelled:()Z
       4: ifne          11
       7: iconst_1
       8: goto          12
      11: iconst_0
      12: ireturn

  private void lambda$load$19(org.bukkit.event.entity.EntityCombustEvent);
    Code:
       0: aload_1
       1: invokevirtual #863                // Method org/bukkit/event/entity/EntityCombustEvent.getEntity:()Lorg/bukkit/entity/Entity;
       4: astore_2
       5: aload_0
       6: invokevirtual #356                // Method getPlugin:()Lio/lumine/mythic/bukkit/utils/plugin/LuminePlugin;
       9: checkcast     #358                // class io/lumine/mythic/bukkit/MythicBukkit
      12: invokevirtual #362                // Method io/lumine/mythic/bukkit/MythicBukkit.getMobManager:()Lio/lumine/mythic/core/mobs/MobExecutor;
      15: aload_2
      16: invokeinterface #606,  1          // InterfaceMethod org/bukkit/entity/Entity.getUniqueId:()Ljava/util/UUID;
      21: invokevirtual #372                // Method io/lumine/mythic/core/mobs/MobExecutor.isActiveMob:(Ljava/util/UUID;)Z
      24: ifeq          67
      27: aload_0
      28: invokevirtual #356                // Method getPlugin:()Lio/lumine/mythic/bukkit/utils/plugin/LuminePlugin;
      31: checkcast     #358                // class io/lumine/mythic/bukkit/MythicBukkit
      34: invokevirtual #362                // Method io/lumine/mythic/bukkit/MythicBukkit.getMobManager:()Lio/lumine/mythic/core/mobs/MobExecutor;
      37: aload_2
      38: invokevirtual #376                // Method io/lumine/mythic/core/mobs/MobExecutor.getMythicMobInstance:(Lorg/bukkit/entity/Entity;)Lio/lumine/mythic/core/mobs/ActiveMob;
      41: astore_3
      42: aload_3
      43: invokevirtual #380                // Method io/lumine/mythic/core/mobs/ActiveMob.getType:()Lio/lumine/mythic/api/mobs/MythicMob;
      46: invokeinterface #866,  1          // InterfaceMethod io/lumine/mythic/api/mobs/MythicMob.getPreventSunburn:()Ljava/lang/Boolean;
      51: invokevirtual #391                // Method java/lang/Boolean.booleanValue:()Z
      54: ifeq          67
      57: aload_1
      58: iconst_0
      59: invokevirtual #869                // Method org/bukkit/event/entity/EntityCombustEvent.setDuration:(I)V
      62: aload_1
      63: iconst_1
      64: invokevirtual #870                // Method org/bukkit/event/entity/EntityCombustEvent.setCancelled:(Z)V
      67: return

  private static boolean lambda$load$18(org.bukkit.event.entity.EntityCombustEvent);
    Code:
       0: aload_0
       1: invokevirtual #863                // Method org/bukkit/event/entity/EntityCombustEvent.getEntity:()Lorg/bukkit/entity/Entity;
       4: invokeinterface #876,  1          // InterfaceMethod org/bukkit/entity/Entity.getWorld:()Lorg/bukkit/World;
       9: invokeinterface #880,  1          // InterfaceMethod org/bukkit/World.getEnvironment:()Lorg/bukkit/World$Environment;
      14: getstatic     #884                // Field org/bukkit/World$Environment.NORMAL:Lorg/bukkit/World$Environment;
      17: if_acmpne     24
      20: iconst_1
      21: goto          25
      24: iconst_0
      25: ireturn

  private static boolean lambda$load$17(org.bukkit.event.entity.EntityCombustEvent);
    Code:
       0: aload_0
       1: instanceof    #886                // class org/bukkit/event/entity/EntityCombustByBlockEvent
       4: ifne          18
       7: aload_0
       8: instanceof    #888                // class org/bukkit/event/entity/EntityCombustByEntityEvent
      11: ifne          18
      14: iconst_1
      15: goto          19
      18: iconst_0
      19: ireturn

  private static boolean lambda$load$16(org.bukkit.event.entity.EntityCombustEvent);
    Code:
       0: aload_0
       1: invokevirtual #889                // Method org/bukkit/event/entity/EntityCombustEvent.isCancelled:()Z
       4: ifne          11
       7: iconst_1
       8: goto          12
      11: iconst_0
      12: ireturn

  private void lambda$load$15(org.bukkit.event.entity.CreatureSpawnEvent);
    Code:
       0: aload_1
       1: invokevirtual #892                // Method org/bukkit/event/entity/CreatureSpawnEvent.getEntity:()Lorg/bukkit/entity/LivingEntity;
       4: astore_2
       5: aload_0
       6: invokevirtual #356                // Method getPlugin:()Lio/lumine/mythic/bukkit/utils/plugin/LuminePlugin;
       9: checkcast     #358                // class io/lumine/mythic/bukkit/MythicBukkit
      12: invokevirtual #362                // Method io/lumine/mythic/bukkit/MythicBukkit.getMobManager:()Lio/lumine/mythic/core/mobs/MobExecutor;
      15: aload_2
      16: invokevirtual #599                // Method io/lumine/mythic/core/mobs/MobExecutor.isMythicMob:(Lorg/bukkit/entity/Entity;)Z
      19: ifeq          43
      22: aload_0
      23: invokevirtual #356                // Method getPlugin:()Lio/lumine/mythic/bukkit/utils/plugin/LuminePlugin;
      26: checkcast     #358                // class io/lumine/mythic/bukkit/MythicBukkit
      29: invokevirtual #362                // Method io/lumine/mythic/bukkit/MythicBukkit.getMobManager:()Lio/lumine/mythic/core/mobs/MobExecutor;
      32: aload_1
      33: invokevirtual #892                // Method org/bukkit/event/entity/CreatureSpawnEvent.getEntity:()Lorg/bukkit/entity/LivingEntity;
      36: invokestatic  #778                // Method io/lumine/mythic/bukkit/BukkitAdapter.adapt:(Lorg/bukkit/entity/Entity;)Lio/lumine/mythic/api/adapters/AbstractEntity;
      39: invokevirtual #781                // Method io/lumine/mythic/core/mobs/MobExecutor.getMythicMobInstance:(Lio/lumine/mythic/api/adapters/AbstractEntity;)Lio/lumine/mythic/core/mobs/ActiveMob;
      42: pop
      43: return

  private static boolean lambda$load$14(org.bukkit.event.entity.CreatureSpawnEvent);
    Code:
       0: aload_0
       1: invokevirtual #897                // Method org/bukkit/event/entity/CreatureSpawnEvent.getSpawnReason:()Lorg/bukkit/event/entity/CreatureSpawnEvent$SpawnReason;
       4: getstatic     #901                // Field org/bukkit/event/entity/CreatureSpawnEvent$SpawnReason.BEEHIVE:Lorg/bukkit/event/entity/CreatureSpawnEvent$SpawnReason;
       7: if_acmpne     14
      10: iconst_1
      11: goto          15
      14: iconst_0
      15: ireturn

  private static boolean lambda$load$13(org.bukkit.event.entity.CreatureSpawnEvent);
    Code:
       0: aload_0
       1: invokevirtual #902                // Method org/bukkit/event/entity/CreatureSpawnEvent.isCancelled:()Z
       4: ifne          11
       7: iconst_1
       8: goto          12
      11: iconst_0
      12: ireturn

  private void lambda$load$12(org.bukkit.event.entity.EntityTransformEvent);
    Code:
       0: aload_0
       1: invokevirtual #356                // Method getPlugin:()Lio/lumine/mythic/bukkit/utils/plugin/LuminePlugin;
       4: checkcast     #358                // class io/lumine/mythic/bukkit/MythicBukkit
       7: invokevirtual #362                // Method io/lumine/mythic/bukkit/MythicBukkit.getMobManager:()Lio/lumine/mythic/core/mobs/MobExecutor;
      10: aload_1
      11: invokevirtual #903                // Method org/bukkit/event/entity/EntityTransformEvent.getEntity:()Lorg/bukkit/entity/Entity;
      14: invokeinterface #606,  1          // InterfaceMethod org/bukkit/entity/Entity.getUniqueId:()Ljava/util/UUID;
      19: invokevirtual #372                // Method io/lumine/mythic/core/mobs/MobExecutor.isActiveMob:(Ljava/util/UUID;)Z
      22: ifeq          63
      25: aload_0
      26: invokevirtual #356                // Method getPlugin:()Lio/lumine/mythic/bukkit/utils/plugin/LuminePlugin;
      29: checkcast     #358                // class io/lumine/mythic/bukkit/MythicBukkit
      32: invokevirtual #362                // Method io/lumine/mythic/bukkit/MythicBukkit.getMobManager:()Lio/lumine/mythic/core/mobs/MobExecutor;
      35: aload_1
      36: invokevirtual #903                // Method org/bukkit/event/entity/EntityTransformEvent.getEntity:()Lorg/bukkit/entity/Entity;
      39: invokevirtual #376                // Method io/lumine/mythic/core/mobs/MobExecutor.getMythicMobInstance:(Lorg/bukkit/entity/Entity;)Lio/lumine/mythic/core/mobs/ActiveMob;
      42: astore_2
      43: aload_2
      44: invokevirtual #380                // Method io/lumine/mythic/core/mobs/ActiveMob.getType:()Lio/lumine/mythic/api/mobs/MythicMob;
      47: invokeinterface #906,  1          // InterfaceMethod io/lumine/mythic/api/mobs/MythicMob.getPreventTransformation:()Ljava/lang/Boolean;
      52: invokevirtual #391                // Method java/lang/Boolean.booleanValue:()Z
      55: ifeq          63
      58: aload_1
      59: iconst_1
      60: invokevirtual #907                // Method org/bukkit/event/entity/EntityTransformEvent.setCancelled:(Z)V
      63: return

  private void lambda$load$11(org.bukkit.event.world.ChunkLoadEvent);
    Code:
       0: aload_0
       1: invokevirtual #356                // Method getPlugin:()Lio/lumine/mythic/bukkit/utils/plugin/LuminePlugin;
       4: checkcast     #358                // class io/lumine/mythic/bukkit/MythicBukkit
       7: invokevirtual #912                // Method io/lumine/mythic/bukkit/MythicBukkit.getConfiguration:()Lio/lumine/mythic/core/config/ConfigExecutor;
      10: invokevirtual #917                // Method io/lumine/mythic/core/config/ConfigExecutor.isDebugMode:()Z
      13: ifeq          17
      16: return
      17: getstatic     #920                // Field io/lumine/mythic/core/logging/MythicLogger$DebugLevel.EVENT:Lio/lumine/mythic/core/logging/MythicLogger$DebugLevel;
      20: ldc_w         #922                // String ChunkLoadEvent (New Chunk) fired
      23: iconst_0
      24: anewarray     #408                // class java/lang/Object
      27: invokestatic  #412                // Method io/lumine/mythic/core/logging/MythicLogger.debug:(Lio/lumine/mythic/core/logging/MythicLogger$DebugLevel;Ljava/lang/String;[Ljava/lang/Object;)V
      30: aload_1
      31: invokevirtual #926                // Method org/bukkit/event/world/ChunkLoadEvent.getChunk:()Lorg/bukkit/Chunk;
      34: invokeinterface #932,  1          // InterfaceMethod org/bukkit/Chunk.getEntities:()[Lorg/bukkit/entity/Entity;
      39: astore_2
      40: aload_2
      41: arraylength
      42: istore_3
      43: iconst_0
      44: istore        4
      46: iload         4
      48: iload_3
      49: if_icmpge     279
      52: aload_2
      53: iload         4
      55: aaload
      56: astore        5
      58: aload         5
      60: invokeinterface #936,  1          // InterfaceMethod org/bukkit/entity/Entity.getType:()Lorg/bukkit/entity/EntityType;
      65: getstatic     #939                // Field org/bukkit/entity/EntityType.PLAYER:Lorg/bukkit/entity/EntityType;
      68: if_acmpne     74
      71: goto          273
      74: aload_0
      75: invokevirtual #356                // Method getPlugin:()Lio/lumine/mythic/bukkit/utils/plugin/LuminePlugin;
      78: checkcast     #358                // class io/lumine/mythic/bukkit/MythicBukkit
      81: invokevirtual #943                // Method io/lumine/mythic/bukkit/MythicBukkit.getCompatibility:()Lio/lumine/mythic/bukkit/compatibility/CompatibilityManager;
      84: invokevirtual #949                // Method io/lumine/mythic/bukkit/compatibility/CompatibilityManager.getWorldGuard:()Ljava/util/Optional;
      87: invokevirtual #952                // Method java/util/Optional.isPresent:()Z
      90: ifeq          128
      93: aload_0
      94: invokevirtual #356                // Method getPlugin:()Lio/lumine/mythic/bukkit/utils/plugin/LuminePlugin;
      97: checkcast     #358                // class io/lumine/mythic/bukkit/MythicBukkit
     100: invokevirtual #943                // Method io/lumine/mythic/bukkit/MythicBukkit.getCompatibility:()Lio/lumine/mythic/bukkit/compatibility/CompatibilityManager;
     103: invokevirtual #949                // Method io/lumine/mythic/bukkit/compatibility/CompatibilityManager.getWorldGuard:()Ljava/util/Optional;
     106: invokevirtual #953                // Method java/util/Optional.get:()Ljava/lang/Object;
     109: checkcast     #955                // class io/lumine/mythic/bukkit/compatibility/WorldGuardSupport
     112: aload         5
     114: invokeinterface #957,  1          // InterfaceMethod org/bukkit/entity/Entity.getLocation:()Lorg/bukkit/Location;
     119: invokevirtual #960                // Method io/lumine/mythic/bukkit/compatibility/WorldGuardSupport.getLocationAllowsMobSpawning:(Lorg/bukkit/Location;)Z
     122: ifne          128
     125: goto          273
     128: aload         5
     130: invokestatic  #778                // Method io/lumine/mythic/bukkit/BukkitAdapter.adapt:(Lorg/bukkit/entity/Entity;)Lio/lumine/mythic/api/adapters/AbstractEntity;
     133: astore        6
     135: aload_0
     136: invokevirtual #356                // Method getPlugin:()Lio/lumine/mythic/bukkit/utils/plugin/LuminePlugin;
     139: checkcast     #358                // class io/lumine/mythic/bukkit/MythicBukkit
     142: invokevirtual #362                // Method io/lumine/mythic/bukkit/MythicBukkit.getMobManager:()Lio/lumine/mythic/core/mobs/MobExecutor;
     145: aload         5
     147: invokevirtual #599                // Method io/lumine/mythic/core/mobs/MobExecutor.isMythicMob:(Lorg/bukkit/entity/Entity;)Z
     150: ifeq          185
     153: aload_0
     154: invokevirtual #356                // Method getPlugin:()Lio/lumine/mythic/bukkit/utils/plugin/LuminePlugin;
     157: checkcast     #358                // class io/lumine/mythic/bukkit/MythicBukkit
     160: invokevirtual #362                // Method io/lumine/mythic/bukkit/MythicBukkit.getMobManager:()Lio/lumine/mythic/core/mobs/MobExecutor;
     163: aload         6
     165: invokevirtual #781                // Method io/lumine/mythic/core/mobs/MobExecutor.getMythicMobInstance:(Lio/lumine/mythic/api/adapters/AbstractEntity;)Lio/lumine/mythic/core/mobs/ActiveMob;
     168: astore        7
     170: aload         7
     172: aload         6
     174: invokeinterface #710,  1          // InterfaceMethod io/lumine/mythic/api/adapters/AbstractEntity.getLocation:()Lio/lumine/mythic/api/adapters/AbstractLocation;
     179: invokevirtual #964                // Method io/lumine/mythic/core/mobs/ActiveMob.setSpawnLocation:(Lio/lumine/mythic/api/adapters/AbstractLocation;)V
     182: goto          273
     185: new           #966                // class io/lumine/mythic/core/spawning/random/RandomSpawnPoint
     188: dup
     189: aload         6
     191: aload         6
     193: invokeinterface #710,  1          // InterfaceMethod io/lumine/mythic/api/adapters/AbstractEntity.getLocation:()Lio/lumine/mythic/api/adapters/AbstractLocation;
     198: getstatic     #969                // Field org/bukkit/event/entity/CreatureSpawnEvent$SpawnReason.NATURAL:Lorg/bukkit/event/entity/CreatureSpawnEvent$SpawnReason;
     201: invokespecial #972                // Method io/lumine/mythic/core/spawning/random/RandomSpawnPoint."<init>":(Lio/lumine/mythic/api/adapters/AbstractEntity;Lio/lumine/mythic/api/adapters/AbstractLocation;Lorg/bukkit/event/entity/CreatureSpawnEvent$SpawnReason;)V
     204: astore        7
     206: aload_0
     207: invokevirtual #356                // Method getPlugin:()Lio/lumine/mythic/bukkit/utils/plugin/LuminePlugin;
     210: checkcast     #358                // class io/lumine/mythic/bukkit/MythicBukkit
     213: invokevirtual #976                // Method io/lumine/mythic/bukkit/MythicBukkit.getRandomSpawningManager:()Lio/lumine/mythic/core/spawning/random/RandomSpawnerManager;
     216: aload         7
     218: invokevirtual #982                // Method io/lumine/mythic/core/spawning/random/RandomSpawnerManager.handleSpawnEvent:(Lio/lumine/mythic/core/spawning/random/RandomSpawnPoint;)Lio/lumine/mythic/api/adapters/AbstractEntity;
     221: invokestatic  #729                // Method io/lumine/mythic/bukkit/BukkitAdapter.adapt:(Lio/lumine/mythic/api/adapters/AbstractEntity;)Lorg/bukkit/entity/Entity;
     224: astore        8
     226: aload         8
     228: ifnull        241
     231: aload         5
     233: invokeinterface #459,  1          // InterfaceMethod org/bukkit/entity/Entity.remove:()V
     238: goto          273
     241: aload_0
     242: invokevirtual #356                // Method getPlugin:()Lio/lumine/mythic/bukkit/utils/plugin/LuminePlugin;
     245: checkcast     #358                // class io/lumine/mythic/bukkit/MythicBukkit
     248: invokevirtual #912                // Method io/lumine/mythic/bukkit/MythicBukkit.getConfiguration:()Lio/lumine/mythic/core/config/ConfigExecutor;
     251: invokevirtual #985                // Method io/lumine/mythic/core/config/ConfigExecutor.isVanillaSpawnsDisabled:()Z
     254: ifeq          273
     257: invokestatic  #990                // Method io/lumine/mythic/bukkit/adapters/BukkitEntityType.getIsSpawning:()Ljava/lang/Boolean;
     260: invokevirtual #391                // Method java/lang/Boolean.booleanValue:()Z
     263: ifne          273
     266: aload         5
     268: invokeinterface #459,  1          // InterfaceMethod org/bukkit/entity/Entity.remove:()V
     273: iinc          4, 1
     276: goto          46
     279: return

  private static boolean lambda$load$10(org.bukkit.event.world.ChunkLoadEvent);
    Code:
       0: aload_0
       1: invokevirtual #998                // Method org/bukkit/event/world/ChunkLoadEvent.isNewChunk:()Z
       4: ireturn

  private void lambda$load$9(org.bukkit.event.world.EntitiesLoadEvent);
    Code:
       0: aload_1
       1: invokevirtual #1001               // Method org/bukkit/event/world/EntitiesLoadEvent.getEntities:()Ljava/util/List;
       4: invokeinterface #1004,  1         // InterfaceMethod java/util/List.iterator:()Ljava/util/Iterator;
       9: astore_2
      10: aload_2
      11: invokeinterface #766,  1          // InterfaceMethod java/util/Iterator.hasNext:()Z
      16: ifeq          228
      19: aload_2
      20: invokeinterface #769,  1          // InterfaceMethod java/util/Iterator.next:()Ljava/lang/Object;
      25: checkcast     #447                // class org/bukkit/entity/Entity
      28: astore_3
      29: aload_3
      30: instanceof    #495                // class org/bukkit/entity/Player
      33: ifeq          39
      36: goto          10
      39: aload_3
      40: instanceof    #427                // class org/bukkit/entity/LivingEntity
      43: ifeq          225
      46: aload_3
      47: checkcast     #427                // class org/bukkit/entity/LivingEntity
      50: astore        4
      52: aload_0
      53: invokevirtual #356                // Method getPlugin:()Lio/lumine/mythic/bukkit/utils/plugin/LuminePlugin;
      56: checkcast     #358                // class io/lumine/mythic/bukkit/MythicBukkit
      59: invokevirtual #362                // Method io/lumine/mythic/bukkit/MythicBukkit.getMobManager:()Lio/lumine/mythic/core/mobs/MobExecutor;
      62: aload_3
      63: invokevirtual #599                // Method io/lumine/mythic/core/mobs/MobExecutor.isMythicMob:(Lorg/bukkit/entity/Entity;)Z
      66: ifeq          72
      69: goto          10
      72: aload_3
      73: invokestatic  #778                // Method io/lumine/mythic/bukkit/BukkitAdapter.adapt:(Lorg/bukkit/entity/Entity;)Lio/lumine/mythic/api/adapters/AbstractEntity;
      76: astore        5
      78: aload_0
      79: invokevirtual #356                // Method getPlugin:()Lio/lumine/mythic/bukkit/utils/plugin/LuminePlugin;
      82: checkcast     #358                // class io/lumine/mythic/bukkit/MythicBukkit
      85: invokevirtual #1008               // Method io/lumine/mythic/bukkit/MythicBukkit.getBootstrap:()Lio/lumine/mythic/bukkit/BukkitBootstrap;
      88: aload_3
      89: invokevirtual #1014               // Method io/lumine/mythic/bukkit/BukkitBootstrap.getMythicEntityType:(Lorg/bukkit/entity/Entity;)Lio/lumine/mythic/api/mobs/entities/MythicEntityType;
      92: astore        6
      94: aload_0
      95: invokevirtual #356                // Method getPlugin:()Lio/lumine/mythic/bukkit/utils/plugin/LuminePlugin;
      98: checkcast     #358                // class io/lumine/mythic/bukkit/MythicBukkit
     101: invokevirtual #362                // Method io/lumine/mythic/bukkit/MythicBukkit.getMobManager:()Lio/lumine/mythic/core/mobs/MobExecutor;
     104: aload         6
     106: invokevirtual #1018               // Method io/lumine/mythic/core/mobs/MobExecutor.getVanillaType:(Lio/lumine/mythic/api/mobs/entities/MythicEntityType;)Ljava/util/Optional;
     109: astore        7
     111: aload         7
     113: invokevirtual #952                // Method java/util/Optional.isPresent:()Z
     116: ifeq          225
     119: aload         7
     121: invokevirtual #953                // Method java/util/Optional.get:()Ljava/lang/Object;
     124: checkcast     #382                // class io/lumine/mythic/api/mobs/MythicMob
     127: astore        8
     129: aload         8
     131: invokeinterface #610,  1          // InterfaceMethod io/lumine/mythic/api/mobs/MythicMob.getMythicEntity:()Lio/lumine/mythic/bukkit/adapters/BukkitEntityType;
     136: aload_3
     137: invokevirtual #1021               // Method io/lumine/mythic/bukkit/adapters/BukkitEntityType.compare:(Lorg/bukkit/entity/Entity;)Z
     140: ifne          146
     143: goto          10
     146: dconst_1
     147: aload         5
     149: invokeinterface #710,  1          // InterfaceMethod io/lumine/mythic/api/adapters/AbstractEntity.getLocation:()Lio/lumine/mythic/api/adapters/AbstractLocation;
     154: invokestatic  #1029               // Method io/lumine/mythic/core/mobs/WorldScaling.getLevelBonus:(Lio/lumine/mythic/api/adapters/AbstractLocation;)D
     157: dadd
     158: dstore        9
     160: aload_0
     161: invokevirtual #356                // Method getPlugin:()Lio/lumine/mythic/bukkit/utils/plugin/LuminePlugin;
     164: checkcast     #358                // class io/lumine/mythic/bukkit/MythicBukkit
     167: invokevirtual #362                // Method io/lumine/mythic/bukkit/MythicBukkit.getMobManager:()Lio/lumine/mythic/core/mobs/MobExecutor;
     170: aload         5
     172: aload         8
     174: dload         9
     176: invokevirtual #1033               // Method io/lumine/mythic/core/mobs/MobExecutor.registerActiveMob:(Lio/lumine/mythic/api/adapters/AbstractEntity;Lio/lumine/mythic/api/mobs/MythicMob;D)Lio/lumine/mythic/core/mobs/ActiveMob;
     179: astore        11
     181: aload         8
     183: invokeinterface #610,  1          // InterfaceMethod io/lumine/mythic/api/mobs/MythicMob.getMythicEntity:()Lio/lumine/mythic/bukkit/adapters/BukkitEntityType;
     188: aload_3
     189: invokevirtual #1037               // Method io/lumine/mythic/bukkit/adapters/BukkitEntityType.applySpawnOptions:(Lorg/bukkit/entity/Entity;)Lorg/bukkit/entity/Entity;
     192: pop
     193: aload         8
     195: aload         11
     197: dload         9
     199: invokeinterface #1041,  4         // InterfaceMethod io/lumine/mythic/api/mobs/MythicMob.applyMobOptions:(Lio/lumine/mythic/core/mobs/ActiveMob;D)Lio/lumine/mythic/core/mobs/ActiveMob;
     204: pop
     205: aload         8
     207: aload         11
     209: invokeinterface #1045,  2         // InterfaceMethod io/lumine/mythic/api/mobs/MythicMob.applyMobVolatileOptions:(Lio/lumine/mythic/core/mobs/ActiveMob;)Lio/lumine/mythic/core/mobs/ActiveMob;
     214: pop
     215: aload         8
     217: aload         11
     219: invokeinterface #1048,  2         // InterfaceMethod io/lumine/mythic/api/mobs/MythicMob.applySpawnModifiers:(Lio/lumine/mythic/core/mobs/ActiveMob;)Lio/lumine/mythic/core/mobs/ActiveMob;
     224: pop
     225: goto          10
     228: return

  private void lambda$load$8(io.lumine.mythic.bukkit.MythicBukkit, org.bukkit.event.entity.CreatureSpawnEvent);
    Code:
       0: aload_0
       1: invokevirtual #356                // Method getPlugin:()Lio/lumine/mythic/bukkit/utils/plugin/LuminePlugin;
       4: checkcast     #358                // class io/lumine/mythic/bukkit/MythicBukkit
       7: invokevirtual #912                // Method io/lumine/mythic/bukkit/MythicBukkit.getConfiguration:()Lio/lumine/mythic/core/config/ConfigExecutor;
      10: invokevirtual #917                // Method io/lumine/mythic/core/config/ConfigExecutor.isDebugMode:()Z
      13: ifeq          17
      16: return
      17: aload_0
      18: invokevirtual #356                // Method getPlugin:()Lio/lumine/mythic/bukkit/utils/plugin/LuminePlugin;
      21: checkcast     #358                // class io/lumine/mythic/bukkit/MythicBukkit
      24: invokevirtual #943                // Method io/lumine/mythic/bukkit/MythicBukkit.getCompatibility:()Lio/lumine/mythic/bukkit/compatibility/CompatibilityManager;
      27: invokevirtual #949                // Method io/lumine/mythic/bukkit/compatibility/CompatibilityManager.getWorldGuard:()Ljava/util/Optional;
      30: invokevirtual #952                // Method java/util/Optional.isPresent:()Z
      33: ifeq          66
      36: aload_0
      37: invokevirtual #356                // Method getPlugin:()Lio/lumine/mythic/bukkit/utils/plugin/LuminePlugin;
      40: checkcast     #358                // class io/lumine/mythic/bukkit/MythicBukkit
      43: invokevirtual #943                // Method io/lumine/mythic/bukkit/MythicBukkit.getCompatibility:()Lio/lumine/mythic/bukkit/compatibility/CompatibilityManager;
      46: invokevirtual #949                // Method io/lumine/mythic/bukkit/compatibility/CompatibilityManager.getWorldGuard:()Ljava/util/Optional;
      49: invokevirtual #953                // Method java/util/Optional.get:()Ljava/lang/Object;
      52: checkcast     #955                // class io/lumine/mythic/bukkit/compatibility/WorldGuardSupport
      55: aload_2
      56: invokevirtual #1059               // Method org/bukkit/event/entity/CreatureSpawnEvent.getLocation:()Lorg/bukkit/Location;
      59: invokevirtual #960                // Method io/lumine/mythic/bukkit/compatibility/WorldGuardSupport.getLocationAllowsMobSpawning:(Lorg/bukkit/Location;)Z
      62: ifne          66
      65: return
      66: getstatic     #920                // Field io/lumine/mythic/core/logging/MythicLogger$DebugLevel.EVENT:Lio/lumine/mythic/core/logging/MythicLogger$DebugLevel;
      69: ldc_w         #1061               // String CreatureSpawnEvent fired
      72: iconst_0
      73: anewarray     #408                // class java/lang/Object
      76: invokestatic  #412                // Method io/lumine/mythic/core/logging/MythicLogger.debug:(Lio/lumine/mythic/core/logging/MythicLogger$DebugLevel;Ljava/lang/String;[Ljava/lang/Object;)V
      79: aload_2
      80: invokevirtual #892                // Method org/bukkit/event/entity/CreatureSpawnEvent.getEntity:()Lorg/bukkit/entity/LivingEntity;
      83: astore_3
      84: aload_3
      85: invokestatic  #778                // Method io/lumine/mythic/bukkit/BukkitAdapter.adapt:(Lorg/bukkit/entity/Entity;)Lio/lumine/mythic/api/adapters/AbstractEntity;
      88: astore        4
      90: aload_2
      91: invokevirtual #897                // Method org/bukkit/event/entity/CreatureSpawnEvent.getSpawnReason:()Lorg/bukkit/event/entity/CreatureSpawnEvent$SpawnReason;
      94: getstatic     #969                // Field org/bukkit/event/entity/CreatureSpawnEvent$SpawnReason.NATURAL:Lorg/bukkit/event/entity/CreatureSpawnEvent$SpawnReason;
      97: if_acmpeq     110
     100: aload_2
     101: invokevirtual #897                // Method org/bukkit/event/entity/CreatureSpawnEvent.getSpawnReason:()Lorg/bukkit/event/entity/CreatureSpawnEvent$SpawnReason;
     104: getstatic     #1064               // Field org/bukkit/event/entity/CreatureSpawnEvent$SpawnReason.CHUNK_GEN:Lorg/bukkit/event/entity/CreatureSpawnEvent$SpawnReason;
     107: if_acmpne     143
     110: aload_0
     111: invokevirtual #356                // Method getPlugin:()Lio/lumine/mythic/bukkit/utils/plugin/LuminePlugin;
     114: checkcast     #358                // class io/lumine/mythic/bukkit/MythicBukkit
     117: invokevirtual #912                // Method io/lumine/mythic/bukkit/MythicBukkit.getConfiguration:()Lio/lumine/mythic/core/config/ConfigExecutor;
     120: invokevirtual #985                // Method io/lumine/mythic/core/config/ConfigExecutor.isVanillaSpawnsDisabled:()Z
     123: ifeq          208
     126: invokestatic  #990                // Method io/lumine/mythic/bukkit/adapters/BukkitEntityType.getIsSpawning:()Ljava/lang/Boolean;
     129: invokevirtual #391                // Method java/lang/Boolean.booleanValue:()Z
     132: ifne          208
     135: aload_2
     136: iconst_1
     137: invokevirtual #1065               // Method org/bukkit/event/entity/CreatureSpawnEvent.setCancelled:(Z)V
     140: goto          208
     143: aload_2
     144: invokevirtual #897                // Method org/bukkit/event/entity/CreatureSpawnEvent.getSpawnReason:()Lorg/bukkit/event/entity/CreatureSpawnEvent$SpawnReason;
     147: getstatic     #1068               // Field org/bukkit/event/entity/CreatureSpawnEvent$SpawnReason.MOUNT:Lorg/bukkit/event/entity/CreatureSpawnEvent$SpawnReason;
     150: if_acmpne     208
     153: aload_2
     154: invokevirtual #892                // Method org/bukkit/event/entity/CreatureSpawnEvent.getEntity:()Lorg/bukkit/entity/LivingEntity;
     157: invokeinterface #1071,  1         // InterfaceMethod org/bukkit/entity/LivingEntity.getPassengers:()Ljava/util/List;
     162: astore        5
     164: aload         5
     166: invokeinterface #1074,  1         // InterfaceMethod java/util/List.isEmpty:()Z
     171: ifne          208
     174: aload_0
     175: invokevirtual #356                // Method getPlugin:()Lio/lumine/mythic/bukkit/utils/plugin/LuminePlugin;
     178: checkcast     #358                // class io/lumine/mythic/bukkit/MythicBukkit
     181: invokevirtual #362                // Method io/lumine/mythic/bukkit/MythicBukkit.getMobManager:()Lio/lumine/mythic/core/mobs/MobExecutor;
     184: astore        6
     186: aload_3
     187: invokestatic  #542                // Method io/lumine/mythic/bukkit/utils/Schedulers.of:(Lorg/bukkit/entity/Entity;)Lio/lumine/mythic/bukkit/utils/tasks/TaskScheduler;
     190: aload         6
     192: aload         5
     194: aload         4
     196: invokedynamic #1082,  0           // InvokeDynamic #32:run:(Lio/lumine/mythic/core/mobs/MobExecutor;Ljava/util/List;Lio/lumine/mythic/api/adapters/AbstractEntity;)Ljava/lang/Runnable;
     201: lconst_1
     202: invokeinterface #558,  4          // InterfaceMethod io/lumine/mythic/bukkit/utils/tasks/TaskScheduler.runLater:(Ljava/lang/Runnable;J)Lio/lumine/mythic/bukkit/utils/promise/Promise;
     207: pop
     208: new           #966                // class io/lumine/mythic/core/spawning/random/RandomSpawnPoint
     211: dup
     212: aload_2
     213: invokevirtual #892                // Method org/bukkit/event/entity/CreatureSpawnEvent.getEntity:()Lorg/bukkit/entity/LivingEntity;
     216: invokestatic  #778                // Method io/lumine/mythic/bukkit/BukkitAdapter.adapt:(Lorg/bukkit/entity/Entity;)Lio/lumine/mythic/api/adapters/AbstractEntity;
     219: aload_2
     220: invokevirtual #1059               // Method org/bukkit/event/entity/CreatureSpawnEvent.getLocation:()Lorg/bukkit/Location;
     223: invokestatic  #1085               // Method io/lumine/mythic/bukkit/BukkitAdapter.adapt:(Lorg/bukkit/Location;)Lio/lumine/mythic/api/adapters/AbstractLocation;
     226: aload_2
     227: invokevirtual #897                // Method org/bukkit/event/entity/CreatureSpawnEvent.getSpawnReason:()Lorg/bukkit/event/entity/CreatureSpawnEvent$SpawnReason;
     230: invokespecial #972                // Method io/lumine/mythic/core/spawning/random/RandomSpawnPoint."<init>":(Lio/lumine/mythic/api/adapters/AbstractEntity;Lio/lumine/mythic/api/adapters/AbstractLocation;Lorg/bukkit/event/entity/CreatureSpawnEvent$SpawnReason;)V
     233: astore        5
     235: aload_0
     236: invokevirtual #356                // Method getPlugin:()Lio/lumine/mythic/bukkit/utils/plugin/LuminePlugin;
     239: checkcast     #358                // class io/lumine/mythic/bukkit/MythicBukkit
     242: invokevirtual #976                // Method io/lumine/mythic/bukkit/MythicBukkit.getRandomSpawningManager:()Lio/lumine/mythic/core/spawning/random/RandomSpawnerManager;
     245: aload         5
     247: invokevirtual #982                // Method io/lumine/mythic/core/spawning/random/RandomSpawnerManager.handleSpawnEvent:(Lio/lumine/mythic/core/spawning/random/RandomSpawnPoint;)Lio/lumine/mythic/api/adapters/AbstractEntity;
     250: invokestatic  #729                // Method io/lumine/mythic/bukkit/BukkitAdapter.adapt:(Lio/lumine/mythic/api/adapters/AbstractEntity;)Lorg/bukkit/entity/Entity;
     253: astore        6
     255: aload         6
     257: ifnull        268
     260: aload_2
     261: iconst_1
     262: invokevirtual #1065               // Method org/bukkit/event/entity/CreatureSpawnEvent.setCancelled:(Z)V
     265: goto          794
     268: aload_2
     269: invokevirtual #897                // Method org/bukkit/event/entity/CreatureSpawnEvent.getSpawnReason:()Lorg/bukkit/event/entity/CreatureSpawnEvent$SpawnReason;
     272: getstatic     #1088               // Field org/bukkit/event/entity/CreatureSpawnEvent$SpawnReason.BREEDING:Lorg/bukkit/event/entity/CreatureSpawnEvent$SpawnReason;
     275: if_acmpeq     794
     278: invokestatic  #990                // Method io/lumine/mythic/bukkit/adapters/BukkitEntityType.getIsSpawning:()Ljava/lang/Boolean;
     281: invokevirtual #391                // Method java/lang/Boolean.booleanValue:()Z
     284: ifne          794
     287: aload_3
     288: invokeinterface #1092,  1         // InterfaceMethod org/bukkit/entity/LivingEntity.getPersistentDataContainer:()Lorg/bukkit/persistence/PersistentDataContainer;
     293: getstatic     #1098               // Field io/lumine/mythic/core/constants/MobKeys.TYPE:Lorg/bukkit/NamespacedKey;
     296: invokeinterface #1104,  2         // InterfaceMethod org/bukkit/persistence/PersistentDataContainer.has:(Lorg/bukkit/NamespacedKey;)Z
     301: ifeq          417
     304: aload_3
     305: invokeinterface #1092,  1         // InterfaceMethod org/bukkit/entity/LivingEntity.getPersistentDataContainer:()Lorg/bukkit/persistence/PersistentDataContainer;
     310: getstatic     #1098               // Field io/lumine/mythic/core/constants/MobKeys.TYPE:Lorg/bukkit/NamespacedKey;
     313: getstatic     #1110               // Field org/bukkit/persistence/PersistentDataType.STRING:Lorg/bukkit/persistence/PersistentDataType;
     316: invokeinterface #1113,  3         // InterfaceMethod org/bukkit/persistence/PersistentDataContainer.get:(Lorg/bukkit/NamespacedKey;Lorg/bukkit/persistence/PersistentDataType;)Ljava/lang/Object;
     321: checkcast     #577                // class java/lang/String
     324: astore        7
     326: aload_0
     327: invokevirtual #356                // Method getPlugin:()Lio/lumine/mythic/bukkit/utils/plugin/LuminePlugin;
     330: checkcast     #358                // class io/lumine/mythic/bukkit/MythicBukkit
     333: invokevirtual #362                // Method io/lumine/mythic/bukkit/MythicBukkit.getMobManager:()Lio/lumine/mythic/core/mobs/MobExecutor;
     336: aload         7
     338: invokevirtual #1117               // Method io/lumine/mythic/core/mobs/MobExecutor.getMythicMob:(Ljava/lang/String;)Ljava/util/Optional;
     341: astore        8
     343: aload         8
     345: invokevirtual #952                // Method java/util/Optional.isPresent:()Z
     348: ifeq          417
     351: aload         8
     353: invokevirtual #953                // Method java/util/Optional.get:()Ljava/lang/Object;
     356: checkcast     #382                // class io/lumine/mythic/api/mobs/MythicMob
     359: astore        9
     361: aload         4
     363: invokeinterface #710,  1          // InterfaceMethod io/lumine/mythic/api/adapters/AbstractEntity.getLocation:()Lio/lumine/mythic/api/adapters/AbstractLocation;
     368: invokestatic  #1029               // Method io/lumine/mythic/core/mobs/WorldScaling.getLevelBonus:(Lio/lumine/mythic/api/adapters/AbstractLocation;)D
     371: dstore        10
     373: aload_0
     374: invokevirtual #356                // Method getPlugin:()Lio/lumine/mythic/bukkit/utils/plugin/LuminePlugin;
     377: checkcast     #358                // class io/lumine/mythic/bukkit/MythicBukkit
     380: invokevirtual #362                // Method io/lumine/mythic/bukkit/MythicBukkit.getMobManager:()Lio/lumine/mythic/core/mobs/MobExecutor;
     383: aload         4
     385: aload         9
     387: dload         10
     389: invokevirtual #1033               // Method io/lumine/mythic/core/mobs/MobExecutor.registerActiveMob:(Lio/lumine/mythic/api/adapters/AbstractEntity;Lio/lumine/mythic/api/mobs/MythicMob;D)Lio/lumine/mythic/core/mobs/ActiveMob;
     392: astore        12
     394: aload         9
     396: aload         12
     398: dload         10
     400: invokeinterface #1041,  4         // InterfaceMethod io/lumine/mythic/api/mobs/MythicMob.applyMobOptions:(Lio/lumine/mythic/core/mobs/ActiveMob;D)Lio/lumine/mythic/core/mobs/ActiveMob;
     405: pop
     406: aload         9
     408: aload         12
     410: invokeinterface #1048,  2         // InterfaceMethod io/lumine/mythic/api/mobs/MythicMob.applySpawnModifiers:(Lio/lumine/mythic/core/mobs/ActiveMob;)Lio/lumine/mythic/core/mobs/ActiveMob;
     415: pop
     416: return
     417: aload_0
     418: invokevirtual #356                // Method getPlugin:()Lio/lumine/mythic/bukkit/utils/plugin/LuminePlugin;
     421: checkcast     #358                // class io/lumine/mythic/bukkit/MythicBukkit
     424: invokevirtual #1008               // Method io/lumine/mythic/bukkit/MythicBukkit.getBootstrap:()Lio/lumine/mythic/bukkit/BukkitBootstrap;
     427: aload_2
     428: invokevirtual #892                // Method org/bukkit/event/entity/CreatureSpawnEvent.getEntity:()Lorg/bukkit/entity/LivingEntity;
     431: invokevirtual #1014               // Method io/lumine/mythic/bukkit/BukkitBootstrap.getMythicEntityType:(Lorg/bukkit/entity/Entity;)Lio/lumine/mythic/api/mobs/entities/MythicEntityType;
     434: astore        7
     436: aload_0
     437: invokevirtual #356                // Method getPlugin:()Lio/lumine/mythic/bukkit/utils/plugin/LuminePlugin;
     440: checkcast     #358                // class io/lumine/mythic/bukkit/MythicBukkit
     443: invokevirtual #362                // Method io/lumine/mythic/bukkit/MythicBukkit.getMobManager:()Lio/lumine/mythic/core/mobs/MobExecutor;
     446: aload         7
     448: invokevirtual #1018               // Method io/lumine/mythic/core/mobs/MobExecutor.getVanillaType:(Lio/lumine/mythic/api/mobs/entities/MythicEntityType;)Ljava/util/Optional;
     451: astore        8
     453: aload         8
     455: invokevirtual #952                // Method java/util/Optional.isPresent:()Z
     458: ifeq          605
     461: aload         8
     463: invokevirtual #953                // Method java/util/Optional.get:()Ljava/lang/Object;
     466: checkcast     #382                // class io/lumine/mythic/api/mobs/MythicMob
     469: astore        9
     471: aload         4
     473: invokeinterface #710,  1          // InterfaceMethod io/lumine/mythic/api/adapters/AbstractEntity.getLocation:()Lio/lumine/mythic/api/adapters/AbstractLocation;
     478: invokestatic  #1029               // Method io/lumine/mythic/core/mobs/WorldScaling.getLevelBonus:(Lio/lumine/mythic/api/adapters/AbstractLocation;)D
     481: dstore        10
     483: aload_0
     484: invokevirtual #356                // Method getPlugin:()Lio/lumine/mythic/bukkit/utils/plugin/LuminePlugin;
     487: checkcast     #358                // class io/lumine/mythic/bukkit/MythicBukkit
     490: invokevirtual #362                // Method io/lumine/mythic/bukkit/MythicBukkit.getMobManager:()Lio/lumine/mythic/core/mobs/MobExecutor;
     493: aload         4
     495: aload         9
     497: dload         10
     499: invokevirtual #1033               // Method io/lumine/mythic/core/mobs/MobExecutor.registerActiveMob:(Lio/lumine/mythic/api/adapters/AbstractEntity;Lio/lumine/mythic/api/mobs/MythicMob;D)Lio/lumine/mythic/core/mobs/ActiveMob;
     502: astore        12
     504: aload         9
     506: invokeinterface #610,  1          // InterfaceMethod io/lumine/mythic/api/mobs/MythicMob.getMythicEntity:()Lio/lumine/mythic/bukkit/adapters/BukkitEntityType;
     511: astore        13
     513: aload         13
     515: aload_2
     516: invokevirtual #892                // Method org/bukkit/event/entity/CreatureSpawnEvent.getEntity:()Lorg/bukkit/entity/LivingEntity;
     519: invokevirtual #1021               // Method io/lumine/mythic/bukkit/adapters/BukkitEntityType.compare:(Lorg/bukkit/entity/Entity;)Z
     522: ifeq          543
     525: aload         9
     527: invokeinterface #610,  1          // InterfaceMethod io/lumine/mythic/api/mobs/MythicMob.getMythicEntity:()Lio/lumine/mythic/bukkit/adapters/BukkitEntityType;
     532: aload_2
     533: invokevirtual #892                // Method org/bukkit/event/entity/CreatureSpawnEvent.getEntity:()Lorg/bukkit/entity/LivingEntity;
     536: invokevirtual #1037               // Method io/lumine/mythic/bukkit/adapters/BukkitEntityType.applySpawnOptions:(Lorg/bukkit/entity/Entity;)Lorg/bukkit/entity/Entity;
     539: pop
     540: goto          570
     543: aload_2
     544: invokevirtual #892                // Method org/bukkit/event/entity/CreatureSpawnEvent.getEntity:()Lorg/bukkit/entity/LivingEntity;
     547: invokeinterface #1118,  1         // InterfaceMethod org/bukkit/entity/LivingEntity.getType:()Lorg/bukkit/entity/EntityType;
     552: invokevirtual #1121               // Method org/bukkit/entity/EntityType.toString:()Ljava/lang/String;
     555: aload         9
     557: invokeinterface #1124,  1         // InterfaceMethod io/lumine/mythic/api/mobs/MythicMob.getInternalName:()Ljava/lang/String;
     562: invokedynamic #1129,  0           // InvokeDynamic #33:makeConcatWithConstants:(Ljava/lang/String;Ljava/lang/String;)Ljava/lang/String;
     567: invokestatic  #1132               // Method io/lumine/mythic/core/logging/MythicLogger.error:(Ljava/lang/String;)V
     570: aload         9
     572: aload         12
     574: dload         10
     576: invokeinterface #1041,  4         // InterfaceMethod io/lumine/mythic/api/mobs/MythicMob.applyMobOptions:(Lio/lumine/mythic/core/mobs/ActiveMob;D)Lio/lumine/mythic/core/mobs/ActiveMob;
     581: pop
     582: aload         9
     584: aload         12
     586: invokeinterface #1045,  2         // InterfaceMethod io/lumine/mythic/api/mobs/MythicMob.applyMobVolatileOptions:(Lio/lumine/mythic/core/mobs/ActiveMob;)Lio/lumine/mythic/core/mobs/ActiveMob;
     591: pop
     592: aload         9
     594: aload         12
     596: invokeinterface #1048,  2         // InterfaceMethod io/lumine/mythic/api/mobs/MythicMob.applySpawnModifiers:(Lio/lumine/mythic/core/mobs/ActiveMob;)Lio/lumine/mythic/core/mobs/ActiveMob;
     601: pop
     602: goto          794
     605: aload         4
     607: invokeinterface #710,  1          // InterfaceMethod io/lumine/mythic/api/adapters/AbstractEntity.getLocation:()Lio/lumine/mythic/api/adapters/AbstractLocation;
     612: invokevirtual #1137               // Method io/lumine/mythic/api/adapters/AbstractLocation.getWorld:()Lio/lumine/mythic/api/adapters/AbstractWorld;
     615: invokeinterface #1140,  1         // InterfaceMethod io/lumine/mythic/api/adapters/AbstractWorld.getName:()Ljava/lang/String;
     620: invokestatic  #1143               // Method io/lumine/mythic/core/mobs/WorldScaling.get:(Ljava/lang/String;)Lio/lumine/mythic/core/mobs/WorldScaling;
     623: astore        9
     625: aload         9
     627: invokevirtual #1146               // Method io/lumine/mythic/core/mobs/WorldScaling.getScaleVanillaMobs:()Z
     630: ifeq          794
     633: aload         4
     635: invokeinterface #710,  1          // InterfaceMethod io/lumine/mythic/api/adapters/AbstractEntity.getLocation:()Lio/lumine/mythic/api/adapters/AbstractLocation;
     640: invokestatic  #1029               // Method io/lumine/mythic/core/mobs/WorldScaling.getLevelBonus:(Lio/lumine/mythic/api/adapters/AbstractLocation;)D
     643: dstore        10
     645: aload_0
     646: invokevirtual #356                // Method getPlugin:()Lio/lumine/mythic/bukkit/utils/plugin/LuminePlugin;
     649: checkcast     #358                // class io/lumine/mythic/bukkit/MythicBukkit
     652: invokevirtual #912                // Method io/lumine/mythic/bukkit/MythicBukkit.getConfiguration:()Lio/lumine/mythic/core/config/ConfigExecutor;
     655: invokevirtual #1150               // Method io/lumine/mythic/core/config/ConfigExecutor.getScalingEquationHealth:()Lnet/objecthunter/exp4j/Expression;
     658: ifnull        718
     661: aload_0
     662: invokevirtual #356                // Method getPlugin:()Lio/lumine/mythic/bukkit/utils/plugin/LuminePlugin;
     665: checkcast     #358                // class io/lumine/mythic/bukkit/MythicBukkit
     668: invokevirtual #912                // Method io/lumine/mythic/bukkit/MythicBukkit.getConfiguration:()Lio/lumine/mythic/core/config/ConfigExecutor;
     671: invokevirtual #1150               // Method io/lumine/mythic/core/config/ConfigExecutor.getScalingEquationHealth:()Lnet/objecthunter/exp4j/Expression;
     674: ldc_w         #1152               // String v
     677: aload         4
     679: invokeinterface #1153,  1         // InterfaceMethod io/lumine/mythic/api/adapters/AbstractEntity.getHealth:()D
     684: invokevirtual #1159               // Method net/objecthunter/exp4j/Expression.setVariable:(Ljava/lang/String;D)Lnet/objecthunter/exp4j/Expression;
     687: ldc_w         #1160               // String l
     690: dload         10
     692: invokevirtual #1159               // Method net/objecthunter/exp4j/Expression.setVariable:(Ljava/lang/String;D)Lnet/objecthunter/exp4j/Expression;
     695: invokevirtual #1163               // Method net/objecthunter/exp4j/Expression.evaluate:()D
     698: dstore        12
     700: aload         4
     702: dload         12
     704: invokeinterface #1164,  3         // InterfaceMethod io/lumine/mythic/api/adapters/AbstractEntity.setMaxHealth:(D)V
     709: aload         4
     711: dload         12
     713: invokeinterface #1165,  3         // InterfaceMethod io/lumine/mythic/api/adapters/AbstractEntity.setHealth:(D)V
     718: aload_0
     719: invokevirtual #356                // Method getPlugin:()Lio/lumine/mythic/bukkit/utils/plugin/LuminePlugin;
     722: checkcast     #358                // class io/lumine/mythic/bukkit/MythicBukkit
     725: invokevirtual #912                // Method io/lumine/mythic/bukkit/MythicBukkit.getConfiguration:()Lio/lumine/mythic/core/config/ConfigExecutor;
     728: invokevirtual #1168               // Method io/lumine/mythic/core/config/ConfigExecutor.getScalingEquationDamage:()Lnet/objecthunter/exp4j/Expression;
     731: ifnull        794
     734: aload         4
     736: invokeinterface #1171,  1         // InterfaceMethod io/lumine/mythic/api/adapters/AbstractEntity.getDamageBase:()D
     741: dconst_0
     742: dcmpl
     743: ifle          794
     746: aload_0
     747: invokevirtual #356                // Method getPlugin:()Lio/lumine/mythic/bukkit/utils/plugin/LuminePlugin;
     750: checkcast     #358                // class io/lumine/mythic/bukkit/MythicBukkit
     753: invokevirtual #912                // Method io/lumine/mythic/bukkit/MythicBukkit.getConfiguration:()Lio/lumine/mythic/core/config/ConfigExecutor;
     756: invokevirtual #1168               // Method io/lumine/mythic/core/config/ConfigExecutor.getScalingEquationDamage:()Lnet/objecthunter/exp4j/Expression;
     759: ldc_w         #1152               // String v
     762: aload         4
     764: invokeinterface #1171,  1         // InterfaceMethod io/lumine/mythic/api/adapters/AbstractEntity.getDamageBase:()D
     769: invokevirtual #1159               // Method net/objecthunter/exp4j/Expression.setVariable:(Ljava/lang/String;D)Lnet/objecthunter/exp4j/Expression;
     772: ldc_w         #1160               // String l
     775: dload         10
     777: invokevirtual #1159               // Method net/objecthunter/exp4j/Expression.setVariable:(Ljava/lang/String;D)Lnet/objecthunter/exp4j/Expression;
     780: invokevirtual #1163               // Method net/objecthunter/exp4j/Expression.evaluate:()D
     783: dstore        12
     785: aload         4
     787: dload         12
     789: invokeinterface #1174,  3         // InterfaceMethod io/lumine/mythic/api/adapters/AbstractEntity.setDamage:(D)V
     794: aload_2
     795: invokevirtual #897                // Method org/bukkit/event/entity/CreatureSpawnEvent.getSpawnReason:()Lorg/bukkit/event/entity/CreatureSpawnEvent$SpawnReason;
     798: getstatic     #1177               // Field org/bukkit/event/entity/CreatureSpawnEvent$SpawnReason.CUSTOM:Lorg/bukkit/event/entity/CreatureSpawnEvent$SpawnReason;
     801: if_acmpne     878
     804: aload_1
     805: invokevirtual #912                // Method io/lumine/mythic/bukkit/MythicBukkit.getConfiguration:()Lio/lumine/mythic/core/config/ConfigExecutor;
     808: invokevirtual #1180               // Method io/lumine/mythic/core/config/ConfigExecutor.getUseCompatibilityMode:()Ljava/lang/Boolean;
     811: invokevirtual #391                // Method java/lang/Boolean.booleanValue:()Z
     814: ifeq          850
     817: aload_2
     818: invokevirtual #892                // Method org/bukkit/event/entity/CreatureSpawnEvent.getEntity:()Lorg/bukkit/entity/LivingEntity;
     821: astore        7
     823: aload         7
     825: invokestatic  #542                // Method io/lumine/mythic/bukkit/utils/Schedulers.of:(Lorg/bukkit/entity/Entity;)Lio/lumine/mythic/bukkit/utils/tasks/TaskScheduler;
     828: aload_0
     829: aload         4
     831: aload         7
     833: invokedynamic #1188,  0           // InvokeDynamic #34:run:(Lio/lumine/mythic/bukkit/listeners/MobListeners;Lio/lumine/mythic/api/adapters/AbstractEntity;Lorg/bukkit/entity/LivingEntity;)Ljava/lang/Runnable;
     838: ldc2_w        #1189               // long 10l
     841: invokeinterface #558,  4          // InterfaceMethod io/lumine/mythic/bukkit/utils/tasks/TaskScheduler.runLater:(Ljava/lang/Runnable;J)Lio/lumine/mythic/bukkit/utils/promise/Promise;
     846: pop
     847: goto          878
     850: aload_2
     851: invokevirtual #892                // Method org/bukkit/event/entity/CreatureSpawnEvent.getEntity:()Lorg/bukkit/entity/LivingEntity;
     854: astore        7
     856: aload         7
     858: invokestatic  #542                // Method io/lumine/mythic/bukkit/utils/Schedulers.of:(Lorg/bukkit/entity/Entity;)Lio/lumine/mythic/bukkit/utils/tasks/TaskScheduler;
     861: aload_0
     862: aload         7
     864: invokedynamic #1198,  0           // InvokeDynamic #35:run:(Lio/lumine/mythic/bukkit/listeners/MobListeners;Lorg/bukkit/entity/LivingEntity;)Ljava/lang/Runnable;
     869: ldc2_w        #1199               // long 20l
     872: invokeinterface #558,  4          // InterfaceMethod io/lumine/mythic/bukkit/utils/tasks/TaskScheduler.runLater:(Ljava/lang/Runnable;J)Lio/lumine/mythic/bukkit/utils/promise/Promise;
     877: pop
     878: return

  private void lambda$load$7(org.bukkit.entity.LivingEntity);
    Code:
       0: aload_0
       1: invokevirtual #356                // Method getPlugin:()Lio/lumine/mythic/bukkit/utils/plugin/LuminePlugin;
       4: checkcast     #358                // class io/lumine/mythic/bukkit/MythicBukkit
       7: invokevirtual #362                // Method io/lumine/mythic/bukkit/MythicBukkit.getMobManager:()Lio/lumine/mythic/core/mobs/MobExecutor;
      10: aload_1
      11: invokeinterface #489,  1          // InterfaceMethod org/bukkit/entity/LivingEntity.getUniqueId:()Ljava/util/UUID;
      16: invokevirtual #372                // Method io/lumine/mythic/core/mobs/MobExecutor.isActiveMob:(Ljava/util/UUID;)Z
      19: ifne          41
      22: aload_0
      23: invokevirtual #356                // Method getPlugin:()Lio/lumine/mythic/bukkit/utils/plugin/LuminePlugin;
      26: checkcast     #358                // class io/lumine/mythic/bukkit/MythicBukkit
      29: invokevirtual #362                // Method io/lumine/mythic/bukkit/MythicBukkit.getMobManager:()Lio/lumine/mythic/core/mobs/MobExecutor;
      32: aload_1
      33: invokeinterface #489,  1          // InterfaceMethod org/bukkit/entity/LivingEntity.getUniqueId:()Ljava/util/UUID;
      38: invokevirtual #1219               // Method io/lumine/mythic/core/mobs/MobExecutor.setIgnoreEntity:(Ljava/util/UUID;)V
      41: return

  private void lambda$load$6(io.lumine.mythic.api.adapters.AbstractEntity, org.bukkit.entity.LivingEntity);
    Code:
       0: aload_0
       1: invokevirtual #356                // Method getPlugin:()Lio/lumine/mythic/bukkit/utils/plugin/LuminePlugin;
       4: checkcast     #358                // class io/lumine/mythic/bukkit/MythicBukkit
       7: invokevirtual #362                // Method io/lumine/mythic/bukkit/MythicBukkit.getMobManager:()Lio/lumine/mythic/core/mobs/MobExecutor;
      10: aload_1
      11: invokeinterface #1220,  1         // InterfaceMethod io/lumine/mythic/api/adapters/AbstractEntity.getUniqueId:()Ljava/util/UUID;
      16: invokevirtual #372                // Method io/lumine/mythic/core/mobs/MobExecutor.isActiveMob:(Ljava/util/UUID;)Z
      19: ifne          99
      22: getstatic     #439                // Field io/lumine/mythic/core/logging/MythicLogger$DebugLevel.INFO:Lio/lumine/mythic/core/logging/MythicLogger$DebugLevel;
      25: aload_2
      26: invokeinterface #1223,  1         // InterfaceMethod org/bukkit/entity/LivingEntity.getCustomName:()Ljava/lang/String;
      31: invokedynamic #1226,  0           // InvokeDynamic #36:makeConcatWithConstants:(Ljava/lang/String;)Ljava/lang/String;
      36: iconst_0
      37: anewarray     #408                // class java/lang/Object
      40: invokestatic  #412                // Method io/lumine/mythic/core/logging/MythicLogger.debug:(Lio/lumine/mythic/core/logging/MythicLogger$DebugLevel;Ljava/lang/String;[Ljava/lang/Object;)V
      43: aload_0
      44: invokevirtual #356                // Method getPlugin:()Lio/lumine/mythic/bukkit/utils/plugin/LuminePlugin;
      47: checkcast     #358                // class io/lumine/mythic/bukkit/MythicBukkit
      50: invokevirtual #362                // Method io/lumine/mythic/bukkit/MythicBukkit.getMobManager:()Lio/lumine/mythic/core/mobs/MobExecutor;
      53: aload_1
      54: invokevirtual #1230               // Method io/lumine/mythic/core/mobs/MobExecutor.getMythicMobByDisplayCompat:(Lio/lumine/mythic/api/adapters/AbstractEntity;)Lio/lumine/mythic/api/mobs/MythicMob;
      57: astore_3
      58: aload_3
      59: ifnull        80
      62: aload_0
      63: invokevirtual #356                // Method getPlugin:()Lio/lumine/mythic/bukkit/utils/plugin/LuminePlugin;
      66: checkcast     #358                // class io/lumine/mythic/bukkit/MythicBukkit
      69: invokevirtual #362                // Method io/lumine/mythic/bukkit/MythicBukkit.getMobManager:()Lio/lumine/mythic/core/mobs/MobExecutor;
      72: aload_2
      73: aload_3
      74: invokevirtual #1234               // Method io/lumine/mythic/core/mobs/MobExecutor.SetupMythicMobCompat:(Lorg/bukkit/entity/LivingEntity;Lio/lumine/mythic/api/mobs/MythicMob;)V
      77: goto          99
      80: aload_0
      81: invokevirtual #356                // Method getPlugin:()Lio/lumine/mythic/bukkit/utils/plugin/LuminePlugin;
      84: checkcast     #358                // class io/lumine/mythic/bukkit/MythicBukkit
      87: invokevirtual #362                // Method io/lumine/mythic/bukkit/MythicBukkit.getMobManager:()Lio/lumine/mythic/core/mobs/MobExecutor;
      90: aload_2
      91: invokeinterface #489,  1          // InterfaceMethod org/bukkit/entity/LivingEntity.getUniqueId:()Ljava/util/UUID;
      96: invokevirtual #1219               // Method io/lumine/mythic/core/mobs/MobExecutor.setIgnoreEntity:(Ljava/util/UUID;)V
      99: return

  private static void lambda$load$5(io.lumine.mythic.core.mobs.MobExecutor, java.util.List, io.lumine.mythic.api.adapters.AbstractEntity);
    Code:
       0: aload_0
       1: aload_1
       2: iconst_0
       3: invokeinterface #1237,  2         // InterfaceMethod java/util/List.get:(I)Ljava/lang/Object;
       8: checkcast     #447                // class org/bukkit/entity/Entity
      11: invokeinterface #606,  1          // InterfaceMethod org/bukkit/entity/Entity.getUniqueId:()Ljava/util/UUID;
      16: invokevirtual #372                // Method io/lumine/mythic/core/mobs/MobExecutor.isActiveMob:(Ljava/util/UUID;)Z
      19: ifeq          66
      22: aload_0
      23: aload_2
      24: invokevirtual #1240               // Method io/lumine/mythic/core/mobs/MobExecutor.isActiveMob:(Lio/lumine/mythic/api/adapters/AbstractEntity;)Z
      27: ifne          66
      30: aload_0
      31: aload_1
      32: iconst_0
      33: invokeinterface #1237,  2         // InterfaceMethod java/util/List.get:(I)Ljava/lang/Object;
      38: checkcast     #447                // class org/bukkit/entity/Entity
      41: invokevirtual #376                // Method io/lumine/mythic/core/mobs/MobExecutor.getMythicMobInstance:(Lorg/bukkit/entity/Entity;)Lio/lumine/mythic/core/mobs/ActiveMob;
      44: invokevirtual #380                // Method io/lumine/mythic/core/mobs/ActiveMob.getType:()Lio/lumine/mythic/api/mobs/MythicMob;
      47: invokeinterface #1243,  1         // InterfaceMethod io/lumine/mythic/api/mobs/MythicMob.getPreventMounts:()Ljava/lang/Boolean;
      52: invokevirtual #391                // Method java/lang/Boolean.booleanValue:()Z
      55: ifeq          66
      58: aload_2
      59: invokeinterface #1245,  1         // InterfaceMethod io/lumine/mythic/api/adapters/AbstractEntity.remove:()Z
      64: pop
      65: return
      66: return

  private static void lambda$load$4(org.bukkit.event.entity.SlimeSplitEvent);
    Code:
       0: aload_0
       1: invokevirtual #1248               // Method org/bukkit/event/entity/SlimeSplitEvent.getEntity:()Lorg/bukkit/entity/Slime;
       4: astore_1
       5: aload_1
       6: invokeinterface #1251,  1         // InterfaceMethod org/bukkit/entity/Slime.getPersistentDataContainer:()Lorg/bukkit/persistence/PersistentDataContainer;
      11: getstatic     #1256               // Field io/lumine/mythic/core/mobs/PersistentMobData.SLIME_NO_SPLIT:Lorg/bukkit/NamespacedKey;
      14: invokeinterface #1104,  2         // InterfaceMethod org/bukkit/persistence/PersistentDataContainer.has:(Lorg/bukkit/NamespacedKey;)Z
      19: ifeq          32
      22: aload_0
      23: iconst_1
      24: invokevirtual #1257               // Method org/bukkit/event/entity/SlimeSplitEvent.setCancelled:(Z)V
      27: aload_0
      28: iconst_0
      29: invokevirtual #1260               // Method org/bukkit/event/entity/SlimeSplitEvent.setCount:(I)V
      32: return

  private void lambda$load$3(org.bukkit.event.entity.EntityDamageByEntityEvent);
    Code:
       0: aload_0
       1: invokevirtual #356                // Method getPlugin:()Lio/lumine/mythic/bukkit/utils/plugin/LuminePlugin;
       4: checkcast     #358                // class io/lumine/mythic/bukkit/MythicBukkit
       7: invokevirtual #362                // Method io/lumine/mythic/bukkit/MythicBukkit.getMobManager:()Lio/lumine/mythic/core/mobs/MobExecutor;
      10: aload_1
      11: invokevirtual #1263               // Method org/bukkit/event/entity/EntityDamageByEntityEvent.getEntity:()Lorg/bukkit/entity/Entity;
      14: invokeinterface #606,  1          // InterfaceMethod org/bukkit/entity/Entity.getUniqueId:()Ljava/util/UUID;
      19: invokevirtual #1267               // Method io/lumine/mythic/core/mobs/MobExecutor.getActiveMob:(Ljava/util/UUID;)Ljava/util/Optional;
      22: aload_0
      23: aload_1
      24: invokedynamic #1277,  0           // InvokeDynamic #37:accept:(Lio/lumine/mythic/bukkit/listeners/MobListeners;Lorg/bukkit/event/entity/EntityDamageByEntityEvent;)Ljava/util/function/Consumer;
      29: invokevirtual #1281               // Method java/util/Optional.ifPresent:(Ljava/util/function/Consumer;)V
      32: return

  private void lambda$load$2(org.bukkit.event.entity.EntityDamageByEntityEvent, io.lumine.mythic.core.mobs.ActiveMob);
    Code:
       0: aload_1
       1: invokevirtual #434                // Method org/bukkit/event/entity/EntityDamageByEntityEvent.getDamager:()Lorg/bukkit/entity/Entity;
       4: invokestatic  #778                // Method io/lumine/mythic/bukkit/BukkitAdapter.adapt:(Lorg/bukkit/entity/Entity;)Lio/lumine/mythic/api/adapters/AbstractEntity;
       7: astore_3
       8: aload_2
       9: invokevirtual #1282               // Method io/lumine/mythic/core/mobs/ActiveMob.getLocation:()Lio/lumine/mythic/api/adapters/AbstractLocation;
      12: astore        4
      14: aload_0
      15: invokevirtual #356                // Method getPlugin:()Lio/lumine/mythic/bukkit/utils/plugin/LuminePlugin;
      18: checkcast     #358                // class io/lumine/mythic/bukkit/MythicBukkit
      21: invokevirtual #653                // Method io/lumine/mythic/bukkit/MythicBukkit.getSkillManager:()Lio/lumine/mythic/core/skills/SkillExecutor;
      24: invokevirtual #659                // Method io/lumine/mythic/core/skills/SkillExecutor.getEventBus:()Lio/lumine/mythic/core/skills/EventExecutor;
      27: getstatic     #1285               // Field io/lumine/mythic/core/skills/SkillTriggers.DAMAGED:Lio/lumine/mythic/api/skills/SkillTrigger;
      30: aload_2
      31: aload_3
      32: aload         4
      34: iconst_1
      35: invokevirtual #671                // Method io/lumine/mythic/core/skills/EventExecutor.buildSkillMetadata:(Lio/lumine/mythic/api/skills/SkillTrigger;Lio/lumine/mythic/api/skills/SkillCaster;Lio/lumine/mythic/api/adapters/AbstractEntity;Lio/lumine/mythic/api/adapters/AbstractLocation;Z)Lio/lumine/mythic/api/skills/SkillMetadata;
      38: astore        5
      40: new           #1287               // class io/lumine/mythic/core/skills/triggers/meta/EntityAttackMetadata
      43: dup
      44: aload_1
      45: aconst_null
      46: aload_3
      47: aload_2
      48: invokevirtual #621                // Method io/lumine/mythic/core/mobs/ActiveMob.getEntity:()Lio/lumine/mythic/api/adapters/AbstractEntity;
      51: invokespecial #1290               // Method io/lumine/mythic/core/skills/triggers/meta/EntityAttackMetadata."<init>":(Lorg/bukkit/event/entity/EntityDamageByEntityEvent;Lio/lumine/mythic/api/skills/damage/DamageMetadata;Lio/lumine/mythic/api/adapters/AbstractEntity;Lio/lumine/mythic/api/adapters/AbstractEntity;)V
      54: astore        6
      56: aload_0
      57: invokevirtual #356                // Method getPlugin:()Lio/lumine/mythic/bukkit/utils/plugin/LuminePlugin;
      60: checkcast     #358                // class io/lumine/mythic/bukkit/MythicBukkit
      63: invokevirtual #653                // Method io/lumine/mythic/bukkit/MythicBukkit.getSkillManager:()Lio/lumine/mythic/core/skills/SkillExecutor;
      66: invokevirtual #659                // Method io/lumine/mythic/core/skills/SkillExecutor.getEventBus:()Lio/lumine/mythic/core/skills/EventExecutor;
      69: aload         5
      71: aload         6
      73: invokevirtual #1293               // Method io/lumine/mythic/core/skills/EventExecutor.processTriggerMechanics:(Lio/lumine/mythic/api/skills/SkillMetadata;Lio/lumine/mythic/core/skills/triggers/SkillTriggerMetadata;)Lio/lumine/mythic/core/skills/TriggeredSkill;
      76: astore        7
      78: aload         7
      80: invokevirtual #680                // Method io/lumine/mythic/core/skills/TriggeredSkill.getCancelled:()Z
      83: ifeq          91
      86: aload_1
      87: iconst_1
      88: invokevirtual #1294               // Method org/bukkit/event/entity/EntityDamageByEntityEvent.setCancelled:(Z)V
      91: return

  private static boolean lambda$load$1(org.bukkit.event.entity.EntityDamageByEntityEvent);
    Code:
       0: aload_0
       1: invokevirtual #1263               // Method org/bukkit/event/entity/EntityDamageByEntityEvent.getEntity:()Lorg/bukkit/entity/Entity;
       4: instanceof    #1303               // class org/bukkit/entity/Interaction
       7: ireturn

  private void lambda$load$0(org.bukkit.event.player.PlayerArmorStandManipulateEvent);
    Code:
       0: getstatic     #920                // Field io/lumine/mythic/core/logging/MythicLogger$DebugLevel.EVENT:Lio/lumine/mythic/core/logging/MythicLogger$DebugLevel;
       3: ldc_w         #1305               // String PlayerArmorStandManipulateEvent fired
       6: iconst_0
       7: anewarray     #408                // class java/lang/Object
      10: invokestatic  #412                // Method io/lumine/mythic/core/logging/MythicLogger.debug:(Lio/lumine/mythic/core/logging/MythicLogger$DebugLevel;Ljava/lang/String;[Ljava/lang/Object;)V
      13: aload_0
      14: invokevirtual #356                // Method getPlugin:()Lio/lumine/mythic/bukkit/utils/plugin/LuminePlugin;
      17: checkcast     #358                // class io/lumine/mythic/bukkit/MythicBukkit
      20: invokevirtual #362                // Method io/lumine/mythic/bukkit/MythicBukkit.getMobManager:()Lio/lumine/mythic/core/mobs/MobExecutor;
      23: aload_1
      24: invokevirtual #1308               // Method org/bukkit/event/player/PlayerArmorStandManipulateEvent.getRightClicked:()Lorg/bukkit/entity/ArmorStand;
      27: invokeinterface #1311,  1         // InterfaceMethod org/bukkit/entity/ArmorStand.getUniqueId:()Ljava/util/UUID;
      32: invokevirtual #1267               // Method io/lumine/mythic/core/mobs/MobExecutor.getActiveMob:(Ljava/util/UUID;)Ljava/util/Optional;
      35: astore_2
      36: aload_2
      37: invokevirtual #952                // Method java/util/Optional.isPresent:()Z
      40: ifeq          68
      43: aload_2
      44: invokevirtual #953                // Method java/util/Optional.get:()Ljava/lang/Object;
      47: checkcast     #17                 // class io/lumine/mythic/core/mobs/ActiveMob
      50: astore_3
      51: aload_3
      52: invokevirtual #380                // Method io/lumine/mythic/core/mobs/ActiveMob.getType:()Lio/lumine/mythic/api/mobs/MythicMob;
      55: invokeinterface #1314,  1         // InterfaceMethod io/lumine/mythic/api/mobs/MythicMob.getIsInteractable:()Z
      60: ifne          68
      63: aload_1
      64: iconst_1
      65: invokevirtual #1315               // Method org/bukkit/event/player/PlayerArmorStandManipulateEvent.setCancelled:(Z)V
      68: return
}
